Workbook

Sheet Cover & Instructions
A1: MASTER ESTIMATE WORKBOOK - LINKED FIRST-PRINCIPLES MODEL - REV3 RISK TRUTH
A2: Permanent estimating template. Direct costs originate in Resource Build-Up and flow through QS Takeoff, Tender Build-Up, Summary and Cashflow. Risk Truth controls residual risk treatment and prevents duplicate risk cost paths.
A4: Project | D4: Location
A5: Scope | D5: Base direct estimate excl. GST | E5: ='Tender Build-Up'!B20 -> 0 | F5: Linked from Tender Build-Up
A6: Issue status | B6: MASTER TEMPLATE - populate the current job intake, documents, scope and evidence before pricing. | D6: Issue date | E6: 17-Aug-2026
A7: Estimate basis | B7: Estimate basis must be rebuilt from the current project's drawings, specifications, takeoff, quotes, resource rates, programme and approved backend tools. Do not carry project-specific quantities, assumptions, RFIs or quotations from another job.
A9: HOW THE WORKBOOK WORKS
A10: 1 | B10: Enter/confirm job scope, item codes, quantities and takeoff references in QS Takeoff.
A11: 2 | B11: For every active QS Code, allocate labour, plant, materials, cartage/testing or subcontract resources in Resource Build-Up.
A12: 3 | B12: Maintain reusable current rates and sources in Resource Rate Library; use Job Rate Override in Resource Build-Up for job-specific quotes/rates.
A13: 4 | B13: QS Rate and Amount calculate from Resource Build-Up. Do not enter a separate QS lump-sum rate.
A14: 5 | B14: Tender Build-Up pulls section totals from QS Takeoff. Commercial Inputs is the only source for below-the-line contingency/overhead and profit/GST/retention provisions.
A15: 6 | B15: Summary pulls the live Tender Build-Up and includes cost-chain integrity checks. All checks must read OK before issue.
A16: 7 | B16: Stage Cashflow pulls tender revenue and Summary direct costs. Only stage timing/%/retention selections are inputs.
A17: 8 | B17: Weather Risk links live weather-exposed labour/plant, programme duration and time-related cost drivers to the approved Weather Tool run, then feeds CA10. Rerun the tool when its input gate changes.
A18: CORE WORKING TABS - LINKED COST, PROGRAMME, WEATHER AND RISK CONTROLS
A19: Cover & Instructions | B19: Job basis, document register, assumptions/RFIs, risks and release QA
A20: Summary | B20: Client/management summary plus end-to-end cost-chain integrity
A21: QS Takeoff | B21: Measured items/quantities; rate and amount are linked outputs from Resource Build-Up
A22: Resource Build-Up | B22: Direct-cost source of truth by QS Code: methodology, productivity and every allocated resource
A23: Resource Rate Library | B23: Reusable company resource master. Retain all resources across jobs; update verified rates/sources centrally. Heavy-access, crane, rigging, cartage and testing resources are reusable library codes; job-specific rates remain job overrides.
A24: Tender Build-Up | B24: QS section totals plus formula-linked commercial build-up
A25: Commercial Inputs | B25: Below-the-line commercial/risk/overhead/profit/GST/retention controls. CA01/CA02 can select Risk Engine / PC Sum / %; CA10 can select Weather Engine / PC Sum / %. Include? is the on/off switch and engine outputs remain live for audit.
A26: Stage Cashflow | B26: Formula-linked stage revenue, direct cost allocation and cashflow
A27: Weather Risk | B27: Approved weather-tool integration, exposed-resource audit, programme/calendar effects, weather cost buckets and rerun gate
A28: Risk Truth | B28: Risk-control and reconciliation module: tender baseline, residual exposure, duplication controls, integration target and release gate
A29: Yellow | B29: Intended input cells.
A30: Green / linked | B30: Formula-controlled outputs. Stop validation blocks ordinary edits and directs the estimator to the upstream source.
... A33: Template rule | B33: Every direct cost must have a QS Code and resource origin. Every commercial allowance must have a selected method, stated basis and Include? status. Engine outputs remain separate from manual PC/% overrides so the evidence trail is never destroyed.
A35: STREAMLINED LINKED MODEL - WORKBOOK FLOW & JOB CONTROLS
A37: Cost chain | B37: Resource Rate Library -> Resource Build-Up -> QS Takeoff -> Tender Build-Up -> Summary
A38: Commercial chain | B38: Commercial Inputs -> Tender Build-Up -> Summary
A39: Cashflow chain | B39: Tender total -> Stage Cashflow
A40: Direct cost rule | B40: No direct-cost lump sum is typed into QS, Tender Build-Up or Summary. Every QS item cost must be created in Resource Build-Up using the same QS Code.
A41: Input rule | B41: Yellow cells are intended inputs. Green/grey linked cells are formula outputs. Method selectors choose the pricing source; Include? controls whether that source enters the tender.
A42: Allowances / quotes | B42: Allowances, PC sums and specialist quotes still require a Resource Build-Up row (normally Lump Sum / Quote mode) unless they are below-the-line Commercial Inputs.
A43: Issue gate | B43: Summary cost-chain checks must all read OK before tender issue.
A44: Risk Truth | B44: Risk-control and reconciliation module. Tracks baseline vs residual exposure, prevents duplicate cost paths and routes risk once to QS, CA01/CA02 or specialist engines.
A46: DRAWING / DOCUMENT REGISTER
A47: Document / Drawing | B47: Reference | C47: Estimate use
A48: Plans / drawings | C48: Geometry, quantities, interfaces and construction details
A49: Specifications | C49: Materials, workmanship, testing, tolerances and scope requirements
A50: Geotechnical / ground information | C50: Ground conditions, earthworks, foundations, groundwater and remediation basis
A51: Survey / CAD / models | C51: Measured quantities, levels, earthworks balance and setout basis
A52: Tender / contract / scope documents | C52: Work-package boundaries, commercial requirements and pricing schedule
A53: Supplier / subcontract quotations | C53: Project-specific pricing, inclusions, exclusions and validity
A54: Other consultants / approvals | C54: Project-specific evidence affecting quantity, method, cost or programme
A55: Correspondence / addenda / clarifications | C55: Instructions and changes affecting the tender basis
A57: ASSUMPTIONS / QUALIFICATIONS / RFIs
A58: A1 | B58: Price is for civil works only. Buildings, architectural fit-out, playground equipment, soft landscaping, architectural fencing and above-ground MEP are excluded.
A59: A1 | B59: Assume [enter project-specific access / working-hours basis].
A60: A2 | B60: Assume [enter project-specific cartage / disposal / haul basis].
A61: A3 | B61: Assume [enter project-specific ground / groundwater baseline].
A62: A4 | B62: Assume [enter project-specific temporary works responsibility].
A63: A5 | B63: Assume [enter project-specific testing / inspection basis].
A64: A6 | B64: Assume [enter project-specific programme / work-front basis].
A65: A7 | B65: Assume [enter project-specific weather / season basis or refer to Weather Risk].
A66: A8 | B66: Assume [enter project-specific client / principal supplied items and interfaces].
A67: EX-01 | B67: Exclude [enter explicit trade / scope exclusion].
A68: EX-02 | B68: Exclude [enter explicit commercial / abnormal-condition exclusion].
A70: PRICING QUALIFICATIONS / RFIs
A71: RFI-01 | B71: [enter missing / contradictory information, source reference, and quantity/cost/programme impact]
A72: RFI-02 | B72: [enter missing / contradictory information, source reference, and quantity/cost/programme impact]
A73: RFI-03 | B73: [enter missing / contradictory information, source reference, and quantity/cost/programme impact]
A74: RFI-04 | B74: [enter missing / contradictory information, source reference, and quantity/cost/programme impact]
A75: RFI-05 | B75: [enter missing / contradictory information, source reference, and quantity/cost/programme impact]
A76: RFI-06 | B76: [enter missing / contradictory information, source reference, and quantity/cost/programme impact]
A77: RFI-07 | B77: [enter missing / contradictory information, source reference, and quantity/cost/programme impact]
A78: RFI-08 | B78: [enter missing / contradictory information, source reference, and quantity/cost/programme impact]
A79: RFI-09 | B79: [enter missing / contradictory information, source reference, and quantity/cost/programme impact]
A80: RFI-10 | B80: [enter missing / contradictory information, source reference, and quantity/cost/programme impact]
A81: RFI-11 | B81: [enter missing / contradictory information, source reference, and quantity/cost/programme impact]
A82: RFI-12 | B82: [enter missing / contradictory information, source reference, and quantity/cost/programme impact]
A87: KEY RISKS / WATCHOUTS
A88: Risk ID | C88: Likelihood | D88: Impact | E88: Rating | F88: Allowance / Response | G88: Owner | H88: Status
A89: ='Risk Truth'!A25 -> 0 | B89: ='Risk Truth'!B25 -> 0 | C89: ='Risk Truth'!D25 -> 0 | D89: ='Risk Truth'!E25 -> 0 | E89: ='Risk Truth'!F25 -> 0 | F89: ='Risk Truth'!G25 -> 0 | G89: Estimator | H89: Open
A90: ='Risk Truth'!A26 -> 0 | B90: ='Risk Truth'!B26 -> 0 | C90: ='Risk Truth'!D26 -> 0 | D90: ='Risk Truth'!E26 -> 0 | E90: ='Risk Truth'!F26 -> 0 | F90: ='Risk Truth'!G26 -> 0 | G90: PM / QS | H90: Open
A91: ='Risk Truth'!A27 -> 0 | B91: ='Risk Truth'!B27 -> 0 | C91: ='Risk Truth'!D27 -> 0 | D91: ='Risk Truth'!E27 -> 0 | E91: ='Risk Truth'!F27 -> 0 | F91: ='Risk Truth'!G27 -> 0 | G91: Geotech / QS | H91: Open
A92: ='Risk Truth'!A28 -> 0 | B92: ='Risk Truth'!B28 -> 0 | C92: ='Risk Truth'!D28 -> 0 | D92: ='Risk Truth'!E28 -> 0 | E92: ='Risk Truth'!F28 -> 0 | F92: ='Risk Truth'!G28 -> 0 | G92: Site team | H92: Open
A93: ='Risk Truth'!A29 -> 0 | B93: ='Risk Truth'!B29 -> 0 | C93: ='Risk Truth'!D29 -> 0 | D93: ='Risk Truth'!E29 -> 0 | E93: ='Risk Truth'!F29 -> 0 | F93: ='Risk Truth'!G29 -> 0 | G93: QS | H93: Open
A94: ='Risk Truth'!A30 -> 0 | B94: ='Risk Truth'!B30 -> 0 | C94: ='Risk Truth'!D30 -> 0 | D94: ='Risk Truth'!E30 -> 0 | E94: ='Risk Truth'!F30 -> 0 | F94: ='Risk Truth'!G30 -> 0 | G94: Engineer / QS | H94: Open
A95: ='Risk Truth'!A31 -> 0 | B95: ='Risk Truth'!B31 -> 0 | C95: ='Risk Truth'!D31 -> 0 | D95: ='Risk Truth'!E31 -> 0 | E95: ='Risk Truth'!F31 -> 0 | F95: ='Risk Truth'!G31 -> 0 | G95: PM | H95: Open
A96: ='Risk Truth'!A32 -> 0 | B96: ='Risk Truth'!B32 -> 0 | C96: ='Risk Truth'!D32 -> 0 | D96: ='Risk Truth'!E32 -> 0 | E96: ='Risk Truth'!F32 -> 0 | F96: ='Risk Truth'!G32 -> 0 | G96: Geotech | H96: Open
A97: ='Risk Truth'!A33 -> 0 | B97: ='Risk Truth'!B33 -> 0 | C97: ='Risk Truth'!D33 -> 0 | D97: ='Risk Truth'!E33 -> 0 | E97: ='Risk Truth'!F33 -> 0 | F97: ='Risk Truth'!G33 -> 0 | G97: PM | H97: Open
A98: ='Risk Truth'!A34 -> 0 | B98: ='Risk Truth'!B34 -> 0 | C98: ='Risk Truth'!D34 -> 0 | D98: ='Risk Truth'!E34 -> 0 | E98: ='Risk Truth'!F34 -> 0 | F98: ='Risk Truth'!G34 -> 0 | G98: QS | H98: Open
A99: ='Risk Truth'!A35 -> 0 | B99: ='Risk Truth'!B35 -> 0 | C99: ='Risk Truth'!D35 -> 0 | D99: ='Risk Truth'!E35 -> 0 | E99: ='Risk Truth'!F35 -> 0 | F99: ='Risk Truth'!G35 -> 0
A100: TENDER RELEASE QA
A101: Section | D101: Owner | E101: Required Before Tender? | F101: Evidence / Reference | G101: Notes
A102: References | B102: Current Intake, Master Prompt, Triple Verification and applicable backend tools confirmed | C102: Not Started | D102: Estimator | E102: Yes | F102: Backend reference check
A103: Documents | B103: Current drawing/specification/tender register complete | C103: Not Started | D103: Estimator | E103: Yes | F103: Document register
A104: Scope | B104: Work-package inclusions, exclusions and interfaces defined | C104: Not Started | D104: Estimator | E104: Yes | F104: Scope / assumptions
A105: Takeoff | B105: Major quantities measured and referenced to current drawings/specs | C105: Not Started | D105: QS | E105: Yes | F105: QS Takeoff
A106: Resource build-up | B106: Every active QS code has linked labour/plant/material/subcontract resources | C106: Not Started | D106: Estimator | E106: Yes | F106: Resource Build-Up
A107: Rate verification | B107: Important rates and allowances classified and three-way verification reviewed | C107: Not Started | D107: Estimator | E107: Yes | F107: Rate Verification
A108: Quotes / PCs | B108: PC sums and quote-required packages reconciled to live project evidence | C108: Not Started | D108: Estimator | E108: Yes | F108: Rate Verification / quotes
A109: Assumptions | B109: Assumptions and exclusions are explicit, current and defensible | C109: Not Started | D109: Estimator | E109: Yes | F109: Cover & Instructions
A110: Interfaces | B110: By-others / client / authority / consultant responsibilities confirmed | C110: Not Started | D110: PM | E110: Yes | F110: Scope / RFIs
A111: Risk Truth | B111: All material risks have baseline, residual exposure and cost-treatment location | C111: Not Started | D111: Estimator | E111: Yes | F111: Risk Truth
A112: Risk duplication | B112: No residual risk is costed twice; overlap groups and cost-treatment owners reviewed | C112: Not Started | D112: Estimator | E112: Yes | F112: Risk Truth
A113: Weather | B113: Weather Risk reviewed; approved tool run current or documented N/A basis accepted | C113: Not Started | D113: Estimator | E113: Yes | F113: Weather Risk
...

Sheet Summary
A1: MASTER ESTIMATE WORKBOOK - ESTIMATE SUMMARY - REV3 RISK TRUTH
A2: Base direct costs are linked from Resource Build-Up through QS Takeoff. Commercial provisions are controlled through Commercial Inputs. CA01/CA02 default to Risk Truth, CA10 defaults to Weather Risk, and explicit PC Sum / % overrides remain visible and auditable.
A3: Project
A4: Location
A5: Drawing set
A6: Issue status | B6: MASTER TEMPLATE - not for issue until current project inputs and release gates are complete.
A7: Issue date | B7: 17-Aug-2026
A8: Source file
A9: Prepared
A10: Prepared by
A11: Scope basis
A12: Key Quantities
A13: Category | B13: Key item | C13: Quantity | D13: Unit | E13: Basis / note
A21: Pricing Summary (direct-cost estimate)
A22: Section | B22: Amount
A23: 1 Preliminaries & General | B23: ='Tender Build-Up'!B10 -> 0
A24: 2 Erosion & Sediment Control | B24: ='Tender Build-Up'!B11 -> 0
A25: 3 Earthworks | B25: ='Tender Build-Up'!B12 -> 0
A26: 4 Stormwater & Detention | B26: ='Tender Build-Up'!B13 -> 0
A27: 5 Wastewater & Water | B27: ='Tender Build-Up'!B14 -> 0
A28: 6 Pavements & Concrete | B28: ='Tender Build-Up'!B15 -> 0
A29: 7 Kerbs, Channels & External Sitework | B29: ='Tender Build-Up'!B16 -> 0
A30: 8 Retaining Walls | B30: ='Tender Build-Up'!B17 -> 0
A31: 9 Testing, As-Builts & Compliance | B31: ='Tender Build-Up'!B18 -> 0
A32: 10 Reinstatement & Handover | B32: ='Tender Build-Up'!B19 -> 0
A33: Total priced amount excl. GST | B33: ='Tender Build-Up'!B20 -> 0
A34: Pricing basis | B34: Resource-linked direct cost; specialist quote/PC rows are visible in Resource Build-Up.
A35: GST | B35: Resource-linked direct cost; current project PC/provisional/quoted items must be visible in Resource Build-Up and QS Takeoff.
A36: Scope | B36: Rates exclude GST unless the optional tax display is activated in Commercial Inputs.
A37: Accuracy | B37: Measured, provided, calculated, allowance/PC and quoted items must retain current source references and verification status.
A38: Programme basis | B38: Programme basis must reconcile working days, productive crew days, elapsed calendar duration, time-related costs and applicable Weather Risk outputs.
A39: Tender Completion Build-Up (client-adjustable commercial provisions)
A40: Purpose | B40: This block reflects Tender Build-Up and current Commercial Inputs selections.
A41: Input sheet | B41: Use Commercial Inputs to adjust allowances, overhead and profit method, bonds, retention finance and GST.
A43: Line
A44: Base direct estimate excl. GST | B44: ='Tender Build-Up'!B20 -> 0 | E44: QS direct-cost estimate
A45: Pre-margin additions | B45: ='Tender Build-Up'!B39 -> 0 | E45: Commercial Inputs CA01-CA16
A46: Commercial adjustments | B46: ='Tender Build-Up'!B46 -> 0
A47: Tender total excl. GST | B47: ='Tender Build-Up'!B47 -> 0
A48: GST if selected | B48: ='Tender Build-Up'!B48 -> 0 | E48: Optional display
A49: Tender total incl. GST if selected | B49: ='Tender Build-Up'!B49 -> 0 | E49: Optional tax-inclusive check
A50: Net pre-GST payment after retention | B50: ='Tender Build-Up'!B53 -> 0 | E50: Tender total less retention withholding after CA25 deposit treatment.
A51: Retention release after holding period | B51: ='Tender Build-Up'!B55 -> 0 | E51: Released after CA23 retention period; amount follows CA25 deposit retention treatment.
A52: Deposit / advance payment | B52: =IF('Commercial Inputs'!F28="Yes",'Tender Build-Up'!B47*'Commercial Inputs'!D28,0) -> 0 | E52: Part of tender total; controlled by CA24
A53: Stage cashflow tab | E53: Editable stage profile and cumulative cashflow
A56: COST CHAIN INTEGRITY
A57: Check | B57: Upstream | C57: Downstream | D57: Difference | E57: Status
A58: Resource Build-Up -> QS | B58: =SUM('Resource Build-Up'!$Z$7:$Z$306) -> 0 | C58: =SUM('QS Takeoff'!$G$3:$G$73) -> 0 | D58: =C58-B58 -> 0 | E58: =IF(ABS(D58)<0.01,"OK","CHECK") -> OK
A59: QS -> Tender Build-Up | B59: =SUM('QS Takeoff'!$G$3:$G$73) -> 0 | C59: ='Tender Build-Up'!$B$20 -> 0 | D59: =C59-B59 -> 0 | E59: =IF(ABS(D59)<0.01,"OK","CHECK") -> OK
A60: Tender Build-Up -> Summary | B60: ='Tender Build-Up'!$B$20 -> 0 | C60: =$B$33 -> 0 | D60: =C60-B60 -> 0 | E60: =IF(ABS(D60)<0.01,"OK","CHECK") -> OK
A61: Commercial Inputs -> Tender Build-Up | B61: =SUM('Tender Build-Up'!$B$23:$B$38)+SUM('Tender Build-Up'!$B$43:$B$45) -> 0 | C61: =$B$45+$B$46 -> 0 | D61: =C61-B61 -> 0 | E61: =IF(ABS(D61)<0.01,"OK","CHECK") -> OK
A62: Formula control | B62: Formula/output cells are edit-blocked with Stop validation; yellow cells are intended inputs.
A63: Release rule | B63: All chain checks must read OK before issue.
A64: Weather Risk -> Commercial Inputs CA10 | B64: ='Weather Risk'!$B$40 -> 0 | C64: ='Commercial Inputs'!$L$14 -> 0 | D64: =C64-B64 -> 0 | E64: =IF(ABS(D64)<0.01,"OK","CHECK") -> OK
A65: RATE & PROGRAMME QA RELEASE GATE
A66: Check | B66: Count / Amount | C66: Status | D66: Action
A67: GREEN active resource rows | B67: ='Rate Verification'!B4 -> 0 | C67: =IF(B67>0,"GREEN","NONE") -> NONE | D67: Three checks present
A68: AMBER active resource rows | B68: ='Rate Verification'!B5 -> 0 | C68: =IF(B68>0,"AMBER","NONE") -> NONE | D68: Disclose allowance and firm before award
A69: RED active resource rows | B69: ='Rate Verification'!F4 -> 0 | C69: =IF(B69>0,"RED","NONE") -> NONE | D69: Quote/design evidence required
A70: Programme task count | B70: 71 | D70: CSV matches one task per QS code
A71: Overall release | B71: =IF(OR(C73="RED",C74="RED",COUNTIF('Programme Export'!$U$7:$U$77,"CHECK")>0),"RED - release blocked",IF(B69>0,"AMBER - tender only / RED closeout required","GREEN - releasable")) -> RED - release blocked | D71: Tender issue only while RED items remain
A72: Weather model / task factors | B72: ='Weather Risk'!$B$30 -> RED - approved weather tool run not loaded | C72: AMBER | D72: Task factors remain AMBER until calibrated
A73: Weather integration rerun gate | B73: ='Weather Risk'!$B$31 -> RERUN WEATHER TOOL | C73: =IF(B73="RERUN WEATHER TOOL","RED","AMBER") -> RED | D73: Rerun when status says RERUN WEATHER TOOL
A74: Risk Truth release gate | B74: ='Risk Truth'!$B$15 -> HOLD - RED ITEMS / INTEGRATION CHECK | C74: =IF(LEFT(B74,4)="PASS","GREEN","RED") -> RED | D74: PASS required for final release
A75: Risk Truth recalculated tender total | B75: ='Risk Truth'!$B$11 -> 0 | C75: INFO | D75: Should equal the live tender total when Risk Truth feeds and commercial logic reconcile.

Sheet Tender Build-Up
A1: MASTER ESTIMATE WORKBOOK - TENDER BUILD-UP - REV2 RISK TRUTH
A3: Project
A4: Pricing status | B4: MASTER TEMPLATE - project-specific scope, quantities, rates, programme and commercial inputs not yet populated.
A5: GST | B5: Optional GST display via Commercial Inputs CA21.
A6: Retention | B6: Cashflow only by default.
A7: No direct-cost values are entered on this sheet. Base costs flow from QS Takeoff; commercial provisions flow from Commercial Inputs.
A9: Base direct estimate | B9: Amount excl. GST | C9: Source | D9: Treatment | E9: Notes
A10: Preliminaries & General | B10: =SUM('QS Takeoff'!G3:G12) -> 0 | C10: QS Takeoff | D10: Priced / provisional | E10: Linked QS section total; confirm current project scope, classification, source and firm-up action.
A11: Erosion & Sediment Control | B11: =SUM('QS Takeoff'!G13:G20) -> 0 | C11: QS Takeoff | D11: Priced / provisional | E11: Linked QS section total; confirm current project ESC scope and requirements.
A12: Earthworks | B12: =SUM('QS Takeoff'!G21:G30) -> 0 | C12: QS Takeoff | D12: Priced / provisional | E12: Linked QS section total; confirm current project quantities, ground basis, haul and disposal assumptions.
A13: Stormwater & Detention | B13: =SUM('QS Takeoff'!G31:G39) -> 0 | C13: QS Takeoff | D13: Priced / provisional | E13: Linked QS section total; confirm current project stormwater / detention design and supplier requirements.
A14: Wastewater & Water | B14: =SUM('QS Takeoff'!G40:G46) -> 0 | C14: QS Takeoff | D14: Priced / provisional | E14: Linked QS section total; confirm current project wastewater / water scope and authority interfaces.
A15: Pavements & Concrete | B15: =SUM('QS Takeoff'!G47:G52) -> 0 | C15: QS Takeoff | D15: Priced / provisional | E15: Linked QS section total; confirm current project pavement / concrete scope and specification.
A16: Kerbs, Channels & External Sitework | B16: =SUM('QS Takeoff'!G53:G61) -> 0 | C16: QS Takeoff | D16: Priced / provisional | E16: Linked QS section total; confirm current project kerb / external sitework scope.
A17: Retaining Walls | B17: =SUM('QS Takeoff'!G62:G67) -> 0 | C17: QS Takeoff | D17: Priced / provisional | E17: Linked QS section total; confirm current project retaining-wall design, quantities and temporary works.
A18: Testing, As-Builts & Compliance | B18: =SUM('QS Takeoff'!G68:G69) -> 0 | C18: QS Takeoff | D18: Priced / provisional | E18: Linked QS section total; confirm current testing, survey, as-built and compliance obligations.
A19: Reinstatement & Handover | B19: =SUM('QS Takeoff'!G70:G73) -> 0 | C19: QS Takeoff | D19: Priced / provisional | E19: Linked QS section total; confirm current reinstatement, defects and handover obligations.
A20: Base direct estimate excl. GST | B20: =SUM(B10:B19) -> 0 | D20: Subtotal | E20: Direct cost sourced from Resource Build-Up through QS Takeoff; includes measured, provisional, allowance and PC items.
A22: Pre-margin additions | B22: Calculated amount excl. GST | C22: Input source | D22: Include? | E22: Basis / Notes
A23: CA01 - Design / scope residual risk - Risk Truth | B23: =IF('Commercial Inputs'!$F$5<>"Yes",0,IF(OR('Commercial Inputs'!$C$5="Risk Engine",'Commercial Inputs'!$C$5="Weather Engine"),N('Commercial Inputs'!$L$5),IF('Commercial Inputs'!$C$5="PC Sum",N('Commercial Inputs'!$E$5),IF('Commercial Inputs'!$C$5="%",$B$20*N('Commercial Inputs'!$D$5),0)))) -> 0 | C23: ='Commercial Inputs'!C5 -> Risk Engine | D23: ='Commercial Inputs'!F5 -> Yes | E23: CA01 defaults to Risk Truth. PC Sum or % may be selected as a stated adjudication override; Include? controls whether the selected treatment enters the tender.
A24: CA02 - Construction / execution residual risk - Risk Truth | B24: =IF('Commercial Inputs'!$F$6<>"Yes",0,IF(OR('Commercial Inputs'!$C$6="Risk Engine",'Commercial Inputs'!$C$6="Weather Engine"),N('Commercial Inputs'!$L$6),IF('Commercial Inputs'!$C$6="PC Sum",N('Commercial Inputs'!$E$6),IF('Commercial Inputs'!$C$6="%",$B$20*N('Commercial Inputs'!$D$6),0)))) -> 0 | C24: ='Commercial Inputs'!C6 -> Risk Engine | D24: ='Commercial Inputs'!F6 -> Yes | E24: CA02 defaults to Risk Truth. PC Sum or % may be selected as a stated adjudication override; Include? controls whether the selected treatment enters the tender.
A25: ='Commercial Inputs'!A7&" - "&'Commercial Inputs'!B7 -> CA03 - Escalation / tender validity allowance | B25: =IF('Commercial Inputs'!$F$7<>"Yes",0,IF(OR('Commercial Inputs'!$C$7="Risk Engine",'Commercial Inputs'!$C$7="Weather Engine"),N('Commercial Inputs'!$L$7),IF('Commercial Inputs'!$C$7="PC Sum",N('Commercial Inputs'!$E$7),IF('Commercial Inputs'!$C$7="%",$B$20*N('Commercial Inputs'!$D$7),0)))) -> 0 | C25: ='Commercial Inputs'!C7 -> % | D25: ='Commercial Inputs'!F7 -> No | E25: ='Commercial Inputs'!I7 -> Enter only where escalation is evidence-based; do not default to a generic percentage.
A26: ='Commercial Inputs'!A8&" - "&'Commercial Inputs'!B8 -> CA04 - Final subcontractor quote gap / market adjustment | B26: =IF('Commercial Inputs'!$F$8<>"Yes",0,IF(OR('Commercial Inputs'!$C$8="Risk Engine",'Commercial Inputs'!$C$8="Weather Engine"),N('Commercial Inputs'!$L$8),IF('Commercial Inputs'!$C$8="PC Sum",N('Commercial Inputs'!$E$8),IF('Commercial Inputs'!$C$8="%",$B$20*N('Commercial Inputs'!$D$8),0)))) -> 0 | C26: ='Commercial Inputs'!C8 -> PC Sum | D26: ='Commercial Inputs'!F8 -> No | E26: ='Commercial Inputs'!I8 -> Use only for a distinct reconciled live-quote gap not already included in QS/PC items or Risk Truth.
A27: ='Commercial Inputs'!A9&" - "&'Commercial Inputs'!B9 -> CA05 - Council / authority consent and inspection fees | B27: =IF('Commercial Inputs'!$F$9<>"Yes",0,IF(OR('Commercial Inputs'!$C$9="Risk Engine",'Commercial Inputs'!$C$9="Weather Engine"),N('Commercial Inputs'!$L$9),IF('Commercial Inputs'!$C$9="PC Sum",N('Commercial Inputs'!$E$9),IF('Commercial Inputs'!$C$9="%",$B$20*N('Commercial Inputs'!$D$9),0)))) -> 0 | C27: ='Commercial Inputs'!C9 -> PC Sum | D27: ='Commercial Inputs'!F9 -> No | E27: ='Commercial Inputs'!I9 -> Confirm contractual responsibility before inclusion.
A28: ='Commercial Inputs'!A10&" - "&'Commercial Inputs'!B10 -> CA06 - Utility authority fees / relocations | B28: =IF('Commercial Inputs'!$F$10<>"Yes",0,IF(OR('Commercial Inputs'!$C$10="Risk Engine",'Commercial Inputs'!$C$10="Weather Engine"),N('Commercial Inputs'!$L$10),IF('Commercial Inputs'!$C$10="PC Sum",N('Commercial Inputs'!$E$10),IF('Commercial Inputs'!$C$10="%",$B$20*N('Commercial Inputs'!$D$10),0)))) -> 0 | C28: ='Commercial Inputs'!C10 -> PC Sum | D28: ='Commercial Inputs'!F10 -> No | E28: ='Commercial Inputs'!I10 -> Confirm contractual responsibility; physical construction scope should normally sit in QS.
A29: ='Commercial Inputs'!A11&" - "&'Commercial Inputs'!B11 -> CA07 - Temporary works engineering / PS documentation | B29: =IF('Commercial Inputs'!$F$11<>"Yes",0,IF(OR('Commercial Inputs'!$C$11="Risk Engine",'Commercial Inputs'!$C$11="Weather Engine"),N('Commercial Inputs'!$L$11),IF('Commercial Inputs'!$C$11="PC Sum",N('Commercial Inputs'!$E$11),IF('Commercial Inputs'!$C$11="%",$B$20*N('Commercial Inputs'!$D$11),0)))) -> 0 | C29: ='Commercial Inputs'!C11 -> PC Sum | D29: ='Commercial Inputs'!F11 -> No | E29: ='Commercial Inputs'!I11 -> Use only for temporary-works engineering / documentation not already in direct scope.
A30: CA08 - Abnormal ground / contamination / rock allowance | B30: =IF('Commercial Inputs'!$F$12<>"Yes",0,IF(OR('Commercial Inputs'!$C$12="Risk Engine",'Commercial Inputs'!$C$12="Weather Engine"),N('Commercial Inputs'!$L$12),IF('Commercial Inputs'!$C$12="PC Sum",N('Commercial Inputs'!$E$12),IF('Commercial Inputs'!$C$12="%",$B$20*N('Commercial Inputs'!$D$12),0)))) -> 0 | C30: ='Commercial Inputs'!C12 -> PC Sum | D30: ='Commercial Inputs'!F12 -> No | E30: No generic ground percentage. Use only an explicit evidence-based provision not more truthfully placed in QS or a specialist engine.
A31: ='Commercial Inputs'!A13&" - "&'Commercial Inputs'!B13 -> CA09 - Construction dewatering / groundwater control | B31: =IF('Commercial Inputs'!$F$13<>"Yes",0,IF(OR('Commercial Inputs'!$C$13="Risk Engine",'Commercial Inputs'!$C$13="Weather Engine"),N('Commercial Inputs'!$L$13),IF('Commercial Inputs'!$C$13="PC Sum",N('Commercial Inputs'!$E$13),IF('Commercial Inputs'!$C$13="%",$B$20*N('Commercial Inputs'!$D$13),0)))) -> 0 | C31: ='Commercial Inputs'!C13 -> PC Sum | D31: ='Commercial Inputs'!F13 -> No | E31: Project-specific construction water-control provision only; check overlap with Weather / Ground risk treatment.
A32: ='Commercial Inputs'!A14&" - "&'Commercial Inputs'!B14 -> CA10 - Weather risk allowance - linked approved engine | B32: =IF('Commercial Inputs'!$F$14<>"Yes",0,IF(OR('Commercial Inputs'!$C$14="Risk Engine",'Commercial Inputs'!$C$14="Weather Engine"),N('Commercial Inputs'!$L$14),IF('Commercial Inputs'!$C$14="PC Sum",N('Commercial Inputs'!$E$14),IF('Commercial Inputs'!$C$14="%",$B$20*N('Commercial Inputs'!$D$14),0)))) -> 0 | C32: ='Commercial Inputs'!C14 -> Weather Engine | D32: ='Commercial Inputs'!F14 -> Yes | E32: CA10 defaults to Weather Engine. PC Sum or % may be selected explicitly; Include? can turn the weather allowance off while the engine output remains retained for audit.
A33: ='Commercial Inputs'!A15&" - "&'Commercial Inputs'!B15 -> CA11 - Extended preliminaries beyond weather-adjusted tender baseline | B33: =IF('Commercial Inputs'!$F$15<>"Yes",0,IF(OR('Commercial Inputs'!$C$15="Risk Engine",'Commercial Inputs'!$C$15="Weather Engine"),N('Commercial Inputs'!$L$15),IF('Commercial Inputs'!$C$15="PC Sum",N('Commercial Inputs'!$E$15),IF('Commercial Inputs'!$C$15="%",$B$20*N('Commercial Inputs'!$D$15),0)))) -> 0 | C33: ='Commercial Inputs'!C15 -> PC Sum | D33: ='Commercial Inputs'!F15 -> No | E33: ='Commercial Inputs'!I15 -> Do not use for weather delay already included through CA10. Base QS preliminaries remain reconciled to 99 working days.
A34: ='Commercial Inputs'!A16&" - "&'Commercial Inputs'!B16 -> CA12 - Defects liability / maintenance beyond base | B34: =IF('Commercial Inputs'!$F$16<>"Yes",0,IF(OR('Commercial Inputs'!$C$16="Risk Engine",'Commercial Inputs'!$C$16="Weather Engine"),N('Commercial Inputs'!$L$16),IF('Commercial Inputs'!$C$16="PC Sum",N('Commercial Inputs'!$E$16),IF('Commercial Inputs'!$C$16="%",$B$20*N('Commercial Inputs'!$D$16),0)))) -> 0 | C34: ='Commercial Inputs'!C16 -> PC Sum | D34: ='Commercial Inputs'!F16 -> No | E34: ='Commercial Inputs'!I16 -> Reasonable defects attendance included under RH02.
A35: ='Commercial Inputs'!A17&" - "&'Commercial Inputs'!B17 -> CA13 - Stakeholder liaison / access marshals beyond base | B35: =IF('Commercial Inputs'!$F$17<>"Yes",0,IF(OR('Commercial Inputs'!$C$17="Risk Engine",'Commercial Inputs'!$C$17="Weather Engine"),N('Commercial Inputs'!$L$17),IF('Commercial Inputs'!$C$17="PC Sum",N('Commercial Inputs'!$E$17),IF('Commercial Inputs'!$C$17="%",$B$20*N('Commercial Inputs'!$D$17),0)))) -> 0 | C35: ='Commercial Inputs'!C17 -> PC Sum | D35: ='Commercial Inputs'!F17 -> No | E35: ='Commercial Inputs'!I17 -> Basic traffic/pedestrian management included in PG07.
A36: ='Commercial Inputs'!A18&" - "&'Commercial Inputs'!B18 -> CA14 - Out-of-hours / restricted access premium | B36: =IF('Commercial Inputs'!$F$18<>"Yes",0,IF(OR('Commercial Inputs'!$C$18="Risk Engine",'Commercial Inputs'!$C$18="Weather Engine"),N('Commercial Inputs'!$L$18),IF('Commercial Inputs'!$C$18="PC Sum",N('Commercial Inputs'!$E$18),IF('Commercial Inputs'!$C$18="%",$B$20*N('Commercial Inputs'!$D$18),0)))) -> 0 | C36: ='Commercial Inputs'!C18 -> PC Sum | D36: ='Commercial Inputs'!F18 -> No | E36: ='Commercial Inputs'!I18 -> Normal weekday access assumed.
A37: ='Commercial Inputs'!A19&" - "&'Commercial Inputs'!B19 -> CA15 - Unforeseen post-tender client scope additions | B37: =IF('Commercial Inputs'!$F$19<>"Yes",0,IF(OR('Commercial Inputs'!$C$19="Risk Engine",'Commercial Inputs'!$C$19="Weather Engine"),N('Commercial Inputs'!$L$19),IF('Commercial Inputs'!$C$19="PC Sum",N('Commercial Inputs'!$E$19),IF('Commercial Inputs'!$C$19="%",$B$20*N('Commercial Inputs'!$D$19),0)))) -> 0 | C37: ='Commercial Inputs'!C19 -> PC Sum | D37: ='Commercial Inputs'!F19 -> No | E37: ='Commercial Inputs'!I19 -> No allowance for later scope changes.
A38: ='Commercial Inputs'!A20&" - "&'Commercial Inputs'!B20 -> CA16 - Final tender rounding / adjudication adjustment | B38: =IF('Commercial Inputs'!$F$20<>"Yes",0,IF(OR('Commercial Inputs'!$C$20="Risk Engine",'Commercial Inputs'!$C$20="Weather Engine"),N('Commercial Inputs'!$L$20),IF('Commercial Inputs'!$C$20="PC Sum",N('Commercial Inputs'!$E$20),IF('Commercial Inputs'!$C$20="%",$B$20*N('Commercial Inputs'!$D$20),0)))) -> 0 | C38: ='Commercial Inputs'!C20 -> PC Sum | D38: ='Commercial Inputs'!F20 -> No | E38: ='Commercial Inputs'!I20 -> No balancing adjustment applied.
A39: Pre-margin additions subtotal | B39: =SUM(B23:B38) -> 0
A40: Subtotal before commercial adjustments | B40: =B20+B39 -> 0
A41: Overhead, profit and other commercial adjustments | B41: Calculated amount excl. GST | C41: Input source | D41: Include? | E41: Basis / Notes
A42: ='Commercial Inputs'!A21&" - "&'Commercial Inputs'!B21 -> CA17 - Company overhead recovery | B42: =IF('Commercial Inputs'!$F$21<>"Yes",0,IF('Commercial Inputs'!$C$21="Markup %",$B$40*N('Commercial Inputs'!$D$21),IF('Commercial Inputs'!$C$21="Fixed Amount",N('Commercial Inputs'!$E$21),0))) -> 0 | C42: ='Commercial Inputs'!C21 -> Markup % | D42: ='Commercial Inputs'!F21 -> No | E42: ='Commercial Inputs'!I21 -> Enter verified company overhead recovery separately from contractor profit.
A43: ='Commercial Inputs'!A22&" - "&'Commercial Inputs'!B22 -> CA18 - Contractor profit | B43: =IF('Commercial Inputs'!$F$22<>"Yes",0,IF('Commercial Inputs'!$C$22="Margin %",($B$40+$B$42+$B$44+$B$45)/(1-N('Commercial Inputs'!$D$22))-($B$40+$B$42+$B$44+$B$45),IF('Commercial Inputs'!$C$22="Markup %",($B$40+$B$42+$B$44+$B$45)*N('Commercial Inputs'!$D$22),IF('Commercial Inputs'!$C$22="Fixed Amount",N('Commercial Inputs'!$E$22),0)))) -> 0 | C43: ='Commercial Inputs'!C22 -> Margin % | D43: ='Commercial Inputs'!F22 -> No | E43: ='Commercial Inputs'!I22 -> Enter approved contractor profit; choose Margin or Markup in the profit-method selector.
A44: ='Commercial Inputs'!A23&" - "&'Commercial Inputs'!B23 -> CA19 - Bonds / contract securities allowance | B44: =IF('Commercial Inputs'!$F$23<>"Yes",0,IF('Commercial Inputs'!$C$23="%",$B$40*N('Commercial Inputs'!$D$23),IF('Commercial Inputs'!$C$23="PC Sum",N('Commercial Inputs'!$E$23),0))) -> 0 | C44: ='Commercial Inputs'!C23 -> % | D44: ='Commercial Inputs'!F23 -> No | E44: ='Commercial Inputs'!I23 -> Include only where contract securities create a genuine contractor cost.
A45: ='Commercial Inputs'!A24&" - "&'Commercial Inputs'!B24 -> CA20 - Retention finance / cashflow cost allowance | B45: =IF('Commercial Inputs'!$F$24<>"Yes",0,IF('Commercial Inputs'!$C$24="%",$B$40*N('Commercial Inputs'!$D$24),IF('Commercial Inputs'!$C$24="PC Sum",N('Commercial Inputs'!$E$24),0))) -> 0 | C45: ='Commercial Inputs'!C24 -> % | D45: ='Commercial Inputs'!F24 -> No | E45: ='Commercial Inputs'!I24 -> Finance cost only; retention withholding itself is a cashflow item.
A46: Commercial adjustments subtotal | B46: =SUM(B42:B45) -> 0
A47: Tender total excl. GST | B47: =B40+B46 -> 0 | D47: Subtotal | E47: Base direct estimate + selected pre-margin additions + commercial adjustments.
A48: GST if selected | B48: =IF('Commercial Inputs'!$F$25="Yes",$B$47*N('Commercial Inputs'!$D$25),0) -> 0 | C48: Commercial Inputs CA21 | D48: Optional | E48: GST applies only when CA21 Include? is Yes.
A49: Tender total incl. GST if selected | B49: =B47+B48 -> 0 | D49: Subtotal | E49: For GST-inclusive check only.
A51: Cashflow / contract security visibility only | B51: Calculated value | C51: Input source | D51: Include? | E51: Notes
A52: Contract retention withholding | B52: =IF('Commercial Inputs'!$F$26<>"Yes",0,$B$47*'Commercial Inputs'!$D$26*(1-IF(AND('Commercial Inputs'!$F$28="Yes",'Commercial Inputs'!$F$29<>"Yes"),'Commercial Inputs'!$D$28,0))) -> 0 | C52: Commercial Inputs CA22 | D52: Cashflow only | E52: Retention withholding on retention-applicable contract value; deposit treatment controlled by CA25.
A53: Net pre-GST payment after retention | B53: =$B$47-$B$52 -> 0 | C53: Calculated | D53: Cashflow only | E53: Tender total excl. GST less current retention withholding.
A54: Retention holding period | B54: =IF('Commercial Inputs'!$F$27="Yes",'Commercial Inputs'!$D$27,0) -> 0 | C54: Commercial Inputs CA23 | D54: Cashflow only | E54: Months from practical completion unless contract states otherwise.
A55: Retention released after holding period | B55: =$B$52 -> 0 | C55: Calculated | D55: Cashflow only | E55: Equals current retention withholding; released after the CA23 holding period.
A56: Total pre-GST receipts including retention release | B56: =$B$53+$B$55 -> 0 | C56: Calculated | D56: Cashflow only | E56: Equals tender total excl. GST.
A58: Stage payment cashflow

Sheet Commercial Inputs
A1: COMMERCIAL INPUTS - BELOW-THE-LINE SOURCE OF TRUTH | H1: Profit method | I1: =C22 -> Margin %
H2: CA18 method (linked) | I2: =IF(C22="Margin %","Margin",IF(C22="Markup %","Markup",IF(C22="Fixed Amount","Fixed Amount",C22))) -> Margin | J2: The calculation method is selected in column C. There is no second profit-method selector.
A3: CA01/CA02: Risk Engine, PC Sum or %. CA10: Weather Engine, PC Sum or %. Other pre-margin allowances: PC Sum or %. Column F Include? is the on/off switch. Engine outputs remain live in column L even when another method is selected, preserving the audit trail.
A4: Ref | B4: Allowance / adjustment | C4: Input method | D4: Input % | E4: PC Sum excl. GST | F4: Include? | G4: Pricing stage | H4: Calculation / treatment | I4: Notes / basis | J4: Firm-up action | K4: Pricing method / flag shown in QS | L4: Engine Amount excl. GST | M4: Engine Source / Status
A5: CA01 | B5: Design / scope residual risk - Risk Truth linked | C5: Risk Engine | F5: Yes | G5: Pre-margin addition | H5: =IF(C5="Risk Engine","Uses linked Risk Truth engine amount in L5",IF(C5="Weather Engine","Uses linked Weather Risk amount in L5",IF(C5="PC Sum","Uses manual PC Sum in E5",IF(C5="%","Uses Input % in D5 against base direct cost","CHECK METHOD")))) -> Uses linked Risk Truth engine amount in L5 | I5: Residual design/scope risk only where the consequence cannot be more truthfully placed in Resource Build-Up/QS or a specialist engine. | J5: Close Risk Truth RED items and confirm residual is distinct / integration complete. | K5: =IF(F5<>"Yes",C5&" - OFF",C5) -> Risk Engine | L5: ='Risk Truth'!$B$12 -> 0 | M5: Risk Truth CA01 design/scope residual
A6: CA02 | B6: Construction / execution residual risk - Risk Truth linked | C6: Risk Engine | F6: Yes | G6: Pre-margin addition | H6: =IF(C6="Risk Engine","Uses linked Risk Truth engine amount in L6",IF(C6="Weather Engine","Uses linked Weather Risk amount in L6",IF(C6="PC Sum","Uses manual PC Sum in E6",IF(C6="%","Uses Input % in D6 against base direct cost","CHECK METHOD")))) -> Uses linked Risk Truth engine amount in L6 | I6: Residual construction/execution risk only where the consequence cannot be more truthfully placed in Resource Build-Up/QS or a specialist engine. | J6: Close Risk Truth RED items and confirm residual is distinct / integration complete. | K6: =IF(F6<>"Yes",C6&" - OFF",C6) -> Risk Engine | L6: ='Risk Truth'!$B$13 -> 0 | M6: Risk Truth CA02 construction/execution residual
A7: CA03 | B7: Escalation / tender validity allowance | C7: % | D7: 0 | F7: No | G7: Pre-margin addition | H7: =IF(C7="Risk Engine","Uses linked Risk Truth engine amount in L7",IF(C7="Weather Engine","Uses linked Weather Risk amount in L7",IF(C7="PC Sum","Uses manual PC Sum in E7",IF(C7="%","Uses Input % in D7 against base direct cost","CHECK METHOD")))) -> Uses Input % in D7 against base direct cost | I7: Enter only where escalation is evidence-based; do not default to a generic percentage. | J7: Confirm construction start and validity. | K7: =IF(F7<>"Yes",C7&" - OFF",C7) -> % - OFF | L7: 0 | M7: No specialist engine linked - select PC Sum or %
A8: CA04 | B8: Final subcontractor quote gap / market adjustment | C8: PC Sum | F8: No | G8: Pre-margin addition | H8: =IF(C8="Risk Engine","Uses linked Risk Truth engine amount in L8",IF(C8="Weather Engine","Uses linked Weather Risk amount in L8",IF(C8="PC Sum","Uses manual PC Sum in E8",IF(C8="%","Uses Input % in D8 against base direct cost","CHECK METHOD")))) -> Uses manual PC Sum in E8 | I8: Use only for a distinct reconciled live-quote gap not already included in QS/PC items or Risk Truth. | J8: Reconcile tank, walls and connections. | K8: =IF(F8<>"Yes",C8&" - OFF",C8) -> PC Sum - OFF | L8: 0 | M8: No specialist engine linked - select PC Sum or %
A9: CA05 | B9: Council / authority consent and inspection fees | C9: PC Sum | F9: No | G9: Pre-margin addition | H9: =IF(C9="Risk Engine","Uses linked Risk Truth engine amount in L9",IF(C9="Weather Engine","Uses linked Weather Risk amount in L9",IF(C9="PC Sum","Uses manual PC Sum in E9",IF(C9="%","Uses Input % in D9 against base direct cost","CHECK METHOD")))) -> Uses manual PC Sum in E9 | I9: Confirm contractual responsibility before inclusion. | J9: Confirm fee responsibility. | K9: =IF(F9<>"Yes",C9&" - OFF",C9) -> PC Sum - OFF | L9: 0 | M9: No specialist engine linked - select PC Sum or %
A10: CA06 | B10: Utility authority fees / relocations | C10: PC Sum | F10: No | G10: Pre-margin addition | H10: =IF(C10="Risk Engine","Uses linked Risk Truth engine amount in L10",IF(C10="Weather Engine","Uses linked Weather Risk amount in L10",IF(C10="PC Sum","Uses manual PC Sum in E10",IF(C10="%","Uses Input % in D10 against base direct cost","CHECK METHOD")))) -> Uses manual PC Sum in E10 | I10: Confirm contractual responsibility; physical construction scope should normally sit in QS. | J10: Confirm utilities. | K10: =IF(F10<>"Yes",C10&" - OFF",C10) -> PC Sum - OFF | L10: 0 | M10: No specialist engine linked - select PC Sum or %
A11: CA07 | B11: Temporary works engineering / PS documentation | C11: PC Sum | F11: No | G11: Pre-margin addition | H11: =IF(C11="Risk Engine","Uses linked Risk Truth engine amount in L11",IF(C11="Weather Engine","Uses linked Weather Risk amount in L11",IF(C11="PC Sum","Uses manual PC Sum in E11",IF(C11="%","Uses Input % in D11 against base direct cost","CHECK METHOD")))) -> Uses manual PC Sum in E11 | I11: Use only for temporary-works engineering / documentation not already in direct scope. | J11: Avoid duplication. | K11: =IF(F11<>"Yes",C11&" - OFF",C11) -> PC Sum - OFF | L11: 0 | M11: No specialist engine linked - select PC Sum or %
A12: CA08 | B12: Abnormal ground / contamination / rock allowance | C12: PC Sum | D12: 0 | F12: No | G12: Pre-margin addition | H12: =IF(C12="Risk Engine","Uses linked Risk Truth engine amount in L12",IF(C12="Weather Engine","Uses linked Weather Risk amount in L12",IF(C12="PC Sum","Uses manual PC Sum in E12",IF(C12="%","Uses Input % in D12 against base direct cost","CHECK METHOD")))) -> Uses manual PC Sum in E12 | I12: Do not use as a generic ground-risk percentage. Quantifiable ground consequences belong in QS or an approved specialist risk treatment. | J12: Review geotech/contamination data. | K12: =IF(F12<>"Yes",C12&" - OFF",C12) -> PC Sum - OFF | L12: 0 | M12: No specialist engine linked - select PC Sum or %
A13: CA09 | B13: Construction dewatering / groundwater control | C13: PC Sum | F13: No | G13: Pre-margin addition | H13: =IF(C13="Risk Engine","Uses linked Risk Truth engine amount in L13",IF(C13="Weather Engine","Uses linked Weather Risk amount in L13",IF(C13="PC Sum","Uses manual PC Sum in E13",IF(C13="%","Uses Input % in D13 against base direct cost","CHECK METHOD")))) -> Uses manual PC Sum in E13 | I13: Project-specific construction water-control allowance only; check Weather / Ground overlap before inclusion. | J13: Confirm methodology/groundwater. | K13: =IF(F13<>"Yes",C13&" - OFF",C13) -> PC Sum - OFF | L13: 0 | M13: No specialist engine linked - select PC Sum or %
A14: CA10 | B14: Weather risk allowance - linked approved engine | C14: Weather Engine | F14: Yes | G14: Pre-margin addition | H14: =IF(C14="Risk Engine","Uses linked Risk Truth engine amount in L14",IF(C14="Weather Engine","Uses linked Weather Risk amount in L14",IF(C14="PC Sum","Uses manual PC Sum in E14",IF(C14="%","Uses Input % in D14 against base direct cost","CHECK METHOD")))) -> Uses linked Weather Risk amount in L14 | I14: Formula-linked approved Weather Risk output. Do not duplicate normal weather in CA02 or direct productivity. | J14: Rerun Weather Tool if start date, baseline duration, exposed resource cost/mix, work calendar or critical path changes. | K14: =IF(F14<>"Yes",C14&" - OFF",C14) -> Weather Engine | L14: ='Weather Risk'!$B$40 -> 0 | M14: Weather Risk specialist engine -> CA10
A15: CA11 | B15: Extended preliminaries beyond weather-adjusted tender baseline | C15: PC Sum | F15: No | G15: Pre-margin addition | H15: =IF(C15="Risk Engine","Uses linked Risk Truth engine amount in L15",IF(C15="Weather Engine","Uses linked Weather Risk amount in L15",IF(C15="PC Sum","Uses manual PC Sum in E15",IF(C15="%","Uses Input % in D15 against base direct cost","CHECK METHOD")))) -> Uses manual PC Sum in E15 | I15: Do not use for weather delay already included through CA10. Base QS preliminaries remain reconciled to 99 working days. | J15: Add only for non-weather instructed extension or revised contract programme after checking CA10 overlap. | K15: =IF(F15<>"Yes",C15&" - OFF",C15) -> PC Sum - OFF | L15: 0 | M15: No specialist engine linked - select PC Sum or %
A16: CA12 | B16: Defects liability / maintenance beyond base | C16: PC Sum | F16: No | G16: Pre-margin addition | H16: =IF(C16="Risk Engine","Uses linked Risk Truth engine amount in L16",IF(C16="Weather Engine","Uses linked Weather Risk amount in L16",IF(C16="PC Sum","Uses manual PC Sum in E16",IF(C16="%","Uses Input % in D16 against base direct cost","CHECK METHOD")))) -> Uses manual PC Sum in E16 | I16: Reasonable defects attendance included under RH02. | J16: Confirm special maintenance obligations. | K16: =IF(F16<>"Yes",C16&" - OFF",C16) -> PC Sum - OFF | L16: 0 | M16: No specialist engine linked - select PC Sum or %
A17: CA13 | B17: Stakeholder liaison / access marshals beyond base | C17: PC Sum | F17: No | G17: Pre-margin addition | H17: =IF(C17="Risk Engine","Uses linked Risk Truth engine amount in L17",IF(C17="Weather Engine","Uses linked Weather Risk amount in L17",IF(C17="PC Sum","Uses manual PC Sum in E17",IF(C17="%","Uses Input % in D17 against base direct cost","CHECK METHOD")))) -> Uses manual PC Sum in E17 | I17: Basic traffic/pedestrian management included in PG07. | J17: Confirm restricted operations. | K17: =IF(F17<>"Yes",C17&" - OFF",C17) -> PC Sum - OFF | L17: 0 | M17: No specialist engine linked - select PC Sum or %
A18: CA14 | B18: Out-of-hours / restricted access premium | C18: PC Sum | F18: No | G18: Pre-margin addition | H18: =IF(C18="Risk Engine","Uses linked Risk Truth engine amount in L18",IF(C18="Weather Engine","Uses linked Weather Risk amount in L18",IF(C18="PC Sum","Uses manual PC Sum in E18",IF(C18="%","Uses Input % in D18 against base direct cost","CHECK METHOD")))) -> Uses manual PC Sum in E18 | I18: Normal weekday access assumed. | J18: Confirm work windows. | K18: =IF(F18<>"Yes",C18&" - OFF",C18) -> PC Sum - OFF | L18: 0 | M18: No specialist engine linked - select PC Sum or %
A19: CA15 | B19: Unforeseen post-tender client scope additions | C19: PC Sum | F19: No | G19: Pre-margin addition | H19: =IF(C19="Risk Engine","Uses linked Risk Truth engine amount in L19",IF(C19="Weather Engine","Uses linked Weather Risk amount in L19",IF(C19="PC Sum","Uses manual PC Sum in E19",IF(C19="%","Uses Input % in D19 against base direct cost","CHECK METHOD")))) -> Uses manual PC Sum in E19 | I19: No allowance for later scope changes. | J19: Include only if instructed. | K19: =IF(F19<>"Yes",C19&" - OFF",C19) -> PC Sum - OFF | L19: 0 | M19: No specialist engine linked - select PC Sum or %
A20: CA16 | B20: Final tender rounding / adjudication adjustment | C20: PC Sum | F20: No | G20: Pre-margin addition | H20: =IF(C20="Risk Engine","Uses linked Risk Truth engine amount in L20",IF(C20="Weather Engine","Uses linked Weather Risk amount in L20",IF(C20="PC Sum","Uses manual PC Sum in E20",IF(C20="%","Uses Input % in D20 against base direct cost","CHECK METHOD")))) -> Uses manual PC Sum in E20 | I20: No balancing adjustment applied. | J20: Use only at approved adjudication. | K20: =IF(F20<>"Yes",C20&" - OFF",C20) -> PC Sum - OFF | L20: 0 | M20: No specialist engine linked - select PC Sum or %
A21: CA17 | B21: Company overhead recovery | C21: Markup % | D21: 0 | F21: No | G21: Commercial adjustment | H21: Markup applied to cost subtotal before profit | I21: Enter verified company overhead recovery separately from contractor profit. | J21: Jason to enter the verified company overhead recovery rate. | K21: % user input provision
A22: CA18 | B22: Contractor profit | C22: Margin % | D22: 0 | F22: No | G22: Commercial adjustment | H22: Selectable true margin or markup after overhead and other commercial costs | I22: Enter approved contractor profit; choose Margin or Markup in the profit-method selector. | J22: Confirm the target profit and calculation method at adjudication. | K22: % user input provision
A23: CA19 | B23: Bonds / contract securities allowance | C23: % | D23: 0 | F23: No | G23: Commercial adjustment | H23: Applied if selected | I23: Include only where contract securities create a genuine contractor cost. | J23: Confirm security terms. | K23: % user input provision
A24: CA20 | B24: Retention finance / cashflow cost allowance | C24: % | D24: 0 | F24: No | G24: Commercial adjustment | H24: Applied if selected | I24: Finance cost only; retention withholding itself is a cashflow item. | J24: Confirm retention terms. | K24: % user input provision
A25: CA21 | B25: GST | C25: % | D25: 0.15 | F25: No | G25: Tax | H25: Applied to tender total if selected | I25: Optional tax display. Set 15% for NZ GST or 10% for Australian GST when applicable; estimate control total remains ex tax. | J25: Confirm submission format. | K25: % user input provision
A26: CA22 | B26: Contract retention withholding | C26: % | D26: 0 | F26: No | G26: Cashflow only | H26: Visibility only | I26: Not added to tender price. | J26: Confirm retention cap/terms. | K26: User input
A27: CA23 | B27: Retention holding period | C27: Months | D27: 0 | F27: No | G27: Cashflow only | H27: Times retention release | I27: Assumed 12 months. | J27: Confirm contract. | K27: % user input provision
A28: CA24 | B28: Deposit / advance payment | C28: % | D28: 0 | F28: No | G28: Cashflow only | H28: Part of tender value | I28: Used as first cashflow stage. | J28: Confirm whether permitted. | K28: User selection
A29: CA25 | B29: Retention applies to deposit | C29: Selection | F29: No | G29: Cashflow only | H29: Yes/No selection | I29: Normally No. | J29: Confirm contract.
A30: Notes
A31: 1 | B31: Leave Include? as No for any provision that is not to be included. Enter Input % or PC Sum depending on the intended basis; PC Sum overrides % where populated.
A32: 2 | B32: Retentions are included as cashflow/security visibility only. They do not increase the tender price unless CA20 retention finance/cashflow cost is included.
A33: 3 | B33: The deposit and stage cashflow are portions of the tender total, not additional revenue. Stage percentages must total 100%.

Sheet QS Takeoff
A1: QS TAKEOFF - MASTER ESTIMATE WORKBOOK REV2 - RESOURCE-LINKED | L1: Rate and Amount are linked from Resource Build-Up. Change scope/quantity here; change cost resources in Resource Build-Up.
A2: Civil Scope / WBS | B2: Code | C2: Description | D2: Unit | E2: Quantity | F2: Rate excl. GST | G2: Amount excl. GST | H2: Quantity Basis | I2: Source drawing / scope | J2: Status | K2: Notes / Assumptions | L2: Pricing Method | M2: Pricing Basis / Build-up | N2: Source Type | O2: Source URL(s) | P2: Pricing Flag | Q2: Confidence / Firm-up Action | R2: Owner | S2: Verification Status | T2: Quote / Reference
F3: =IF(OR(B3="",E3=0),0,G3/E3) -> 0 | G3: =IF(B3="",0,SUMIF('Resource Build-Up'!$B$7:$B$306,B3,'Resource Build-Up'!$Z$7:$Z$306)) -> 0 | L3: =IF(B3="","",IF(J3="Excluded","Excluded","Resource-linked")) | M3: =IF(B3="","",IF(G3=0,"No resource cost / review","Resource Build-Up -> "&B3)) | N3: =IF(B3="","","Resource Build-Up") | O3: =IF(B3="","","See Resource Build-Up / Resource Rate Library") | P3: =IF(B3="","",IF(COUNTIF('Resource Build-Up'!$B$7:$B$306,B3)=0,IF(G3=0,"ZERO / REVIEW","NO RESOURCE"),"RESOURCE LINKED")) | R3: =IF(OR(ISNUMBER(SEARCH("PC",P3)),ISNUMBER(SEARCH("quote",Q3))),"Jason","Rick") -> Rick | S3: =IF(B3="","",IF(COUNTIF('Resource Build-Up'!$B$7:$B$306,B3)=0,"NO RESOURCE",IF(COUNTIFS('Resource Build-Up'!$B$7:$B$306,B3,'Resource Build-Up'!$AI$7:$AI$306,"<>OK")>0,"RESOURCE QA","LINKED")))
F4: =IF(OR(B4="",E4=0),0,G4/E4) -> 0 | G4: =IF(B4="",0,SUMIF('Resource Build-Up'!$B$7:$B$306,B4,'Resource Build-Up'!$Z$7:$Z$306)) -> 0 | L4: =IF(B4="","",IF(J4="Excluded","Excluded","Resource-linked")) | M4: =IF(B4="","",IF(G4=0,"No resource cost / review","Resource Build-Up -> "&B4)) | N4: =IF(B4="","","Resource Build-Up") | O4: =IF(B4="","","See Resource Build-Up / Resource Rate Library") | P4: =IF(B4="","",IF(COUNTIF('Resource Build-Up'!$B$7:$B$306,B4)=0,IF(G4=0,"ZERO / REVIEW","NO RESOURCE"),"RESOURCE LINKED")) | R4: =IF(OR(ISNUMBER(SEARCH("PC",P4)),ISNUMBER(SEARCH("quote",Q4))),"Jason","Rick") -> Rick | S4: =IF(B4="","",IF(COUNTIF('Resource Build-Up'!$B$7:$B$306,B4)=0,"NO RESOURCE",IF(COUNTIFS('Resource Build-Up'!$B$7:$B$306,B4,'Resource Build-Up'!$AI$7:$AI$306,"<>OK")>0,"RESOURCE QA","LINKED")))
F5: =IF(OR(B5="",E5=0),0,G5/E5) -> 0 | G5: =IF(B5="",0,SUMIF('Resource Build-Up'!$B$7:$B$306,B5,'Resource Build-Up'!$Z$7:$Z$306)) -> 0 | L5: =IF(B5="","",IF(J5="Excluded","Excluded","Resource-linked")) | M5: =IF(B5="","",IF(G5=0,"No resource cost / review","Resource Build-Up -> "&B5)) | N5: =IF(B5="","","Resource Build-Up") | O5: =IF(B5="","","See Resource Build-Up / Resource Rate Library") | P5: =IF(B5="","",IF(COUNTIF('Resource Build-Up'!$B$7:$B$306,B5)=0,IF(G5=0,"ZERO / REVIEW","NO RESOURCE"),"RESOURCE LINKED")) | R5: =IF(OR(ISNUMBER(SEARCH("PC",P5)),ISNUMBER(SEARCH("quote",Q5))),"Jason","Rick") -> Rick | S5: =IF(B5="","",IF(COUNTIF('Resource Build-Up'!$B$7:$B$306,B5)=0,"NO RESOURCE",IF(COUNTIFS('Resource Build-Up'!$B$7:$B$306,B5,'Resource Build-Up'!$AI$7:$AI$306,"<>OK")>0,"RESOURCE QA","LINKED")))
F6: =IF(OR(B6="",E6=0),0,G6/E6) -> 0 | G6: =IF(B6="",0,SUMIF('Resource Build-Up'!$B$7:$B$306,B6,'Resource Build-Up'!$Z$7:$Z$306)) -> 0 | L6: =IF(B6="","",IF(J6="Excluded","Excluded","Resource-linked")) | M6: =IF(B6="","",IF(G6=0,"No resource cost / review","Resource Build-Up -> "&B6)) | N6: =IF(B6="","","Resource Build-Up") | O6: =IF(B6="","","See Resource Build-Up / Resource Rate Library") | P6: =IF(B6="","",IF(COUNTIF('Resource Build-Up'!$B$7:$B$306,B6)=0,IF(G6=0,"ZERO / REVIEW","NO RESOURCE"),"RESOURCE LINKED")) | R6: =IF(OR(ISNUMBER(SEARCH("PC",P6)),ISNUMBER(SEARCH("quote",Q6))),"Jason","Rick") -> Rick | S6: =IF(B6="","",IF(COUNTIF('Resource Build-Up'!$B$7:$B$306,B6)=0,"NO RESOURCE",IF(COUNTIFS('Resource Build-Up'!$B$7:$B$306,B6,'Resource Build-Up'!$AI$7:$AI$306,"<>OK")>0,"RESOURCE QA","LINKED")))
F7: =IF(OR(B7="",E7=0),0,G7/E7) -> 0 | G7: =IF(B7="",0,SUMIF('Resource Build-Up'!$B$7:$B$306,B7,'Resource Build-Up'!$Z$7:$Z$306)) -> 0 | L7: =IF(B7="","",IF(J7="Excluded","Excluded","Resource-linked")) | M7: =IF(B7="","",IF(G7=0,"No resource cost / review","Resource Build-Up -> "&B7)) | N7: =IF(B7="","","Resource Build-Up") | O7: =IF(B7="","","See Resource Build-Up / Resource Rate Library") | P7: =IF(B7="","",IF(COUNTIF('Resource Build-Up'!$B$7:$B$306,B7)=0,IF(G7=0,"ZERO / REVIEW","NO RESOURCE"),"RESOURCE LINKED")) | R7: =IF(OR(ISNUMBER(SEARCH("PC",P7)),ISNUMBER(SEARCH("quote",Q7))),"Jason","Rick") -> Rick | S7: =IF(B7="","",IF(COUNTIF('Resource Build-Up'!$B$7:$B$306,B7)=0,"NO RESOURCE",IF(COUNTIFS('Resource Build-Up'!$B$7:$B$306,B7,'Resource Build-Up'!$AI$7:$AI$306,"<>OK")>0,"RESOURCE QA","LINKED")))
F8: =IF(OR(B8="",E8=0),0,G8/E8) -> 0 | G8: =IF(B8="",0,SUMIF('Resource Build-Up'!$B$7:$B$306,B8,'Resource Build-Up'!$Z$7:$Z$306)) -> 0 | L8: =IF(B8="","",IF(J8="Excluded","Excluded","Resource-linked")) | M8: =IF(B8="","",IF(G8=0,"No resource cost / review","Resource Build-Up -> "&B8)) | N8: =IF(B8="","","Resource Build-Up") | O8: =IF(B8="","","See Resource Build-Up / Resource Rate Library") | P8: =IF(B8="","",IF(COUNTIF('Resource Build-Up'!$B$7:$B$306,B8)=0,IF(G8=0,"ZERO / REVIEW","NO RESOURCE"),"RESOURCE LINKED")) | R8: =IF(OR(ISNUMBER(SEARCH("PC",P8)),ISNUMBER(SEARCH("quote",Q8))),"Jason","Rick") -> Rick | S8: =IF(B8="","",IF(COUNTIF('Resource Build-Up'!$B$7:$B$306,B8)=0,"NO RESOURCE",IF(COUNTIFS('Resource Build-Up'!$B$7:$B$306,B8,'Resource Build-Up'!$AI$7:$AI$306,"<>OK")>0,"RESOURCE QA","LINKED")))
F9: =IF(OR(B9="",E9=0),0,G9/E9) -> 0 | G9: =IF(B9="",0,SUMIF('Resource Build-Up'!$B$7:$B$306,B9,'Resource Build-Up'!$Z$7:$Z$306)) -> 0 | L9: =IF(B9="","",IF(J9="Excluded","Excluded","Resource-linked")) | M9: =IF(B9="","",IF(G9=0,"No resource cost / review","Resource Build-Up -> "&B9)) | N9: =IF(B9="","","Resource Build-Up") | O9: =IF(B9="","","See Resource Build-Up / Resource Rate Library") | P9: =IF(B9="","",IF(COUNTIF('Resource Build-Up'!$B$7:$B$306,B9)=0,IF(G9=0,"ZERO / REVIEW","NO RESOURCE"),"RESOURCE LINKED")) | R9: =IF(OR(ISNUMBER(SEARCH("PC",P9)),ISNUMBER(SEARCH("quote",Q9))),"Jason","Rick") -> Rick | S9: =IF(B9="","",IF(COUNTIF('Resource Build-Up'!$B$7:$B$306,B9)=0,"NO RESOURCE",IF(COUNTIFS('Resource Build-Up'!$B$7:$B$306,B9,'Resource Build-Up'!$AI$7:$AI$306,"<>OK")>0,"RESOURCE QA","LINKED")))
F10: =IF(OR(B10="",E10=0),0,G10/E10) -> 0 | G10: =IF(B10="",0,SUMIF('Resource Build-Up'!$B$7:$B$306,B10,'Resource Build-Up'!$Z$7:$Z$306)) -> 0 | L10: =IF(B10="","",IF(J10="Excluded","Excluded","Resource-linked")) | M10: =IF(B10="","",IF(G10=0,"No resource cost / review","Resource Build-Up -> "&B10)) | N10: =IF(B10="","","Resource Build-Up") | O10: =IF(B10="","","See Resource Build-Up / Resource Rate Library") | P10: =IF(B10="","",IF(COUNTIF('Resource Build-Up'!$B$7:$B$306,B10)=0,IF(G10=0,"ZERO / REVIEW","NO RESOURCE"),"RESOURCE LINKED")) | R10: =IF(OR(ISNUMBER(SEARCH("PC",P10)),ISNUMBER(SEARCH("quote",Q10))),"Jason","Rick") -> Rick | S10: =IF(B10="","",IF(COUNTIF('Resource Build-Up'!$B$7:$B$306,B10)=0,"NO RESOURCE",IF(COUNTIFS('Resource Build-Up'!$B$7:$B$306,B10,'Resource Build-Up'!$AI$7:$AI$306,"<>OK")>0,"RESOURCE QA","LINKED")))
F11: =IF(OR(B11="",E11=0),0,G11/E11) -> 0 | G11: =IF(B11="",0,SUMIF('Resource Build-Up'!$B$7:$B$306,B11,'Resource Build-Up'!$Z$7:$Z$306)) -> 0 | L11: =IF(B11="","",IF(J11="Excluded","Excluded","Resource-linked")) | M11: =IF(B11="","",IF(G11=0,"No resource cost / review","Resource Build-Up -> "&B11)) | N11: =IF(B11="","","Resource Build-Up") | O11: =IF(B11="","","See Resource Build-Up / Resource Rate Library") | P11: =IF(B11="","",IF(COUNTIF('Resource Build-Up'!$B$7:$B$306,B11)=0,IF(G11=0,"ZERO / REVIEW","NO RESOURCE"),"RESOURCE LINKED")) | R11: =IF(OR(ISNUMBER(SEARCH("PC",P11)),ISNUMBER(SEARCH("quote",Q11))),"Jason","Rick") -> Rick | S11: =IF(B11="","",IF(COUNTIF('Resource Build-Up'!$B$7:$B$306,B11)=0,"NO RESOURCE",IF(COUNTIFS('Resource Build-Up'!$B$7:$B$306,B11,'Resource Build-Up'!$AI$7:$AI$306,"<>OK")>0,"RESOURCE QA","LINKED")))
F12: =IF(OR(B12="",E12=0),0,G12/E12) -> 0 | G12: =IF(B12="",0,SUMIF('Resource Build-Up'!$B$7:$B$306,B12,'Resource Build-Up'!$Z$7:$Z$306)) -> 0 | L12: =IF(B12="","",IF(J12="Excluded","Excluded","Resource-linked")) | M12: =IF(B12="","",IF(G12=0,"No resource cost / review","Resource Build-Up -> "&B12)) | N12: =IF(B12="","","Resource Build-Up") | O12: =IF(B12="","","See Resource Build-Up / Resource Rate Library") | P12: =IF(B12="","",IF(COUNTIF('Resource Build-Up'!$B$7:$B$306,B12)=0,IF(G12=0,"ZERO / REVIEW","NO RESOURCE"),"RESOURCE LINKED")) | R12: =IF(OR(ISNUMBER(SEARCH("PC",P12)),ISNUMBER(SEARCH("quote",Q12))),"Jason","Rick") -> Rick | S12: =IF(B12="","",IF(COUNTIF('Resource Build-Up'!$B$7:$B$306,B12)=0,"NO RESOURCE",IF(COUNTIFS('Resource Build-Up'!$B$7:$B$306,B12,'Resource Build-Up'!$AI$7:$AI$306,"<>OK")>0,"RESOURCE QA","LINKED")))
F13: =IF(OR(B13="",E13=0),0,G13/E13) -> 0 | G13: =IF(B13="",0,SUMIF('Resource Build-Up'!$B$7:$B$306,B13,'Resource Build-Up'!$Z$7:$Z$306)) -> 0 | L13: =IF(B13="","",IF(J13="Excluded","Excluded","Resource-linked")) | M13: =IF(B13="","",IF(G13=0,"No resource cost / review","Resource Build-Up -> "&B13)) | N13: =IF(B13="","","Resource Build-Up") | O13: =IF(B13="","","See Resource Build-Up / Resource Rate Library") | P13: =IF(B13="","",IF(COUNTIF('Resource Build-Up'!$B$7:$B$306,B13)=0,IF(G13=0,"ZERO / REVIEW","NO RESOURCE"),"RESOURCE LINKED")) | R13: =IF(OR(ISNUMBER(SEARCH("PC",P13)),ISNUMBER(SEARCH("quote",Q13))),"Jason","Rick") -> Rick | S13: =IF(B13="","",IF(COUNTIF('Resource Build-Up'!$B$7:$B$306,B13)=0,"NO RESOURCE",IF(COUNTIFS('Resource Build-Up'!$B$7:$B$306,B13,'Resource Build-Up'!$AI$7:$AI$306,"<>OK")>0,"RESOURCE QA","LINKED")))
F14: =IF(OR(B14="",E14=0),0,G14/E14) -> 0 | G14: =IF(B14="",0,SUMIF('Resource Build-Up'!$B$7:$B$306,B14,'Resource Build-Up'!$Z$7:$Z$306)) -> 0 | L14: =IF(B14="","",IF(J14="Excluded","Excluded","Resource-linked")) | M14: =IF(B14="","",IF(G14=0,"No resource cost / review","Resource Build-Up -> "&B14)) | N14: =IF(B14="","","Resource Build-Up") | O14: =IF(B14="","","See Resource Build-Up / Resource Rate Library") | P14: =IF(B14="","",IF(COUNTIF('Resource Build-Up'!$B$7:$B$306,B14)=0,IF(G14=0,"ZERO / REVIEW","NO RESOURCE"),"RESOURCE LINKED")) | R14: =IF(OR(ISNUMBER(SEARCH("PC",P14)),ISNUMBER(SEARCH("quote",Q14))),"Jason","Rick") -> Rick | S14: =IF(B14="","",IF(COUNTIF('Resource Build-Up'!$B$7:$B$306,B14)=0,"NO RESOURCE",IF(COUNTIFS('Resource Build-Up'!$B$7:$B$306,B14,'Resource Build-Up'!$AI$7:$AI$306,"<>OK")>0,"RESOURCE QA","LINKED")))
... F73: =IF(OR(B73="",E73=0),0,G73/E73) -> 0 | G73: =IF(B73="",0,SUMIF('Resource Build-Up'!$B$7:$B$306,B73,'Resource Build-Up'!$Z$7:$Z$306)) -> 0 | L73: =IF(B73="","",IF(J73="Excluded","Excluded","Resource-linked")) | M73: =IF(B73="","",IF(G73=0,"No resource cost / review","Resource Build-Up -> "&B73)) | N73: =IF(B73="","","Resource Build-Up") | O73: =IF(B73="","","See Resource Build-Up / Resource Rate Library") | P73: =IF(B73="","",IF(COUNTIF('Resource Build-Up'!$B$7:$B$306,B73)=0,IF(G73=0,"ZERO / REVIEW","NO RESOURCE"),"RESOURCE LINKED")) | R73: =IF(OR(ISNUMBER(SEARCH("PC",P73)),ISNUMBER(SEARCH("quote",Q73))),"Jason","Rick") -> Rick | S73: =IF(B73="","",IF(COUNTIF('Resource Build-Up'!$B$7:$B$306,B73)=0,"NO RESOURCE",IF(COUNTIFS('Resource Build-Up'!$B$7:$B$306,B73,'Resource Build-Up'!$AI$7:$AI$306,"<>OK")>0,"RESOURCE QA","LINKED")))
A74: TOTAL MEASURED DIRECT COST | G74: =SUM(G3:G73) -> 0

Sheet Stage Cashflow
A1: STAGE PAYMENT & CASHFLOW - MASTER ESTIMATE WORKBOOK REV2
A2: Only stage timing, stage percentages and retention applicability are inputs. Revenue and direct-cost allocations remain formula linked.
A3: Cash on hand = cumulative net pre-GST receipts less base direct stage costs and included pre-margin provisions. Commercial adjustments (overhead/profit/bonds/finance) remain visible as commercial return/cost after those provisions.
A4: Stage | B4: Timing / milestone | C4: Stage % | D4: Retention applies? | E4: Opening cash | F4: Gross stage revenue excl. GST | G4: Retention withheld | H4: Net stage revenue excl. GST | I4: Stage cost / provision | J4: Net cash movement | K4: Closing cash on hand | L4: Cumulative net revenue | M4: Cumulative retention held | N4: GST if selected | O4: Net stage receipt incl. GST | P4: Notes
A5: Deposit / advance | B5: On contract award | C5: =IF('Commercial Inputs'!$F$28="Yes",'Commercial Inputs'!$D$28,0) -> 0 | D5: =IF('Commercial Inputs'!$F$29="Yes","Yes","No") -> No | E5: =0 -> 0 | F5: ='Tender Build-Up'!$B$47*C5 -> 0 | G5: =IF(AND(D5="Yes",'Commercial Inputs'!$F$26="Yes"),F5*'Commercial Inputs'!$D$26,0) -> 0 | H5: =F5-G5 -> 0 | I5: =0 -> 0 | J5: =H5-I5 -> 0 | K5: =E5+J5 -> 0 | L5: =H5 -> 0 | M5: =G5 -> 0 | N5: =IF('Commercial Inputs'!$F$25="Yes",H5*'Commercial Inputs'!$D$25,0) -> 0 | O5: =H5+N5 -> 0
A6: Mobilisation, preliminaries and ESC | E6: =K5 -> 0 | F6: ='Tender Build-Up'!$B$47*C6 -> 0 | G6: =IF(AND(D6="Yes",'Commercial Inputs'!$F$26="Yes"),F6*'Commercial Inputs'!$D$26,0) -> 0 | H6: =F6-G6 -> 0 | I6: =SUM(Summary!$B$23:$B$24) -> 0 | J6: =H6-I6 -> 0 | K6: =E6+J6 -> 0 | L6: =L5+H6 -> 0 | M6: =M5+G6 -> 0 | N6: =IF('Commercial Inputs'!$F$25="Yes",H6*'Commercial Inputs'!$D$25,0) -> 0 | O6: =H6+N6 -> 0
A7: Earthworks and imported fill | E7: =K6 -> 0 | F7: ='Tender Build-Up'!$B$47*C7 -> 0 | G7: =IF(AND(D7="Yes",'Commercial Inputs'!$F$26="Yes"),F7*'Commercial Inputs'!$D$26,0) -> 0 | H7: =F7-G7 -> 0 | I7: =Summary!$B$25 -> 0 | J7: =H7-I7 -> 0 | K7: =E7+J7 -> 0 | L7: =L6+H7 -> 0 | M7: =M6+G7 -> 0 | N7: =IF('Commercial Inputs'!$F$25="Yes",H7*'Commercial Inputs'!$D$25,0) -> 0 | O7: =H7+N7 -> 0
A8: Stormwater, detention, sewer and water | E8: =K7 -> 0 | F8: ='Tender Build-Up'!$B$47*C8 -> 0 | G8: =IF(AND(D8="Yes",'Commercial Inputs'!$F$26="Yes"),F8*'Commercial Inputs'!$D$26,0) -> 0 | H8: =F8-G8 -> 0 | I8: =SUM(Summary!$B$26:$B$27) -> 0 | J8: =H8-I8 -> 0 | K8: =E8+J8 -> 0 | L8: =L7+H8 -> 0 | M8: =M7+G8 -> 0 | N8: =IF('Commercial Inputs'!$F$25="Yes",H8*'Commercial Inputs'!$D$25,0) -> 0 | O8: =H8+N8 -> 0
A9: Pavements, kerbs and sitework | E9: =K8 -> 0 | F9: ='Tender Build-Up'!$B$47*C9 -> 0 | G9: =IF(AND(D9="Yes",'Commercial Inputs'!$F$26="Yes"),F9*'Commercial Inputs'!$D$26,0) -> 0 | H9: =F9-G9 -> 0 | I9: =SUM(Summary!$B$28:$B$29) -> 0 | J9: =H9-I9 -> 0 | K9: =E9+J9 -> 0 | L9: =L8+H9 -> 0 | M9: =M8+G9 -> 0 | N9: =IF('Commercial Inputs'!$F$25="Yes",H9*'Commercial Inputs'!$D$25,0) -> 0 | O9: =H9+N9 -> 0
A10: Retaining walls and interfaces | E10: =K9 -> 0 | F10: ='Tender Build-Up'!$B$47*C10 -> 0 | G10: =IF(AND(D10="Yes",'Commercial Inputs'!$F$26="Yes"),F10*'Commercial Inputs'!$D$26,0) -> 0 | H10: =F10-G10 -> 0 | I10: =Summary!$B$30 -> 0 | J10: =H10-I10 -> 0 | K10: =E10+J10 -> 0 | L10: =L9+H10 -> 0 | M10: =M9+G10 -> 0 | N10: =IF('Commercial Inputs'!$F$25="Yes",H10*'Commercial Inputs'!$D$25,0) -> 0 | O10: =H10+N10 -> 0
A11: Testing, completion and handover | E11: =K10 -> 0 | F11: ='Tender Build-Up'!$B$47*C11 -> 0 | G11: =IF(AND(D11="Yes",'Commercial Inputs'!$F$26="Yes"),F11*'Commercial Inputs'!$D$26,0) -> 0 | H11: =F11-G11 -> 0 | I11: =SUM(Summary!$B$31:$B$32) -> 0 | J11: =H11-I11 -> 0 | K11: =E11+J11 -> 0 | L11: =L10+H11 -> 0 | M11: =M10+G11 -> 0 | N11: =IF('Commercial Inputs'!$F$25="Yes",H11*'Commercial Inputs'!$D$25,0) -> 0 | O11: =H11+N11 -> 0
A12: Included pre-margin cost / risk provisions | B12: Timing to allocate / refine | C12: 0 | D12: No | E12: =K11 -> 0 | F12: 0 | G12: 0 | H12: 0 | I12: ='Tender Build-Up'!$B$39 -> 0 | J12: =H12-I12 -> 0 | K12: =E12+J12 -> 0 | L12: =L11+H12 -> 0 | M12: =M11+G12 -> 0 | N12: =0 -> 0 | O12: =H12+N12 -> 0
A13: Retention release | B13: ="After "&TEXT('Commercial Inputs'!$D$27,"0")&" months" -> After 0 months | D13: No | E13: =K12 -> 0 | F13: =SUM(G5:G11) -> 0 | G13: =0 -> 0 | H13: =F13 -> 0 | I13: =0 -> 0 | J13: =H13 -> 0 | K13: =E13+J13 -> 0 | L13: =L12+H13 -> 0 | M13: =0 -> 0 | N13: =IF('Commercial Inputs'!$F$25="Yes",H13*'Commercial Inputs'!$D$25,0) -> 0 | O13: =H13+N13 -> 0
A15: Cashflow checks
A16: Stage percentages total | C16: =SUM(C5:C11) -> 0 | P16: =IF(ABS(C16-1)<0.000001,"OK","CHECK") -> CHECK
A17: Gross stage revenue equals tender excl. GST | F17: =SUM(F5:F11) -> 0 | P17: =IF(ABS(F17-'Tender Build-Up'!$B$47)<0.01,"OK","CHECK") -> OK
A18: Base direct costs + pre-margin provisions allocated | I18: =SUM(I5:I12) -> 0 | P18: =IF(ABS(I18-(Summary!$B$33+'Tender Build-Up'!$B$39))<0.01,"OK","CHECK") -> OK
A19: Net receipts plus retention release equal tender | L19: =L13 -> 0 | P19: =IF(ABS(L19-'Tender Build-Up'!$B$47)<0.01,"OK","CHECK") -> OK
A20: Final cash equals commercial adjustments after cost provisions | K20: =K13 -> 0 | P20: =IF(ABS(K20-'Tender Build-Up'!$B$46)<0.01,"OK","CHECK") -> OK
A21: Lowest closing cash before retention release | K21: =MIN(K5:K12) -> 0 | P21: =IF(K21>=0,"POSITIVE","FUNDING REQUIRED") -> POSITIVE

Sheet Resource Rate Library
A1: COMPANY RESOURCE RATE LIBRARY - MASTER ESTIMATE WORKBOOK REV2
A2: Reusable company / benchmark resource library. Retain useful history; update verified rates with source, effective date, region, GST basis, inclusions/exclusions and supersession reason.
A3: Jason: enter verified actual company/supplier rates with source, date, region, GST basis, inclusions and exclusions. Mark replaced rates superseded/inactive rather than deleting them.
A4: Resource Code | B4: Resource Category | C4: Resource Description | D4: Default Cost Type | E4: Unit | F4: Procurement Mode | G4: Operator Included? | H4: Fuel Included? | I4: Base Rate excl. GST | J4: Region / Market | K4: Effective Date | L4: Source Type | M4: Supplier / Source | N4: Source URL / Quote Ref | O4: Minimum / Mobilisation | P4: Rate Inclusions | Q4: Rate Exclusions | R4: Confidence | S4: Verification Status | T4: Notes
A5: LAB-FOREMAN | B5: Labour | C5: Civil foreman / working foreman | D5: Labour | E5: hr | F5: Internal / agency | G5: N/A | H5: N/A | I5: 64 | J5: Auckland / NZ | K5: 13-Aug-2026 | L5: Template market benchmark | M5: SEEK / statutory on-cost basis | N5: https://nz.seek.com/civil-drainage-jobs/in-All-Auckland | https://nz.seek.com/drainage-foreman-jobs/in-All-Auckland/full-time | P5: Direct employment allowance | Q5: Margin, vehicle, overtime | R5: Medium | S5: AMBER - market/on-cost benchmark; company payroll required | T5: Firm to company payroll before award
A6: LAB-SUPERVISOR | B6: Labour | C6: Site supervisor / project manager | D6: Labour | E6: hr | F6: Internal / agency | G6: N/A | H6: N/A | I6: 73 | J6: Auckland / NZ | K6: 13-Aug-2026 | L6: Template market benchmark | M6: SEEK / statutory on-cost basis | N6: https://nz.seek.com/civil-drainage-jobs/in-All-Auckland | https://nz.seek.com/drainage-foreman-jobs/in-All-Auckland/full-time | P6: Direct employment allowance | Q6: Margin, vehicle, overtime | R6: Medium | S6: AMBER - market/on-cost benchmark; company payroll required | T6: Firm to company payroll before award
A7: LAB-OPERATOR | B7: Labour | C7: Plant operator | D7: Labour | E7: hr | F7: Internal / agency | G7: N/A | H7: N/A | I7: 45 | J7: Auckland / NZ | K7: 13-Aug-2026 | L7: Template market benchmark | M7: Auckland civil market | N7: https://nz.seek.com/civil-drainage-jobs/in-All-Auckland | https://nz.seek.com/drainage-foreman-jobs/in-All-Auckland/full-time | P7: Direct employment allowance | Q7: Plant and overtime | R7: Medium | S7: AMBER - market/on-cost benchmark; company payroll required
A8: LAB-DRAINLAYER | B8: Labour | C8: Registered drainlayer / pipe layer | D8: Labour | E8: hr | F8: Internal / agency | G8: N/A | H8: N/A | I8: 51 | J8: Auckland / NZ | K8: 13-Aug-2026 | L8: Template market benchmark | M8: Auckland civil market | N8: https://nz.seek.com/civil-drainage-jobs/in-All-Auckland | https://nz.seek.com/drainage-foreman-jobs/in-All-Auckland/full-time | P8: Direct employment allowance | Q8: Vehicle and overtime | R8: Medium | S8: AMBER - market/on-cost benchmark; company payroll required
A9: LAB-LABOURER | B9: Labour | C9: Civil labourer | D9: Labour | E9: hr | F9: Internal / agency | G9: N/A | H9: N/A | I9: 38 | J9: Auckland / NZ | K9: 13-Aug-2026 | L9: Template market benchmark | M9: Auckland civil market | N9: https://nz.seek.com/civil-drainage-jobs/in-All-Auckland | https://nz.seek.com/drainage-foreman-jobs/in-All-Auckland/full-time | P9: Direct employment allowance | Q9: Overtime | R9: Medium | S9: AMBER - market/on-cost benchmark; company payroll required
A10: LAB-CONCRETE | B10: Labour | C10: Concrete placer / finisher | D10: Labour | E10: hr | F10: Internal / agency | G10: N/A | H10: N/A | I10: 44 | J10: Auckland / NZ | K10: 13-Aug-2026 | L10: Template market benchmark | M10: Auckland civil market | N10: https://nz.seek.com/civil-drainage-jobs/in-All-Auckland | https://nz.seek.com/drainage-foreman-jobs/in-All-Auckland/full-time | P10: Direct employment allowance | Q10: Specialist pump | R10: Medium | S10: AMBER - market/on-cost benchmark; company payroll required
A11: PL-EXC-1.7 | B11: Plant | C11: 1.7 t excavator wet hire | D11: Plant | E11: hr | F11: Wet hire | G11: Yes | H11: Yes | I11: 85 | J11: Auckland | K11: 13-Aug-2026 | L11: Published supplier wet-hire rate | M11: ASAP Machine Hire; NZ Machine Hire cross-check | N11: https://www.asapmachinehire.co.nz/price-list | https://www.nzmachinehire.co.nz/_files/ugd/d7f8c7_1379402df1a242f88fef70fc3ce1475c.pdf | O11: Delivery by quote | P11: Machine, operator, fuel and normal buckets | Q11: Delivery, overtime and specialist attachments | R11: High | S11: GREEN - 3-point checked | T11: Wet rate. Do not add a separate operator or fuel line.
A12: PL-EXC-5 | B12: Plant | C12: 5.5 t excavator wet hire | D12: Plant | E12: hr | F12: Wet hire | G12: Yes | H12: Yes | I12: 110 | J12: Auckland | K12: 13-Aug-2026 | L12: Published supplier wet-hire rate | M12: ASAP Machine Hire; NZ Machine Hire cross-check | N12: https://www.asapmachinehire.co.nz/price-list | https://www.nzmachinehire.co.nz/_files/ugd/d7f8c7_1379402df1a242f88fef70fc3ce1475c.pdf | O12: Delivery by quote | P12: Machine, operator, fuel and normal buckets | Q12: Delivery, overtime and specialist attachments | R12: High | S12: GREEN - 3-point checked | T12: Wet rate. Separate excavator-operator lines set to zero.
A13: PL-EXC-13 | B13: Plant | C13: 14 t excavator wet hire | D13: Plant | E13: hr | F13: Wet hire | G13: Yes | H13: Yes | I13: 150 | J13: Auckland | K13: 13-Aug-2026 | L13: Published supplier wet-hire rate | M13: ASAP Machine Hire; NZ Machine Hire cross-check | N13: https://www.asapmachinehire.co.nz/price-list | https://www.nzmachinehire.co.nz/_files/ugd/d7f8c7_1379402df1a242f88fef70fc3ce1475c.pdf | O13: Delivery by quote | P13: Machine, operator, fuel and normal buckets | Q13: Delivery, overtime and specialist attachments | R13: High | S13: GREEN - 3-point checked | T13: Published current wet rate. Separate excavator-operator lines set to zero.
A14: PL-ROLLER | B14: Plant | C14: 7-9 t roller wet-hire equivalent | D14: Plant | E14: hr | F14: Wet-hire equivalent | G14: Yes | H14: Yes | I14: 110 | J14: Auckland | K14: 13-Aug-2026 | L14: Two-supplier dry-rate build-up | M14: NZ Machine Hire; Hire Smart | N14: https://www.nzmachinehire.co.nz/all-rollers | https://www.hiresmart.co.nz/for-hire/rollers/ | O14: Transport by quote | P14: Dry hire, operator, normal fuel and insurance allowance | Q14: Transport, overtime and specialist attachments | R14: Medium | S14: AMBER - 3-point benchmark; quote required | T14: Built from two published dry rates plus operator/fuel allowance; obtain a project quote.
A15: PL-LOADER | B15: Plant | C15: Loader / skid-steer dry hire | D15: Plant | E15: hr | F15: Dry hire | G15: No | H15: No | I15: 120 | J15: Auckland | K15: 13-Aug-2026 | L15: Estimator benchmark | M15: Plant-hire market | N15: Allowance - obtain hire quote | P15: Machine only | Q15: Operator, fuel, mobilisation | R15: Medium | S15: AMBER - benchmark/allowance only
A16: MAT-IMPFILL | B16: Material | C16: AP65-equivalent approved engineered fill delivered | D16: Material | E16: m3 | F16: Merchant supply | G16: N/A | H16: N/A | I16: 65 | J16: Auckland | K16: 13-Aug-2026 | L16: Tender allowance | M16: Aggregate supplier | N16: https://www.urbanquarry.co.nz/pricelist-2-2 | https://www.aggregate2u.co.nz/aggregates-delivery-south-auckland | P16: Delivered clean approved fill | Q16: Testing and placement | R16: Low | S16: AMBER - two market checks; specification/delivery quote required | T16: Product specification and delivered rate still require supplier confirmation.
A17: MAT-AP65 | B17: Material | C17: AP65 subbase aggregate | D17: Material | E17: t | F17: Merchant supply | G17: N/A | H17: N/A | I17: 30.5 | J17: Auckland | K17: 13-Aug-2026 | L17: Template market benchmark | M17: Auckland quarry market | N17: https://www.urbanquarry.co.nz/pricelist-2-2 | https://www.aggregate2u.co.nz/aggregates-delivery-south-auckland | P17: Ex-quarry / base material allowance | Q17: Haul and placement | R17: High | S17: AMBER - two market checks; specification/delivery quote required | T17: Published GAP/AP benchmark; confirm specified grading and haul.
A18: MAT-AP40 | B18: Material | C18: AP40 / GAP40 basecourse aggregate | D18: Material | E18: t | F18: Merchant supply | G18: N/A | H18: N/A | I18: 31 | J18: Auckland | K18: 13-Aug-2026 | L18: Template market benchmark | M18: Auckland quarry market | N18: https://www.urbanquarry.co.nz/pricelist-2-2 | https://www.aggregate2u.co.nz/aggregates-delivery-south-auckland | P18: Ex-quarry / base material allowance | Q18: Haul and placement | R18: High | S18: AMBER - two market checks; specification/delivery quote required | T18: Published GAP/AP benchmark; confirm specified grading and haul.
A19: MAT-DRAINAGG | B19: Material | C19: Drainage aggregate | D19: Material | E19: t | F19: Merchant supply | G19: N/A | H19: N/A | I19: 48.5 | J19: Auckland | K19: 13-Aug-2026 | L19: Template market benchmark | M19: Auckland quarry market | N19: https://www.aggregate2u.co.nz/aggregates-delivery-south-auckland | https://www.urbanquarry.co.nz/pricelist-2-2 | P19: Aggregate | Q19: Haul and placement | R19: High | S19: AMBER - two market checks; specification/delivery quote required | T19: Drainage aggregate benchmark; confirm delivered project quote.
A20: MAT-GEOTEXTILE | B20: Material | C20: Bidim A19 or approved geotextile | D20: Material | E20: m2 | F20: Merchant supply | G20: N/A | H20: N/A | I20: 3.25 | J20: Auckland | K20: 13-Aug-2026 | L20: Template market benchmark | M20: Civil merchant | N20: Template baseline dated 13-Aug-2026 | P20: Material only | Q20: Installation | R20: Medium | S20: AMBER - benchmark/allowance only
A21: MAT-CONC25 | B21: Material | C21: 25 MPa ready-mix concrete | D21: Material | E21: m3 | F21: Delivered supply | G21: N/A | H21: N/A | I21: 325 | J21: Auckland | K21: 13-Aug-2026 | L21: Template market benchmark | M21: Ready-mix market | N21: Template baseline dated 13-Aug-2026 | P21: Delivered concrete allowance | Q21: Pump, testing, placing | R21: Medium | S21: AMBER - benchmark/allowance only
A22: MAT-MESH | B22: Material | C22: SE62 / 662 mesh allowance | D22: Material | E22: m2 | F22: Merchant supply | G22: N/A | H22: N/A | I22: 20 | J22: Auckland | K22: 13-Aug-2026 | L22: Template market benchmark | M22: Steel merchant | N22: Template baseline dated 13-Aug-2026 | P22: Mesh material | Q22: Chairs, laps above waste factor | R22: Medium | S22: AMBER - benchmark/allowance only | T22: Confirm project-specific mesh grade and specification before order.
A23: MAT-PIPE150 | B23: Material | C23: 150 mm uPVC RRJ drainage pipe | D23: Material | E23: lm | F23: Merchant supply | G23: N/A | H23: N/A | I23: 45 | J23: Auckland | K23: 13-Aug-2026 | L23: Tender allowance | M23: Civil merchant | N23: Quote required | P23: Pipe and standard joints | Q23: Fittings, bedding, install | R23: Low | S23: AMBER - benchmark/allowance only
A24: MAT-PIPE225 | B24: Material | C24: 225 mm uPVC RRJ stormwater pipe | D24: Material | E24: lm | F24: Merchant supply | G24: N/A | H24: N/A | I24: 95 | J24: Auckland | K24: 13-Aug-2026 | L24: Tender allowance | M24: Civil merchant | N24: Quote required | P24: Pipe and standard joints | Q24: Fittings, bedding, install | R24: Low | S24: AMBER - benchmark/allowance only
A25: MAT-SUB110 | B25: Material | C25: 110 mm perforated subsoil pipe with sock | D25: Material | E25: lm | F25: Merchant supply | G25: N/A | H25: N/A | I25: 20 | J25: Auckland | K25: 13-Aug-2026 | L25: Tender allowance | M25: Civil merchant | N25: Quote required | P25: Pipe and sock | Q25: Aggregate and install | R25: Low | S25: AMBER - benchmark/allowance only
A26: MAT-WATER50 | B26: Material | C26: 50 mm PE watermain and fittings allowance | D26: Material | E26: lm | F26: Merchant supply | G26: N/A | H26: N/A | I26: 22 | J26: Auckland | K26: 13-Aug-2026 | L26: Tender allowance | M26: Civil merchant | N26: Quote required | P26: PE pipe and normal fittings | Q26: Connection, meter, testing | R26: Low | S26: AMBER - benchmark/allowance only
A27: MAT-SWMH | B27: Material | C27: Precast stormwater manhole set | D27: Material | E27: ea | F27: Precast supplier | G27: N/A | H27: N/A | I27: 5500 | J27: Auckland | K27: 13-Aug-2026 | L27: Tender allowance | M27: Precast supplier | N27: Quote required | P27: Chamber/riser/lid allowance | Q27: Excavation, concrete, install | R27: Low | S27: AMBER - benchmark/allowance only
A28: MAT-SSMH | B28: Material | C28: Precast sewer manhole set | D28: Material | E28: ea | F28: Precast supplier | G28: N/A | H28: N/A | I28: 7000 | J28: Auckland | K28: 13-Aug-2026 | L28: Tender allowance | M28: Precast supplier | N28: Quote required | P28: Chamber/riser/lid allowance | Q28: Excavation, testing, install | R28: Low | S28: AMBER - benchmark/allowance only
A29: MAT-IC600 | B29: Material | C29: 600 mm inspection chamber set | D29: Material | E29: ea | F29: Merchant supply | G29: N/A | H29: N/A | I29: 1800 | J29: Auckland | K29: 13-Aug-2026 | L29: Tender allowance | M29: Civil merchant | N29: Quote required | P29: Chamber and lid | Q29: Excavation and install | R29: Low | S29: AMBER - benchmark/allowance only
A30: MAT-CP | B30: Material | C30: Standard catchpit set | D30: Material | E30: ea | F30: Precast supplier | G30: N/A | H30: N/A | I30: 1800 | J30: Auckland | K30: 13-Aug-2026 | L30: Tender allowance | M30: Precast supplier | N30: Quote required | P30: Chamber, lid and grate | Q30: Excavation and install | R30: Low | S30: AMBER - benchmark/allowance only
A31: MAT-DCP | B31: Material | C31: Double side-entry cesspit set | D31: Material | E31: ea | F31: Precast supplier | G31: N/A | H31: N/A | I31: 4500 | J31: Auckland | K31: 13-Aug-2026 | L31: Tender allowance | M31: Precast supplier | N31: Quote required | P31: Chamber, lid and grates | Q31: Excavation and install | R31: Low | S31: AMBER - benchmark/allowance only
A32: SUB-ASPHALT30 | B32: Subcontract | C32: 30 mm asphalt surfacing incl prime/seal | D32: Subcontract | E32: m2 | F32: Specialist subcontract | G32: Yes | H32: Yes | I32: 55 | J32: Auckland | K32: 13-Aug-2026 | L32: Budget allowance | M32: Asphalt subcontractor | N32: Quote required | P32: 30 mm asphalt surfacing allowance | Q32: Basecourse and testing | R32: Low | S32: RED - quote or job-specific evidence required
A33: SUB-KERB-T3 | B33: Subcontract | C33: Type 3 kerb and channel installed | D33: Subcontract | E33: lm | F33: Specialist subcontract | G33: Yes | H33: Yes | I33: 145 | J33: Auckland | K33: 13-Aug-2026 | L33: Budget allowance | M33: Kerb contractor | N33: Quote required | P33: Form/place/finish concrete kerb/channel | Q33: Excavation and major base repair | R33: Low | S33: RED - quote or job-specific evidence required
A34: SUB-KERB-T7 | B34: Subcontract | C34: Type 7 kerb installed | D34: Subcontract | E34: lm | F34: Specialist subcontract | G34: Yes | H34: Yes | I34: 115 | J34: Auckland | K34: 13-Aug-2026 | L34: Budget allowance | M34: Kerb contractor | N34: Quote required | P34: Form/place/finish kerb | Q34: Excavation and major base repair | R34: Low | S34: RED - quote or job-specific evidence required
A35: SUB-ACO-K100 | B35: Subcontract | C35: ACO K100S channel drain installed | D35: Subcontract | E35: lm | F35: Specialist subcontract | G35: Yes | H35: Yes | I35: 275 | J35: Auckland | K35: 13-Aug-2026 | L35: Budget allowance | M35: ACO / drainage installer | N35: Quote required | P35: Channel, grates and concrete surround allowance | Q35: Outlet structures and design changes | R35: Low | S35: RED - quote or job-specific evidence required
A36: SUB-SPECIALIST | B36: Subcontract | C36: Project-specific specialist package | D36: Subcontract | E36: LS | F36: Specialist subcontract | G36: N/A | H36: N/A | I36: 1 | J36: Project-specific | K36: 13-Aug-2026 | L36: Job override required | M36: Relevant specialist | N36: Quote / PC allowance shown in Resource Build-Up | P36: Only scope stated on build-up row | Q36: Unstated scope | R36: Low | S36: RED - quote or job-specific evidence required | T36: Base $1 forces explicit job-rate override
A37: OTH-GENERAL | B37: Other | C37: Project-specific transparent allowance | D37: Other | E37: LS | F37: Job-specific | G37: N/A | H37: N/A | I37: 1 | J37: Project-specific | K37: 13-Aug-2026 | L37: Job override required | M37: Estimator allowance | N37: Basis shown in Resource Build-Up | P37: Only scope stated on build-up row | Q37: Unstated scope | R37: Medium | S37: RED - quote or job-specific evidence required | T37: Base $1 forces explicit job-rate override
A38: OTH-DISPOSAL | B38: Other | C38: Clean spoil disposal / tipping fee | D38: Other | E38: t | F38: Commercial tip | G38: N/A | H38: N/A | I38: 22 | J38: Auckland | K38: 13-Aug-2026 | L38: Template market benchmark | M38: Auckland disposal market | N38: Template baseline dated 13-Aug-2026 | P38: Clean spoil tipping | Q38: Haul and contaminated material | R38: High | S38: AMBER - benchmark/allowance only
A39: LAB-RIGGER | B39: Labour | C39: Certified crane rigger / dogman / lifting crew | D39: Labour | E39: hr | F39: Specialist labour / subcontract | G39: N/A | H39: N/A | I39: 1 | J39: NZ / AU project-specific | K39: 15-Aug-2026 | L39: Job override required | M39: Crane / rigging subcontractor | N39: Quote required | O39: Minimum call-out by quote | P39: Certified rigger/dogman labour to stated lift methodology | Q39: Crane, rigging gear, travel and overtime unless specifically included | R39: Low | S39: RED - quote or job-specific evidence required | T39: Base $1 forces explicit job-rate override; verify competency and crew composition.
A40: PL-CRANE-70AT | B40: Plant | C40: 70 t all-terrain mobile crane wet hire | D40: Plant | E40: hr | F40: Specialist crane hire | G40: Yes | H40: Yes | I40: 1 | J40: NZ / AU project-specific | K40: 15-Aug-2026 | L40: Job override required | M40: Mobile crane supplier | N40: Quote required | O40: Minimum hire + mobilisation by quote | P40: Crane, operator and normal fuel subject to supplier quote | Q40: Mobilisation, ballast transport, rigging, dogman, mats, travel/overtime unless included | R40: Low | S40: RED - quote or job-specific evidence required | T40: Capacity class only. Verify certified load chart, lift radius, ballast, outrigger reactions, access and minimum hire.
A41: PL-CRANE-90AT | B41: Plant | C41: 90 t all-terrain mobile crane wet hire | D41: Plant | E41: hr | F41: Specialist crane hire | G41: Yes | H41: Yes | I41: 1 | J41: NZ / AU project-specific | K41: 15-Aug-2026 | L41: Job override required | M41: Mobile crane supplier | N41: Quote required | O41: Minimum hire + mobilisation by quote | P41: Crane, operator and normal fuel subject to supplier quote | Q41: Mobilisation, ballast transport, rigging, dogman, mats, travel/overtime unless included | R41: Low | S41: RED - quote or job-specific evidence required | T41: Capacity class only. Verify certified load chart, lift radius, ballast, outrigger reactions, access and minimum hire.
A42: PL-CRANE-120AT | B42: Plant | C42: 120 t all-terrain mobile crane wet hire | D42: Plant | E42: hr | F42: Specialist crane hire | G42: Yes | H42: Yes | I42: 1 | J42: NZ / AU project-specific | K42: 15-Aug-2026 | L42: Job override required | M42: Mobile crane supplier | N42: Quote required | O42: Minimum hire + mobilisation by quote | P42: Crane, operator and normal fuel subject to supplier quote | Q42: Mobilisation, ballast transport, rigging, dogman, mats, travel/overtime unless included | R42: Low | S42: RED - quote or job-specific evidence required | T42: Capacity class only. Verify certified load chart, lift radius, ballast, outrigger reactions, access and minimum hire.
A43: PL-CRANE-MATS | B43: Plant | C43: Crane mats / outrigger spreader mats hire set | D43: Plant | E43: day | F43: Specialist hire | G43: N/A | H43: N/A | I43: 1 | J43: NZ / AU project-specific | K43: 15-Aug-2026 | L43: Job override required | M43: Crane / temporary works supplier | N43: Quote required | O43: Minimum hire / transport by quote | P43: Mats/spreader set to supplier/temp-works requirement | Q43: Transport, placement, design/certification and abnormal ground treatment unless included | R43: Low | S43: RED - quote or job-specific evidence required | T43: Base $1 forces explicit job override. Check whether crane supplier already includes mats to avoid duplication.
A44: PL-RIGGING-SET | B44: Plant | C44: Certified crane rigging / lifting gear set | D44: Plant | E44: day | F44: Specialist hire | G44: N/A | H44: N/A | I44: 1 | J44: NZ / AU project-specific | K44: 15-Aug-2026 | L44: Job override required | M44: Crane / rigging supplier | N44: Quote required | O44: Minimum hire / mobilisation by quote | P44: Certified slings, shackles and stated lifting gear set | Q44: Project-specific lifting beam, proprietary clutches, engineered lifting frame and rigger labour unless included | R44: Low | S44: RED - quote or job-specific evidence required | T44: Base $1 forces explicit job override; reconcile with crane quote and precaster lifting requirements.
A45: PL-TRUCK-6W | B45: Plant | C45: 6-wheel tip truck wet hire | D45: Plant | E45: hr | F45: Wet hire / cartage | G45: Yes | H45: Yes | I45: 1 | J45: NZ / AU project-specific | K45: 15-Aug-2026 | L45: Job override required | M45: Civil cartage supplier | N45: Quote required | O45: Minimum hours / travel by quote | P45: Truck, driver and normal fuel subject to quote | Q45: Tipping fees, material supply, permits and abnormal waiting unless included | R45: Low | S45: RED - quote or job-specific evidence required | T45: Use for internal/site cartage where hourly wet hire is the truthful basis; do not duplicate supplier-delivery charges.
A46: PL-TRANSPORT-HEAVY | B46: Plant | C46: Heavy / oversize transporter or precast internal haul | D46: Plant | E46: trip | F46: Specialist transport | G46: Yes | H46: Yes | I46: 1 | J46: NZ / AU project-specific | K46: 15-Aug-2026 | L46: Job override required | M46: Heavy transport / precast carrier | N46: Quote required | O46: Mobilisation, permits and escort by quote | P46: Transport vehicle and driver to stated route/load | Q46: Craneage, loading/unloading, permits/escorts and route strengthening unless included | R46: Low | S46: RED - quote or job-specific evidence required | T46: Use only where contractor transport scope is confirmed. Verify route, axle/load limits, turning and delivery responsibility.
A47: OTH-CARTAGE-LOAD | B47: Other | C47: Supplier delivery / cartage charge per load | D47: Other | E47: load | F47: Job-specific supplier delivery | G47: N/A | H47: N/A | I47: 1 | J47: Project-specific | K47: 15-Aug-2026 | L47: Job override required | M47: Material supplier / carrier | N47: Quote required | O47: Load size / zone / minimum by quote | P47: Delivery/cartage charge only to stated site and load size | Q47: Material supply, waiting time, tipping, permits and rehandling unless included | R47: Low | S47: RED - quote or job-specific evidence required | T47: Reusable cost code only; project location, load size and delivered rate must be overridden from current evidence.
A48: SUB-PROOFROLL | B48: Subcontract | C48: Proof-roll / working-platform verification / field testing attendance | D48: Subcontract | E48: LS | F48: Specialist subcontract | G48: N/A | H48: N/A | I48: 1 | J48: NZ / AU project-specific | K48: 15-Aug-2026 | L48: Job override required | M48: Geotech / testing provider | N48: Quote required | O48: Attendance / testing scope by quote | P48: Proof-roll or stated field-verification/testing attendance | Q48: Temporary works design, geotech design certification, remediation and repeat visits unless included | R48: Low | S48: RED - quote or job-specific evidence required | T48: Keep testing/verification separate from temporary-works design and from physical platform construction.
A49: MAT-GEOGRID | B49: Material | C49: Geogrid / ground-stabilisation reinforcement - project specified | D49: Material | E49: m2 | F49: Merchant supply | G49: N/A | H49: N/A | I49: 1 | J49: NZ / AU project-specific | K49: 15-Aug-2026 | L49: Job override required | M49: Civil merchant / geosynthetics supplier | N49: Quote required | O49: Product/specification by quote | P49: Specified geogrid material only | Q49: Design, geotextile, aggregate, installation and laps/waste unless included | R49: Low | S49: RED - quote or job-specific evidence required | T49: No generic rate. Select product from temporary works/geotech design and obtain project-specific quote.
A50: ALLIED-LAB-FOREMAN | B50: Labour | C50: Civil foreman / working foreman - Allied specific | D50: Labour | E50: hr | F50: Internal / agency | G50: N/A | H50: N/A | I50: 65 | J50: Auckland / NZ | K50: 17-Aug-2026 | L50: Allied-specific rate - company input (AMBER) | M50: Allied Civil - Jason review | N50: Clevedon_Civil_Works_Tender_Estimate_Rev5JW.xlsx; comparison baseline LAB-FOREMAN = $64.00/hr | P50: Direct employment allowance | Q50: Margin, vehicle, overtime
A51: ALLIED-LAB-SUPERVISOR | B51: Labour | C51: Site supervisor / project manager - Allied specific | D51: Labour | E51: hr | F51: Internal / agency | G51: N/A | H51: N/A | I51: 70 | J51: Auckland / NZ | K51: 17-Aug-2026 | L51: Allied-specific rate - company input (AMBER) | M51: Allied Civil - Jason review | N51: Clevedon_Civil_Works_Tender_Estimate_Rev5JW.xlsx; comparison baseline LAB-SUPERVISOR = $73.00/hr | P51: Direct employment allowance | Q51: Margin, vehicle, overtime
A52: ALLIED-LAB-DRAINLAYER | B52: Labour | C52: Registered drainlayer / pipe layer - Allied specific | D52: Labour | E52: hr | F52: Internal / agency | G52: N/A | H52: N/A | I52: 45 | J52: Auckland / NZ | K52: 17-Aug-2026 | L52: Allied-specific rate - company input (AMBER) | M52: Allied Civil - Jason review | N52: Clevedon_Civil_Works_Tender_Estimate_Rev5JW.xlsx; comparison baseline LAB-DRAINLAYER = $51.00/hr | P52: Direct employment allowance | Q52: Vehicle and overtime
A53: ALLIED-PL-EXC-1.7 | B53: Plant | C53: 1.7 t excavator wet hire - Allied specific | D53: Plant | E53: hr | F53: Wet hire | G53: Yes | H53: Yes | I53: 75 | J53: Auckland | K53: 17-Aug-2026 | L53: Allied-specific rate - company input (AMBER) | M53: Allied Civil - Jason review | N53: Clevedon_Civil_Works_Tender_Estimate_Rev5JW.xlsx; comparison baseline PL-EXC-1.7 = $85.00/hr | O53: Delivery by quote | P53: Machine, operator, fuel and normal buckets | Q53: Delivery, overtime and specialist attachments
A54: ALLIED-MAT-AP65 | B54: Material | C54: AP65 subbase aggregate - Allied specific | D54: Material | E54: t | F54: Merchant supply | G54: N/A | H54: N/A | I54: 29 | J54: Auckland | K54: 17-Aug-2026 | L54: Allied-specific rate - company input (AMBER) | M54: Rockshop Quarry - Allied direct-delivery / T&T basis | N54: Clevedon_Civil_Works_Tender_Estimate_Rev5JW.xlsx; comparison baseline MAT-AP65 = $30.50/t | P54: Ex-quarry / base material allowance | Q54: Haul and placement; confirm whether Allied $/t basis includes T&T direct delivery
A55: ALLIED-MAT-AP40 | B55: Material | C55: AP40 / GAP40 basecourse aggregate - Allied specific | D55: Material | E55: t | F55: Merchant supply | G55: N/A | H55: N/A | I55: 29 | J55: Auckland | K55: 17-Aug-2026 | L55: Allied-specific rate - company input (AMBER) | M55: Rockshop Quarry - Allied direct-delivery / T&T basis | N55: Clevedon_Civil_Works_Tender_Estimate_Rev5JW.xlsx; comparison baseline MAT-AP40 = $31.00/t | P55: Ex-quarry / base material allowance | Q55: Haul and placement; confirm whether Allied $/t basis includes T&T direct delivery
A56: ALLIED-MAT-DRAINAGG | B56: Material | C56: Drainage aggregate - Allied specific | D56: Material | E56: t | F56: Merchant supply | G56: N/A | H56: N/A | I56: 36 | J56: Auckland | K56: 17-Aug-2026 | L56: Allied-specific rate - company input (AMBER) | M56: Rockshop Quarry - Allied direct-delivery / T&T basis | N56: Clevedon_Civil_Works_Tender_Estimate_Rev5JW.xlsx; comparison baseline MAT-DRAINAGG = $48.50/t | P56: Aggregate | Q56: Haul and placement; confirm whether Allied $/t basis includes T&T direct delivery
A57: ALLIED-MAT-SWMH | B57: Material | C57: Precast stormwater manhole set - Allied specific | D57: Material | E57: ea | F57: Precast supplier | G57: N/A | H57: N/A | I57: 7000 | J57: Auckland | K57: 17-Aug-2026 | L57: Allied-specific rate - company input (AMBER) | M57: Allied Civil / Auckland Council safety-grate requirement | N57: Clevedon_Civil_Works_Tender_Estimate_Rev5JW.xlsx; comparison baseline MAT-SWMH = $5500.00/ea | P57: Chamber, riser, lid and safety grate allowance | Q57: Excavation, concrete and installation
A58: ALLIED-OTH-FACILITIES | B58: Other | C58: Temporary facilities, utilities and welfare weekly allowance - Allied specific | D58: Other | E58: week | F58: Job-specific / hire allowance | G58: N/A | H58: N/A | I58: 410 | J58: Auckland | K58: 17-Aug-2026 | L58: Allied-specific rate - company input (AMBER) | M58: Allied Civil - Jason review | N58: Clevedon_Civil_Works_Tender_Estimate_Rev5JW.xlsx; PG03 note; 20 weeks = $8,200.00 | O58: Confirm hire minimums and mobilisation | P58: Weekly facilities, toilet, temporary power/water and consumables allowance | Q58: Mobilisation, site-specific setup and abnormal servicing unless confirmed
A59: ALLIED-SUB-SURVEY-SET | B59: Subcontract | C59: Drainage construction setout package - Allied specific | D59: Subcontract | E59: LS | F59: Specialist subcontract | G59: N/A | H59: N/A | I59: 1500 | J59: Auckland | K59: 17-Aug-2026 | L59: Allied-specific supplier input (AMBER) | M59: Allied Civil survey supplier - not named | N59: Clevedon_Civil_Works_Tender_Estimate_Rev5JW.xlsx; Rate Verification note; rate recorded excl. GST | O59: One drainage setout package | P59: Drainage construction setout | Q59: Other survey, rework, as-builts and additional visits
A60: ALLIED-SUB-SURVEY-ASB | B60: Subcontract | C60: Drainage as-built survey package - Allied specific | D60: Subcontract | E60: LS | F60: Specialist subcontract | G60: N/A | H60: N/A | I60: 2500 | J60: Auckland | K60: 17-Aug-2026 | L60: Allied-specific supplier input (AMBER) | M60: Allied Civil survey supplier - not named | N60: Clevedon_Civil_Works_Tender_Estimate_Rev5JW.xlsx; Rate Verification note; rate recorded excl. GST | O60: One drainage as-built package | P60: Drainage as-built survey | Q60: Setout, other survey, rework and additional visits
A61: ALLIED-SUB-GPR-VISIT | B61: Subcontract | C61: GPR utility-locating visit - Allied specific | D61: Subcontract | E61: visit | F61: Specialist subcontract | G61: N/A | H61: N/A | I61: 250 | J61: Auckland | K61: 17-Aug-2026 | L61: Allied-specific supplier input (AMBER) | M61: Allied Civil GPR supplier - not named | N61: Clevedon_Civil_Works_Tender_Estimate_Rev5JW.xlsx; Jason noted cash rate/no GST - formal invoicing and scope require verification | O61: Per visit; minimums and mobilisation to confirm | P61: GPR utility-locating visit | Q61: Potholing, traffic management, additional visits and formal report unless confirmed
A62: ALLIED-SUB-TMP-DAY | B62: Subcontract | C62: Traffic management delivery day - Allied specific | D62: Subcontract | E62: day | F62: Specialist subcontract | G62: Yes | H62: Yes | I62: 1600 | J62: Auckland | K62: 17-Aug-2026 | L62: Allied-specific supplier input (AMBER) | M62: Allied Civil TMP supplier - not named | N62: Clevedon_Civil_Works_Tender_Estimate_Rev5JW.xlsx; Rate Verification note; TMP plan/design is additional | O62: Daily minimum; confirm working hours | P62: On-site traffic management delivery day | Q62: TMP plan/design, approvals, after-hours, fees and extensions
A63: ALLIED-SUB-LINEMARK | B63: Subcontract | C63: Standard line marking - Allied specific | D63: Subcontract | E63: lm | F63: Specialist subcontract | G63: Yes | H63: Yes | I63: 22 | J63: Auckland | K63: 17-Aug-2026 | L63: Allied-specific supplier input (AMBER) | M63: Allied Civil line-marking supplier - not named | N63: Clevedon_Civil_Works_Tender_Estimate_Rev5JW.xlsx; QS PV06 firm-up note | O63: Minimum job charge to confirm | P63: Standard line marking per lineal metre | Q63: Arrows, symbols, accessible markings, signs, preparation and traffic management unless quoted

Sheet Resource Build-Up
A1: RESOURCE BUILD-UP - MASTER ESTIMATE WORKBOOK REV2 - LINKED COST / DURATION FORMULAS
A2: Every active QS Code must have resource rows here. Extended Cost totals by QS Code are pulled into QS Takeoff; do not type a second QS rate or amount.
A3: Ordinary civil plant stays Plant whether owned or hired. Specialist delivered capability such as mobile cranes is normally Subcontract. Wet hire must record operator/fuel inclusions to stop double counting.
A4: Calculation modes: Time x Count; QS Qty x Factor; Direct Qty; Lump Sum / Quote. Duration is derived from quantity/productivity or explicitly overridden where sequencing requires it.
A5: Weather controls: AK:AM are estimator inputs; AN is formula-controlled exposed Labour/Plant cost feeding Weather Risk. Materials, fixed subcontract and Other costs are excluded from direct weather productivity by default.
A6: Build-Up Row ID | B6: QS Code | C6: WBS / Section | D6: Task Description | E6: QS Qty | F6: QS Unit | G6: Estimate Class | H6: Methodology / Work Step | I6: Productivity Rate | J6: Productivity Unit | K6: Calc Duration hrs | L6: Duration Override hrs | M6: Applied Duration hrs | N6: Calculation Mode | O6: Resource Type | P6: Resource Code | Q6: Resource Description | R6: Resource Count / Factor | S6: Manual Resource Qty | T6: Resource Unit | U6: Utilisation % | V6: Waste % | W6: Library Rate | X6: Job Rate Override | Y6: Applied Rate | Z6: Extended Cost | AA6: Library Source | AB6: Job Quote / Source Ref | AC6: Source Date | AD6: Operator Included? | AE6: Fuel Included? | AF6: Confidence | AG6: Assumption / RFI | AH6: Verified? | AI6: QA / Double-Count Check | AJ6: Notes | AK6: Weather Exposed? | AL6: Weather Task Type | AM6: Weather Basis / Status | AN6: Weather-Exposed Labour + Plant Cost
A7: =IF(B7="","",B7&"-"&TEXT(COUNTIF($B$7:B7,B7),"000")) | C7: =IFERROR(INDEX('QS Takeoff'!$A$3:$A$194,MATCH(B7,'QS Takeoff'!$B$3:$B$194,0)),"") | D7: =IFERROR(INDEX('QS Takeoff'!$C$3:$C$194,MATCH(B7,'QS Takeoff'!$B$3:$B$194,0)),"") | E7: =IFERROR(INDEX('QS Takeoff'!$E$3:$E$194,MATCH(B7,'QS Takeoff'!$B$3:$B$194,0)),"") | F7: =IFERROR(INDEX('QS Takeoff'!$D$3:$D$194,MATCH(B7,'QS Takeoff'!$B$3:$B$194,0)),"") | G7: =IFERROR(INDEX('QS Takeoff'!$J$3:$J$194,MATCH(B7,'QS Takeoff'!$B$3:$B$194,0)),"") | K7: =IF(OR(B7="",I7="",I7=0),"",E7/I7) | M7: =IF(L7>0,L7,K7) | Q7: =IFERROR(INDEX('Resource Rate Library'!$C$5:$C$85,MATCH(P7,'Resource Rate Library'!$A$5:$A$85,0)),"") | T7: =IFERROR(INDEX('Resource Rate Library'!$E$5:$E$85,MATCH(P7,'Resource Rate Library'!$A$5:$A$85,0)),"") | W7: =IFERROR(INDEX('Resource Rate Library'!$I$5:$I$85,MATCH(P7,'Resource Rate Library'!$A$5:$A$85,0)),0) -> 0 | Y7: =IF(X7>0,X7,W7) -> 0 | Z7: =IF(B7="","",IF(N7="Time x Count",M7*R7*IF(U7="",1,U7)*Y7,IF(N7="QS Qty x Factor",E7*R7*(1+IF(V7="",0,V7))*Y7,IF(N7="Direct Qty",S7*(1+IF(V7="",0,V7))*Y7,IF(N7="Lump Sum / Quote",S7*Y7,0))))) | AA7: =IFERROR(INDEX('Resource Rate Library'!$N$5:$N$85,MATCH(P7,'Resource Rate Library'!$A$5:$A$85,0)),"") | AD7: =IFERROR(INDEX('Resource Rate Library'!$G$5:$G$85,MATCH(P7,'Resource Rate Library'!$A$5:$A$85,0)),"") | AE7: =IFERROR(INDEX('Resource Rate Library'!$H$5:$H$85,MATCH(P7,'Resource Rate Library'!$A$5:$A$85,0)),"") | AI7: =IF(B7="","",IF(AND(P7="",N7<>"Lump Sum / Quote"),"RESOURCE CODE",IF(Y7=0,"RATE MISSING",IF(AND(O7="Plant",AD7="Yes",COUNTIFS($B$7:$B$306,B7,$O$7:$O$306,"Labour",$Q$7:$Q$306,"*Operator*")>0),"OPERATOR DOUBLE-COUNT",IF(AND(O7="Plant",AE7="Yes",COUNTIFS($B$7:$B$306,B7,$Q$7:$Q$306,"*Fuel*")>0),"FUEL DOUBLE-COUNT",IF(AH7<>"Yes","VERIFY","OK")))))) | AN7: =IF(AND(AK7="Yes",OR(O7="Labour",O7="Plant")),Z7,0) -> 0
A8: =IF(B8="","",B8&"-"&TEXT(COUNTIF($B$7:B8,B8),"000")) | C8: =IFERROR(INDEX('QS Takeoff'!$A$3:$A$194,MATCH(B8,'QS Takeoff'!$B$3:$B$194,0)),"") | D8: =IFERROR(INDEX('QS Takeoff'!$C$3:$C$194,MATCH(B8,'QS Takeoff'!$B$3:$B$194,0)),"") | E8: =IFERROR(INDEX('QS Takeoff'!$E$3:$E$194,MATCH(B8,'QS Takeoff'!$B$3:$B$194,0)),"") | F8: =IFERROR(INDEX('QS Takeoff'!$D$3:$D$194,MATCH(B8,'QS Takeoff'!$B$3:$B$194,0)),"") | G8: =IFERROR(INDEX('QS Takeoff'!$J$3:$J$194,MATCH(B8,'QS Takeoff'!$B$3:$B$194,0)),"") | K8: =IF(OR(B8="",I8="",I8=0),"",E8/I8) | M8: =IF(L8>0,L8,K8) | Q8: =IFERROR(INDEX('Resource Rate Library'!$C$5:$C$85,MATCH(P8,'Resource Rate Library'!$A$5:$A$85,0)),"") | T8: =IFERROR(INDEX('Resource Rate Library'!$E$5:$E$85,MATCH(P8,'Resource Rate Library'!$A$5:$A$85,0)),"") | W8: =IFERROR(INDEX('Resource Rate Library'!$I$5:$I$85,MATCH(P8,'Resource Rate Library'!$A$5:$A$85,0)),0) -> 0 | Y8: =IF(X8>0,X8,W8) -> 0 | Z8: =IF(B8="","",IF(N8="Time x Count",M8*R8*IF(U8="",1,U8)*Y8,IF(N8="QS Qty x Factor",E8*R8*(1+IF(V8="",0,V8))*Y8,IF(N8="Direct Qty",S8*(1+IF(V8="",0,V8))*Y8,IF(N8="Lump Sum / Quote",S8*Y8,0))))) | AA8: =IFERROR(INDEX('Resource Rate Library'!$N$5:$N$85,MATCH(P8,'Resource Rate Library'!$A$5:$A$85,0)),"") | AD8: =IFERROR(INDEX('Resource Rate Library'!$G$5:$G$85,MATCH(P8,'Resource Rate Library'!$A$5:$A$85,0)),"") | AE8: =IFERROR(INDEX('Resource Rate Library'!$H$5:$H$85,MATCH(P8,'Resource Rate Library'!$A$5:$A$85,0)),"") | AI8: =IF(B8="","",IF(AND(P8="",N8<>"Lump Sum / Quote"),"RESOURCE CODE",IF(Y8=0,"RATE MISSING",IF(AND(O8="Plant",AD8="Yes",COUNTIFS($B$7:$B$306,B8,$O$7:$O$306,"Labour",$Q$7:$Q$306,"*Operator*")>0),"OPERATOR DOUBLE-COUNT",IF(AND(O8="Plant",AE8="Yes",COUNTIFS($B$7:$B$306,B8,$Q$7:$Q$306,"*Fuel*")>0),"FUEL DOUBLE-COUNT",IF(AH8<>"Yes","VERIFY","OK")))))) | AN8: =IF(AND(AK8="Yes",OR(O8="Labour",O8="Plant")),Z8,0) -> 0
A9: =IF(B9="","",B9&"-"&TEXT(COUNTIF($B$7:B9,B9),"000")) | C9: =IFERROR(INDEX('QS Takeoff'!$A$3:$A$194,MATCH(B9,'QS Takeoff'!$B$3:$B$194,0)),"") | D9: =IFERROR(INDEX('QS Takeoff'!$C$3:$C$194,MATCH(B9,'QS Takeoff'!$B$3:$B$194,0)),"") | E9: =IFERROR(INDEX('QS Takeoff'!$E$3:$E$194,MATCH(B9,'QS Takeoff'!$B$3:$B$194,0)),"") | F9: =IFERROR(INDEX('QS Takeoff'!$D$3:$D$194,MATCH(B9,'QS Takeoff'!$B$3:$B$194,0)),"") | G9: =IFERROR(INDEX('QS Takeoff'!$J$3:$J$194,MATCH(B9,'QS Takeoff'!$B$3:$B$194,0)),"") | K9: =IF(OR(B9="",I9="",I9=0),"",E9/I9) | M9: =IF(L9>0,L9,K9) | Q9: =IFERROR(INDEX('Resource Rate Library'!$C$5:$C$85,MATCH(P9,'Resource Rate Library'!$A$5:$A$85,0)),"") | T9: =IFERROR(INDEX('Resource Rate Library'!$E$5:$E$85,MATCH(P9,'Resource Rate Library'!$A$5:$A$85,0)),"") | W9: =IFERROR(INDEX('Resource Rate Library'!$I$5:$I$85,MATCH(P9,'Resource Rate Library'!$A$5:$A$85,0)),0) -> 0 | Y9: =IF(X9>0,X9,W9) -> 0 | Z9: =IF(B9="","",IF(N9="Time x Count",M9*R9*IF(U9="",1,U9)*Y9,IF(N9="QS Qty x Factor",E9*R9*(1+IF(V9="",0,V9))*Y9,IF(N9="Direct Qty",S9*(1+IF(V9="",0,V9))*Y9,IF(N9="Lump Sum / Quote",S9*Y9,0))))) | AA9: =IFERROR(INDEX('Resource Rate Library'!$N$5:$N$85,MATCH(P9,'Resource Rate Library'!$A$5:$A$85,0)),"") | AD9: =IFERROR(INDEX('Resource Rate Library'!$G$5:$G$85,MATCH(P9,'Resource Rate Library'!$A$5:$A$85,0)),"") | AE9: =IFERROR(INDEX('Resource Rate Library'!$H$5:$H$85,MATCH(P9,'Resource Rate Library'!$A$5:$A$85,0)),"") | AI9: =IF(B9="","",IF(AND(P9="",N9<>"Lump Sum / Quote"),"RESOURCE CODE",IF(Y9=0,"RATE MISSING",IF(AND(O9="Plant",AD9="Yes",COUNTIFS($B$7:$B$306,B9,$O$7:$O$306,"Labour",$Q$7:$Q$306,"*Operator*")>0),"OPERATOR DOUBLE-COUNT",IF(AND(O9="Plant",AE9="Yes",COUNTIFS($B$7:$B$306,B9,$Q$7:$Q$306,"*Fuel*")>0),"FUEL DOUBLE-COUNT",IF(AH9<>"Yes","VERIFY","OK")))))) | AN9: =IF(AND(AK9="Yes",OR(O9="Labour",O9="Plant")),Z9,0) -> 0
A10: =IF(B10="","",B10&"-"&TEXT(COUNTIF($B$7:B10,B10),"000")) | C10: =IFERROR(INDEX('QS Takeoff'!$A$3:$A$194,MATCH(B10,'QS Takeoff'!$B$3:$B$194,0)),"") | D10: =IFERROR(INDEX('QS Takeoff'!$C$3:$C$194,MATCH(B10,'QS Takeoff'!$B$3:$B$194,0)),"") | E10: =IFERROR(INDEX('QS Takeoff'!$E$3:$E$194,MATCH(B10,'QS Takeoff'!$B$3:$B$194,0)),"") | F10: =IFERROR(INDEX('QS Takeoff'!$D$3:$D$194,MATCH(B10,'QS Takeoff'!$B$3:$B$194,0)),"") | G10: =IFERROR(INDEX('QS Takeoff'!$J$3:$J$194,MATCH(B10,'QS Takeoff'!$B$3:$B$194,0)),"") | K10: =IF(OR(B10="",I10="",I10=0),"",E10/I10) | M10: =IF(L10>0,L10,K10) | Q10: =IFERROR(INDEX('Resource Rate Library'!$C$5:$C$85,MATCH(P10,'Resource Rate Library'!$A$5:$A$85,0)),"") | T10: =IFERROR(INDEX('Resource Rate Library'!$E$5:$E$85,MATCH(P10,'Resource Rate Library'!$A$5:$A$85,0)),"") | W10: =IFERROR(INDEX('Resource Rate Library'!$I$5:$I$85,MATCH(P10,'Resource Rate Library'!$A$5:$A$85,0)),0) -> 0 | Y10: =IF(X10>0,X10,W10) -> 0 | Z10: =IF(B10="","",IF(N10="Time x Count",M10*R10*IF(U10="",1,U10)*Y10,IF(N10="QS Qty x Factor",E10*R10*(1+IF(V10="",0,V10))*Y10,IF(N10="Direct Qty",S10*(1+IF(V10="",0,V10))*Y10,IF(N10="Lump Sum / Quote",S10*Y10,0))))) | AA10: =IFERROR(INDEX('Resource Rate Library'!$N$5:$N$85,MATCH(P10,'Resource Rate Library'!$A$5:$A$85,0)),"") | AD10: =IFERROR(INDEX('Resource Rate Library'!$G$5:$G$85,MATCH(P10,'Resource Rate Library'!$A$5:$A$85,0)),"") | AE10: =IFERROR(INDEX('Resource Rate Library'!$H$5:$H$85,MATCH(P10,'Resource Rate Library'!$A$5:$A$85,0)),"") | AI10: =IF(B10="","",IF(AND(P10="",N10<>"Lump Sum / Quote"),"RESOURCE CODE",IF(Y10=0,"RATE MISSING",IF(AND(O10="Plant",AD10="Yes",COUNTIFS($B$7:$B$306,B10,$O$7:$O$306,"Labour",$Q$7:$Q$306,"*Operator*")>0),"OPERATOR DOUBLE-COUNT",IF(AND(O10="Plant",AE10="Yes",COUNTIFS($B$7:$B$306,B10,$Q$7:$Q$306,"*Fuel*")>0),"FUEL DOUBLE-COUNT",IF(AH10<>"Yes","VERIFY","OK")))))) | AN10: =IF(AND(AK10="Yes",OR(O10="Labour",O10="Plant")),Z10,0) -> 0
A11: =IF(B11="","",B11&"-"&TEXT(COUNTIF($B$7:B11,B11),"000")) | C11: =IFERROR(INDEX('QS Takeoff'!$A$3:$A$194,MATCH(B11,'QS Takeoff'!$B$3:$B$194,0)),"") | D11: =IFERROR(INDEX('QS Takeoff'!$C$3:$C$194,MATCH(B11,'QS Takeoff'!$B$3:$B$194,0)),"") | E11: =IFERROR(INDEX('QS Takeoff'!$E$3:$E$194,MATCH(B11,'QS Takeoff'!$B$3:$B$194,0)),"") | F11: =IFERROR(INDEX('QS Takeoff'!$D$3:$D$194,MATCH(B11,'QS Takeoff'!$B$3:$B$194,0)),"") | G11: =IFERROR(INDEX('QS Takeoff'!$J$3:$J$194,MATCH(B11,'QS Takeoff'!$B$3:$B$194,0)),"") | K11: =IF(OR(B11="",I11="",I11=0),"",E11/I11) | M11: =IF(L11>0,L11,K11) | Q11: =IFERROR(INDEX('Resource Rate Library'!$C$5:$C$85,MATCH(P11,'Resource Rate Library'!$A$5:$A$85,0)),"") | T11: =IFERROR(INDEX('Resource Rate Library'!$E$5:$E$85,MATCH(P11,'Resource Rate Library'!$A$5:$A$85,0)),"") | W11: =IFERROR(INDEX('Resource Rate Library'!$I$5:$I$85,MATCH(P11,'Resource Rate Library'!$A$5:$A$85,0)),0) -> 0 | Y11: =IF(X11>0,X11,W11) -> 0 | Z11: =IF(B11="","",IF(N11="Time x Count",M11*R11*IF(U11="",1,U11)*Y11,IF(N11="QS Qty x Factor",E11*R11*(1+IF(V11="",0,V11))*Y11,IF(N11="Direct Qty",S11*(1+IF(V11="",0,V11))*Y11,IF(N11="Lump Sum / Quote",S11*Y11,0))))) | AA11: =IFERROR(INDEX('Resource Rate Library'!$N$5:$N$85,MATCH(P11,'Resource Rate Library'!$A$5:$A$85,0)),"") | AD11: =IFERROR(INDEX('Resource Rate Library'!$G$5:$G$85,MATCH(P11,'Resource Rate Library'!$A$5:$A$85,0)),"") | AE11: =IFERROR(INDEX('Resource Rate Library'!$H$5:$H$85,MATCH(P11,'Resource Rate Library'!$A$5:$A$85,0)),"") | AI11: =IF(B11="","",IF(AND(P11="",N11<>"Lump Sum / Quote"),"RESOURCE CODE",IF(Y11=0,"RATE MISSING",IF(AND(O11="Plant",AD11="Yes",COUNTIFS($B$7:$B$306,B11,$O$7:$O$306,"Labour",$Q$7:$Q$306,"*Operator*")>0),"OPERATOR DOUBLE-COUNT",IF(AND(O11="Plant",AE11="Yes",COUNTIFS($B$7:$B$306,B11,$Q$7:$Q$306,"*Fuel*")>0),"FUEL DOUBLE-COUNT",IF(AH11<>"Yes","VERIFY","OK")))))) | AN11: =IF(AND(AK11="Yes",OR(O11="Labour",O11="Plant")),Z11,0) -> 0
A12: =IF(B12="","",B12&"-"&TEXT(COUNTIF($B$7:B12,B12),"000")) | C12: =IFERROR(INDEX('QS Takeoff'!$A$3:$A$194,MATCH(B12,'QS Takeoff'!$B$3:$B$194,0)),"") | D12: =IFERROR(INDEX('QS Takeoff'!$C$3:$C$194,MATCH(B12,'QS Takeoff'!$B$3:$B$194,0)),"") | E12: =IFERROR(INDEX('QS Takeoff'!$E$3:$E$194,MATCH(B12,'QS Takeoff'!$B$3:$B$194,0)),"") | F12: =IFERROR(INDEX('QS Takeoff'!$D$3:$D$194,MATCH(B12,'QS Takeoff'!$B$3:$B$194,0)),"") | G12: =IFERROR(INDEX('QS Takeoff'!$J$3:$J$194,MATCH(B12,'QS Takeoff'!$B$3:$B$194,0)),"") | K12: =IF(OR(B12="",I12="",I12=0),"",E12/I12) | M12: =IF(L12>0,L12,K12) | Q12: =IFERROR(INDEX('Resource Rate Library'!$C$5:$C$85,MATCH(P12,'Resource Rate Library'!$A$5:$A$85,0)),"") | T12: =IFERROR(INDEX('Resource Rate Library'!$E$5:$E$85,MATCH(P12,'Resource Rate Library'!$A$5:$A$85,0)),"") | W12: =IFERROR(INDEX('Resource Rate Library'!$I$5:$I$85,MATCH(P12,'Resource Rate Library'!$A$5:$A$85,0)),0) -> 0 | Y12: =IF(X12>0,X12,W12) -> 0 | Z12: =IF(B12="","",IF(N12="Time x Count",M12*R12*IF(U12="",1,U12)*Y12,IF(N12="QS Qty x Factor",E12*R12*(1+IF(V12="",0,V12))*Y12,IF(N12="Direct Qty",S12*(1+IF(V12="",0,V12))*Y12,IF(N12="Lump Sum / Quote",S12*Y12,0))))) | AA12: =IFERROR(INDEX('Resource Rate Library'!$N$5:$N$85,MATCH(P12,'Resource Rate Library'!$A$5:$A$85,0)),"") | AD12: =IFERROR(INDEX('Resource Rate Library'!$G$5:$G$85,MATCH(P12,'Resource Rate Library'!$A$5:$A$85,0)),"") | AE12: =IFERROR(INDEX('Resource Rate Library'!$H$5:$H$85,MATCH(P12,'Resource Rate Library'!$A$5:$A$85,0)),"") | AI12: =IF(B12="","",IF(AND(P12="",N12<>"Lump Sum / Quote"),"RESOURCE CODE",IF(Y12=0,"RATE MISSING",IF(AND(O12="Plant",AD12="Yes",COUNTIFS($B$7:$B$306,B12,$O$7:$O$306,"Labour",$Q$7:$Q$306,"*Operator*")>0),"OPERATOR DOUBLE-COUNT",IF(AND(O12="Plant",AE12="Yes",COUNTIFS($B$7:$B$306,B12,$Q$7:$Q$306,"*Fuel*")>0),"FUEL DOUBLE-COUNT",IF(AH12<>"Yes","VERIFY","OK")))))) | AN12: =IF(AND(AK12="Yes",OR(O12="Labour",O12="Plant")),Z12,0) -> 0
A13: =IF(B13="","",B13&"-"&TEXT(COUNTIF($B$7:B13,B13),"000")) | C13: =IFERROR(INDEX('QS Takeoff'!$A$3:$A$194,MATCH(B13,'QS Takeoff'!$B$3:$B$194,0)),"") | D13: =IFERROR(INDEX('QS Takeoff'!$C$3:$C$194,MATCH(B13,'QS Takeoff'!$B$3:$B$194,0)),"") | E13: =IFERROR(INDEX('QS Takeoff'!$E$3:$E$194,MATCH(B13,'QS Takeoff'!$B$3:$B$194,0)),"") | F13: =IFERROR(INDEX('QS Takeoff'!$D$3:$D$194,MATCH(B13,'QS Takeoff'!$B$3:$B$194,0)),"") | G13: =IFERROR(INDEX('QS Takeoff'!$J$3:$J$194,MATCH(B13,'QS Takeoff'!$B$3:$B$194,0)),"") | K13: =IF(OR(B13="",I13="",I13=0),"",E13/I13) | M13: =IF(L13>0,L13,K13) | Q13: =IFERROR(INDEX('Resource Rate Library'!$C$5:$C$85,MATCH(P13,'Resource Rate Library'!$A$5:$A$85,0)),"") | T13: =IFERROR(INDEX('Resource Rate Library'!$E$5:$E$85,MATCH(P13,'Resource Rate Library'!$A$5:$A$85,0)),"") | W13: =IFERROR(INDEX('Resource Rate Library'!$I$5:$I$85,MATCH(P13,'Resource Rate Library'!$A$5:$A$85,0)),0) -> 0 | Y13: =IF(X13>0,X13,W13) -> 0 | Z13: =IF(B13="","",IF(N13="Time x Count",M13*R13*IF(U13="",1,U13)*Y13,IF(N13="QS Qty x Factor",E13*R13*(1+IF(V13="",0,V13))*Y13,IF(N13="Direct Qty",S13*(1+IF(V13="",0,V13))*Y13,IF(N13="Lump Sum / Quote",S13*Y13,0))))) | AA13: =IFERROR(INDEX('Resource Rate Library'!$N$5:$N$85,MATCH(P13,'Resource Rate Library'!$A$5:$A$85,0)),"") | AD13: =IFERROR(INDEX('Resource Rate Library'!$G$5:$G$85,MATCH(P13,'Resource Rate Library'!$A$5:$A$85,0)),"") | AE13: =IFERROR(INDEX('Resource Rate Library'!$H$5:$H$85,MATCH(P13,'Resource Rate Library'!$A$5:$A$85,0)),"") | AI13: =IF(B13="","",IF(AND(P13="",N13<>"Lump Sum / Quote"),"RESOURCE CODE",IF(Y13=0,"RATE MISSING",IF(AND(O13="Plant",AD13="Yes",COUNTIFS($B$7:$B$306,B13,$O$7:$O$306,"Labour",$Q$7:$Q$306,"*Operator*")>0),"OPERATOR DOUBLE-COUNT",IF(AND(O13="Plant",AE13="Yes",COUNTIFS($B$7:$B$306,B13,$Q$7:$Q$306,"*Fuel*")>0),"FUEL DOUBLE-COUNT",IF(AH13<>"Yes","VERIFY","OK")))))) | AN13: =IF(AND(AK13="Yes",OR(O13="Labour",O13="Plant")),Z13,0) -> 0
A14: =IF(B14="","",B14&"-"&TEXT(COUNTIF($B$7:B14,B14),"000")) | C14: =IFERROR(INDEX('QS Takeoff'!$A$3:$A$194,MATCH(B14,'QS Takeoff'!$B$3:$B$194,0)),"") | D14: =IFERROR(INDEX('QS Takeoff'!$C$3:$C$194,MATCH(B14,'QS Takeoff'!$B$3:$B$194,0)),"") | E14: =IFERROR(INDEX('QS Takeoff'!$E$3:$E$194,MATCH(B14,'QS Takeoff'!$B$3:$B$194,0)),"") | F14: =IFERROR(INDEX('QS Takeoff'!$D$3:$D$194,MATCH(B14,'QS Takeoff'!$B$3:$B$194,0)),"") | G14: =IFERROR(INDEX('QS Takeoff'!$J$3:$J$194,MATCH(B14,'QS Takeoff'!$B$3:$B$194,0)),"") | K14: =IF(OR(B14="",I14="",I14=0),"",E14/I14) | M14: =IF(L14>0,L14,K14) | Q14: =IFERROR(INDEX('Resource Rate Library'!$C$5:$C$85,MATCH(P14,'Resource Rate Library'!$A$5:$A$85,0)),"") | T14: =IFERROR(INDEX('Resource Rate Library'!$E$5:$E$85,MATCH(P14,'Resource Rate Library'!$A$5:$A$85,0)),"") | W14: =IFERROR(INDEX('Resource Rate Library'!$I$5:$I$85,MATCH(P14,'Resource Rate Library'!$A$5:$A$85,0)),0) -> 0 | Y14: =IF(X14>0,X14,W14) -> 0 | Z14: =IF(B14="","",IF(N14="Time x Count",M14*R14*IF(U14="",1,U14)*Y14,IF(N14="QS Qty x Factor",E14*R14*(1+IF(V14="",0,V14))*Y14,IF(N14="Direct Qty",S14*(1+IF(V14="",0,V14))*Y14,IF(N14="Lump Sum / Quote",S14*Y14,0))))) | AA14: =IFERROR(INDEX('Resource Rate Library'!$N$5:$N$85,MATCH(P14,'Resource Rate Library'!$A$5:$A$85,0)),"") | AD14: =IFERROR(INDEX('Resource Rate Library'!$G$5:$G$85,MATCH(P14,'Resource Rate Library'!$A$5:$A$85,0)),"") | AE14: =IFERROR(INDEX('Resource Rate Library'!$H$5:$H$85,MATCH(P14,'Resource Rate Library'!$A$5:$A$85,0)),"") | AI14: =IF(B14="","",IF(AND(P14="",N14<>"Lump Sum / Quote"),"RESOURCE CODE",IF(Y14=0,"RATE MISSING",IF(AND(O14="Plant",AD14="Yes",COUNTIFS($B$7:$B$306,B14,$O$7:$O$306,"Labour",$Q$7:$Q$306,"*Operator*")>0),"OPERATOR DOUBLE-COUNT",IF(AND(O14="Plant",AE14="Yes",COUNTIFS($B$7:$B$306,B14,$Q$7:$Q$306,"*Fuel*")>0),"FUEL DOUBLE-COUNT",IF(AH14<>"Yes","VERIFY","OK")))))) | AN14: =IF(AND(AK14="Yes",OR(O14="Labour",O14="Plant")),Z14,0) -> 0
A15: =IF(B15="","",B15&"-"&TEXT(COUNTIF($B$7:B15,B15),"000")) | C15: =IFERROR(INDEX('QS Takeoff'!$A$3:$A$194,MATCH(B15,'QS Takeoff'!$B$3:$B$194,0)),"") | D15: =IFERROR(INDEX('QS Takeoff'!$C$3:$C$194,MATCH(B15,'QS Takeoff'!$B$3:$B$194,0)),"") | E15: =IFERROR(INDEX('QS Takeoff'!$E$3:$E$194,MATCH(B15,'QS Takeoff'!$B$3:$B$194,0)),"") | F15: =IFERROR(INDEX('QS Takeoff'!$D$3:$D$194,MATCH(B15,'QS Takeoff'!$B$3:$B$194,0)),"") | G15: =IFERROR(INDEX('QS Takeoff'!$J$3:$J$194,MATCH(B15,'QS Takeoff'!$B$3:$B$194,0)),"") | K15: =IF(OR(B15="",I15="",I15=0),"",E15/I15) | M15: =IF(L15>0,L15,K15) | Q15: =IFERROR(INDEX('Resource Rate Library'!$C$5:$C$85,MATCH(P15,'Resource Rate Library'!$A$5:$A$85,0)),"") | T15: =IFERROR(INDEX('Resource Rate Library'!$E$5:$E$85,MATCH(P15,'Resource Rate Library'!$A$5:$A$85,0)),"") | W15: =IFERROR(INDEX('Resource Rate Library'!$I$5:$I$85,MATCH(P15,'Resource Rate Library'!$A$5:$A$85,0)),0) -> 0 | Y15: =IF(X15>0,X15,W15) -> 0 | Z15: =IF(B15="","",IF(N15="Time x Count",M15*R15*IF(U15="",1,U15)*Y15,IF(N15="QS Qty x Factor",E15*R15*(1+IF(V15="",0,V15))*Y15,IF(N15="Direct Qty",S15*(1+IF(V15="",0,V15))*Y15,IF(N15="Lump Sum / Quote",S15*Y15,0))))) | AA15: =IFERROR(INDEX('Resource Rate Library'!$N$5:$N$85,MATCH(P15,'Resource Rate Library'!$A$5:$A$85,0)),"") | AD15: =IFERROR(INDEX('Resource Rate Library'!$G$5:$G$85,MATCH(P15,'Resource Rate Library'!$A$5:$A$85,0)),"") | AE15: =IFERROR(INDEX('Resource Rate Library'!$H$5:$H$85,MATCH(P15,'Resource Rate Library'!$A$5:$A$85,0)),"") | AI15: =IF(B15="","",IF(AND(P15="",N15<>"Lump Sum / Quote"),"RESOURCE CODE",IF(Y15=0,"RATE MISSING",IF(AND(O15="Plant",AD15="Yes",COUNTIFS($B$7:$B$306,B15,$O$7:$O$306,"Labour",$Q$7:$Q$306,"*Operator*")>0),"OPERATOR DOUBLE-COUNT",IF(AND(O15="Plant",AE15="Yes",COUNTIFS($B$7:$B$306,B15,$Q$7:$Q$306,"*Fuel*")>0),"FUEL DOUBLE-COUNT",IF(AH15<>"Yes","VERIFY","OK")))))) | AN15: =IF(AND(AK15="Yes",OR(O15="Labour",O15="Plant")),Z15,0) -> 0
A16: =IF(B16="","",B16&"-"&TEXT(COUNTIF($B$7:B16,B16),"000")) | C16: =IFERROR(INDEX('QS Takeoff'!$A$3:$A$194,MATCH(B16,'QS Takeoff'!$B$3:$B$194,0)),"") | D16: =IFERROR(INDEX('QS Takeoff'!$C$3:$C$194,MATCH(B16,'QS Takeoff'!$B$3:$B$194,0)),"") | E16: =IFERROR(INDEX('QS Takeoff'!$E$3:$E$194,MATCH(B16,'QS Takeoff'!$B$3:$B$194,0)),"") | F16: =IFERROR(INDEX('QS Takeoff'!$D$3:$D$194,MATCH(B16,'QS Takeoff'!$B$3:$B$194,0)),"") | G16: =IFERROR(INDEX('QS Takeoff'!$J$3:$J$194,MATCH(B16,'QS Takeoff'!$B$3:$B$194,0)),"") | K16: =IF(OR(B16="",I16="",I16=0),"",E16/I16) | M16: =IF(L16>0,L16,K16) | Q16: =IFERROR(INDEX('Resource Rate Library'!$C$5:$C$85,MATCH(P16,'Resource Rate Library'!$A$5:$A$85,0)),"") | T16: =IFERROR(INDEX('Resource Rate Library'!$E$5:$E$85,MATCH(P16,'Resource Rate Library'!$A$5:$A$85,0)),"") | W16: =IFERROR(INDEX('Resource Rate Library'!$I$5:$I$85,MATCH(P16,'Resource Rate Library'!$A$5:$A$85,0)),0) -> 0 | Y16: =IF(X16>0,X16,W16) -> 0 | Z16: =IF(B16="","",IF(N16="Time x Count",M16*R16*IF(U16="",1,U16)*Y16,IF(N16="QS Qty x Factor",E16*R16*(1+IF(V16="",0,V16))*Y16,IF(N16="Direct Qty",S16*(1+IF(V16="",0,V16))*Y16,IF(N16="Lump Sum / Quote",S16*Y16,0))))) | AA16: =IFERROR(INDEX('Resource Rate Library'!$N$5:$N$85,MATCH(P16,'Resource Rate Library'!$A$5:$A$85,0)),"") | AD16: =IFERROR(INDEX('Resource Rate Library'!$G$5:$G$85,MATCH(P16,'Resource Rate Library'!$A$5:$A$85,0)),"") | AE16: =IFERROR(INDEX('Resource Rate Library'!$H$5:$H$85,MATCH(P16,'Resource Rate Library'!$A$5:$A$85,0)),"") | AI16: =IF(B16="","",IF(AND(P16="",N16<>"Lump Sum / Quote"),"RESOURCE CODE",IF(Y16=0,"RATE MISSING",IF(AND(O16="Plant",AD16="Yes",COUNTIFS($B$7:$B$306,B16,$O$7:$O$306,"Labour",$Q$7:$Q$306,"*Operator*")>0),"OPERATOR DOUBLE-COUNT",IF(AND(O16="Plant",AE16="Yes",COUNTIFS($B$7:$B$306,B16,$Q$7:$Q$306,"*Fuel*")>0),"FUEL DOUBLE-COUNT",IF(AH16<>"Yes","VERIFY","OK")))))) | AN16: =IF(AND(AK16="Yes",OR(O16="Labour",O16="Plant")),Z16,0) -> 0
A17: =IF(B17="","",B17&"-"&TEXT(COUNTIF($B$7:B17,B17),"000")) | C17: =IFERROR(INDEX('QS Takeoff'!$A$3:$A$194,MATCH(B17,'QS Takeoff'!$B$3:$B$194,0)),"") | D17: =IFERROR(INDEX('QS Takeoff'!$C$3:$C$194,MATCH(B17,'QS Takeoff'!$B$3:$B$194,0)),"") | E17: =IFERROR(INDEX('QS Takeoff'!$E$3:$E$194,MATCH(B17,'QS Takeoff'!$B$3:$B$194,0)),"") | F17: =IFERROR(INDEX('QS Takeoff'!$D$3:$D$194,MATCH(B17,'QS Takeoff'!$B$3:$B$194,0)),"") | G17: =IFERROR(INDEX('QS Takeoff'!$J$3:$J$194,MATCH(B17,'QS Takeoff'!$B$3:$B$194,0)),"") | K17: =IF(OR(B17="",I17="",I17=0),"",E17/I17) | M17: =IF(L17>0,L17,K17) | Q17: =IFERROR(INDEX('Resource Rate Library'!$C$5:$C$85,MATCH(P17,'Resource Rate Library'!$A$5:$A$85,0)),"") | T17: =IFERROR(INDEX('Resource Rate Library'!$E$5:$E$85,MATCH(P17,'Resource Rate Library'!$A$5:$A$85,0)),"") | W17: =IFERROR(INDEX('Resource Rate Library'!$I$5:$I$85,MATCH(P17,'Resource Rate Library'!$A$5:$A$85,0)),0) -> 0 | Y17: =IF(X17>0,X17,W17) -> 0 | Z17: =IF(B17="","",IF(N17="Time x Count",M17*R17*IF(U17="",1,U17)*Y17,IF(N17="QS Qty x Factor",E17*R17*(1+IF(V17="",0,V17))*Y17,IF(N17="Direct Qty",S17*(1+IF(V17="",0,V17))*Y17,IF(N17="Lump Sum / Quote",S17*Y17,0))))) | AA17: =IFERROR(INDEX('Resource Rate Library'!$N$5:$N$85,MATCH(P17,'Resource Rate Library'!$A$5:$A$85,0)),"") | AD17: =IFERROR(INDEX('Resource Rate Library'!$G$5:$G$85,MATCH(P17,'Resource Rate Library'!$A$5:$A$85,0)),"") | AE17: =IFERROR(INDEX('Resource Rate Library'!$H$5:$H$85,MATCH(P17,'Resource Rate Library'!$A$5:$A$85,0)),"") | AI17: =IF(B17="","",IF(AND(P17="",N17<>"Lump Sum / Quote"),"RESOURCE CODE",IF(Y17=0,"RATE MISSING",IF(AND(O17="Plant",AD17="Yes",COUNTIFS($B$7:$B$306,B17,$O$7:$O$306,"Labour",$Q$7:$Q$306,"*Operator*")>0),"OPERATOR DOUBLE-COUNT",IF(AND(O17="Plant",AE17="Yes",COUNTIFS($B$7:$B$306,B17,$Q$7:$Q$306,"*Fuel*")>0),"FUEL DOUBLE-COUNT",IF(AH17<>"Yes","VERIFY","OK")))))) | AN17: =IF(AND(AK17="Yes",OR(O17="Labour",O17="Plant")),Z17,0) -> 0
A18: =IF(B18="","",B18&"-"&TEXT(COUNTIF($B$7:B18,B18),"000")) | C18: =IFERROR(INDEX('QS Takeoff'!$A$3:$A$194,MATCH(B18,'QS Takeoff'!$B$3:$B$194,0)),"") | D18: =IFERROR(INDEX('QS Takeoff'!$C$3:$C$194,MATCH(B18,'QS Takeoff'!$B$3:$B$194,0)),"") | E18: =IFERROR(INDEX('QS Takeoff'!$E$3:$E$194,MATCH(B18,'QS Takeoff'!$B$3:$B$194,0)),"") | F18: =IFERROR(INDEX('QS Takeoff'!$D$3:$D$194,MATCH(B18,'QS Takeoff'!$B$3:$B$194,0)),"") | G18: =IFERROR(INDEX('QS Takeoff'!$J$3:$J$194,MATCH(B18,'QS Takeoff'!$B$3:$B$194,0)),"") | K18: =IF(OR(B18="",I18="",I18=0),"",E18/I18) | M18: =IF(L18>0,L18,K18) | Q18: =IFERROR(INDEX('Resource Rate Library'!$C$5:$C$85,MATCH(P18,'Resource Rate Library'!$A$5:$A$85,0)),"") | T18: =IFERROR(INDEX('Resource Rate Library'!$E$5:$E$85,MATCH(P18,'Resource Rate Library'!$A$5:$A$85,0)),"") | W18: =IFERROR(INDEX('Resource Rate Library'!$I$5:$I$85,MATCH(P18,'Resource Rate Library'!$A$5:$A$85,0)),0) -> 0 | Y18: =IF(X18>0,X18,W18) -> 0 | Z18: =IF(B18="","",IF(N18="Time x Count",M18*R18*IF(U18="",1,U18)*Y18,IF(N18="QS Qty x Factor",E18*R18*(1+IF(V18="",0,V18))*Y18,IF(N18="Direct Qty",S18*(1+IF(V18="",0,V18))*Y18,IF(N18="Lump Sum / Quote",S18*Y18,0))))) | AA18: =IFERROR(INDEX('Resource Rate Library'!$N$5:$N$85,MATCH(P18,'Resource Rate Library'!$A$5:$A$85,0)),"") | AD18: =IFERROR(INDEX('Resource Rate Library'!$G$5:$G$85,MATCH(P18,'Resource Rate Library'!$A$5:$A$85,0)),"") | AE18: =IFERROR(INDEX('Resource Rate Library'!$H$5:$H$85,MATCH(P18,'Resource Rate Library'!$A$5:$A$85,0)),"") | AI18: =IF(B18="","",IF(AND(P18="",N18<>"Lump Sum / Quote"),"RESOURCE CODE",IF(Y18=0,"RATE MISSING",IF(AND(O18="Plant",AD18="Yes",COUNTIFS($B$7:$B$306,B18,$O$7:$O$306,"Labour",$Q$7:$Q$306,"*Operator*")>0),"OPERATOR DOUBLE-COUNT",IF(AND(O18="Plant",AE18="Yes",COUNTIFS($B$7:$B$306,B18,$Q$7:$Q$306,"*Fuel*")>0),"FUEL DOUBLE-COUNT",IF(AH18<>"Yes","VERIFY","OK")))))) | AN18: =IF(AND(AK18="Yes",OR(O18="Labour",O18="Plant")),Z18,0) -> 0
... A306: =IF(B306="","",B306&"-"&TEXT(COUNTIF($B$7:B306,B306),"000")) | C306: =IFERROR(INDEX('QS Takeoff'!$A$3:$A$194,MATCH(B306,'QS Takeoff'!$B$3:$B$194,0)),"") | D306: =IFERROR(INDEX('QS Takeoff'!$C$3:$C$194,MATCH(B306,'QS Takeoff'!$B$3:$B$194,0)),"") | E306: =IFERROR(INDEX('QS Takeoff'!$E$3:$E$194,MATCH(B306,'QS Takeoff'!$B$3:$B$194,0)),"") | F306: =IFERROR(INDEX('QS Takeoff'!$D$3:$D$194,MATCH(B306,'QS Takeoff'!$B$3:$B$194,0)),"") | G306: =IFERROR(INDEX('QS Takeoff'!$J$3:$J$194,MATCH(B306,'QS Takeoff'!$B$3:$B$194,0)),"") | K306: =IF(OR(B306="",I306="",I306=0),"",E306/I306) | M306: =IF(L306>0,L306,K306) | Q306: =IFERROR(INDEX('Resource Rate Library'!$C$5:$C$85,MATCH(P306,'Resource Rate Library'!$A$5:$A$85,0)),"") | T306: =IFERROR(INDEX('Resource Rate Library'!$E$5:$E$85,MATCH(P306,'Resource Rate Library'!$A$5:$A$85,0)),"") | W306: =IFERROR(INDEX('Resource Rate Library'!$I$5:$I$85,MATCH(P306,'Resource Rate Library'!$A$5:$A$85,0)),0) -> 0 | Y306: =IF(X306>0,X306,W306) -> 0 | Z306: =IF(B306="","",IF(N306="Time x Count",M306*R306*IF(U306="",1,U306)*Y306,IF(N306="QS Qty x Factor",E306*R306*(1+IF(V306="",0,V306))*Y306,IF(N306="Direct Qty",S306*(1+IF(V306="",0,V306))*Y306,IF(N306="Lump Sum / Quote",S306*Y306,0))))) | AA306: =IFERROR(INDEX('Resource Rate Library'!$N$5:$N$85,MATCH(P306,'Resource Rate Library'!$A$5:$A$85,0)),"") | AD306: =IFERROR(INDEX('Resource Rate Library'!$G$5:$G$85,MATCH(P306,'Resource Rate Library'!$A$5:$A$85,0)),"") | AE306: =IFERROR(INDEX('Resource Rate Library'!$H$5:$H$85,MATCH(P306,'Resource Rate Library'!$A$5:$A$85,0)),"") | AI306: =IF(B306="","",IF(AND(P306="",N306<>"Lump Sum / Quote"),"RESOURCE CODE",IF(Y306=0,"RATE MISSING",IF(AND(O306="Plant",AD306="Yes",COUNTIFS($B$7:$B$306,B306,$O$7:$O$306,"Labour",$Q$7:$Q$306,"*Operator*")>0),"OPERATOR DOUBLE-COUNT",IF(AND(O306="Plant",AE306="Yes",COUNTIFS($B$7:$B$306,B306,$Q$7:$Q$306,"*Fuel*")>0),"FUEL DOUBLE-COUNT",IF(AH306<>"Yes","VERIFY","OK")))))) | AN306: =IF(AND(AK306="Yes",OR(O306="Labour",O306="Plant")),Z306,0) -> 0

Sheet Rate Verification
A1: RATE & ALLOWANCE VERIFICATION - MASTER ESTIMATE WORKBOOK REV2
A2: GREEN requires: (1) current primary evidence, (2) an independent market check, and (3) a first-principles quantity/scope/arithmetic check. An allowance may remain AMBER; unsupported quote/design items are RED.
A3: Status | B3: Active rows | C3: Cost exposure excl. GST | E3: Status | F3: Active rows | G3: Cost exposure excl. GST
A4: GREEN | B4: =COUNTIF($T$8:$T$136,"GREEN - 3-point checked")+COUNTIF($T$8:$T$136,"GREEN - duplicate prevented") -> 0 | C4: =SUMIF($T$8:$T$136,"GREEN - 3-point checked",$J$8:$J$136)+SUMIF($T$8:$T$136,"GREEN - duplicate prevented",$J$8:$J$136) -> 0 | E4: RED | F4: =COUNTIF($T$8:$T$136,"RED - live quote/design evidence required")+COUNTIF($T$8:$T$136,"RED - allowance basis/quote required") -> 0 | G4: =SUMIF($T$8:$T$136,"RED - live quote/design evidence required",$J$8:$J$136)+SUMIF($T$8:$T$136,"RED - allowance basis/quote required",$J$8:$J$136) -> 0
A5: AMBER | B5: =COUNTIF($T$8:$T$136,"AMBER - company cost rate required")+COUNTIF($T$8:$T$136,"AMBER - explicit allowance; second evidence required")+COUNTIF($T$8:$T$136,"AMBER - benchmark only")+COUNTIF($T$8:$T$136,"AMBER - 3-point benchmark; quote required")+COUNTIF($T$8:$T$136,"AMBER - specification/delivery quote required")+COUNTIF($T$8:$T$136,"AMBER - benchmarked PC; NZ supplier quote required") -> 0 | C5: =SUMIF($T$8:$T$136,"AMBER - company cost rate required",$J$8:$J$136)+SUMIF($T$8:$T$136,"AMBER - explicit allowance; second evidence required",$J$8:$J$136)+SUMIF($T$8:$T$136,"AMBER - benchmark only",$J$8:$J$136)+SUMIF($T$8:$T$136,"AMBER - 3-point benchmark; quote required",$J$8:$J$136)+SUMIF($T$8:$T$136,"AMBER - specification/delivery quote required",$J$8:$J$136)+SUMIF($T$8:$T$136,"AMBER - benchmarked PC; NZ supplier quote required",$J$8:$J$136) -> 0 | E5: Release gate | F5: Tender issue only | G5: RED items must be disclosed and replaced before award
A7: Audit ID | B7: Build-Up Row | C7: QS Code | D7: WBS / Section | E7: Task / Method | F7: Resource Code | G7: Resource | H7: Unit | I7: Applied Rate | J7: Extended Cost | K7: Evidence 1 - primary/current | L7: Result 1 | M7: Evidence 2 - independent check | N7: Result 2 | O7: Evidence 3 - build-up/scope | P7: Result 3 | Q7: Score | R7: Source Date | S7: Confidence | T7: Release Status | U7: Required Action | V7: Scope / Assumption
A8: RV-001 | B8: ='Resource Build-Up'!A7 | C8: ='Resource Build-Up'!B7 -> 0 | D8: ='Resource Build-Up'!C7 | E8: ='Resource Build-Up'!H7 -> 0 | F8: ='Resource Build-Up'!P7 -> 0 | G8: ='Resource Build-Up'!Q7 | H8: ='Resource Build-Up'!T7 | I8: ='Resource Build-Up'!Y7 -> 0 | J8: ='Resource Build-Up'!Z7 | Q8: =COUNTIF(L8,"PASS")+COUNTIF(N8,"PASS")+COUNTIF(P8,"PASS") -> 0 | R8: ='Resource Build-Up'!AC7 -> 0 | S8: ='Resource Build-Up'!AF7 -> 0 | V8: ='Resource Build-Up'!AG7 -> 0
A9: RV-002 | B9: ='Resource Build-Up'!A8 | C9: ='Resource Build-Up'!B8 -> 0 | D9: ='Resource Build-Up'!C8 | E9: ='Resource Build-Up'!H8 -> 0 | F9: ='Resource Build-Up'!P8 -> 0 | G9: ='Resource Build-Up'!Q8 | H9: ='Resource Build-Up'!T8 | I9: ='Resource Build-Up'!Y8 -> 0 | J9: ='Resource Build-Up'!Z8 | Q9: =COUNTIF(L9,"PASS")+COUNTIF(N9,"PASS")+COUNTIF(P9,"PASS") -> 0 | R9: ='Resource Build-Up'!AC8 -> 0 | S9: ='Resource Build-Up'!AF8 -> 0 | V9: ='Resource Build-Up'!AG8 -> 0
A10: RV-003 | B10: ='Resource Build-Up'!A9 | C10: ='Resource Build-Up'!B9 -> 0 | D10: ='Resource Build-Up'!C9 | E10: ='Resource Build-Up'!H9 -> 0 | F10: ='Resource Build-Up'!P9 -> 0 | G10: ='Resource Build-Up'!Q9 | H10: ='Resource Build-Up'!T9 | I10: ='Resource Build-Up'!Y9 -> 0 | J10: ='Resource Build-Up'!Z9 | Q10: =COUNTIF(L10,"PASS")+COUNTIF(N10,"PASS")+COUNTIF(P10,"PASS") -> 0 | R10: ='Resource Build-Up'!AC9 -> 0 | S10: ='Resource Build-Up'!AF9 -> 0 | V10: ='Resource Build-Up'!AG9 -> 0
A11: RV-004 | B11: ='Resource Build-Up'!A10 | C11: ='Resource Build-Up'!B10 -> 0 | D11: ='Resource Build-Up'!C10 | E11: ='Resource Build-Up'!H10 -> 0 | F11: ='Resource Build-Up'!P10 -> 0 | G11: ='Resource Build-Up'!Q10 | H11: ='Resource Build-Up'!T10 | I11: ='Resource Build-Up'!Y10 -> 0 | J11: ='Resource Build-Up'!Z10 | Q11: =COUNTIF(L11,"PASS")+COUNTIF(N11,"PASS")+COUNTIF(P11,"PASS") -> 0 | R11: ='Resource Build-Up'!AC10 -> 0 | S11: ='Resource Build-Up'!AF10 -> 0 | V11: ='Resource Build-Up'!AG10 -> 0
A12: RV-005 | B12: ='Resource Build-Up'!A11 | C12: ='Resource Build-Up'!B11 -> 0 | D12: ='Resource Build-Up'!C11 | E12: ='Resource Build-Up'!H11 -> 0 | F12: ='Resource Build-Up'!P11 -> 0 | G12: ='Resource Build-Up'!Q11 | H12: ='Resource Build-Up'!T11 | I12: ='Resource Build-Up'!Y11 -> 0 | J12: ='Resource Build-Up'!Z11 | Q12: =COUNTIF(L12,"PASS")+COUNTIF(N12,"PASS")+COUNTIF(P12,"PASS") -> 0 | R12: ='Resource Build-Up'!AC11 -> 0 | S12: ='Resource Build-Up'!AF11 -> 0 | V12: ='Resource Build-Up'!AG11 -> 0
A13: RV-006 | B13: ='Resource Build-Up'!A12 | C13: ='Resource Build-Up'!B12 -> 0 | D13: ='Resource Build-Up'!C12 | E13: ='Resource Build-Up'!H12 -> 0 | F13: ='Resource Build-Up'!P12 -> 0 | G13: ='Resource Build-Up'!Q12 | H13: ='Resource Build-Up'!T12 | I13: ='Resource Build-Up'!Y12 -> 0 | J13: ='Resource Build-Up'!Z12 | Q13: =COUNTIF(L13,"PASS")+COUNTIF(N13,"PASS")+COUNTIF(P13,"PASS") -> 0 | R13: ='Resource Build-Up'!AC12 -> 0 | S13: ='Resource Build-Up'!AF12 -> 0 | V13: ='Resource Build-Up'!AG12 -> 0
A14: RV-007 | B14: ='Resource Build-Up'!A13 | C14: ='Resource Build-Up'!B13 -> 0 | D14: ='Resource Build-Up'!C13 | E14: ='Resource Build-Up'!H13 -> 0 | F14: ='Resource Build-Up'!P13 -> 0 | G14: ='Resource Build-Up'!Q13 | H14: ='Resource Build-Up'!T13 | I14: ='Resource Build-Up'!Y13 -> 0 | J14: ='Resource Build-Up'!Z13 | Q14: =COUNTIF(L14,"PASS")+COUNTIF(N14,"PASS")+COUNTIF(P14,"PASS") -> 0 | R14: ='Resource Build-Up'!AC13 -> 0 | S14: ='Resource Build-Up'!AF13 -> 0 | V14: ='Resource Build-Up'!AG13 -> 0
A15: RV-008 | B15: ='Resource Build-Up'!A14 | C15: ='Resource Build-Up'!B14 -> 0 | D15: ='Resource Build-Up'!C14 | E15: ='Resource Build-Up'!H14 -> 0 | F15: ='Resource Build-Up'!P14 -> 0 | G15: ='Resource Build-Up'!Q14 | H15: ='Resource Build-Up'!T14 | I15: ='Resource Build-Up'!Y14 -> 0 | J15: ='Resource Build-Up'!Z14 | Q15: =COUNTIF(L15,"PASS")+COUNTIF(N15,"PASS")+COUNTIF(P15,"PASS") -> 0 | R15: ='Resource Build-Up'!AC14 -> 0 | S15: ='Resource Build-Up'!AF14 -> 0 | V15: ='Resource Build-Up'!AG14 -> 0
A16: RV-009 | B16: ='Resource Build-Up'!A15 | C16: ='Resource Build-Up'!B15 -> 0 | D16: ='Resource Build-Up'!C15 | E16: ='Resource Build-Up'!H15 -> 0 | F16: ='Resource Build-Up'!P15 -> 0 | G16: ='Resource Build-Up'!Q15 | H16: ='Resource Build-Up'!T15 | I16: ='Resource Build-Up'!Y15 -> 0 | J16: ='Resource Build-Up'!Z15 | Q16: =COUNTIF(L16,"PASS")+COUNTIF(N16,"PASS")+COUNTIF(P16,"PASS") -> 0 | R16: ='Resource Build-Up'!AC15 -> 0 | S16: ='Resource Build-Up'!AF15 -> 0 | V16: ='Resource Build-Up'!AG15 -> 0
A17: RV-010 | B17: ='Resource Build-Up'!A16 | C17: ='Resource Build-Up'!B16 -> 0 | D17: ='Resource Build-Up'!C16 | E17: ='Resource Build-Up'!H16 -> 0 | F17: ='Resource Build-Up'!P16 -> 0 | G17: ='Resource Build-Up'!Q16 | H17: ='Resource Build-Up'!T16 | I17: ='Resource Build-Up'!Y16 -> 0 | J17: ='Resource Build-Up'!Z16 | Q17: =COUNTIF(L17,"PASS")+COUNTIF(N17,"PASS")+COUNTIF(P17,"PASS") -> 0 | R17: ='Resource Build-Up'!AC16 -> 0 | S17: ='Resource Build-Up'!AF16 -> 0 | V17: ='Resource Build-Up'!AG16 -> 0
A18: RV-011 | B18: ='Resource Build-Up'!A17 | C18: ='Resource Build-Up'!B17 -> 0 | D18: ='Resource Build-Up'!C17 | E18: ='Resource Build-Up'!H17 -> 0 | F18: ='Resource Build-Up'!P17 -> 0 | G18: ='Resource Build-Up'!Q17 | H18: ='Resource Build-Up'!T17 | I18: ='Resource Build-Up'!Y17 -> 0 | J18: ='Resource Build-Up'!Z17 | Q18: =COUNTIF(L18,"PASS")+COUNTIF(N18,"PASS")+COUNTIF(P18,"PASS") -> 0 | R18: ='Resource Build-Up'!AC17 -> 0 | S18: ='Resource Build-Up'!AF17 -> 0 | V18: ='Resource Build-Up'!AG17 -> 0
A19: RV-012 | B19: ='Resource Build-Up'!A18 | C19: ='Resource Build-Up'!B18 -> 0 | D19: ='Resource Build-Up'!C18 | E19: ='Resource Build-Up'!H18 -> 0 | F19: ='Resource Build-Up'!P18 -> 0 | G19: ='Resource Build-Up'!Q18 | H19: ='Resource Build-Up'!T18 | I19: ='Resource Build-Up'!Y18 -> 0 | J19: ='Resource Build-Up'!Z18 | Q19: =COUNTIF(L19,"PASS")+COUNTIF(N19,"PASS")+COUNTIF(P19,"PASS") -> 0 | R19: ='Resource Build-Up'!AC18 -> 0 | S19: ='Resource Build-Up'!AF18 -> 0 | V19: ='Resource Build-Up'!AG18 -> 0
... A136: RV-129 | B136: ='Resource Build-Up'!A135 | C136: ='Resource Build-Up'!B135 -> 0 | D136: ='Resource Build-Up'!C135 | E136: ='Resource Build-Up'!H135 -> 0 | F136: ='Resource Build-Up'!P135 -> 0 | G136: ='Resource Build-Up'!Q135 | H136: ='Resource Build-Up'!T135 | I136: ='Resource Build-Up'!Y135 -> 0 | J136: ='Resource Build-Up'!Z135 | Q136: =COUNTIF(L136,"PASS")+COUNTIF(N136,"PASS")+COUNTIF(P136,"PASS") -> 0 | R136: ='Resource Build-Up'!AC135 -> 0 | S136: ='Resource Build-Up'!AF135 -> 0 | V136: ='Resource Build-Up'!AG135 -> 0

Sheet Programme Export
A1: PROGRAMME BUILD-UP & MICROSOFT PROJECT EXPORT - MASTER ESTIMATE WORKBOOK REV2
A2: Programme durations derive from Resource Build-Up quantity/productivity unless an explicit programme override is entered. Set the current project calendar, start date, holidays, shutdowns and work fronts before issue.
A3: MS Project: import Tasks and map Name, Duration, Predecessors, Fixed Cost, Text fields, Notes, Task Mode and Fixed Cost Accrual. Do not also import the same resource costs when Fixed Cost is used, or costs will double.
A4: Microsoft import guidance: https://support.microsoft.com/en-us/project/export-or-import-data-to-another-file-format
A5: PROGRAMME RECONCILIATION: J takes the largest linked Resource Build-Up applied duration for each QS code using AGGREGATE; K converts hours to working days; M uses a stated Programme Override where entered otherwise the derived duration. Reconcile critical path, elapsed duration and time-related costs before issue.
A6: Import ID | B6: QS Row | C6: WBS / Section | D6: QS Code | E6: Task Name | F6: Quantity | G6: Unit | H6: QS Fixed Cost | I6: Resource Cost Check | J6: Max Resource Duration hrs | K6: Derived Duration days | L6: Programme Override days | M6: Export Duration days | N6: Duration | O6: Duration Basis | P6: Predecessor QS Codes | Q6: Predecessors | R6: Resource Summary | S6: Rate QA Status | T6: QS / Resource Difference | U6: Cost Check | V6: Task Mode | W6: Cost Accrual | X6: Notes
A7: 1 | B7: 3 | C7: ='QS Takeoff'!A3 -> 0 | D7: ='QS Takeoff'!B3 -> 0 | E7: ='QS Takeoff'!C3 -> 0 | F7: ='QS Takeoff'!E3 -> 0 | G7: ='QS Takeoff'!D3 -> 0 | H7: ='QS Takeoff'!G3 -> 0 | I7: =SUMIF('Resource Build-Up'!$B$7:$B$306,D7,'Resource Build-Up'!$Z$7:$Z$306) -> 0 | J7: =IFERROR(_xludf.AGGREGATE(14,6,'Resource Build-Up'!$M$7:$M$306/('Resource Build-Up'!$B$7:$B$306=D7),1),0) -> 0 | K7: =IF(J7=0,"",ROUNDUP(J7/8,0)) | M7: =IF(L7<>"",L7,K7) | N7: =IF(M7="","",TEXT(M7,"0")&" days") | T7: =I7-H7 -> 0 | U7: =IF(ABS(T7)<0.01,"OK","CHECK") -> OK | V7: Auto Scheduled | W7: Prorated
A8: 2 | B8: 4 | C8: ='QS Takeoff'!A4 -> 0 | D8: ='QS Takeoff'!B4 -> 0 | E8: ='QS Takeoff'!C4 -> 0 | F8: ='QS Takeoff'!E4 -> 0 | G8: ='QS Takeoff'!D4 -> 0 | H8: ='QS Takeoff'!G4 -> 0 | I8: =SUMIF('Resource Build-Up'!$B$7:$B$306,D8,'Resource Build-Up'!$Z$7:$Z$306) -> 0 | J8: =IFERROR(_xludf.AGGREGATE(14,6,'Resource Build-Up'!$M$7:$M$306/('Resource Build-Up'!$B$7:$B$306=D8),1),0) -> 0 | K8: =IF(J8=0,"",ROUNDUP(J8/8,0)) | M8: =IF(L8<>"",L8,K8) | N8: =IF(M8="","",TEXT(M8,"0")&" days") | T8: =I8-H8 -> 0 | U8: =IF(ABS(T8)<0.01,"OK","CHECK") -> OK | V8: Auto Scheduled | W8: Prorated
A9: 3 | B9: 5 | C9: ='QS Takeoff'!A5 -> 0 | D9: ='QS Takeoff'!B5 -> 0 | E9: ='QS Takeoff'!C5 -> 0 | F9: ='QS Takeoff'!E5 -> 0 | G9: ='QS Takeoff'!D5 -> 0 | H9: ='QS Takeoff'!G5 -> 0 | I9: =SUMIF('Resource Build-Up'!$B$7:$B$306,D9,'Resource Build-Up'!$Z$7:$Z$306) -> 0 | J9: =IFERROR(_xludf.AGGREGATE(14,6,'Resource Build-Up'!$M$7:$M$306/('Resource Build-Up'!$B$7:$B$306=D9),1),0) -> 0 | K9: =IF(J9=0,"",ROUNDUP(J9/8,0)) | M9: =IF(L9<>"",L9,K9) | N9: =IF(M9="","",TEXT(M9,"0")&" days") | T9: =I9-H9 -> 0 | U9: =IF(ABS(T9)<0.01,"OK","CHECK") -> OK | V9: Auto Scheduled | W9: Prorated
A10: 4 | B10: 6 | C10: ='QS Takeoff'!A6 -> 0 | D10: ='QS Takeoff'!B6 -> 0 | E10: ='QS Takeoff'!C6 -> 0 | F10: ='QS Takeoff'!E6 -> 0 | G10: ='QS Takeoff'!D6 -> 0 | H10: ='QS Takeoff'!G6 -> 0 | I10: =SUMIF('Resource Build-Up'!$B$7:$B$306,D10,'Resource Build-Up'!$Z$7:$Z$306) -> 0 | J10: =IFERROR(_xludf.AGGREGATE(14,6,'Resource Build-Up'!$M$7:$M$306/('Resource Build-Up'!$B$7:$B$306=D10),1),0) -> 0 | K10: =IF(J10=0,"",ROUNDUP(J10/8,0)) | M10: =IF(L10<>"",L10,K10) | N10: =IF(M10="","",TEXT(M10,"0")&" days") | T10: =I10-H10 -> 0 | U10: =IF(ABS(T10)<0.01,"OK","CHECK") -> OK | V10: Auto Scheduled | W10: Prorated
A11: 5 | B11: 7 | C11: ='QS Takeoff'!A7 -> 0 | D11: ='QS Takeoff'!B7 -> 0 | E11: ='QS Takeoff'!C7 -> 0 | F11: ='QS Takeoff'!E7 -> 0 | G11: ='QS Takeoff'!D7 -> 0 | H11: ='QS Takeoff'!G7 -> 0 | I11: =SUMIF('Resource Build-Up'!$B$7:$B$306,D11,'Resource Build-Up'!$Z$7:$Z$306) -> 0 | J11: =IFERROR(_xludf.AGGREGATE(14,6,'Resource Build-Up'!$M$7:$M$306/('Resource Build-Up'!$B$7:$B$306=D11),1),0) -> 0 | K11: =IF(J11=0,"",ROUNDUP(J11/8,0)) | M11: =IF(L11<>"",L11,K11) | N11: =IF(M11="","",TEXT(M11,"0")&" days") | T11: =I11-H11 -> 0 | U11: =IF(ABS(T11)<0.01,"OK","CHECK") -> OK | V11: Auto Scheduled | W11: Prorated
A12: 6 | B12: 8 | C12: ='QS Takeoff'!A8 -> 0 | D12: ='QS Takeoff'!B8 -> 0 | E12: ='QS Takeoff'!C8 -> 0 | F12: ='QS Takeoff'!E8 -> 0 | G12: ='QS Takeoff'!D8 -> 0 | H12: ='QS Takeoff'!G8 -> 0 | I12: =SUMIF('Resource Build-Up'!$B$7:$B$306,D12,'Resource Build-Up'!$Z$7:$Z$306) -> 0 | J12: =IFERROR(_xludf.AGGREGATE(14,6,'Resource Build-Up'!$M$7:$M$306/('Resource Build-Up'!$B$7:$B$306=D12),1),0) -> 0 | K12: =IF(J12=0,"",ROUNDUP(J12/8,0)) | M12: =IF(L12<>"",L12,K12) | N12: =IF(M12="","",TEXT(M12,"0")&" days") | T12: =I12-H12 -> 0 | U12: =IF(ABS(T12)<0.01,"OK","CHECK") -> OK | V12: Auto Scheduled | W12: Prorated
A13: 7 | B13: 9 | C13: ='QS Takeoff'!A9 -> 0 | D13: ='QS Takeoff'!B9 -> 0 | E13: ='QS Takeoff'!C9 -> 0 | F13: ='QS Takeoff'!E9 -> 0 | G13: ='QS Takeoff'!D9 -> 0 | H13: ='QS Takeoff'!G9 -> 0 | I13: =SUMIF('Resource Build-Up'!$B$7:$B$306,D13,'Resource Build-Up'!$Z$7:$Z$306) -> 0 | J13: =IFERROR(_xludf.AGGREGATE(14,6,'Resource Build-Up'!$M$7:$M$306/('Resource Build-Up'!$B$7:$B$306=D13),1),0) -> 0 | K13: =IF(J13=0,"",ROUNDUP(J13/8,0)) | M13: =IF(L13<>"",L13,K13) | N13: =IF(M13="","",TEXT(M13,"0")&" days") | T13: =I13-H13 -> 0 | U13: =IF(ABS(T13)<0.01,"OK","CHECK") -> OK | V13: Auto Scheduled | W13: Prorated
A14: 8 | B14: 10 | C14: ='QS Takeoff'!A10 -> 0 | D14: ='QS Takeoff'!B10 -> 0 | E14: ='QS Takeoff'!C10 -> 0 | F14: ='QS Takeoff'!E10 -> 0 | G14: ='QS Takeoff'!D10 -> 0 | H14: ='QS Takeoff'!G10 -> 0 | I14: =SUMIF('Resource Build-Up'!$B$7:$B$306,D14,'Resource Build-Up'!$Z$7:$Z$306) -> 0 | J14: =IFERROR(_xludf.AGGREGATE(14,6,'Resource Build-Up'!$M$7:$M$306/('Resource Build-Up'!$B$7:$B$306=D14),1),0) -> 0 | K14: =IF(J14=0,"",ROUNDUP(J14/8,0)) | M14: =IF(L14<>"",L14,K14) | N14: =IF(M14="","",TEXT(M14,"0")&" days") | T14: =I14-H14 -> 0 | U14: =IF(ABS(T14)<0.01,"OK","CHECK") -> OK | V14: Auto Scheduled | W14: Prorated
A15: 9 | B15: 11 | C15: ='QS Takeoff'!A11 -> 0 | D15: ='QS Takeoff'!B11 -> 0 | E15: ='QS Takeoff'!C11 -> 0 | F15: ='QS Takeoff'!E11 -> 0 | G15: ='QS Takeoff'!D11 -> 0 | H15: ='QS Takeoff'!G11 -> 0 | I15: =SUMIF('Resource Build-Up'!$B$7:$B$306,D15,'Resource Build-Up'!$Z$7:$Z$306) -> 0 | J15: =IFERROR(_xludf.AGGREGATE(14,6,'Resource Build-Up'!$M$7:$M$306/('Resource Build-Up'!$B$7:$B$306=D15),1),0) -> 0 | K15: =IF(J15=0,"",ROUNDUP(J15/8,0)) | M15: =IF(L15<>"",L15,K15) | N15: =IF(M15="","",TEXT(M15,"0")&" days") | T15: =I15-H15 -> 0 | U15: =IF(ABS(T15)<0.01,"OK","CHECK") -> OK | V15: Auto Scheduled | W15: Prorated
A16: 10 | B16: 12 | C16: ='QS Takeoff'!A12 -> 0 | D16: ='QS Takeoff'!B12 -> 0 | E16: ='QS Takeoff'!C12 -> 0 | F16: ='QS Takeoff'!E12 -> 0 | G16: ='QS Takeoff'!D12 -> 0 | H16: ='QS Takeoff'!G12 -> 0 | I16: =SUMIF('Resource Build-Up'!$B$7:$B$306,D16,'Resource Build-Up'!$Z$7:$Z$306) -> 0 | J16: =IFERROR(_xludf.AGGREGATE(14,6,'Resource Build-Up'!$M$7:$M$306/('Resource Build-Up'!$B$7:$B$306=D16),1),0) -> 0 | K16: =IF(J16=0,"",ROUNDUP(J16/8,0)) | M16: =IF(L16<>"",L16,K16) | N16: =IF(M16="","",TEXT(M16,"0")&" days") | T16: =I16-H16 -> 0 | U16: =IF(ABS(T16)<0.01,"OK","CHECK") -> OK | V16: Auto Scheduled | W16: Prorated
A17: 11 | B17: 15 | C17: ='QS Takeoff'!A13 -> 0 | D17: ='QS Takeoff'!B13 -> 0 | E17: ='QS Takeoff'!C13 -> 0 | F17: ='QS Takeoff'!E13 -> 0 | G17: ='QS Takeoff'!D13 -> 0 | H17: ='QS Takeoff'!G13 -> 0 | I17: =SUMIF('Resource Build-Up'!$B$7:$B$306,D17,'Resource Build-Up'!$Z$7:$Z$306) -> 0 | J17: =IFERROR(_xludf.AGGREGATE(14,6,'Resource Build-Up'!$M$7:$M$306/('Resource Build-Up'!$B$7:$B$306=D17),1),0) -> 0 | K17: =IF(J17=0,"",ROUNDUP(J17/8,0)) | M17: =IF(L17<>"",L17,K17) | N17: =IF(M17="","",TEXT(M17,"0")&" days") | T17: =I17-H17 -> 0 | U17: =IF(ABS(T17)<0.01,"OK","CHECK") -> OK | V17: Auto Scheduled | W17: Prorated
A18: 12 | B18: 16 | C18: ='QS Takeoff'!A14 -> 0 | D18: ='QS Takeoff'!B14 -> 0 | E18: ='QS Takeoff'!C14 -> 0 | F18: ='QS Takeoff'!E14 -> 0 | G18: ='QS Takeoff'!D14 -> 0 | H18: ='QS Takeoff'!G14 -> 0 | I18: =SUMIF('Resource Build-Up'!$B$7:$B$306,D18,'Resource Build-Up'!$Z$7:$Z$306) -> 0 | J18: =IFERROR(_xludf.AGGREGATE(14,6,'Resource Build-Up'!$M$7:$M$306/('Resource Build-Up'!$B$7:$B$306=D18),1),0) -> 0 | K18: =IF(J18=0,"",ROUNDUP(J18/8,0)) | M18: =IF(L18<>"",L18,K18) | N18: =IF(M18="","",TEXT(M18,"0")&" days") | T18: =I18-H18 -> 0 | U18: =IF(ABS(T18)<0.01,"OK","CHECK") -> OK | V18: Auto Scheduled | W18: Prorated
... A77: 71 | B77: 78 | C77: ='QS Takeoff'!A73 -> 0 | D77: ='QS Takeoff'!B73 -> 0 | E77: ='QS Takeoff'!C73 -> 0 | F77: ='QS Takeoff'!E73 -> 0 | G77: ='QS Takeoff'!D73 -> 0 | H77: ='QS Takeoff'!G73 -> 0 | I77: =SUMIF('Resource Build-Up'!$B$7:$B$306,D77,'Resource Build-Up'!$Z$7:$Z$306) -> 0 | J77: =IFERROR(_xludf.AGGREGATE(14,6,'Resource Build-Up'!$M$7:$M$306/('Resource Build-Up'!$B$7:$B$306=D77),1),0) -> 0 | K77: =IF(J77=0,"",ROUNDUP(J77/8,0)) | M77: =IF(L77<>"",L77,K77) | N77: =IF(M77="","",TEXT(M77,"0")&" days") | T77: =I77-H77 -> 0 | U77: =IF(ABS(T77)<0.01,"OK","CHECK") -> OK | V77: Auto Scheduled | W77: Prorated

Sheet Weather Risk
A1: WEATHER RISK INTEGRATION - MASTER ESTIMATE WORKBOOK REV2
A2: Use the approved NZ Weather Risk Estimating Tool for climate/task calculations. This sheet links the tool run to live resources, programme, Commercial Inputs CA10, tender total and cashflow without using a flat weather percentage.
A4: LIVE PROJECT / PROGRAMME INPUTS | D4: INTEGRATION / RELEASE CONTROLS
A5: Project location | B5: =Summary!$B$4 -> 0 | D5: 1 | E5: Weather tool remains the approved climate/task calculation source; this workbook does not replace NIWA/tool logic.
A6: Weather station / representative location | D6: 2 | E6: CA10 is formula-linked to Selected Weather Allowance. Do not re-enter a flat weather percentage in Commercial Inputs.
A7: Assumed construction start | D7: 3 | E7: Direct productivity applies only to Resource Build-Up rows tagged Weather Exposed = Yes and Resource Type = Labour or Plant.
A8: Baseline working days | B8: =MAX('Programme Export'!$M$7:$M$77) -> 0 | D8: 4 | E8: Critical-path delay is not summed across concurrent tasks. Update the external Weather Tool when sequence or critical path changes.
A9: Working days per week | B9: 5 | D9: 5 | E9: Daily preliminaries derive from PG01 + PG04 + PG10. Weekly billed hire/facilities derive from PG03 + PG08.
A10: Weather-tool weekday-only base finish | B10: =IF(OR(B7="",B8=""),"",WORKDAY(B7,B8-1)) | D10: 6 | E10: CA09 dewatering remains separate. Recovery/remediation in this sheet defaults to zero to avoid double counting unless project-specific evidence justifies it.
A11: Public holiday / entered shutdown adjusted base finish | B11: =IF(OR(B7="",B8=""),"",WORKDAY(B7,B8-1,$F$55:$F$70)) | D11: 7 | E11: Wind proxy is excluded by default and remains AMBER unless a project-specific wind basis is verified.
A12: Weather-exposed labour + plant cost | B12: =SUM('Resource Build-Up'!$AN$7:$AN$306) -> 0 | D12: 8 | E12: Rerun the Weather Tool when start date, baseline duration, exposed cost mix, work calendar or critical path materially changes.
A13: Daily time-related preliminaries | B13: =IFERROR((SUMIFS('QS Takeoff'!$G$3:$G$73,'QS Takeoff'!$B$3:$B$73,"PG01")+SUMIFS('QS Takeoff'!$G$3:$G$73,'QS Takeoff'!$B$3:$B$73,"PG04")+SUMIFS('QS Takeoff'!$G$3:$G$73,'QS Takeoff'!$B$3:$B$73,"PG10"))/B8,0) -> 0 | D13: 9 | E13: Entered statutory holidays/shutdowns affect calendar completion only; they are not weather delay.
A14: Weekly billed hire / facilities | B14: =IFERROR((SUMIFS('QS Takeoff'!$G$3:$G$73,'QS Takeoff'!$B$3:$B$73,"PG03")+SUMIFS('QS Takeoff'!$G$3:$G$73,'QS Takeoff'!$B$3:$B$73,"PG08"))/B15,0) -> 0
A15: Baseline billed weeks | B15: =IF(OR(B8="",B9="",B9=0),0,ROUNDUP(B8/B9,0)) -> 0 | D15: Source / evidence | E15: NIWA 1991-2020 climate normals via NZ_Weather_Risk_Estimating_Tool_Rev2; public holiday dates via Employment New Zealand.
A16: Project-specific recovery / remediation allowance | B16: 0 | D16: Holiday source URL | E16: https://www.employment.govt.nz/leave-and-holidays/public-holidays/public-holidays-and-anniversary-dates
A18: APPROVED WEATHER TOOL RUN RECORD | D18: WEATHER / TENDER RECONCILIATION
A19: Approved tool version | B19: NZ_Weather_Risk_Estimating_Tool_Rev2.xlsx | D19: Current exposed-cost difference vs tool run | E19: =B12-B23 -> 0
A20: Tool run station | D20: Current start vs tool run | E20: =B7-B21 -> 0
A21: Tool run start date | D21: Current baseline WD vs tool run | E21: =B8-B22 -> 0
A22: Tool run baseline working days | D22: Weather Risk -> Commercial Inputs CA10 | E22: ='Commercial Inputs'!$E$14-B40 -> 0
A23: Tool run exposed labour + plant cost | D23: Selected wind status | E23: =IF(B29="Yes","AMBER - included","AMBER - sensitivity only / excluded") -> AMBER - sensitivity only / excluded
A24: Rain / wet-ground direct productivity output
A25: Direct productivity impact rate | B25: =IFERROR(B24/B23,0) -> 0
A26: Critical-path weather delay working days
A27: Additional billed hire weeks
A28: Wind proxy sensitivity - additional cost
A29: Include AMBER wind proxy? | B29: No
A30: Tool output confidence | B30: RED - approved weather tool run not loaded
A31: Tool rerun status | B31: =IF(OR(B20="",B21="",B22="",B23="",B24=""),"RERUN WEATHER TOOL",IF(OR(B6<>B20,B7<>B21,B8<>B22,ABS(B12-B23)/MAX(1,B23)>1%),"RERUN WEATHER TOOL","CURRENT - within 1% exposed-cost tolerance")) -> RERUN WEATHER TOOL
A33: LIVE WEATHER COST INTEGRATION
A34: Direct productivity allowance - resource linked | B34: =IFERROR(B24*(B12/B23),0) -> 0
A35: Critical-path time-related preliminaries | B35: =B26*B13 -> 0
A36: Additional billed hire / facilities | B36: =B27*B14 -> 0
A37: Project recovery / remediation | B37: =B16 -> 0
A38: Rain + wet-ground allowance | B38: =SUM(B34:B37) -> 0
A39: AMBER wind proxy sensitivity | B39: =B28 -> 0
A40: SELECTED WEATHER ALLOWANCE -> Commercial Inputs CA10 | B40: =B38+IF(B29="Yes",B39,0) -> 0
A41: Selected weather as % of base direct cost | B41: =IFERROR(B40/'Tender Build-Up'!$B$20,0) -> 0
A42: Previous approved weather allowance (optional) | B42: 0
A43: Weather allowance delta vs previous approved | B43: =B40-B42 -> 0
A44: Previous approved tender total excl. GST (optional) | B44: 0
A45: Current tender total excl. GST | B45: ='Tender Build-Up'!$B$47 -> 0
A46: Tender delta vs previous approved | B46: =B45-B44 -> 0
A47: Weather-adjusted completion incl. entered non-working dates | B47: =IF(OR(B11="",B26=""),"",WORKDAY(B11,ROUNDUP(B26,0),$F$55:$F$70))
A48: Elapsed calendar days from assumed start | B48: =IF(OR(B47="",B7=""),"",B47-B7+1)
F53: NON-WORKING DATE REGISTER - affects calendar span, not weather probability | J53: Weather Task Type - approved Rev2 library
F54: Non-working date | G54: Type / reason | H54: Evidence / note | J54: Erosion & sediment controls
G55: Project non-working date / shutdown - enter if applicable | H55: Estimator / contract calendar evidence | J55: Bulk earthworks
J56: Detailed earthworks / trim subgrade
J57: Cut to fill / cartage
J58: Building platform / pad prep
J59: Drainage trenching
J60: Manholes / chambers
J61: Service trenches / ducting
J62: Retaining wall excavation
J63: Retaining wall installation
J64: External concrete placing
J65: External concrete finishing
J66: Kerb & channel
J67: Subbase / pavement prep
... J71: External painting / coatings

Sheet Risk Truth
A1: RISK TRUTH ENGINE - MASTER ESTIMATE WORKBOOK REV2
A2: Permanent risk-control and reconciliation module. Record tender baseline before residual exposure. Quantifiable physical consequences return to Resource Build-Up / QS Takeoff; specialist engines remain separate. CA01/CA02 receive residual cross-cutting provisions only and are never default project-value percentages.
A4: RISK TRUTH / RELEASE CONTROL | B4: Value / Status | D4: INTEGRATION RULES | I4: RISK TRUTH COMMERCIAL RECALC | J4: Value
A5: Previous approved tender total (optional) | B5: 0 | D5: 1 | E5: Likelihood / impact prioritise management; they never create dollars automatically. | I5: Subtotal before commercial adjustments | J5: ='Tender Build-Up'!$B$40 -> 0
A6: Current live tender total | B6: ='Tender Build-Up'!$B$47 -> 0 | D6: 2 | E6: Every exposure identifies where the risk is already treated before any residual is considered. | I6: CA17 overhead | J6: =IF('Commercial Inputs'!$F$21<>"Yes",0,IF('Commercial Inputs'!$C$21="Markup %",J5*N('Commercial Inputs'!$D$21),IF('Commercial Inputs'!$C$21="Fixed Amount",N('Commercial Inputs'!$E$21),0))) -> 0
A7: Previous approved CA01 (optional) | B7: 0 | D7: 3 | E7: Quantifiable physical work returns to Resource Build-Up / QS Takeoff. | I7: CA19 bonds | J7: =IF('Commercial Inputs'!$F$23<>"Yes",0,IF('Commercial Inputs'!$C$23="%",J5*N('Commercial Inputs'!$D$23),IF('Commercial Inputs'!$C$23="PC Sum",N('Commercial Inputs'!$E$23),0))) -> 0
A8: Previous approved CA02 (optional) | B8: 0 | D8: 4 | E8: CA01 / CA02 receive residual cross-cutting provisions only when a more direct cost location is not truthful. | I8: CA20 retention finance | J8: =IF('Commercial Inputs'!$F$24<>"Yes",0,IF('Commercial Inputs'!$C$24="%",J5*N('Commercial Inputs'!$D$24),IF('Commercial Inputs'!$C$24="PC Sum",N('Commercial Inputs'!$E$24),0))) -> 0
A9: Risk Truth CA01 design/scope residual total | B9: =SUMIFS($T$41:$T$61,$R$41:$R$61,"CA01",$S$41:$S$61,"Yes") -> 0 | D9: 5 | E9: Weather remains Weather Risk -> CA10. Dewatering remains CA09 unless separately changed. | I9: CA18 profit | J9: =IF('Commercial Inputs'!$F$22<>"Yes",0,IF('Commercial Inputs'!$C$22="Margin %",(J5+J6+J7+J8)/(1-N('Commercial Inputs'!$D$22))-(J5+J6+J7+J8),IF('Commercial Inputs'!$C$22="Markup %",(J5+J6+J7+J8)*N('Commercial Inputs'!$D$22),IF('Commercial Inputs'!$C$22="Fixed Amount",N('Commercial Inputs'!$E$22),0)))) -> 0
A10: Risk Truth CA02 construction/execution residual total | B10: =SUMIFS($T$41:$T$61,$R$41:$R$61,"CA02",$S$41:$S$61,"Yes") -> 0 | D10: 6 | E10: Any RED exposure, unproven duplicate or incomplete programme dependency blocks final release. | I10: Recalculated tender total | J10: =SUM(J5:J9) -> 0
A11: Risk Truth recalculated tender total | B11: =$J$10 -> 0 | D11: 7 | E11: One cost can have several contributing risks, but only one PRIMARY cost-treatment owner.
A12: Live CA01 feed -> Commercial Inputs | B12: =$B$9 -> 0 | D12: 8 | E12: Actual outcomes are retained later for estimate-v-actual calibration; historic tender assumptions are not overwritten.
A13: Live CA02 feed -> Commercial Inputs | B13: =$B$10 -> 0
A14: Current Risk Truth residual total | B14: =$B$9+$B$10 -> 0
A15: Risk Truth release gate | B15: =IF(OR(B16>0,B17>0,B18<>"OK",LEFT(B19,3)="RED"),"HOLD - RED ITEMS / INTEGRATION CHECK","PASS") -> HOLD - RED ITEMS / INTEGRATION CHECK
A16: RED risk count | B16: =COUNTIF($K$25:$K$36,"RED") -> 1
A17: RED exposure count | B17: =COUNTIF($Z$41:$Z$61,"RED") -> 1
A18: Duplicate-cost gate | B18: =IF(OR(COUNTIF($X$41:$X$61,"RED - RESIDUAL NOT DISTINCT")>0,COUNTIF($X$41:$X$61,"RED - UNDECLARED OVERLAP")>0),"RED","OK") -> OK
A19: Programme dependency gate | B19: =IF(COUNTIF('Programme Export'!$U$7:$U$77,"CHECK")>0,"RED - PROGRAMME COST RECONCILIATION","OK") -> OK
A20: Tender delta vs previous approved | B20: =IF(B5=0,"",B6-B5)
A21: Current tender equals Risk Truth recalculation? | B21: =IF(ABS(B6-B11)<0.01,"YES","NO") -> YES
A22: Risk Truth calculation difference | B22: =B6-B11 -> 0
A24: Risk ID | B24: Risk Description | C24: Primary Class | D24: Likelihood | E24: Impact | F24: Rating | G24: Current Response | H24: Owner | I24: RFI / Action | J24: Tender Baseline | K24: Overall Status
K25: =IF(A25="","",IF(COUNTIFS($B$41:$B$61,A25,$Z$41:$Z$61,"RED")>0,"RED",IF(COUNTIFS($B$41:$B$61,A25,$Z$41:$Z$61,"AMBER")>0,"AMBER","GREEN")))
K26: =IF(A26="","",IF(COUNTIFS($B$41:$B$61,A26,$Z$41:$Z$61,"RED")>0,"RED",IF(COUNTIFS($B$41:$B$61,A26,$Z$41:$Z$61,"AMBER")>0,"AMBER","GREEN")))
K27: =IF(A27="","",IF(COUNTIFS($B$41:$B$61,A27,$Z$41:$Z$61,"RED")>0,"RED",IF(COUNTIFS($B$41:$B$61,A27,$Z$41:$Z$61,"AMBER")>0,"AMBER","GREEN")))
K28: =IF(A28="","",IF(COUNTIFS($B$41:$B$61,A28,$Z$41:$Z$61,"RED")>0,"RED",IF(COUNTIFS($B$41:$B$61,A28,$Z$41:$Z$61,"AMBER")>0,"AMBER","GREEN")))
K29: =IF(A29="","",IF(COUNTIFS($B$41:$B$61,A29,$Z$41:$Z$61,"RED")>0,"RED",IF(COUNTIFS($B$41:$B$61,A29,$Z$41:$Z$61,"AMBER")>0,"AMBER","GREEN")))
K30: =IF(A30="","",IF(COUNTIFS($B$41:$B$61,A30,$Z$41:$Z$61,"RED")>0,"RED",IF(COUNTIFS($B$41:$B$61,A30,$Z$41:$Z$61,"AMBER")>0,"AMBER","GREEN")))
K31: =IF(A31="","",IF(COUNTIFS($B$41:$B$61,A31,$Z$41:$Z$61,"RED")>0,"RED",IF(COUNTIFS($B$41:$B$61,A31,$Z$41:$Z$61,"AMBER")>0,"AMBER","GREEN")))
K32: =IF(A32="","",IF(COUNTIFS($B$41:$B$61,A32,$Z$41:$Z$61,"RED")>0,"RED",IF(COUNTIFS($B$41:$B$61,A32,$Z$41:$Z$61,"AMBER")>0,"AMBER","GREEN")))
K33: =IF(A33="","",IF(COUNTIFS($B$41:$B$61,A33,$Z$41:$Z$61,"RED")>0,"RED",IF(COUNTIFS($B$41:$B$61,A33,$Z$41:$Z$61,"AMBER")>0,"AMBER","GREEN")))
K34: =IF(A34="","",IF(COUNTIFS($B$41:$B$61,A34,$Z$41:$Z$61,"RED")>0,"RED",IF(COUNTIFS($B$41:$B$61,A34,$Z$41:$Z$61,"AMBER")>0,"AMBER","GREEN")))
K35: =IF(A35="","",IF(COUNTIFS($B$41:$B$61,A35,$Z$41:$Z$61,"RED")>0,"RED",IF(COUNTIFS($B$41:$B$61,A35,$Z$41:$Z$61,"AMBER")>0,"AMBER","GREEN")))
A36: WX01 | B36: Normal foreseeable weather exposure | C36: B - Normal foreseeable variability | D36: N/A | E36: N/A | F36: Modelled | G36: Approved Weather Risk engine -> CA10; do not duplicate in CA02 | H36: Estimator | I36: Weather rerun / N/A review | J36: CA10 linked Weather Risk | K36: =IF(A36="","",IF(COUNTIFS($B$41:$B$61,A36,$Z$41:$Z$61,"RED")>0,"RED",IF(COUNTIFS($B$41:$B$61,A36,$Z$41:$Z$61,"AMBER")>0,"AMBER","GREEN"))) -> RED
A40: Exposure ID | B40: Risk ID | C40: Exposure / Cost Consequence | D40: Affected Driver | E40: Affected Cost Ref | F40: Existing Treatment | G40: Existing Baseline Amount | H40: Residual Exposure | I40: Calculation Mode | J40: Residual Qty | K40: Unit | L40: Unit Rate / Impact | M40: Probability | N40: Modelled Residual | O40: Selected Tender Provision | P40: Cost Treatment Owner | Q40: Residual Distinct? | R40: Integration Target | S40: Include New Risk Cost? | T40: Risk Truth Addition | U40: Overlap Group | V40: Embedded Variability / Response? | W40: Evidence Status | X40: Duplication Check | Y40: Integration Complete? | Z40: Final Status | AA40: Sensitivity / Basis | AB40: Firm-Up / Rerun Action | AC40: Source / Reference
N41: =IF(I41="Already in Base / No Add",0,IF(I41="Unit Rate Delta",IF(OR(J41="",L41=""),"",J41*L41),IF(I41="Probability x Impact",IF(OR(M41="",L41=""),"",M41*L41),IF(I41="Fixed Allowance",O41,IF(I41="Specialist Engine",O41,IF(I41="By Others / Excluded",0,"")))))) | T41: =IF(S41="Yes",N(O41),0) -> 0 | X41: =IF(AND(S41="Yes",N(O41)>0,Q41<>"Yes"),"RED - RESIDUAL NOT DISTINCT",IF(AND(COUNTIF($E$41:$E$61,E41)>1,U41=""),"RED - UNDECLARED OVERLAP",IF(COUNTIF($E$41:$E$61,E41)>1,"DECLARED OVERLAP","OK"))) -> OK | Z41: =IF(LEFT(X41,3)="RED","RED",IF(OR(W41="RED",I41="RFI Hold",AND(I41="Unit Rate Delta",ISBLANK(J41))),"RED",IF(OR(W41="AMBER",LEFT(V41,5)="CHECK"),"AMBER","GREEN"))) -> GREEN
N42: =IF(I42="Already in Base / No Add",0,IF(I42="Unit Rate Delta",IF(OR(J42="",L42=""),"",J42*L42),IF(I42="Probability x Impact",IF(OR(M42="",L42=""),"",M42*L42),IF(I42="Fixed Allowance",O42,IF(I42="Specialist Engine",O42,IF(I42="By Others / Excluded",0,"")))))) | T42: =IF(S42="Yes",N(O42),0) -> 0 | X42: =IF(AND(S42="Yes",N(O42)>0,Q42<>"Yes"),"RED - RESIDUAL NOT DISTINCT",IF(AND(COUNTIF($E$41:$E$61,E42)>1,U42=""),"RED - UNDECLARED OVERLAP",IF(COUNTIF($E$41:$E$61,E42)>1,"DECLARED OVERLAP","OK"))) -> OK | Z42: =IF(LEFT(X42,3)="RED","RED",IF(OR(W42="RED",I42="RFI Hold",AND(I42="Unit Rate Delta",ISBLANK(J42))),"RED",IF(OR(W42="AMBER",LEFT(V42,5)="CHECK"),"AMBER","GREEN"))) -> GREEN
N43: =IF(I43="Already in Base / No Add",0,IF(I43="Unit Rate Delta",IF(OR(J43="",L43=""),"",J43*L43),IF(I43="Probability x Impact",IF(OR(M43="",L43=""),"",M43*L43),IF(I43="Fixed Allowance",O43,IF(I43="Specialist Engine",O43,IF(I43="By Others / Excluded",0,"")))))) | T43: =IF(S43="Yes",N(O43),0) -> 0 | X43: =IF(AND(S43="Yes",N(O43)>0,Q43<>"Yes"),"RED - RESIDUAL NOT DISTINCT",IF(AND(COUNTIF($E$41:$E$61,E43)>1,U43=""),"RED - UNDECLARED OVERLAP",IF(COUNTIF($E$41:$E$61,E43)>1,"DECLARED OVERLAP","OK"))) -> OK | Z43: =IF(LEFT(X43,3)="RED","RED",IF(OR(W43="RED",I43="RFI Hold",AND(I43="Unit Rate Delta",ISBLANK(J43))),"RED",IF(OR(W43="AMBER",LEFT(V43,5)="CHECK"),"AMBER","GREEN"))) -> GREEN
N44: =IF(I44="Already in Base / No Add",0,IF(I44="Unit Rate Delta",IF(OR(J44="",L44=""),"",J44*L44),IF(I44="Probability x Impact",IF(OR(M44="",L44=""),"",M44*L44),IF(I44="Fixed Allowance",O44,IF(I44="Specialist Engine",O44,IF(I44="By Others / Excluded",0,"")))))) | T44: =IF(S44="Yes",N(O44),0) -> 0 | X44: =IF(AND(S44="Yes",N(O44)>0,Q44<>"Yes"),"RED - RESIDUAL NOT DISTINCT",IF(AND(COUNTIF($E$41:$E$61,E44)>1,U44=""),"RED - UNDECLARED OVERLAP",IF(COUNTIF($E$41:$E$61,E44)>1,"DECLARED OVERLAP","OK"))) -> OK | Z44: =IF(LEFT(X44,3)="RED","RED",IF(OR(W44="RED",I44="RFI Hold",AND(I44="Unit Rate Delta",ISBLANK(J44))),"RED",IF(OR(W44="AMBER",LEFT(V44,5)="CHECK"),"AMBER","GREEN"))) -> GREEN
N45: =IF(I45="Already in Base / No Add",0,IF(I45="Unit Rate Delta",IF(OR(J45="",L45=""),"",J45*L45),IF(I45="Probability x Impact",IF(OR(M45="",L45=""),"",M45*L45),IF(I45="Fixed Allowance",O45,IF(I45="Specialist Engine",O45,IF(I45="By Others / Excluded",0,"")))))) | T45: =IF(S45="Yes",N(O45),0) -> 0 | X45: =IF(AND(S45="Yes",N(O45)>0,Q45<>"Yes"),"RED - RESIDUAL NOT DISTINCT",IF(AND(COUNTIF($E$41:$E$61,E45)>1,U45=""),"RED - UNDECLARED OVERLAP",IF(COUNTIF($E$41:$E$61,E45)>1,"DECLARED OVERLAP","OK"))) -> OK | Z45: =IF(LEFT(X45,3)="RED","RED",IF(OR(W45="RED",I45="RFI Hold",AND(I45="Unit Rate Delta",ISBLANK(J45))),"RED",IF(OR(W45="AMBER",LEFT(V45,5)="CHECK"),"AMBER","GREEN"))) -> GREEN
N46: =IF(I46="Already in Base / No Add",0,IF(I46="Unit Rate Delta",IF(OR(J46="",L46=""),"",J46*L46),IF(I46="Probability x Impact",IF(OR(M46="",L46=""),"",M46*L46),IF(I46="Fixed Allowance",O46,IF(I46="Specialist Engine",O46,IF(I46="By Others / Excluded",0,"")))))) | T46: =IF(S46="Yes",N(O46),0) -> 0 | X46: =IF(AND(S46="Yes",N(O46)>0,Q46<>"Yes"),"RED - RESIDUAL NOT DISTINCT",IF(AND(COUNTIF($E$41:$E$61,E46)>1,U46=""),"RED - UNDECLARED OVERLAP",IF(COUNTIF($E$41:$E$61,E46)>1,"DECLARED OVERLAP","OK"))) -> OK | Z46: =IF(LEFT(X46,3)="RED","RED",IF(OR(W46="RED",I46="RFI Hold",AND(I46="Unit Rate Delta",ISBLANK(J46))),"RED",IF(OR(W46="AMBER",LEFT(V46,5)="CHECK"),"AMBER","GREEN"))) -> GREEN
N47: =IF(I47="Already in Base / No Add",0,IF(I47="Unit Rate Delta",IF(OR(J47="",L47=""),"",J47*L47),IF(I47="Probability x Impact",IF(OR(M47="",L47=""),"",M47*L47),IF(I47="Fixed Allowance",O47,IF(I47="Specialist Engine",O47,IF(I47="By Others / Excluded",0,"")))))) | T47: =IF(S47="Yes",N(O47),0) -> 0 | X47: =IF(AND(S47="Yes",N(O47)>0,Q47<>"Yes"),"RED - RESIDUAL NOT DISTINCT",IF(AND(COUNTIF($E$41:$E$61,E47)>1,U47=""),"RED - UNDECLARED OVERLAP",IF(COUNTIF($E$41:$E$61,E47)>1,"DECLARED OVERLAP","OK"))) -> OK | Z47: =IF(LEFT(X47,3)="RED","RED",IF(OR(W47="RED",I47="RFI Hold",AND(I47="Unit Rate Delta",ISBLANK(J47))),"RED",IF(OR(W47="AMBER",LEFT(V47,5)="CHECK"),"AMBER","GREEN"))) -> GREEN
N48: =IF(I48="Already in Base / No Add",0,IF(I48="Unit Rate Delta",IF(OR(J48="",L48=""),"",J48*L48),IF(I48="Probability x Impact",IF(OR(M48="",L48=""),"",M48*L48),IF(I48="Fixed Allowance",O48,IF(I48="Specialist Engine",O48,IF(I48="By Others / Excluded",0,"")))))) | T48: =IF(S48="Yes",N(O48),0) -> 0 | X48: =IF(AND(S48="Yes",N(O48)>0,Q48<>"Yes"),"RED - RESIDUAL NOT DISTINCT",IF(AND(COUNTIF($E$41:$E$61,E48)>1,U48=""),"RED - UNDECLARED OVERLAP",IF(COUNTIF($E$41:$E$61,E48)>1,"DECLARED OVERLAP","OK"))) -> OK | Z48: =IF(LEFT(X48,3)="RED","RED",IF(OR(W48="RED",I48="RFI Hold",AND(I48="Unit Rate Delta",ISBLANK(J48))),"RED",IF(OR(W48="AMBER",LEFT(V48,5)="CHECK"),"AMBER","GREEN"))) -> GREEN
N49: =IF(I49="Already in Base / No Add",0,IF(I49="Unit Rate Delta",IF(OR(J49="",L49=""),"",J49*L49),IF(I49="Probability x Impact",IF(OR(M49="",L49=""),"",M49*L49),IF(I49="Fixed Allowance",O49,IF(I49="Specialist Engine",O49,IF(I49="By Others / Excluded",0,"")))))) | T49: =IF(S49="Yes",N(O49),0) -> 0 | X49: =IF(AND(S49="Yes",N(O49)>0,Q49<>"Yes"),"RED - RESIDUAL NOT DISTINCT",IF(AND(COUNTIF($E$41:$E$61,E49)>1,U49=""),"RED - UNDECLARED OVERLAP",IF(COUNTIF($E$41:$E$61,E49)>1,"DECLARED OVERLAP","OK"))) -> OK | Z49: =IF(LEFT(X49,3)="RED","RED",IF(OR(W49="RED",I49="RFI Hold",AND(I49="Unit Rate Delta",ISBLANK(J49))),"RED",IF(OR(W49="AMBER",LEFT(V49,5)="CHECK"),"AMBER","GREEN"))) -> GREEN
N50: =IF(I50="Already in Base / No Add",0,IF(I50="Unit Rate Delta",IF(OR(J50="",L50=""),"",J50*L50),IF(I50="Probability x Impact",IF(OR(M50="",L50=""),"",M50*L50),IF(I50="Fixed Allowance",O50,IF(I50="Specialist Engine",O50,IF(I50="By Others / Excluded",0,"")))))) | T50: =IF(S50="Yes",N(O50),0) -> 0 | X50: =IF(AND(S50="Yes",N(O50)>0,Q50<>"Yes"),"RED - RESIDUAL NOT DISTINCT",IF(AND(COUNTIF($E$41:$E$61,E50)>1,U50=""),"RED - UNDECLARED OVERLAP",IF(COUNTIF($E$41:$E$61,E50)>1,"DECLARED OVERLAP","OK"))) -> OK | Z50: =IF(LEFT(X50,3)="RED","RED",IF(OR(W50="RED",I50="RFI Hold",AND(I50="Unit Rate Delta",ISBLANK(J50))),"RED",IF(OR(W50="AMBER",LEFT(V50,5)="CHECK"),"AMBER","GREEN"))) -> GREEN
N51: =IF(I51="Already in Base / No Add",0,IF(I51="Unit Rate Delta",IF(OR(J51="",L51=""),"",J51*L51),IF(I51="Probability x Impact",IF(OR(M51="",L51=""),"",M51*L51),IF(I51="Fixed Allowance",O51,IF(I51="Specialist Engine",O51,IF(I51="By Others / Excluded",0,"")))))) | T51: =IF(S51="Yes",N(O51),0) -> 0 | X51: =IF(AND(S51="Yes",N(O51)>0,Q51<>"Yes"),"RED - RESIDUAL NOT DISTINCT",IF(AND(COUNTIF($E$41:$E$61,E51)>1,U51=""),"RED - UNDECLARED OVERLAP",IF(COUNTIF($E$41:$E$61,E51)>1,"DECLARED OVERLAP","OK"))) -> OK | Z51: =IF(LEFT(X51,3)="RED","RED",IF(OR(W51="RED",I51="RFI Hold",AND(I51="Unit Rate Delta",ISBLANK(J51))),"RED",IF(OR(W51="AMBER",LEFT(V51,5)="CHECK"),"AMBER","GREEN"))) -> GREEN
N52: =IF(I52="Already in Base / No Add",0,IF(I52="Unit Rate Delta",IF(OR(J52="",L52=""),"",J52*L52),IF(I52="Probability x Impact",IF(OR(M52="",L52=""),"",M52*L52),IF(I52="Fixed Allowance",O52,IF(I52="Specialist Engine",O52,IF(I52="By Others / Excluded",0,"")))))) | T52: =IF(S52="Yes",N(O52),0) -> 0 | X52: =IF(AND(S52="Yes",N(O52)>0,Q52<>"Yes"),"RED - RESIDUAL NOT DISTINCT",IF(AND(COUNTIF($E$41:$E$61,E52)>1,U52=""),"RED - UNDECLARED OVERLAP",IF(COUNTIF($E$41:$E$61,E52)>1,"DECLARED OVERLAP","OK"))) -> OK | Z52: =IF(LEFT(X52,3)="RED","RED",IF(OR(W52="RED",I52="RFI Hold",AND(I52="Unit Rate Delta",ISBLANK(J52))),"RED",IF(OR(W52="AMBER",LEFT(V52,5)="CHECK"),"AMBER","GREEN"))) -> GREEN
... N60: =IF(I60="Already in Base / No Add",0,IF(I60="Unit Rate Delta",IF(OR(J60="",L60=""),"",J60*L60),IF(I60="Probability x Impact",IF(OR(M60="",L60=""),"",M60*L60),IF(I60="Fixed Allowance",O60,IF(I60="Specialist Engine",O60,IF(I60="By Others / Excluded",0,"")))))) | T60: =IF(S60="Yes",N(O60),0) -> 0 | X60: =IF(AND(S60="Yes",N(O60)>0,Q60<>"Yes"),"RED - RESIDUAL NOT DISTINCT",IF(AND(COUNTIF($E$41:$E$61,E60)>1,U60=""),"RED - UNDECLARED OVERLAP",IF(COUNTIF($E$41:$E$61,E60)>1,"DECLARED OVERLAP","OK"))) -> OK | Z60: =IF(LEFT(X60,3)="RED","RED",IF(OR(W60="RED",I60="RFI Hold",AND(I60="Unit Rate Delta",ISBLANK(J60))),"RED",IF(OR(W60="AMBER",LEFT(V60,5)="CHECK"),"AMBER","GREEN"))) -> GREEN
A61: WX01-001 | B61: WX01 | C61: Normal foreseeable weather productivity / critical-path exposure | D61: Productivity / Duration | E61: CA10 | F61: Specialist Weather Engine | G61: ='Weather Risk'!$B$40 -> 0 | H61: Weather model must be current or documented N/A | I61: Specialist Engine | K61: LS | N61: =IF(I61="Already in Base / No Add",0,IF(I61="Unit Rate Delta",IF(OR(J61="",L61=""),"",J61*L61),IF(I61="Probability x Impact",IF(OR(M61="",L61=""),"",M61*L61),IF(I61="Fixed Allowance",O61,IF(I61="Specialist Engine",O61,IF(I61="By Others / Excluded",0,"")))))) -> 0 | O61: ='Weather Risk'!$B$40 -> 0 | P61: Primary | Q61: N/A | R61: CA10 | S61: No | T61: =IF(S61="Yes",N(O61),0) -> 0 | U61: WEATHER-PROGRAMME | V61: No | W61: RED | X61: =IF(AND(S61="Yes",N(O61)>0,Q61<>"Yes"),"RED - RESIDUAL NOT DISTINCT",IF(AND(COUNTIF($E$41:$E$61,E61)>1,U61=""),"RED - UNDECLARED OVERLAP",IF(COUNTIF($E$41:$E$61,E61)>1,"DECLARED OVERLAP","OK"))) -> OK | Y61: Existing | Z61: =IF(LEFT(X61,3)="RED","RED",IF(OR(W61="RED",I61="RFI Hold",AND(I61="Unit Rate Delta",ISBLANK(J61))),"RED",IF(OR(W61="AMBER",LEFT(V61,5)="CHECK"),"AMBER","GREEN"))) -> RED | AA61: Weather is modelled in the specialist engine and cannot also be included in CA02. | AB61: Run the approved Weather Tool or document N/A basis; then update Evidence Status after review. | AC61: Weather Risk / approved climate tool
A64: PERMANENT MASTER RELEASE RULES
A65: Rule 1 | B65: Likelihood / impact prioritise management; they do not create dollars automatically.
A66: Rule 2 | B66: Every risk exposure identifies where the risk is already treated before residual cost is considered.
A67: Rule 3 | B67: Quantifiable physical consequences return to Resource Build-Up / QS Takeoff.
A68: Rule 4 | B68: CA01 / CA02 contain residual cross-cutting risk only; generic project-value percentages are prohibited.
A69: Rule 5 | B69: Specialist-engine risks remain in their specialist cost path and are referenced, not duplicated.
A70: Rule 6 | B70: A positive Risk Truth addition requires a distinct residual basis, integration target and evidence status.
A71: Rule 7 | B71: Any RED duplication, programme reconciliation or material risk item blocks final release.
A72: Rule 8 | B72: Actual outcomes are retained later for estimate-v-actual calibration; historic tender assumptions are not overwritten.
A74: MASTER PROMOTION VALIDATION
A75: Cost-chain propagation | B75: PASS | C75: Resource rate and quantity changes propagated through linked direct-cost and tender outputs during development testing.
A76: Risk residual propagation | B76: PASS | C76: Approved residual CA01/CA02 feeds were proven to enter the tender exactly once.
A77: Duplicate-cost blocker | B77: PASS | C77: Non-distinct duplicate risk provisions were proven to return RED and block release.
A78: Programme propagation | B78: PASS | C78: Productivity/duration changes were proven to flow to Programme Export and trigger weather rerun logic.
A79: Formula compatibility | B79: PASS | C79: Programme maximum-duration logic uses AGGREGATE rather than incompatible MAXIFS storage.
