Workbook

Sheet Template Guide
A1: MASTER ESTIMATE WORKBOOK - TEMPLATE | B1: Blackline QSi Pro | template Rev1 (14 Oct 2026)
A2: Purpose | B2: Clean master for one job. An external AI (or the estimator) fills it from the tender documents; the Blackline QSi Pro app imports it and recalculates every figure itself.
A3: Instructions | B3: Read instructions/Workbook_Builder_Instructions.md before filling anything. The sheet names, header rows and column positions below are a contract with the app.
A5: CAPACITY
A6: QS Takeoff | B6: Rows 3-202 (one item per row; total on row 203). Formula columns F, G, L-O, R are pre-filled.
A7: Resource Build-Up | B7: Rows 7-306. All formula columns are pre-filled; type only the input columns (see instructions section 5.2).
A8: Resource Rate Library | B8: Rows 5-200. The existing company rates are kept; add rates only with source, date and verification status.
A9: Programme Export | B9: Rows 7-206 follow QS rows 3-202; rows 207-226 are for control tasks (cure, holds) that are not QS items.
A10: Rate Verification | B10: One row per Build-Up row (rows 8-307); fill the evidence columns K-P, T, U.
A11: Tender Build-Up | B11: Type the QS section names in A10:A19 (exactly as written on QS Takeoff). Row 21 must read OK.
A12: Cover & Instructions | B12: Assumptions A1-A15, exclusions EX-01 to EX-08, RFIs RFI-01 to RFI-30, 9 document categories. Copy a row inside a block to add more.
A13: Consolidated Package | B13: Rows 6-11 are subcontract package slots. Row 13 holds a confirmed overlap.
A14: Weather Risk | B14: B13 and B14 are set to =0 in the template. Point them at the Build-Up rows that carry daily time-related preliminaries and weekly hire, e.g. B13 ='Resource Build-Up'!Y22*8 and B14 ='Resource Build-Up'!Y48+'Resource Build-Up'!Y60.
A16: COMPANY DEFAULTS KEPT | B16: Overhead 10% (markup) and profit 15% (true margin) on Commercial Inputs CA17/CA18 are the company's current settings; confirm per job. All other allowances are OFF and zero.
A17: FULL MASTER | B17: All the supporting sheets are present (Summary, Stage Cashflow, Estimate Review Board, ERB Adjudication, Programme Adjudication, Programme Notes, Materials & Component Takeoff, MS Project Import). The app reads what it needs and ignores the rest; they stay for the old workflow and future import.
A18: MS Project Import | B18: Generated from Programme Export: compact rows, predecessors as task IDs (column F), predecessor codes (R) and a helper column (S). Save as CSV (or copy the filled rows) to load into MS Project; the platform reads the same table and builds its programme from it.
... A23: RECALCULATE | B23: After editing, recalculate and save so formulas hold values (LibreOffice: soffice --headless --convert-to xlsx --outdir out file.xlsx).

Sheet Cover & Instructions
A1: TENDER SNAPSHOT / START HERE
A2: ="Working all-in tender excl. GST: "&TEXT('Consolidated Package'!F56,"$#,##0.00")&" | overhead "&TEXT('Commercial Inputs'!D21,"0.0%")&" + profit "&TEXT('Commercial Inputs'!D22,"0.0%")
A4: THE FIRST QUESTION: WHAT WILL THIS COST? | E4: CURRENT COMMERCIAL BUILD-UP
A5: ='Consolidated Package'!F56 | E5: Own works pre-commercial | F5: ='Consolidated Package'!B5
E6: Subcontract packages (known) | F6: =SUM('Consolidated Package'!B6:B11)
E7: Current known cost before OH/profit | F7: ='Consolidated Package'!B56
E8: Company overhead | F8: ='Consolidated Package'!C56
A9: WORKING ALL-IN TENDER, EXCL. GST | E9: Profit | F9: ='Consolidated Package'!E56
E10: WORKING ALL-IN TENDER | F10: ='Consolidated Package'!F56
E11: Gross margin on sell | F11: =IFERROR(('Consolidated Package'!F56-'Consolidated Package'!B56)/'Consolidated Package'!F56,0)
E13: KEY CONTROLS
E14: Own works standalone tender | F14: ='Tender Build-Up'!B47
E15: Management Reserve, pre-margin | F15: ='Commercial Inputs'!E20
E16: Weather allowance | F16: ='Weather Risk'!B38
E17: Dry programme (working days) | F17: ='Weather Risk'!B8
E18: Weather-adjusted planning (days) | F18: ='Weather Risk'!B8+'Weather Risk'!B26
E19: Risk Truth release gate | F19: ='Risk Truth'!B15
A21: HOW TO READ THIS WORKBOOK - SIMPLE WORKFLOW
A22: 1 | B22: Cover & Instructions | C22: Job details, document register, assumptions, exclusions, RFIs, release QA
A23: 2 | B23: Consolidated Package | C23: Own works + subcontract packages + overhead + profit = all-in tender
A24: 3 | B24: QS Takeoff | C24: One row per priced item with quantity, source, status
A25: 4 | B25: Resource Build-Up | C25: How each QS item is built: labour, plant, materials, subcontract, preliminaries
A26: 5 | B26: Commercial Inputs | C26: Allowances, management reserve, overhead, profit, GST
A27: 6 | B27: Tender Build-Up | C27: The commercial stack, calculated
A28: 7 | B28: Risk Truth | C28: Risk register, exposures, duplication controls, release gate
A29: 8 | B29: Weather Risk / Programme Export | C29: Project weather inputs and task durations / logic
A30: 9 | B30: Supplier Quote Register + logs | C30: Quotes, emails, RFIs, documents, decisions, changes
A33: CURRENT RELEASE POSITION
A34: (Write where the estimate stands and what blocks release. List every RED item.)
A38: Project | B38: NOT PROVIDED | D38: Location | E38: NOT PROVIDED
A39: Current drawings | B39: NOT PROVIDED | D39: Issue date | E39: NOT PROVIDED
A40: Scope | B40: NOT PROVIDED | D40: GST | E40: All values shown exclude GST
A41: Programme | B41: NOT PROVIDED | D41: Weather | E41: NOT PROVIDED
A42: Price status | B42: NOT PROVIDED | D42: Commercial | E42: NOT PROVIDED
A44: Risk Truth | B44: Risk-control and reconciliation module. Tracks baseline vs residual exposure, provision routing, duplication and release gate.
A46: DRAWING / DOCUMENT REGISTER
A47: Document / Drawing | B47: Reference | C47: Estimate use
A48: Plans / drawings
A49: Specifications
A50: Geotechnical / ground information
A51: Survey / CAD / models
A52: Tender / contract / scope documents
A53: Supplier / subcontract quotations
A54: Other consultants / approvals
A55: Correspondence / addenda / clarifications
A56: Backend construction intelligence
A57: ASSUMPTIONS / QUALIFICATIONS / RFIs
A58: A1
A59: A2
... A112: KEY RISKS / WATCHOUTS
A113: Risk ID | B113: Risk | C113: Likelihood | D113: Impact
A114: =IF('Risk Truth'!A25="","",'Risk Truth'!A25) | B114: =IF('Risk Truth'!B25="","",'Risk Truth'!B25) | C114: =IF('Risk Truth'!D25="","",'Risk Truth'!D25) | D114: =IF('Risk Truth'!E25="","",'Risk Truth'!E25)
A115: =IF('Risk Truth'!A26="","",'Risk Truth'!A26) | B115: =IF('Risk Truth'!B26="","",'Risk Truth'!B26) | C115: =IF('Risk Truth'!D26="","",'Risk Truth'!D26) | D115: =IF('Risk Truth'!E26="","",'Risk Truth'!E26)
A116: =IF('Risk Truth'!A27="","",'Risk Truth'!A27) | B116: =IF('Risk Truth'!B27="","",'Risk Truth'!B27) | C116: =IF('Risk Truth'!D27="","",'Risk Truth'!D27) | D116: =IF('Risk Truth'!E27="","",'Risk Truth'!E27)
A117: =IF('Risk Truth'!A28="","",'Risk Truth'!A28) | B117: =IF('Risk Truth'!B28="","",'Risk Truth'!B28) | C117: =IF('Risk Truth'!D28="","",'Risk Truth'!D28) | D117: =IF('Risk Truth'!E28="","",'Risk Truth'!E28)
A118: =IF('Risk Truth'!A29="","",'Risk Truth'!A29) | B118: =IF('Risk Truth'!B29="","",'Risk Truth'!B29) | C118: =IF('Risk Truth'!D29="","",'Risk Truth'!D29) | D118: =IF('Risk Truth'!E29="","",'Risk Truth'!E29)
A119: =IF('Risk Truth'!A30="","",'Risk Truth'!A30) | B119: =IF('Risk Truth'!B30="","",'Risk Truth'!B30) | C119: =IF('Risk Truth'!D30="","",'Risk Truth'!D30) | D119: =IF('Risk Truth'!E30="","",'Risk Truth'!E30)
A120: =IF('Risk Truth'!A31="","",'Risk Truth'!A31) | B120: =IF('Risk Truth'!B31="","",'Risk Truth'!B31) | C120: =IF('Risk Truth'!D31="","",'Risk Truth'!D31) | D120: =IF('Risk Truth'!E31="","",'Risk Truth'!E31)
A121: =IF('Risk Truth'!A32="","",'Risk Truth'!A32) | B121: =IF('Risk Truth'!B32="","",'Risk Truth'!B32) | C121: =IF('Risk Truth'!D32="","",'Risk Truth'!D32) | D121: =IF('Risk Truth'!E32="","",'Risk Truth'!E32)
A122: =IF('Risk Truth'!A33="","",'Risk Truth'!A33) | B122: =IF('Risk Truth'!B33="","",'Risk Truth'!B33) | C122: =IF('Risk Truth'!D33="","",'Risk Truth'!D33) | D122: =IF('Risk Truth'!E33="","",'Risk Truth'!E33)
A123: =IF('Risk Truth'!A34="","",'Risk Truth'!A34) | B123: =IF('Risk Truth'!B34="","",'Risk Truth'!B34) | C123: =IF('Risk Truth'!D34="","",'Risk Truth'!D34) | D123: =IF('Risk Truth'!E34="","",'Risk Truth'!E34)
A124: =IF('Risk Truth'!A35="","",'Risk Truth'!A35) | B124: =IF('Risk Truth'!B35="","",'Risk Truth'!B35) | C124: =IF('Risk Truth'!D35="","",'Risk Truth'!D35) | D124: =IF('Risk Truth'!E35="","",'Risk Truth'!E35)
A125: =IF('Risk Truth'!A36="","",'Risk Truth'!A36) | B125: =IF('Risk Truth'!B36="","",'Risk Truth'!B36) | C125: =IF('Risk Truth'!D36="","",'Risk Truth'!D36) | D125: =IF('Risk Truth'!E36="","",'Risk Truth'!E36)
... A128: =IF('Risk Truth'!A39="","",'Risk Truth'!A39) | B128: =IF('Risk Truth'!B39="","",'Risk Truth'!B39) | C128: =IF('Risk Truth'!D39="","",'Risk Truth'!D39) | D128: =IF('Risk Truth'!E39="","",'Risk Truth'!E39)
A130: TENDER RELEASE QA
A131: Section | B131: Requirement | C131: Status (colour + reason) | D131: Owner | E131: Required Before Tender?
A132: References | B132: Current Intake, Master Prompt, Triple Verification and applicable standards recorded
A133: Documents | B133: Current drawing/specification/tender register complete
A134: Scope | B134: Work-package inclusions, exclusions and interfaces defined
A135: Takeoff | B135: Major quantities measured/provided/calculated and referenced to current documents
A136: Resource build-up | B136: Every active QS code has linked labour/plant/material/subcontract rows or an explicit PC
A137: Rate verification | B137: Important rates classified and three-way verified or flagged
A138: Quotes / PCs | B138: PC sums and quote-required packages reconciled to the Quote Log
A139: Assumptions | B139: Assumptions and exclusions are explicit, current and defensible
A140: Interfaces | B140: By-others / client / authority / consultant responsibilities identified
A141: Risk Truth | B141: All material risks have baseline, residual exposure and cost treatment
A142: Risk duplication | B142: No residual risk is costed twice; overlap groups and cost-treatment owners checked
A143: Weather | B143: Weather Risk reviewed; approved tool run current or documented
... A153: Approval | B153: Final tender/estimate approved by the authorised reviewer
A155: TRIPLE VERIFICATION & RISK TRUTH - MANDATORY
A156: 1 | B156: No rate, quantity, productivity, duration, allowance or risk treatment is GREEN without current primary evidence, an independent check and a first-principles check.
A157: 2 | B157: Quantifiable physical risk consequences return to Resource Build-Up / QS; only distinct residual uncertainty goes to Risk Truth.
A158: 3 | B158: CA01 and CA02 default to Risk Truth residual feeds; manual percentages are not used unless documented.
A159: 4 | B159: Weather remains in the Weather Risk specialist path and is never also added inside rates.
A160: 5 | B160: Any RED duplication, programme reconciliation or unresolved material RED exposure blocks final release.
A162: REVISION RECORD (full history on the Change Log sheet)
A163: Revision | B163: Date | C163: Description

Sheet Scope Coverage
A1: Scope ID | B1: Group | C1: Requirement | D1: Detail | E1: Source (document / sheet / page) | F1: Owner | G1: Treatment | H1: Cost refs (QS codes / CA lines) | I1: Register refs (A#, EX-#, RFI-#) | J1: Quote refs | K1: Basis (what was priced and why) | L1: Action
A2: SC-001
A3: SC-002
A4: SC-003
A5: SC-004
A6: SC-005
A7: SC-006
A8: SC-007
A9: SC-008
A10: SC-009
A11: SC-010
A12: SC-011
A13: SC-012
... A301: SC-300

Sheet Summary
A1: ESTIMATE SUMMARY - MASTER ESTIMATE WORKBOOK
A2: WORKING ALL-IN TENDER | B2: ='Consolidated Package'!F56
A4: Current known cost before OH/profit | B4: ='Consolidated Package'!B56 | D4: Project | E4: ='Cover & Instructions'!B38
A5: ="Company OH, "&TEXT('Commercial Inputs'!D21,"0.0%") | B5: ='Consolidated Package'!C56 | D5: Issue | E5: ='Cover & Instructions'!E39
A6: ="Profit, "&TEXT('Commercial Inputs'!D22,"0.0%")&" true margin" | B6: ='Consolidated Package'!E56 | D6: Programme | E6: ='Cover & Instructions'!B41
A7: Siteworks standalone tender | B7: ='Tender Build-Up'!B47 | D7: Weather allowance | E7: ='Weather Risk'!B38
A8: Subcontract packages (known) | B8: =SUM('Consolidated Package'!B6:B11) | D8: Management Reserve | E8: ='Commercial Inputs'!E20
D9: GST | E9: ='Cover & Instructions'!E40
A10: Release status | B10: ='Risk Truth'!B15 | D10: Ground basis
A11: Supplier/material costs within the own-works estimate are already included in the Resource Build-Up; subcontract packages are added once in the Consolidated Package.
A12: Key Quantities
A21: Pricing Summary (direct-cost estimate)
A22: Section | B22: Amount
A23: =IF('Tender Build-Up'!A10="","",1&" "&'Tender Build-Up'!A10) | B23: ='Tender Build-Up'!B10
A24: =IF('Tender Build-Up'!A11="","",2&" "&'Tender Build-Up'!A11) | B24: ='Tender Build-Up'!B11
A25: =IF('Tender Build-Up'!A12="","",3&" "&'Tender Build-Up'!A12) | B25: ='Tender Build-Up'!B12
A26: =IF('Tender Build-Up'!A13="","",4&" "&'Tender Build-Up'!A13) | B26: ='Tender Build-Up'!B13
A27: =IF('Tender Build-Up'!A14="","",5&" "&'Tender Build-Up'!A14) | B27: ='Tender Build-Up'!B14
A28: =IF('Tender Build-Up'!A15="","",6&" "&'Tender Build-Up'!A15) | B28: ='Tender Build-Up'!B15
A29: =IF('Tender Build-Up'!A16="","",7&" "&'Tender Build-Up'!A16) | B29: ='Tender Build-Up'!B16
A30: =IF('Tender Build-Up'!A17="","",8&" "&'Tender Build-Up'!A17) | B30: ='Tender Build-Up'!B17
A31: =IF('Tender Build-Up'!A18="","",9&" "&'Tender Build-Up'!A18) | B31: ='Tender Build-Up'!B18
A32: =IF('Tender Build-Up'!A19="","",10&" "&'Tender Build-Up'!A19) | B32: ='Tender Build-Up'!B19
A33: Total priced amount excl. GST | B33: ='Tender Build-Up'!B20
A34: Pricing basis
A35: GST
A36: Scope
A37: Accuracy
A38: Programme basis
A39: Tender Completion Build-Up (client-adjustable commercial provisions)
A40: Purpose | B40: This block reflects Tender Build-Up and current Commercial Inputs selections.
A41: Input sheet | B41: Use Commercial Inputs to adjust allowances, overhead and profit method, bonds, retention finance and GST.
A43: Line
A44: Base direct estimate excl. GST | B44: ='Tender Build-Up'!B20 | E44: QS direct-cost estimate
A45: Pre-margin additions | B45: ='Tender Build-Up'!B39 | E45: Commercial Inputs CA01-CA16 incl. CA16 Management Reserve
A46: Commercial adjustments | B46: ='Tender Build-Up'!B46 | E46: Commercial Inputs CA17-CA20 commercial adjustments
A47: Tender total excl. GST | B47: ='Tender Build-Up'!B47 | E47: Working tender incl. Management Reserve; excl GST
A48: GST if selected | B48: ='Tender Build-Up'!B48 | E48: Optional display
A49: Tender total incl. GST if selected | B49: ='Tender Build-Up'!B49 | E49: Optional tax-inclusive check
A50: Net pre-GST payment after retention | B50: ='Tender Build-Up'!B53 | E50: Tender total less retention withholding after CA25 deposit treatment.
A51: Retention release after holding period | B51: ='Tender Build-Up'!B55 | E51: Released after CA23 retention period; amount follows CA25 deposit retention treatment.
A52: Deposit / advance payment | B52: =IF('Commercial Inputs'!F28="Yes",'Tender Build-Up'!B47*'Commercial Inputs'!D28,0) | E52: Part of tender total; controlled by CA24
A53: Stage cashflow tab | E53: Editable stage profile and cumulative cashflow
A56: COST CHAIN INTEGRITY
A57: Check | B57: Upstream | C57: Downstream | D57: Difference | E57: Status
A58: Resource Build-Up -> QS | B58: =SUM('Resource Build-Up'!$Z$7:$Z$306) | C58: ='QS Takeoff'!$G$203 | D58: =C58-B58 | E58: =IF(ABS(D58)<0.01,"OK","CHECK")
A59: QS -> Tender Build-Up | B59: ='QS Takeoff'!$G$203 | C59: ='Tender Build-Up'!$B$20 | D59: =C59-B59 | E59: =IF(ABS(D59)<0.01,"OK","CHECK")
A60: Tender Build-Up -> Summary | B60: ='Tender Build-Up'!$B$20 | C60: =$B$33 | D60: =C60-B60 | E60: =IF(ABS(D60)<0.01,"OK","CHECK")
A61: Commercial Inputs -> Tender Build-Up | B61: =SUM('Tender Build-Up'!$B$23:$B$38)+SUM('Tender Build-Up'!$B$42:$B$45) | C61: =$B$45+$B$46 | D61: =C61-B61 | E61: =IF(ABS(D61)<0.01,"OK","CHECK")
A62: Formula control | B62: Formula/output cells are edit-blocked with Stop validation; yellow cells are intended inputs.
A63: Release rule | B63: All chain checks must read OK before issue.
A64: Weather Engine output -> Commercial Inputs CA10 Engine Amount (audit only) | B64: ='Weather Risk'!$B$40 | C64: ='Commercial Inputs'!$L$14 | D64: =C64-B64 | E64: =IF(ABS(D64)<0.01,"OK","CHECK")
A65: RATE & PROGRAMME QA RELEASE GATE
A66: Check | B66: Count / Amount | C66: Status | D66: Action
A67: GREEN active resource rows | B67: ='Rate Verification'!B4 | C67: =IF(B67>0,"GREEN","NONE") | D67: Three checks present
A68: AMBER active resource rows | B68: ='Rate Verification'!B5 | C68: =IF(B68>0,"AMBER","NONE") | D68: Disclose allowance and firm before award
A69: RED active resource rows | B69: ='Rate Verification'!F4 | C69: =IF(B69>0,"RED","NONE") | D69: Quote/design evidence required
A70: Active QS items mapped to programme | B70: ='Estimate Review Board'!$B$16 | D70: Checked against populated Programme Export QS codes
A71: Overall release | B71: =IF(OR(C69="RED",LEFT(B74,4)<>"PASS"),"RED - release blocked","AMBER - review before release") | C71: =IF(LEFT(B71,3)="RED","RED","AMBER")
A72: Weather model / task factors
A73: Weather integration rerun gate
A74: Risk Truth release gate | B74: ='Risk Truth'!$B$15 | C74: =IF(LEFT(B74,4)="PASS","GREEN","RED") | D74: PASS required for final release
A75: Risk Truth recalculated tender total | B75: ='Risk Truth'!$B$11 | C75: INFO | D75: Should equal the live tender total when Risk Truth feeds and commercial logic reconcile.
A76: INDEPENDENT ESTIMATE REVIEW BOARD RELEASE GATE
A77: Review Board gate | B77: ='Estimate Review Board'!$B$19 | C77: =IF(LEFT(B77,4)="PASS",IF(ISNUMBER(SEARCH("AMBER",B77)),"AMBER","GREEN"),"RED") | D77: PASS or PASS WITH AMBER required for release
A78: Active QS items fully reviewed | B78: ='Estimate Review Board'!$B$17&" / "&'Estimate Review Board'!$B$16 | C78: =IF('Estimate Review Board'!$B$17<'Estimate Review Board'!$B$16,"RED","GREEN") | D78: Every active QS item must pass all mandatory review columns
A79: Unresolved material findings | B79: ='Estimate Review Board'!$B$12&" RED / "&'Estimate Review Board'!$B$13&" AMBER" | C79: =IF('Estimate Review Board'!$B$12>0,"RED",IF('Estimate Review Board'!$B$13>0,"AMBER","GREEN")) | D79: RED blocks release; AMBER must be disclosed and actioned
A80: Reviewer independence / commitment | B80: ='Estimate Review Board'!$B$11&" independence failures" | C80: =IF('Estimate Review Board'!$B$11>0,"RED",IF(OR('Estimate Review Board'!$B$9<'Estimate Review Board'!$B$7,'Estimate Review Board'!$B$10<'Estimate Review Board'!$B$8,'Estimate Review Board'!$B$18<>"COMPLETE"),"AMBER","GREEN")) | D80: Required reviewers must be blind, independent and committed before comparison
A81: PROGRAMME RECONCILIATION
A82: Calculated controlling path working days
A83: Tender baseline working days | B83: ='Weather Risk'!B8
A84: Coordination float / buffer working days | B84: 0
A85: Controlling path
A86: Programme release
A87: PROGRAMME CALENDAR BASIS
A88: Tender-season assumed start | B88: ='Weather Risk'!B7
A89: Weekday-only base finish | B89: ='Weather Risk'!B10
A90: Elapsed calendar span | B90: =IF(OR(B88="",B89=""),"",B89-B88+1)
A91: Holiday / shutdown treatment
A93: CONSOLIDATED PACKAGE REVIEW - NOT FINAL TENDER UNTIL RELEASED
A94: Own works current pre-commercial | B94: ='Tender Build-Up'!B40 | C94: LINKED
A95: Subcontract packages (known) | B95: =SUM('Consolidated Package'!B6:B11) | C95: QUOTED
A96: Gross current known package | B96: =B94+B95 | C96: CALCULATED
A97: Confirmed overlap with own works | B97: ='Consolidated Package'!B13 | C97: CLOSED
A98: Current known package after reconciliation | B98: =B96-B97 | C98: CALCULATED
A99: Company O/H | B99: ='Commercial Inputs'!D21 | C99: PROVIDED
A100: Contractor profit | B100: ='Commercial Inputs'!D22 | C100: PROVIDED
A101: Tender adjudication status | B101: ='Risk Truth'!B15

Sheet Consolidated Package
A1: CONSOLIDATED ALL-IN PACKAGE - OWN WORKS + SUBCONTRACT PACKAGES
A2: WORKING ALL-IN TENDER EXCL GST | B2: =F56
A4: Package / Control | B4: Amount excl GST | C4: Classification | D4: Included in Siteworks direct? | E4: Status | F4: Release
A5: Own works current pre-commercial package | B5: ='Tender Build-Up'!B40 | C5: LINKED / CURRENT | D5: Yes | E5: Own works | F5: AMBER / WORKING
C6: QUOTED | D6: No | F6: AMBER
C7: QUOTED | D7: No | F7: AMBER
C8: QUOTED | D8: No | F8: AMBER
C9: QUOTED | D9: No | F9: AMBER
C10: QUOTED | D10: No | F10: AMBER
C11: QUOTED | D11: No | F11: AMBER
A12: GROSS CURRENT KNOWN PACKAGE | B12: =B5+SUM(B6:B11) | C12: CALCULATED | D12: Review total only | E12: Not final tender | F12: HOLD
A13: Confirmed overlap between own works and a package | B13: 0 | C13: CLOSED | D13: None | E13: Interface closed | F13: AMBER / CLOSED
A14: Current known package after overlap | B14: =B12-B13 | C14: CALCULATED | D14: Review only | E14: Not final tender | F14: HOLD
A15: Unpriced packages (see Quote Log) | C15: UNPRICED | D15: No
A16: WORKING ALL-IN TENDER EXCL GST | B16: =F56 | C16: CALCULATED / WORKING | D16: N/A
A20: Rules: one row per subcontract package (rows 6-11; insert more by copying a row). Amount as a number, 'Included in Siteworks direct?' = No, classification QUOTED / QUOTED BASE / CONFIRMED ADDITIONAL / ALLOCATED (never CALCULATED). A package with no price yet stays as a row with no amount and is recorded on the Quote Log.
A54: CURRENT WORKING COMMERCIAL SCENARIO - OVERHEAD AND PROFIT FROM COMMERCIAL INPUTS CA17 / CA18
A55: Scenario | B55: Precommercial cost | C55: Overhead | D55: Subtotal after OH | E55: Profit | F55: Tender excl GST | G55: Commercial uplift
A56: Current known package after overlap | B56: =B14 | C56: =IF('Commercial Inputs'!$F$21<>"Yes",0,IF('Commercial Inputs'!$C$21="Markup %",B56*N('Commercial Inputs'!$D$21),N('Commercial Inputs'!$E$21))) | D56: =B56+C56 | E56: =IF('Commercial Inputs'!$F$22<>"Yes",0,IF('Commercial Inputs'!$C$22="Margin %",D56/(1-N('Commercial Inputs'!$D$22))-D56,IF('Commercial Inputs'!$C$22="Markup %",D56*N('Commercial Inputs'!$D$22),N('Commercial Inputs'!$E$22)))) | F56: =D56+E56 | G56: =F56-B56

Sheet Tender Build-Up
A1: MASTER ESTIMATE WORKBOOK - TENDER BUILD-UP
A3: Project | B3: ='Cover & Instructions'!B38
A4: Pricing status | B4: ='Cover & Instructions'!B42
A5: GST | B5: Optional GST display via Commercial Inputs CA21.
A6: Retention | B6: Cashflow only by default.
A7: No direct-cost values are entered on this sheet. Base costs flow from QS Takeoff; commercial provisions flow from Commercial Inputs.
A9: Base direct estimate (by QS section) | B9: Amount excl. GST | C9: Source | D9: Treatment | E9: Notes
B10: =IF(A10="",0,SUMIF('QS Takeoff'!$A$3:$A$202,A10,'QS Takeoff'!$G$3:$G$202)) | C10: QS Takeoff (type the section name exactly as used on QS Takeoff) | D10: Priced / provisional | E10: Linked QS section total; confirm current project scope, classification, source and firm-up action.
B11: =IF(A11="",0,SUMIF('QS Takeoff'!$A$3:$A$202,A11,'QS Takeoff'!$G$3:$G$202)) | C11: QS Takeoff (type the section name exactly as used on QS Takeoff) | D11: Priced / provisional | E11: Linked QS section total; confirm current project ESC scope and requirements.
B12: =IF(A12="",0,SUMIF('QS Takeoff'!$A$3:$A$202,A12,'QS Takeoff'!$G$3:$G$202)) | C12: QS Takeoff (type the section name exactly as used on QS Takeoff) | D12: Priced / provisional | E12: Linked QS section total; confirm current project quantities, ground basis, haul and disposal assumptions.
B13: =IF(A13="",0,SUMIF('QS Takeoff'!$A$3:$A$202,A13,'QS Takeoff'!$G$3:$G$202)) | C13: QS Takeoff (type the section name exactly as used on QS Takeoff) | D13: Priced / provisional | E13: Linked QS section total; confirm current project stormwater / detention design and supplier requirements.
B14: =IF(A14="",0,SUMIF('QS Takeoff'!$A$3:$A$202,A14,'QS Takeoff'!$G$3:$G$202)) | C14: QS Takeoff (type the section name exactly as used on QS Takeoff) | D14: Priced / provisional | E14: Linked QS section total; confirm current project wastewater / water scope and authority interfaces.
B15: =IF(A15="",0,SUMIF('QS Takeoff'!$A$3:$A$202,A15,'QS Takeoff'!$G$3:$G$202)) | C15: QS Takeoff (type the section name exactly as used on QS Takeoff) | D15: Priced / provisional | E15: Linked QS section total; confirm current project pavement / concrete scope and specification.
B16: =IF(A16="",0,SUMIF('QS Takeoff'!$A$3:$A$202,A16,'QS Takeoff'!$G$3:$G$202)) | C16: QS Takeoff (type the section name exactly as used on QS Takeoff) | D16: Priced / provisional | E16: Linked QS section total; confirm current project kerb / external sitework scope.
B17: =IF(A17="",0,SUMIF('QS Takeoff'!$A$3:$A$202,A17,'QS Takeoff'!$G$3:$G$202)) | C17: QS Takeoff (type the section name exactly as used on QS Takeoff) | D17: Priced / provisional | E17: Linked QS section total; confirm current project retaining-wall design, quantities and temporary works.
B18: =IF(A18="",0,SUMIF('QS Takeoff'!$A$3:$A$202,A18,'QS Takeoff'!$G$3:$G$202)) | C18: QS Takeoff (type the section name exactly as used on QS Takeoff) | D18: Priced / provisional | E18: Linked QS section total; confirm current testing, survey, as-built and compliance obligations.
B19: =IF(A19="",0,SUMIF('QS Takeoff'!$A$3:$A$202,A19,'QS Takeoff'!$G$3:$G$202)) | C19: QS Takeoff (type the section name exactly as used on QS Takeoff) | D19: Priced / provisional | E19: Linked QS section total; confirm current reinstatement, defects and handover obligations.
A20: Base direct estimate excl. GST | B20: =SUM('QS Takeoff'!$G$3:$G$202) | D20: Subtotal | E20: Direct cost sourced from Resource Build-Up through QS Takeoff; includes measured, provisional, allowance and PC items.
A21: Check: QS sections not listed above (must be zero) | B21: =ROUND(B20-SUM(B10:B19),2) | C21: =IF(B21=0,"OK","CHECK - list every QS section above")
A22: Pre-margin additions | B22: Calculated amount excl. GST | C22: Input source | D22: Include? | E22: Basis / Notes
A23: CA01 - Design / scope residual risk - Risk Truth | B23: =IF('Commercial Inputs'!$F$5<>"Yes",0,IF(OR('Commercial Inputs'!$C$5="Risk Engine",'Commercial Inputs'!$C$5="Weather Engine"),N('Commercial Inputs'!$L$5),IF('Commercial Inputs'!$C$5="PC Sum",N('Commercial Inputs'!$E$5),IF('Commercial Inputs'!$C$5="%",$B$20*N('Commercial Inputs'!$D$5),0)))) | C23: ='Commercial Inputs'!C5 | D23: ='Commercial Inputs'!F5 | E23: CA01 defaults to Risk Truth. PC Sum or % may be selected as a stated adjudication override; Include? controls whether the selected treatment enters the tender.
A24: CA02 - Construction / execution residual risk - Risk Truth | B24: =IF('Commercial Inputs'!$F$6<>"Yes",0,IF(OR('Commercial Inputs'!$C$6="Risk Engine",'Commercial Inputs'!$C$6="Weather Engine"),N('Commercial Inputs'!$L$6),IF('Commercial Inputs'!$C$6="PC Sum",N('Commercial Inputs'!$E$6),IF('Commercial Inputs'!$C$6="%",$B$20*N('Commercial Inputs'!$D$6),0)))) | C24: ='Commercial Inputs'!C6 | D24: ='Commercial Inputs'!F6 | E24: CA02 defaults to Risk Truth. PC Sum or % may be selected as a stated adjudication override; Include? controls whether the selected treatment enters the tender.
A25: ='Commercial Inputs'!A7&" - "&'Commercial Inputs'!B7 | B25: =IF('Commercial Inputs'!$F$7<>"Yes",0,IF(OR('Commercial Inputs'!$C$7="Risk Engine",'Commercial Inputs'!$C$7="Weather Engine"),N('Commercial Inputs'!$L$7),IF('Commercial Inputs'!$C$7="PC Sum",N('Commercial Inputs'!$E$7),IF('Commercial Inputs'!$C$7="%",$B$20*N('Commercial Inputs'!$D$7),0)))) | C25: ='Commercial Inputs'!C7 | D25: ='Commercial Inputs'!F7 | E25: ='Commercial Inputs'!I7
A26: ='Commercial Inputs'!A8&" - "&'Commercial Inputs'!B8 | B26: =IF('Commercial Inputs'!$F$8<>"Yes",0,IF(OR('Commercial Inputs'!$C$8="Risk Engine",'Commercial Inputs'!$C$8="Weather Engine"),N('Commercial Inputs'!$L$8),IF('Commercial Inputs'!$C$8="PC Sum",N('Commercial Inputs'!$E$8),IF('Commercial Inputs'!$C$8="%",$B$20*N('Commercial Inputs'!$D$8),0)))) | C26: ='Commercial Inputs'!C8 | D26: ='Commercial Inputs'!F8 | E26: ='Commercial Inputs'!I8
A27: ='Commercial Inputs'!A9&" - "&'Commercial Inputs'!B9 | B27: =IF('Commercial Inputs'!$F$9<>"Yes",0,IF(OR('Commercial Inputs'!$C$9="Risk Engine",'Commercial Inputs'!$C$9="Weather Engine"),N('Commercial Inputs'!$L$9),IF('Commercial Inputs'!$C$9="PC Sum",N('Commercial Inputs'!$E$9),IF('Commercial Inputs'!$C$9="%",$B$20*N('Commercial Inputs'!$D$9),0)))) | C27: ='Commercial Inputs'!C9 | D27: ='Commercial Inputs'!F9 | E27: ='Commercial Inputs'!I9
A28: ='Commercial Inputs'!A10&" - "&'Commercial Inputs'!B10 | B28: =IF('Commercial Inputs'!$F$10<>"Yes",0,IF(OR('Commercial Inputs'!$C$10="Risk Engine",'Commercial Inputs'!$C$10="Weather Engine"),N('Commercial Inputs'!$L$10),IF('Commercial Inputs'!$C$10="PC Sum",N('Commercial Inputs'!$E$10),IF('Commercial Inputs'!$C$10="%",$B$20*N('Commercial Inputs'!$D$10),0)))) | C28: ='Commercial Inputs'!C10 | D28: ='Commercial Inputs'!F10 | E28: ='Commercial Inputs'!I10
A29: ='Commercial Inputs'!A11&" - "&'Commercial Inputs'!B11 | B29: =IF('Commercial Inputs'!$F$11<>"Yes",0,IF(OR('Commercial Inputs'!$C$11="Risk Engine",'Commercial Inputs'!$C$11="Weather Engine"),N('Commercial Inputs'!$L$11),IF('Commercial Inputs'!$C$11="PC Sum",N('Commercial Inputs'!$E$11),IF('Commercial Inputs'!$C$11="%",$B$20*N('Commercial Inputs'!$D$11),0)))) | C29: ='Commercial Inputs'!C11 | D29: ='Commercial Inputs'!F11 | E29: ='Commercial Inputs'!I11
A30: CA08 - Abnormal ground / contamination / rock allowance | B30: =IF('Commercial Inputs'!$F$12<>"Yes",0,IF(OR('Commercial Inputs'!$C$12="Risk Engine",'Commercial Inputs'!$C$12="Weather Engine"),N('Commercial Inputs'!$L$12),IF('Commercial Inputs'!$C$12="PC Sum",N('Commercial Inputs'!$E$12),IF('Commercial Inputs'!$C$12="%",$B$20*N('Commercial Inputs'!$D$12),0)))) | C30: ='Commercial Inputs'!C12 | D30: ='Commercial Inputs'!F12 | E30: No generic ground percentage. Use only an explicit evidence-based provision not more truthfully placed in QS or a specialist engine.
A31: ='Commercial Inputs'!A13&" - "&'Commercial Inputs'!B13 | B31: =IF('Commercial Inputs'!$F$13<>"Yes",0,IF(OR('Commercial Inputs'!$C$13="Risk Engine",'Commercial Inputs'!$C$13="Weather Engine"),N('Commercial Inputs'!$L$13),IF('Commercial Inputs'!$C$13="PC Sum",N('Commercial Inputs'!$E$13),IF('Commercial Inputs'!$C$13="%",$B$20*N('Commercial Inputs'!$D$13),0)))) | C31: ='Commercial Inputs'!C13 | D31: ='Commercial Inputs'!F13 | E31: Project-specific construction water-control provision only; check overlap with Weather / Ground risk treatment.
A32: ='Commercial Inputs'!A14&" - "&'Commercial Inputs'!B14 | B32: =IF('Commercial Inputs'!$F$14<>"Yes",0,IF(OR('Commercial Inputs'!$C$14="Risk Engine",'Commercial Inputs'!$C$14="Weather Engine"),N('Commercial Inputs'!$L$14),IF('Commercial Inputs'!$C$14="PC Sum",N('Commercial Inputs'!$E$14),IF('Commercial Inputs'!$C$14="%",$B$20*N('Commercial Inputs'!$D$14),0)))) | C32: ='Commercial Inputs'!C14 | D32: ='Commercial Inputs'!F14 | E32: CA10 defaults to Weather Engine. PC Sum or % may be selected explicitly; Include? can turn the weather allowance off while the engine output remains retained for audit.
A33: ='Commercial Inputs'!A15&" - "&'Commercial Inputs'!B15 | B33: =IF('Commercial Inputs'!$F$15<>"Yes",0,IF(OR('Commercial Inputs'!$C$15="Risk Engine",'Commercial Inputs'!$C$15="Weather Engine"),N('Commercial Inputs'!$L$15),IF('Commercial Inputs'!$C$15="PC Sum",N('Commercial Inputs'!$E$15),IF('Commercial Inputs'!$C$15="%",$B$20*N('Commercial Inputs'!$D$15),0)))) | C33: ='Commercial Inputs'!C15 | D33: ='Commercial Inputs'!F15 | E33: ='Commercial Inputs'!I15
A34: ='Commercial Inputs'!A16&" - "&'Commercial Inputs'!B16 | B34: =IF('Commercial Inputs'!$F$16<>"Yes",0,IF(OR('Commercial Inputs'!$C$16="Risk Engine",'Commercial Inputs'!$C$16="Weather Engine"),N('Commercial Inputs'!$L$16),IF('Commercial Inputs'!$C$16="PC Sum",N('Commercial Inputs'!$E$16),IF('Commercial Inputs'!$C$16="%",$B$20*N('Commercial Inputs'!$D$16),0)))) | C34: ='Commercial Inputs'!C16 | D34: ='Commercial Inputs'!F16 | E34: Reasonable defects / closeout attendance is included under RH01.
A35: ='Commercial Inputs'!A17&" - "&'Commercial Inputs'!B17 | B35: =IF('Commercial Inputs'!$F$17<>"Yes",0,IF(OR('Commercial Inputs'!$C$17="Risk Engine",'Commercial Inputs'!$C$17="Weather Engine"),N('Commercial Inputs'!$L$17),IF('Commercial Inputs'!$C$17="PC Sum",N('Commercial Inputs'!$E$17),IF('Commercial Inputs'!$C$17="%",$B$20*N('Commercial Inputs'!$D$17),0)))) | C35: ='Commercial Inputs'!C17 | D35: ='Commercial Inputs'!F17 | E35: Basic Siteworks traffic / pedestrian / access controls are included within the itemised PG01 preliminaries.
A36: ='Commercial Inputs'!A18&" - "&'Commercial Inputs'!B18 | B36: =IF('Commercial Inputs'!$F$18<>"Yes",0,IF(OR('Commercial Inputs'!$C$18="Risk Engine",'Commercial Inputs'!$C$18="Weather Engine"),N('Commercial Inputs'!$L$18),IF('Commercial Inputs'!$C$18="PC Sum",N('Commercial Inputs'!$E$18),IF('Commercial Inputs'!$C$18="%",$B$20*N('Commercial Inputs'!$D$18),0)))) | C36: ='Commercial Inputs'!C18 | D36: ='Commercial Inputs'!F18 | E36: ='Commercial Inputs'!I18
A37: ='Commercial Inputs'!A19&" - "&'Commercial Inputs'!B19 | B37: =IF('Commercial Inputs'!$F$19<>"Yes",0,IF(OR('Commercial Inputs'!$C$19="Risk Engine",'Commercial Inputs'!$C$19="Weather Engine"),N('Commercial Inputs'!$L$19),IF('Commercial Inputs'!$C$19="PC Sum",N('Commercial Inputs'!$E$19),IF('Commercial Inputs'!$C$19="%",$B$20*N('Commercial Inputs'!$D$19),0)))) | C37: ='Commercial Inputs'!C19 | D37: ='Commercial Inputs'!F19 | E37: ='Commercial Inputs'!I19
A38: ='Commercial Inputs'!A20&" - "&'Commercial Inputs'!B20 | B38: =IF('Commercial Inputs'!$F$20<>"Yes",0,IF(OR('Commercial Inputs'!$C$20="Risk Engine",'Commercial Inputs'!$C$20="Weather Engine"),N('Commercial Inputs'!$L$20),IF(OR('Commercial Inputs'!$C$20="PC Sum",'Commercial Inputs'!$C$20="Fixed Amount"),N('Commercial Inputs'!$E$20),IF('Commercial Inputs'!$C$20="%",$B$20*N('Commercial Inputs'!$D$20),0)))) | C38: ='Commercial Inputs'!C20 | D38: ='Commercial Inputs'!F20 | E38: PROVIDED / AMBER management adjudication reserve
A39: Pre-margin additions subtotal | B39: =SUM(B23:B38)
A40: Subtotal before commercial adjustments | B40: =B20+B39
A41: Overhead, profit and other commercial adjustments | B41: Calculated amount excl. GST | C41: Input source | D41: Include? | E41: Basis / Notes
A42: ='Commercial Inputs'!A21&" - "&'Commercial Inputs'!B21 | B42: =IF('Commercial Inputs'!$F$21<>"Yes",0,IF('Commercial Inputs'!$C$21="Markup %",$B$40*N('Commercial Inputs'!$D$21),IF('Commercial Inputs'!$C$21="Fixed Amount",N('Commercial Inputs'!$E$21),0))) | C42: ='Commercial Inputs'!C21 | D42: ='Commercial Inputs'!F21
A43: ='Commercial Inputs'!A22&" - "&'Commercial Inputs'!B22 | B43: =IF('Commercial Inputs'!$F$22<>"Yes",0,IF('Commercial Inputs'!$C$22="Margin %",($B$40+$B$42+$B$44+$B$45)/(1-N('Commercial Inputs'!$D$22))-($B$40+$B$42+$B$44+$B$45),IF('Commercial Inputs'!$C$22="Markup %",($B$40+$B$42+$B$44+$B$45)*N('Commercial Inputs'!$D$22),IF('Commercial Inputs'!$C$22="Fixed Amount",N('Commercial Inputs'!$E$22),0)))) | C43: ='Commercial Inputs'!C22 | D43: ='Commercial Inputs'!F22
A44: ='Commercial Inputs'!A23&" - "&'Commercial Inputs'!B23 | B44: =IF('Commercial Inputs'!$F$23<>"Yes",0,IF('Commercial Inputs'!$C$23="%",$B$40*N('Commercial Inputs'!$D$23),IF('Commercial Inputs'!$C$23="PC Sum",N('Commercial Inputs'!$E$23),0))) | C44: ='Commercial Inputs'!C23 | D44: ='Commercial Inputs'!F23 | E44: ='Commercial Inputs'!I23
A45: ='Commercial Inputs'!A24&" - "&'Commercial Inputs'!B24 | B45: =IF('Commercial Inputs'!$F$24<>"Yes",0,IF('Commercial Inputs'!$C$24="%",$B$40*N('Commercial Inputs'!$D$24),IF('Commercial Inputs'!$C$24="PC Sum",N('Commercial Inputs'!$E$24),0))) | C45: ='Commercial Inputs'!C24 | D45: ='Commercial Inputs'!F24 | E45: ='Commercial Inputs'!I24
A46: Commercial adjustments subtotal | B46: =SUM(B42:B45)
A47: Tender total excl. GST | B47: =B40+B46 | D47: Subtotal | E47: Base direct estimate + selected pre-margin additions + commercial adjustments.
A48: GST if selected | B48: =IF('Commercial Inputs'!$F$25="Yes",$B$47*N('Commercial Inputs'!$D$25),0) | C48: Commercial Inputs CA21 | D48: Optional | E48: GST applies only when CA21 Include? is Yes.
A49: Tender total incl. GST if selected | B49: =B47+B48 | D49: Subtotal | E49: For GST-inclusive check only.
A51: Cashflow / contract security visibility only | B51: Calculated value | C51: Input source | D51: Include? | E51: Notes
A52: Contract retention withholding | B52: =IF('Commercial Inputs'!$F$26<>"Yes",0,$B$47*'Commercial Inputs'!$D$26*(1-IF(AND('Commercial Inputs'!$F$28="Yes",'Commercial Inputs'!$F$29<>"Yes"),'Commercial Inputs'!$D$28,0))) | C52: Commercial Inputs CA22 | D52: Cashflow only | E52: Retention withholding on retention-applicable contract value; deposit treatment controlled by CA25.
A53: Net pre-GST payment after retention | B53: =$B$47-$B$52 | C53: Calculated | D53: Cashflow only | E53: Tender total excl. GST less current retention withholding.
A54: Retention holding period | B54: =IF('Commercial Inputs'!$F$27="Yes",'Commercial Inputs'!$D$27,0) | C54: Commercial Inputs CA23 | D54: Cashflow only | E54: Months from practical completion unless contract states otherwise.
A55: Retention released after holding period | B55: =$B$52 | C55: Calculated | D55: Cashflow only | E55: Equals current retention withholding; released after the CA23 holding period.
A56: Total pre-GST receipts including retention release | B56: =$B$53+$B$55 | C56: Calculated | D56: Cashflow only | E56: Equals tender total excl. GST.

Sheet Commercial Inputs
A1: COMMERCIAL INPUTS - BELOW-THE-LINE SOURCE OF TRUTH | H1: Profit method | I1: =C22
H2: CA18 method (linked) | I2: =IF(C22="Margin %","Margin",IF(C22="Markup %","Markup",IF(C22="Fixed Amount","Fixed Amount",C22))) | J2: The calculation method is selected in column C. There is no second profit-method selector.
A3: CA01/CA02: Risk Engine, PC Sum or %. CA10: Weather Engine, PC Sum or %. Other pre-margin allowances: PC Sum or %. Column F Include? is the on/off switch. Engine outputs remain live in column L even when another method is selected, preserving the audit trail.
A4: Ref | B4: Allowance / adjustment | C4: Input method | D4: Input % | E4: PC Sum excl. GST | F4: Include? | G4: Pricing stage | H4: Calculation / treatment | I4: Notes / basis | J4: Firm-up action | K4: Pricing method / flag shown in QS | L4: Engine Amount excl. GST | M4: Engine Source / Status
A5: CA01 | B5: Design / scope residual risk - Risk Truth linked | C5: Risk Engine | F5: Yes | G5: Pre-margin addition | H5: =IF(C5="Risk Engine","Uses linked Risk Truth engine amount in L5",IF(C5="Weather Engine","Uses linked Weather Risk amount in L5",IF(C5="PC Sum","Uses manual PC Sum in E5",IF(C5="%","Uses Input % in D5 against base direct cost","CHECK METHOD")))) | I5: Residual design/scope risk only where the consequence cannot be more truthfully placed in Resource Build-Up/QS or a specialist engine. | J5: Close Risk Truth RED items and confirm residual is distinct / integration complete. | K5: =IF(F5<>"Yes",C5&" - OFF",C5) | L5: ='Risk Truth'!$B$12
A6: CA02 | B6: Construction / execution residual risk - Risk Truth linked | C6: Risk Engine | F6: Yes | G6: Pre-margin addition | H6: =IF(C6="Risk Engine","Uses linked Risk Truth engine amount in L6",IF(C6="Weather Engine","Uses linked Weather Risk amount in L6",IF(C6="PC Sum","Uses manual PC Sum in E6",IF(C6="%","Uses Input % in D6 against base direct cost","CHECK METHOD")))) | I6: Residual construction/execution risk only where the consequence cannot be more truthfully placed in Resource Build-Up/QS or a specialist engine. | J6: Close Risk Truth RED items and confirm residual is distinct / integration complete. | K6: =IF(F6<>"Yes",C6&" - OFF",C6) | L6: ='Risk Truth'!$B$13
A7: CA03 | B7: Escalation / tender validity allowance | C7: % | F7: No | G7: Pre-margin addition | H7: =IF(C7="Risk Engine","Uses linked Risk Truth engine amount in L7",IF(C7="Weather Engine","Uses linked Weather Risk amount in L7",IF(C7="PC Sum","Uses manual PC Sum in E7",IF(C7="%","Uses Input % in D7 against base direct cost","CHECK METHOD")))) | I7: Enter only where escalation is evidence-based; do not default to a generic percentage. | J7: Confirm construction start and validity. | K7: =IF(F7<>"Yes",C7&" - OFF",C7)
A8: CA04 | B8: Final subcontractor quote gap / market adjustment | C8: PC Sum | F8: No | G8: Pre-margin addition | H8: =IF(C8="Risk Engine","Uses linked Risk Truth engine amount in L8",IF(C8="Weather Engine","Uses linked Weather Risk amount in L8",IF(C8="PC Sum","Uses manual PC Sum in E8",IF(C8="%","Uses Input % in D8 against base direct cost","CHECK METHOD")))) | I8: Use only for a distinct reconciled live-quote gap not already included in QS/PC items or Risk Truth. | J8: Use only after supplier quote returns are reconciled and a distinct uncovered market gap is evidenced. | K8: =IF(F8<>"Yes",C8&" - OFF",C8)
A9: CA05 | B9: Council / authority consent and inspection fees | C9: PC Sum | F9: No | G9: Pre-margin addition | H9: =IF(C9="Risk Engine","Uses linked Risk Truth engine amount in L9",IF(C9="Weather Engine","Uses linked Weather Risk amount in L9",IF(C9="PC Sum","Uses manual PC Sum in E9",IF(C9="%","Uses Input % in D9 against base direct cost","CHECK METHOD")))) | I9: Confirm contractual responsibility before inclusion. | J9: Confirm fee responsibility. | K9: =IF(F9<>"Yes",C9&" - OFF",C9)
A10: CA06 | B10: Utility authority fees / relocations | C10: PC Sum | F10: No | G10: Pre-margin addition | H10: =IF(C10="Risk Engine","Uses linked Risk Truth engine amount in L10",IF(C10="Weather Engine","Uses linked Weather Risk amount in L10",IF(C10="PC Sum","Uses manual PC Sum in E10",IF(C10="%","Uses Input % in D10 against base direct cost","CHECK METHOD")))) | I10: Confirm contractual responsibility; physical construction scope should normally sit in QS. | J10: Confirm utilities. | K10: =IF(F10<>"Yes",C10&" - OFF",C10)
A11: CA07 | B11: Temporary works engineering / PS documentation | C11: PC Sum | F11: No | G11: Pre-margin addition | H11: =IF(C11="Risk Engine","Uses linked Risk Truth engine amount in L11",IF(C11="Weather Engine","Uses linked Weather Risk amount in L11",IF(C11="PC Sum","Uses manual PC Sum in E11",IF(C11="%","Uses Input % in D11 against base direct cost","CHECK METHOD")))) | I11: Use only for temporary-works engineering / documentation not already in direct scope. | J11: Avoid duplication. | K11: =IF(F11<>"Yes",C11&" - OFF",C11)
A12: CA08 | B12: Abnormal ground / contamination / rock allowance | C12: PC Sum | F12: No | G12: Pre-margin addition | H12: =IF(C12="Risk Engine","Uses linked Risk Truth engine amount in L12",IF(C12="Weather Engine","Uses linked Weather Risk amount in L12",IF(C12="PC Sum","Uses manual PC Sum in E12",IF(C12="%","Uses Input % in D12 against base direct cost","CHECK METHOD")))) | I12: Do not use as a generic ground-risk percentage. Quantifiable ground consequences belong in QS or an approved specialist risk treatment. | J12: Review geotech/contamination data. | K12: =IF(F12<>"Yes",C12&" - OFF",C12)
A13: CA09 | B13: Construction dewatering / groundwater control | C13: PC Sum | F13: No | G13: Pre-margin addition | H13: =IF(C13="Risk Engine","Uses linked Risk Truth engine amount in L13",IF(C13="Weather Engine","Uses linked Weather Risk amount in L13",IF(C13="PC Sum","Uses manual PC Sum in E13",IF(C13="%","Uses Input % in D13 against base direct cost","CHECK METHOD")))) | I13: Construction water / dewatering PC pending final programme/groundwater conditions. Distinct from normal weather CA10. | J13: Firm methodology after earthworks programme and site conditions are confirmed. | K13: =IF(F13<>"Yes",C13&" - OFF",C13)
A14: CA10 | B14: Weather risk allowance - linked approved engine | C14: Weather Engine | F14: Yes | G14: Pre-margin addition | H14: =IF(C14="Risk Engine","Uses linked Risk Truth engine amount in L14",IF(C14="Weather Engine","Uses linked Weather Risk amount in L14",IF(C14="PC Sum","Uses manual PC Sum in E14",IF(C14="%","Uses Input % in D14 against base direct cost","CHECK METHOD")))) | I14: Weather Risk engine feeds this line when the method is Weather Engine. | J14: Rerun the weather tool when the start date, programme or weather-exposed scope changes. | K14: Weather Engine - AMBER / CURRENT TENDER SCENARIO | L14: ='Weather Risk'!$B$40 | M14: Weather tool run recorded on Weather Risk (CA10 engine feed)
A15: CA11 | B15: Extended preliminaries beyond weather-adjusted tender baseline | C15: PC Sum | F15: No | G15: Pre-margin addition | H15: =IF(C15="Risk Engine","Uses linked Risk Truth engine amount in L15",IF(C15="Weather Engine","Uses linked Weather Risk amount in L15",IF(C15="PC Sum","Uses manual PC Sum in E15",IF(C15="%","Uses Input % in D15 against base direct cost","CHECK METHOD")))) | I15: Do not use for weather delay already treated through CA10. | J15: Add only for non-weather instructed extension or revised contract programme after checking CA10 overlap. | K15: =IF(F15<>"Yes",C15&" - OFF",C15)
A16: CA12 | B16: Defects liability / maintenance beyond base | C16: PC Sum | F16: No | G16: Pre-margin addition | H16: =IF(C16="Risk Engine","Uses linked Risk Truth engine amount in L16",IF(C16="Weather Engine","Uses linked Weather Risk amount in L16",IF(C16="PC Sum","Uses manual PC Sum in E16",IF(C16="%","Uses Input % in D16 against base direct cost","CHECK METHOD")))) | I16: Reasonable defects / closeout attendance is carried in RH01. | J16: Confirm special maintenance obligations. | K16: =IF(F16<>"Yes",C16&" - OFF",C16)
A17: CA13 | B17: Stakeholder liaison / access marshals beyond base | C17: PC Sum | F17: No | G17: Pre-margin addition | H17: =IF(C17="Risk Engine","Uses linked Risk Truth engine amount in L17",IF(C17="Weather Engine","Uses linked Weather Risk amount in L17",IF(C17="PC Sum","Uses manual PC Sum in E17",IF(C17="%","Uses Input % in D17 against base direct cost","CHECK METHOD")))) | I17: Basic Siteworks traffic / pedestrian / access controls are carried within the itemised PG01 preliminaries. | J17: Confirm restricted operations. | K17: =IF(F17<>"Yes",C17&" - OFF",C17)
A18: CA14 | B18: Out-of-hours / restricted access premium | C18: PC Sum | F18: No | G18: Pre-margin addition | H18: =IF(C18="Risk Engine","Uses linked Risk Truth engine amount in L18",IF(C18="Weather Engine","Uses linked Weather Risk amount in L18",IF(C18="PC Sum","Uses manual PC Sum in E18",IF(C18="%","Uses Input % in D18 against base direct cost","CHECK METHOD")))) | I18: Normal weekday access assumed. | J18: Confirm work windows. | K18: =IF(F18<>"Yes",C18&" - OFF",C18)
A19: CA15 | B19: Unforeseen post-tender client scope additions | C19: PC Sum | F19: No | G19: Pre-margin addition | H19: =IF(C19="Risk Engine","Uses linked Risk Truth engine amount in L19",IF(C19="Weather Engine","Uses linked Weather Risk amount in L19",IF(C19="PC Sum","Uses manual PC Sum in E19",IF(C19="%","Uses Input % in D19 against base direct cost","CHECK METHOD")))) | I19: No allowance for later scope changes. | J19: Include only if instructed. | K19: =IF(F19<>"Yes",C19&" - OFF",C19)
A20: CA16 | B20: Management Reserve - residual tender-stage uncertainty (adjudication) | C20: Fixed Amount | F20: No | G20: Pre-margin adjudication provision | H20: =IF(C20="Fixed Amount","Uses fixed management reserve in E20",IF(C20="Risk Engine","Uses linked Risk Truth engine amount in L20",IF(C20="Weather Engine","Uses linked Weather Risk amount in L20",IF(C20="PC Sum","Uses manual PC Sum in E20",IF(C20="%","Uses Input % in D20 against base direct cost","CHECK METHOD"))))) | I20: PROVIDED management reserve selected at tender adjudication. Purpose: protect the tender against aggregate residual tender-stage uncertainty and unknown-unknowns that remain after known/measurable scope, PCs, quoted packages, Weather Risk and Risk Truth treatments have already been allowed. It is not a Risk Truth contingency and does not close or downgrade any RED item. | J20: Reassess whenever a RED is resolved, a material scope/quantity/rate changes, or before contract award. If an exposure becomes measurable, price the actual consequence in the correct cost line and reassess the reserve rather than automatically consuming it. | K20: Fixed Amount - PROVIDED / AMBER / 4.0% ADJUDICATION BASIS
A21: CA17 | B21: Company overhead recovery | C21: Markup % | D21: 0.1 | F21: Yes | G21: Commercial adjustment | H21: 10% markup applied to subtotal before profit | I21: Company overhead recovery, applied as markup to the subtotal before profit. Set per job. | J21: Review against Siteworks actual overhead recovery when company financial basis is available; no tender hold created by this user-provided input. | K21: Markup % - PROVIDED / WORKING BASIS
A22: CA18 | B22: Contractor profit | C22: Margin % | D22: 0.15 | F22: Yes | G22: Commercial adjustment | H22: 15% TRUE MARGIN after overhead and other selected commercial costs | I22: Contractor profit as true margin after overhead and other selected allowances. Set per job. | J22: Change only if Siteworks instructs a different profit method/rate. | K22: Margin % - PROVIDED / WORKING BASIS
A23: CA19 | B23: Bonds / contract securities allowance | C23: % | F23: No | G23: Commercial adjustment | H23: Applied if selected | I23: Include only where contract securities create a genuine contractor cost. | J23: Confirm security terms. | K23: % user input provision
A24: CA20 | B24: Retention finance / cashflow cost allowance | C24: % | F24: No | G24: Commercial adjustment | H24: Applied if selected | I24: Finance cost only; retention withholding itself is a cashflow item. | J24: Confirm retention terms. | K24: % user input provision
A25: CA21 | B25: GST | C25: % | D25: 0.15 | F25: No | G25: Tax | H25: Applied to tender total if selected | I25: Optional tax display. Set 15% for NZ GST or 10% for Australian GST when applicable; estimate control total remains ex tax. | J25: Confirm submission format. | K25: % user input provision
A26: CA22 | B26: Contract retention withholding | C26: % | D26: 0 | F26: No | G26: Cashflow only | H26: Visibility only | I26: Not added to tender price. | J26: Confirm retention cap/terms. | K26: User input
A27: CA23 | B27: Retention holding period | C27: Months | D27: 0 | F27: No | G27: Cashflow only | H27: Times retention release | I27: No retention holding period assumed; CA23 remains 0 until contract terms are supplied. | J27: Confirm contract. | K27: % user input provision
A28: CA24 | B28: Deposit / advance payment | I28: Used as first cashflow stage. | J28: Confirm whether permitted. | K28: User selection
A29: CA25 | B29: Retention applies to deposit | I29: Normally No. | J29: Confirm contract.
A30: Notes
A31: 1 | B31: Leave Include? as No for any provision that is not to be included. Enter Input % or PC Sum depending on the intended basis; PC Sum overrides % where populated.
A32: MANAGEMENT RESERVE - ADJUDICATION BASIS
A33: Control | B33: Value | C33: Classification | D33: Basis / meaning | E33: Unresolved item 1 RED | F33: Unresolved item 2 RED | G33: Unresolved item 3 RED | H33: Unresolved item 4 RED
A34: Reserve base
A35: Selected reserve rate
A36: Pre-OH/profit Management Reserve
A37: Tender effect of reserve
A38: Probability note | B38: N/A | D38: Do not weight any item with a probability unless it is evidenced. Unknown probability = sensitivity only, never an expected value.
A39: Consumption rule | B39: N/A | D39: Do not automatically consume the reserve when a risk resolves; Rick adjudicates any change under change control.

Sheet QS Takeoff
A1: QS TAKEOFF - MASTER ESTIMATE WORKBOOK - RESOURCE-LINKED | L1: Rate and Amount are linked from Resource Build-Up. One row per priced item; the section name goes on every row. Do not type over the grey formula columns.
A2: Civil Scope / WBS | B2: Code | C2: Description | D2: Unit | E2: Quantity | F2: Rate excl. GST | G2: Amount excl. GST | H2: Quantity Basis | I2: Source drawing / scope | J2: Status | K2: Notes / Assumptions | L2: Pricing Method | M2: Pricing Basis / Build-up | N2: Source Type | O2: Source URL(s) | P2: Pricing Flag | Q2: Confidence / Firm-up Action | R2: Owner | S2: Verification Status | T2: Quote / Reference
F3: =IF(B3="","",IF(E3=0,0,G3/E3)) | G3: =IF(B3="","",SUMIF('Resource Build-Up'!$B$7:$B$306,B3,'Resource Build-Up'!$Z$7:$Z$306)) | L3: =IF(B3="","",IF(J3="Excluded","Excluded","Resource-linked")) | M3: =IF(B3="","",IF(G3=0,"No resource cost / review","Resource Build-Up -> "&B3)) | N3: =IF(B3="","","Resource Build-Up") | O3: =IF(B3="","","See Resource Build-Up / Resource Rate Library") | R3: =IF(OR(ISNUMBER(SEARCH("PC",P3)),ISNUMBER(SEARCH("quote",Q3))),"Jason","Rick")
F4: =IF(B4="","",IF(E4=0,0,G4/E4)) | G4: =IF(B4="","",SUMIF('Resource Build-Up'!$B$7:$B$306,B4,'Resource Build-Up'!$Z$7:$Z$306)) | L4: =IF(B4="","",IF(J4="Excluded","Excluded","Resource-linked")) | M4: =IF(B4="","",IF(G4=0,"No resource cost / review","Resource Build-Up -> "&B4)) | N4: =IF(B4="","","Resource Build-Up") | O4: =IF(B4="","","See Resource Build-Up / Resource Rate Library") | R4: =IF(OR(ISNUMBER(SEARCH("PC",P4)),ISNUMBER(SEARCH("quote",Q4))),"Jason","Rick")
F5: =IF(B5="","",IF(E5=0,0,G5/E5)) | G5: =IF(B5="","",SUMIF('Resource Build-Up'!$B$7:$B$306,B5,'Resource Build-Up'!$Z$7:$Z$306)) | L5: =IF(B5="","",IF(J5="Excluded","Excluded","Resource-linked")) | M5: =IF(B5="","",IF(G5=0,"No resource cost / review","Resource Build-Up -> "&B5)) | N5: =IF(B5="","","Resource Build-Up") | O5: =IF(B5="","","See Resource Build-Up / Resource Rate Library") | R5: =IF(OR(ISNUMBER(SEARCH("PC",P5)),ISNUMBER(SEARCH("quote",Q5))),"Jason","Rick")
F6: =IF(B6="","",IF(E6=0,0,G6/E6)) | G6: =IF(B6="","",SUMIF('Resource Build-Up'!$B$7:$B$306,B6,'Resource Build-Up'!$Z$7:$Z$306)) | L6: =IF(B6="","",IF(J6="Excluded","Excluded","Resource-linked")) | M6: =IF(B6="","",IF(G6=0,"No resource cost / review","Resource Build-Up -> "&B6)) | N6: =IF(B6="","","Resource Build-Up") | O6: =IF(B6="","","See Resource Build-Up / Resource Rate Library") | R6: =IF(OR(ISNUMBER(SEARCH("PC",P6)),ISNUMBER(SEARCH("quote",Q6))),"Jason","Rick")
F7: =IF(B7="","",IF(E7=0,0,G7/E7)) | G7: =IF(B7="","",SUMIF('Resource Build-Up'!$B$7:$B$306,B7,'Resource Build-Up'!$Z$7:$Z$306)) | L7: =IF(B7="","",IF(J7="Excluded","Excluded","Resource-linked")) | M7: =IF(B7="","",IF(G7=0,"No resource cost / review","Resource Build-Up -> "&B7)) | N7: =IF(B7="","","Resource Build-Up") | O7: =IF(B7="","","See Resource Build-Up / Resource Rate Library") | R7: =IF(OR(ISNUMBER(SEARCH("PC",P7)),ISNUMBER(SEARCH("quote",Q7))),"Jason","Rick")
F8: =IF(B8="","",IF(E8=0,0,G8/E8)) | G8: =IF(B8="","",SUMIF('Resource Build-Up'!$B$7:$B$306,B8,'Resource Build-Up'!$Z$7:$Z$306)) | L8: =IF(B8="","",IF(J8="Excluded","Excluded","Resource-linked")) | M8: =IF(B8="","",IF(G8=0,"No resource cost / review","Resource Build-Up -> "&B8)) | N8: =IF(B8="","","Resource Build-Up") | O8: =IF(B8="","","See Resource Build-Up / Resource Rate Library") | R8: =IF(OR(ISNUMBER(SEARCH("PC",P8)),ISNUMBER(SEARCH("quote",Q8))),"Jason","Rick")
F9: =IF(B9="","",IF(E9=0,0,G9/E9)) | G9: =IF(B9="","",SUMIF('Resource Build-Up'!$B$7:$B$306,B9,'Resource Build-Up'!$Z$7:$Z$306)) | L9: =IF(B9="","",IF(J9="Excluded","Excluded","Resource-linked")) | M9: =IF(B9="","",IF(G9=0,"No resource cost / review","Resource Build-Up -> "&B9)) | N9: =IF(B9="","","Resource Build-Up") | O9: =IF(B9="","","See Resource Build-Up / Resource Rate Library") | R9: =IF(OR(ISNUMBER(SEARCH("PC",P9)),ISNUMBER(SEARCH("quote",Q9))),"Jason","Rick")
F10: =IF(B10="","",IF(E10=0,0,G10/E10)) | G10: =IF(B10="","",SUMIF('Resource Build-Up'!$B$7:$B$306,B10,'Resource Build-Up'!$Z$7:$Z$306)) | L10: =IF(B10="","",IF(J10="Excluded","Excluded","Resource-linked")) | M10: =IF(B10="","",IF(G10=0,"No resource cost / review","Resource Build-Up -> "&B10)) | N10: =IF(B10="","","Resource Build-Up") | O10: =IF(B10="","","See Resource Build-Up / Resource Rate Library") | R10: =IF(OR(ISNUMBER(SEARCH("PC",P10)),ISNUMBER(SEARCH("quote",Q10))),"Jason","Rick")
F11: =IF(B11="","",IF(E11=0,0,G11/E11)) | G11: =IF(B11="","",SUMIF('Resource Build-Up'!$B$7:$B$306,B11,'Resource Build-Up'!$Z$7:$Z$306)) | L11: =IF(B11="","",IF(J11="Excluded","Excluded","Resource-linked")) | M11: =IF(B11="","",IF(G11=0,"No resource cost / review","Resource Build-Up -> "&B11)) | N11: =IF(B11="","","Resource Build-Up") | O11: =IF(B11="","","See Resource Build-Up / Resource Rate Library") | R11: =IF(OR(ISNUMBER(SEARCH("PC",P11)),ISNUMBER(SEARCH("quote",Q11))),"Jason","Rick")
F12: =IF(B12="","",IF(E12=0,0,G12/E12)) | G12: =IF(B12="","",SUMIF('Resource Build-Up'!$B$7:$B$306,B12,'Resource Build-Up'!$Z$7:$Z$306)) | L12: =IF(B12="","",IF(J12="Excluded","Excluded","Resource-linked")) | M12: =IF(B12="","",IF(G12=0,"No resource cost / review","Resource Build-Up -> "&B12)) | N12: =IF(B12="","","Resource Build-Up") | O12: =IF(B12="","","See Resource Build-Up / Resource Rate Library") | R12: =IF(OR(ISNUMBER(SEARCH("PC",P12)),ISNUMBER(SEARCH("quote",Q12))),"Jason","Rick")
F13: =IF(B13="","",IF(E13=0,0,G13/E13)) | G13: =IF(B13="","",SUMIF('Resource Build-Up'!$B$7:$B$306,B13,'Resource Build-Up'!$Z$7:$Z$306)) | L13: =IF(B13="","",IF(J13="Excluded","Excluded","Resource-linked")) | M13: =IF(B13="","",IF(G13=0,"No resource cost / review","Resource Build-Up -> "&B13)) | N13: =IF(B13="","","Resource Build-Up") | O13: =IF(B13="","","See Resource Build-Up / Resource Rate Library") | R13: =IF(OR(ISNUMBER(SEARCH("PC",P13)),ISNUMBER(SEARCH("quote",Q13))),"Jason","Rick")
F14: =IF(B14="","",IF(E14=0,0,G14/E14)) | G14: =IF(B14="","",SUMIF('Resource Build-Up'!$B$7:$B$306,B14,'Resource Build-Up'!$Z$7:$Z$306)) | L14: =IF(B14="","",IF(J14="Excluded","Excluded","Resource-linked")) | M14: =IF(B14="","",IF(G14=0,"No resource cost / review","Resource Build-Up -> "&B14)) | N14: =IF(B14="","","Resource Build-Up") | O14: =IF(B14="","","See Resource Build-Up / Resource Rate Library") | R14: =IF(OR(ISNUMBER(SEARCH("PC",P14)),ISNUMBER(SEARCH("quote",Q14))),"Jason","Rick")
... F202: =IF(B202="","",IF(E202=0,0,G202/E202)) | G202: =IF(B202="","",SUMIF('Resource Build-Up'!$B$7:$B$306,B202,'Resource Build-Up'!$Z$7:$Z$306)) | L202: =IF(B202="","",IF(J202="Excluded","Excluded","Resource-linked")) | M202: =IF(B202="","",IF(G202=0,"No resource cost / review","Resource Build-Up -> "&B202)) | N202: =IF(B202="","","Resource Build-Up") | O202: =IF(B202="","","See Resource Build-Up / Resource Rate Library") | R202: =IF(OR(ISNUMBER(SEARCH("PC",P202)),ISNUMBER(SEARCH("quote",Q202))),"Jason","Rick")
A203: TOTAL DIRECT COST | G203: =SUM(G3:G202)

Sheet Resource Build-Up
A1: RESOURCE BUILD-UP - MASTER ESTIMATE WORKBOOK - LINKED COST / DURATION FORMULAS
A2: Every active QS Code must have resource rows here. Extended Cost totals by QS Code are pulled into QS Takeoff; do not type a second QS rate or amount.
A3: Ordinary civil plant stays Plant whether owned or hired. Specialist delivered capability such as mobile cranes is normally Subcontract. Wet hire must record operator/fuel inclusions to stop double counting.
A4: Calculation modes: Time x Count; QS Qty x Factor; Direct Qty; Lump Sum / Quote. Duration is derived from quantity/productivity or explicitly overridden where sequencing requires it.
A5: Weather controls: AK:AM are estimator inputs; AN is formula-controlled exposed Labour/Plant cost feeding Weather Risk. Materials, fixed subcontract and Other costs are excluded from direct weather productivity by default.
A6: Build-Up Row ID | B6: QS Code | C6: WBS / Section | D6: Task Description | E6: QS Qty | F6: QS Unit | G6: Estimate Class | H6: Methodology / Work Step | I6: Productivity Rate | J6: Productivity Unit | K6: Calc Duration hrs | L6: Duration Override hrs | M6: Applied Duration hrs | N6: Calculation Mode | O6: Resource Type | P6: Resource Code | Q6: Resource Description | R6: Resource Count / Factor | S6: Manual Resource Qty | T6: Resource Unit | U6: Utilisation % | V6: Waste % | W6: Library Rate | X6: Job Rate Override | Y6: Applied Rate | Z6: Extended Cost | AA6: Library Source | AB6: Job Quote / Source Ref | AC6: Source Date | AD6: Operator Included? | AE6: Fuel Included? | AF6: Confidence | AG6: Assumption / RFI | AH6: Verified? | AI6: QA / Double-Count Check | AJ6: Notes | AK6: Weather Exposed? | AL6: Weather Task Type | AM6: Weather Basis / Status | AN6: Weather-Exposed Labour + Plant Cost
A7: =IF(B7="","",B7&"-"&TEXT(COUNTIF($B$7:B7,B7),"000")) | C7: =IFERROR(INDEX('QS Takeoff'!$A$3:$A$202,MATCH(B7,'QS Takeoff'!$B$3:$B$202,0)),"") | D7: =IFERROR(INDEX('QS Takeoff'!$C$3:$C$202,MATCH(B7,'QS Takeoff'!$B$3:$B$202,0)),"") | E7: =IFERROR(INDEX('QS Takeoff'!$E$3:$E$202,MATCH(B7,'QS Takeoff'!$B$3:$B$202,0)),"") | F7: =IFERROR(INDEX('QS Takeoff'!$D$3:$D$202,MATCH(B7,'QS Takeoff'!$B$3:$B$202,0)),"") | G7: =IFERROR(INDEX('QS Takeoff'!$J$3:$J$202,MATCH(B7,'QS Takeoff'!$B$3:$B$202,0)),"") | K7: =IF(OR(B7="",I7="",I7=0),"",E7/I7) | M7: =IF(L7>0,L7,K7) | Q7: =IFERROR(INDEX('Resource Rate Library'!$C$5:$C$200,MATCH(P7,'Resource Rate Library'!$A$5:$A$200,0)),"") | T7: =IFERROR(INDEX('Resource Rate Library'!$E$5:$E$200,MATCH(P7,'Resource Rate Library'!$A$5:$A$200,0)),"") | W7: =IFERROR(INDEX('Resource Rate Library'!$I$5:$I$200,MATCH(P7,'Resource Rate Library'!$A$5:$A$200,0)),0) | Y7: =IF(X7>0,X7,W7) | Z7: =IF(B7="","",IF(N7="Time x Count",M7*R7*IF(U7="",1,U7)*Y7,IF(N7="QS Qty x Factor",E7*R7*(1+IF(V7="",0,V7))*Y7,IF(N7="Direct Qty",S7*(1+IF(V7="",0,V7))*Y7,IF(N7="Lump Sum / Quote",S7*Y7,0))))) | AA7: =IFERROR(INDEX('Resource Rate Library'!$N$5:$N$200,MATCH(P7,'Resource Rate Library'!$A$5:$A$200,0)),"") | AD7: =IFERROR(INDEX('Resource Rate Library'!$G$5:$G$200,MATCH(P7,'Resource Rate Library'!$A$5:$A$200,0)),"") | AE7: =IFERROR(INDEX('Resource Rate Library'!$H$5:$H$200,MATCH(P7,'Resource Rate Library'!$A$5:$A$200,0)),"") | AI7: =IF(B7="","",IF(AND(P7="",N7<>"Lump Sum / Quote"),"RESOURCE CODE",IF(Y7=0,"RATE MISSING",IF(AND(O7="Plant",AD7="Yes",COUNTIFS($B$7:$B$306,B7,$O$7:$O$306,"Labour",$Q$7:$Q$306,"*Operator*")>0),"OPERATOR DOUBLE-COUNT",IF(AND(O7="Plant",AE7="Yes",COUNTIFS($B$7:$B$306,B7,$Q$7:$Q$306,"*Fuel*")>0),"FUEL DOUBLE-COUNT",IF(AH7<>"Yes","VERIFY","OK")))))) | AN7: =IF(AND(AK7="Yes",OR(O7="Labour",O7="Plant")),Z7,0)
A8: =IF(B8="","",B8&"-"&TEXT(COUNTIF($B$7:B8,B8),"000")) | C8: =IFERROR(INDEX('QS Takeoff'!$A$3:$A$202,MATCH(B8,'QS Takeoff'!$B$3:$B$202,0)),"") | D8: =IFERROR(INDEX('QS Takeoff'!$C$3:$C$202,MATCH(B8,'QS Takeoff'!$B$3:$B$202,0)),"") | E8: =IFERROR(INDEX('QS Takeoff'!$E$3:$E$202,MATCH(B8,'QS Takeoff'!$B$3:$B$202,0)),"") | F8: =IFERROR(INDEX('QS Takeoff'!$D$3:$D$202,MATCH(B8,'QS Takeoff'!$B$3:$B$202,0)),"") | G8: =IFERROR(INDEX('QS Takeoff'!$J$3:$J$202,MATCH(B8,'QS Takeoff'!$B$3:$B$202,0)),"") | K8: =IF(OR(B8="",I8="",I8=0),"",E8/I8) | M8: =IF(L8>0,L8,K8) | Q8: =IFERROR(INDEX('Resource Rate Library'!$C$5:$C$200,MATCH(P8,'Resource Rate Library'!$A$5:$A$200,0)),"") | T8: =IFERROR(INDEX('Resource Rate Library'!$E$5:$E$200,MATCH(P8,'Resource Rate Library'!$A$5:$A$200,0)),"") | W8: =IFERROR(INDEX('Resource Rate Library'!$I$5:$I$200,MATCH(P8,'Resource Rate Library'!$A$5:$A$200,0)),0) | Y8: =IF(X8>0,X8,W8) | Z8: =IF(B8="","",IF(N8="Time x Count",M8*R8*IF(U8="",1,U8)*Y8,IF(N8="QS Qty x Factor",E8*R8*(1+IF(V8="",0,V8))*Y8,IF(N8="Direct Qty",S8*(1+IF(V8="",0,V8))*Y8,IF(N8="Lump Sum / Quote",S8*Y8,0))))) | AA8: =IFERROR(INDEX('Resource Rate Library'!$N$5:$N$200,MATCH(P8,'Resource Rate Library'!$A$5:$A$200,0)),"") | AD8: =IFERROR(INDEX('Resource Rate Library'!$G$5:$G$200,MATCH(P8,'Resource Rate Library'!$A$5:$A$200,0)),"") | AE8: =IFERROR(INDEX('Resource Rate Library'!$H$5:$H$200,MATCH(P8,'Resource Rate Library'!$A$5:$A$200,0)),"") | AI8: =IF(B8="","",IF(AND(P8="",N8<>"Lump Sum / Quote"),"RESOURCE CODE",IF(Y8=0,"RATE MISSING",IF(AND(O8="Plant",AD8="Yes",COUNTIFS($B$7:$B$306,B8,$O$7:$O$306,"Labour",$Q$7:$Q$306,"*Operator*")>0),"OPERATOR DOUBLE-COUNT",IF(AND(O8="Plant",AE8="Yes",COUNTIFS($B$7:$B$306,B8,$Q$7:$Q$306,"*Fuel*")>0),"FUEL DOUBLE-COUNT",IF(AH8<>"Yes","VERIFY","OK")))))) | AN8: =IF(AND(AK8="Yes",OR(O8="Labour",O8="Plant")),Z8,0)
A9: =IF(B9="","",B9&"-"&TEXT(COUNTIF($B$7:B9,B9),"000")) | C9: =IFERROR(INDEX('QS Takeoff'!$A$3:$A$202,MATCH(B9,'QS Takeoff'!$B$3:$B$202,0)),"") | D9: =IFERROR(INDEX('QS Takeoff'!$C$3:$C$202,MATCH(B9,'QS Takeoff'!$B$3:$B$202,0)),"") | E9: =IFERROR(INDEX('QS Takeoff'!$E$3:$E$202,MATCH(B9,'QS Takeoff'!$B$3:$B$202,0)),"") | F9: =IFERROR(INDEX('QS Takeoff'!$D$3:$D$202,MATCH(B9,'QS Takeoff'!$B$3:$B$202,0)),"") | G9: =IFERROR(INDEX('QS Takeoff'!$J$3:$J$202,MATCH(B9,'QS Takeoff'!$B$3:$B$202,0)),"") | K9: =IF(OR(B9="",I9="",I9=0),"",E9/I9) | M9: =IF(L9>0,L9,K9) | Q9: =IFERROR(INDEX('Resource Rate Library'!$C$5:$C$200,MATCH(P9,'Resource Rate Library'!$A$5:$A$200,0)),"") | T9: =IFERROR(INDEX('Resource Rate Library'!$E$5:$E$200,MATCH(P9,'Resource Rate Library'!$A$5:$A$200,0)),"") | W9: =IFERROR(INDEX('Resource Rate Library'!$I$5:$I$200,MATCH(P9,'Resource Rate Library'!$A$5:$A$200,0)),0) | Y9: =IF(X9>0,X9,W9) | Z9: =IF(B9="","",IF(N9="Time x Count",M9*R9*IF(U9="",1,U9)*Y9,IF(N9="QS Qty x Factor",E9*R9*(1+IF(V9="",0,V9))*Y9,IF(N9="Direct Qty",S9*(1+IF(V9="",0,V9))*Y9,IF(N9="Lump Sum / Quote",S9*Y9,0))))) | AA9: =IFERROR(INDEX('Resource Rate Library'!$N$5:$N$200,MATCH(P9,'Resource Rate Library'!$A$5:$A$200,0)),"") | AD9: =IFERROR(INDEX('Resource Rate Library'!$G$5:$G$200,MATCH(P9,'Resource Rate Library'!$A$5:$A$200,0)),"") | AE9: =IFERROR(INDEX('Resource Rate Library'!$H$5:$H$200,MATCH(P9,'Resource Rate Library'!$A$5:$A$200,0)),"") | AI9: =IF(B9="","",IF(AND(P9="",N9<>"Lump Sum / Quote"),"RESOURCE CODE",IF(Y9=0,"RATE MISSING",IF(AND(O9="Plant",AD9="Yes",COUNTIFS($B$7:$B$306,B9,$O$7:$O$306,"Labour",$Q$7:$Q$306,"*Operator*")>0),"OPERATOR DOUBLE-COUNT",IF(AND(O9="Plant",AE9="Yes",COUNTIFS($B$7:$B$306,B9,$Q$7:$Q$306,"*Fuel*")>0),"FUEL DOUBLE-COUNT",IF(AH9<>"Yes","VERIFY","OK")))))) | AN9: =IF(AND(AK9="Yes",OR(O9="Labour",O9="Plant")),Z9,0)
A10: =IF(B10="","",B10&"-"&TEXT(COUNTIF($B$7:B10,B10),"000")) | C10: =IFERROR(INDEX('QS Takeoff'!$A$3:$A$202,MATCH(B10,'QS Takeoff'!$B$3:$B$202,0)),"") | D10: =IFERROR(INDEX('QS Takeoff'!$C$3:$C$202,MATCH(B10,'QS Takeoff'!$B$3:$B$202,0)),"") | E10: =IFERROR(INDEX('QS Takeoff'!$E$3:$E$202,MATCH(B10,'QS Takeoff'!$B$3:$B$202,0)),"") | F10: =IFERROR(INDEX('QS Takeoff'!$D$3:$D$202,MATCH(B10,'QS Takeoff'!$B$3:$B$202,0)),"") | G10: =IFERROR(INDEX('QS Takeoff'!$J$3:$J$202,MATCH(B10,'QS Takeoff'!$B$3:$B$202,0)),"") | K10: =IF(OR(B10="",I10="",I10=0),"",E10/I10) | M10: =IF(L10>0,L10,K10) | Q10: =IFERROR(INDEX('Resource Rate Library'!$C$5:$C$200,MATCH(P10,'Resource Rate Library'!$A$5:$A$200,0)),"") | T10: =IFERROR(INDEX('Resource Rate Library'!$E$5:$E$200,MATCH(P10,'Resource Rate Library'!$A$5:$A$200,0)),"") | W10: =IFERROR(INDEX('Resource Rate Library'!$I$5:$I$200,MATCH(P10,'Resource Rate Library'!$A$5:$A$200,0)),0) | Y10: =IF(X10>0,X10,W10) | Z10: =IF(B10="","",IF(N10="Time x Count",M10*R10*IF(U10="",1,U10)*Y10,IF(N10="QS Qty x Factor",E10*R10*(1+IF(V10="",0,V10))*Y10,IF(N10="Direct Qty",S10*(1+IF(V10="",0,V10))*Y10,IF(N10="Lump Sum / Quote",S10*Y10,0))))) | AA10: =IFERROR(INDEX('Resource Rate Library'!$N$5:$N$200,MATCH(P10,'Resource Rate Library'!$A$5:$A$200,0)),"") | AD10: =IFERROR(INDEX('Resource Rate Library'!$G$5:$G$200,MATCH(P10,'Resource Rate Library'!$A$5:$A$200,0)),"") | AE10: =IFERROR(INDEX('Resource Rate Library'!$H$5:$H$200,MATCH(P10,'Resource Rate Library'!$A$5:$A$200,0)),"") | AI10: =IF(B10="","",IF(AND(P10="",N10<>"Lump Sum / Quote"),"RESOURCE CODE",IF(Y10=0,"RATE MISSING",IF(AND(O10="Plant",AD10="Yes",COUNTIFS($B$7:$B$306,B10,$O$7:$O$306,"Labour",$Q$7:$Q$306,"*Operator*")>0),"OPERATOR DOUBLE-COUNT",IF(AND(O10="Plant",AE10="Yes",COUNTIFS($B$7:$B$306,B10,$Q$7:$Q$306,"*Fuel*")>0),"FUEL DOUBLE-COUNT",IF(AH10<>"Yes","VERIFY","OK")))))) | AN10: =IF(AND(AK10="Yes",OR(O10="Labour",O10="Plant")),Z10,0)
A11: =IF(B11="","",B11&"-"&TEXT(COUNTIF($B$7:B11,B11),"000")) | C11: =IFERROR(INDEX('QS Takeoff'!$A$3:$A$202,MATCH(B11,'QS Takeoff'!$B$3:$B$202,0)),"") | D11: =IFERROR(INDEX('QS Takeoff'!$C$3:$C$202,MATCH(B11,'QS Takeoff'!$B$3:$B$202,0)),"") | E11: =IFERROR(INDEX('QS Takeoff'!$E$3:$E$202,MATCH(B11,'QS Takeoff'!$B$3:$B$202,0)),"") | F11: =IFERROR(INDEX('QS Takeoff'!$D$3:$D$202,MATCH(B11,'QS Takeoff'!$B$3:$B$202,0)),"") | G11: =IFERROR(INDEX('QS Takeoff'!$J$3:$J$202,MATCH(B11,'QS Takeoff'!$B$3:$B$202,0)),"") | K11: =IF(OR(B11="",I11="",I11=0),"",E11/I11) | M11: =IF(L11>0,L11,K11) | Q11: =IFERROR(INDEX('Resource Rate Library'!$C$5:$C$200,MATCH(P11,'Resource Rate Library'!$A$5:$A$200,0)),"") | T11: =IFERROR(INDEX('Resource Rate Library'!$E$5:$E$200,MATCH(P11,'Resource Rate Library'!$A$5:$A$200,0)),"") | W11: =IFERROR(INDEX('Resource Rate Library'!$I$5:$I$200,MATCH(P11,'Resource Rate Library'!$A$5:$A$200,0)),0) | Y11: =IF(X11>0,X11,W11) | Z11: =IF(B11="","",IF(N11="Time x Count",M11*R11*IF(U11="",1,U11)*Y11,IF(N11="QS Qty x Factor",E11*R11*(1+IF(V11="",0,V11))*Y11,IF(N11="Direct Qty",S11*(1+IF(V11="",0,V11))*Y11,IF(N11="Lump Sum / Quote",S11*Y11,0))))) | AA11: =IFERROR(INDEX('Resource Rate Library'!$N$5:$N$200,MATCH(P11,'Resource Rate Library'!$A$5:$A$200,0)),"") | AD11: =IFERROR(INDEX('Resource Rate Library'!$G$5:$G$200,MATCH(P11,'Resource Rate Library'!$A$5:$A$200,0)),"") | AE11: =IFERROR(INDEX('Resource Rate Library'!$H$5:$H$200,MATCH(P11,'Resource Rate Library'!$A$5:$A$200,0)),"") | AI11: =IF(B11="","",IF(AND(P11="",N11<>"Lump Sum / Quote"),"RESOURCE CODE",IF(Y11=0,"RATE MISSING",IF(AND(O11="Plant",AD11="Yes",COUNTIFS($B$7:$B$306,B11,$O$7:$O$306,"Labour",$Q$7:$Q$306,"*Operator*")>0),"OPERATOR DOUBLE-COUNT",IF(AND(O11="Plant",AE11="Yes",COUNTIFS($B$7:$B$306,B11,$Q$7:$Q$306,"*Fuel*")>0),"FUEL DOUBLE-COUNT",IF(AH11<>"Yes","VERIFY","OK")))))) | AN11: =IF(AND(AK11="Yes",OR(O11="Labour",O11="Plant")),Z11,0)
A12: =IF(B12="","",B12&"-"&TEXT(COUNTIF($B$7:B12,B12),"000")) | C12: =IFERROR(INDEX('QS Takeoff'!$A$3:$A$202,MATCH(B12,'QS Takeoff'!$B$3:$B$202,0)),"") | D12: =IFERROR(INDEX('QS Takeoff'!$C$3:$C$202,MATCH(B12,'QS Takeoff'!$B$3:$B$202,0)),"") | E12: =IFERROR(INDEX('QS Takeoff'!$E$3:$E$202,MATCH(B12,'QS Takeoff'!$B$3:$B$202,0)),"") | F12: =IFERROR(INDEX('QS Takeoff'!$D$3:$D$202,MATCH(B12,'QS Takeoff'!$B$3:$B$202,0)),"") | G12: =IFERROR(INDEX('QS Takeoff'!$J$3:$J$202,MATCH(B12,'QS Takeoff'!$B$3:$B$202,0)),"") | K12: =IF(OR(B12="",I12="",I12=0),"",E12/I12) | M12: =IF(L12>0,L12,K12) | Q12: =IFERROR(INDEX('Resource Rate Library'!$C$5:$C$200,MATCH(P12,'Resource Rate Library'!$A$5:$A$200,0)),"") | T12: =IFERROR(INDEX('Resource Rate Library'!$E$5:$E$200,MATCH(P12,'Resource Rate Library'!$A$5:$A$200,0)),"") | W12: =IFERROR(INDEX('Resource Rate Library'!$I$5:$I$200,MATCH(P12,'Resource Rate Library'!$A$5:$A$200,0)),0) | Y12: =IF(X12>0,X12,W12) | Z12: =IF(B12="","",IF(N12="Time x Count",M12*R12*IF(U12="",1,U12)*Y12,IF(N12="QS Qty x Factor",E12*R12*(1+IF(V12="",0,V12))*Y12,IF(N12="Direct Qty",S12*(1+IF(V12="",0,V12))*Y12,IF(N12="Lump Sum / Quote",S12*Y12,0))))) | AA12: =IFERROR(INDEX('Resource Rate Library'!$N$5:$N$200,MATCH(P12,'Resource Rate Library'!$A$5:$A$200,0)),"") | AD12: =IFERROR(INDEX('Resource Rate Library'!$G$5:$G$200,MATCH(P12,'Resource Rate Library'!$A$5:$A$200,0)),"") | AE12: =IFERROR(INDEX('Resource Rate Library'!$H$5:$H$200,MATCH(P12,'Resource Rate Library'!$A$5:$A$200,0)),"") | AI12: =IF(B12="","",IF(AND(P12="",N12<>"Lump Sum / Quote"),"RESOURCE CODE",IF(Y12=0,"RATE MISSING",IF(AND(O12="Plant",AD12="Yes",COUNTIFS($B$7:$B$306,B12,$O$7:$O$306,"Labour",$Q$7:$Q$306,"*Operator*")>0),"OPERATOR DOUBLE-COUNT",IF(AND(O12="Plant",AE12="Yes",COUNTIFS($B$7:$B$306,B12,$Q$7:$Q$306,"*Fuel*")>0),"FUEL DOUBLE-COUNT",IF(AH12<>"Yes","VERIFY","OK")))))) | AN12: =IF(AND(AK12="Yes",OR(O12="Labour",O12="Plant")),Z12,0)
A13: =IF(B13="","",B13&"-"&TEXT(COUNTIF($B$7:B13,B13),"000")) | C13: =IFERROR(INDEX('QS Takeoff'!$A$3:$A$202,MATCH(B13,'QS Takeoff'!$B$3:$B$202,0)),"") | D13: =IFERROR(INDEX('QS Takeoff'!$C$3:$C$202,MATCH(B13,'QS Takeoff'!$B$3:$B$202,0)),"") | E13: =IFERROR(INDEX('QS Takeoff'!$E$3:$E$202,MATCH(B13,'QS Takeoff'!$B$3:$B$202,0)),"") | F13: =IFERROR(INDEX('QS Takeoff'!$D$3:$D$202,MATCH(B13,'QS Takeoff'!$B$3:$B$202,0)),"") | G13: =IFERROR(INDEX('QS Takeoff'!$J$3:$J$202,MATCH(B13,'QS Takeoff'!$B$3:$B$202,0)),"") | K13: =IF(OR(B13="",I13="",I13=0),"",E13/I13) | M13: =IF(L13>0,L13,K13) | Q13: =IFERROR(INDEX('Resource Rate Library'!$C$5:$C$200,MATCH(P13,'Resource Rate Library'!$A$5:$A$200,0)),"") | T13: =IFERROR(INDEX('Resource Rate Library'!$E$5:$E$200,MATCH(P13,'Resource Rate Library'!$A$5:$A$200,0)),"") | W13: =IFERROR(INDEX('Resource Rate Library'!$I$5:$I$200,MATCH(P13,'Resource Rate Library'!$A$5:$A$200,0)),0) | Y13: =IF(X13>0,X13,W13) | Z13: =IF(B13="","",IF(N13="Time x Count",M13*R13*IF(U13="",1,U13)*Y13,IF(N13="QS Qty x Factor",E13*R13*(1+IF(V13="",0,V13))*Y13,IF(N13="Direct Qty",S13*(1+IF(V13="",0,V13))*Y13,IF(N13="Lump Sum / Quote",S13*Y13,0))))) | AA13: =IFERROR(INDEX('Resource Rate Library'!$N$5:$N$200,MATCH(P13,'Resource Rate Library'!$A$5:$A$200,0)),"") | AD13: =IFERROR(INDEX('Resource Rate Library'!$G$5:$G$200,MATCH(P13,'Resource Rate Library'!$A$5:$A$200,0)),"") | AE13: =IFERROR(INDEX('Resource Rate Library'!$H$5:$H$200,MATCH(P13,'Resource Rate Library'!$A$5:$A$200,0)),"") | AI13: =IF(B13="","",IF(AND(P13="",N13<>"Lump Sum / Quote"),"RESOURCE CODE",IF(Y13=0,"RATE MISSING",IF(AND(O13="Plant",AD13="Yes",COUNTIFS($B$7:$B$306,B13,$O$7:$O$306,"Labour",$Q$7:$Q$306,"*Operator*")>0),"OPERATOR DOUBLE-COUNT",IF(AND(O13="Plant",AE13="Yes",COUNTIFS($B$7:$B$306,B13,$Q$7:$Q$306,"*Fuel*")>0),"FUEL DOUBLE-COUNT",IF(AH13<>"Yes","VERIFY","OK")))))) | AN13: =IF(AND(AK13="Yes",OR(O13="Labour",O13="Plant")),Z13,0)
A14: =IF(B14="","",B14&"-"&TEXT(COUNTIF($B$7:B14,B14),"000")) | C14: =IFERROR(INDEX('QS Takeoff'!$A$3:$A$202,MATCH(B14,'QS Takeoff'!$B$3:$B$202,0)),"") | D14: =IFERROR(INDEX('QS Takeoff'!$C$3:$C$202,MATCH(B14,'QS Takeoff'!$B$3:$B$202,0)),"") | E14: =IFERROR(INDEX('QS Takeoff'!$E$3:$E$202,MATCH(B14,'QS Takeoff'!$B$3:$B$202,0)),"") | F14: =IFERROR(INDEX('QS Takeoff'!$D$3:$D$202,MATCH(B14,'QS Takeoff'!$B$3:$B$202,0)),"") | G14: =IFERROR(INDEX('QS Takeoff'!$J$3:$J$202,MATCH(B14,'QS Takeoff'!$B$3:$B$202,0)),"") | K14: =IF(OR(B14="",I14="",I14=0),"",E14/I14) | M14: =IF(L14>0,L14,K14) | Q14: =IFERROR(INDEX('Resource Rate Library'!$C$5:$C$200,MATCH(P14,'Resource Rate Library'!$A$5:$A$200,0)),"") | T14: =IFERROR(INDEX('Resource Rate Library'!$E$5:$E$200,MATCH(P14,'Resource Rate Library'!$A$5:$A$200,0)),"") | W14: =IFERROR(INDEX('Resource Rate Library'!$I$5:$I$200,MATCH(P14,'Resource Rate Library'!$A$5:$A$200,0)),0) | Y14: =IF(X14>0,X14,W14) | Z14: =IF(B14="","",IF(N14="Time x Count",M14*R14*IF(U14="",1,U14)*Y14,IF(N14="QS Qty x Factor",E14*R14*(1+IF(V14="",0,V14))*Y14,IF(N14="Direct Qty",S14*(1+IF(V14="",0,V14))*Y14,IF(N14="Lump Sum / Quote",S14*Y14,0))))) | AA14: =IFERROR(INDEX('Resource Rate Library'!$N$5:$N$200,MATCH(P14,'Resource Rate Library'!$A$5:$A$200,0)),"") | AD14: =IFERROR(INDEX('Resource Rate Library'!$G$5:$G$200,MATCH(P14,'Resource Rate Library'!$A$5:$A$200,0)),"") | AE14: =IFERROR(INDEX('Resource Rate Library'!$H$5:$H$200,MATCH(P14,'Resource Rate Library'!$A$5:$A$200,0)),"") | AI14: =IF(B14="","",IF(AND(P14="",N14<>"Lump Sum / Quote"),"RESOURCE CODE",IF(Y14=0,"RATE MISSING",IF(AND(O14="Plant",AD14="Yes",COUNTIFS($B$7:$B$306,B14,$O$7:$O$306,"Labour",$Q$7:$Q$306,"*Operator*")>0),"OPERATOR DOUBLE-COUNT",IF(AND(O14="Plant",AE14="Yes",COUNTIFS($B$7:$B$306,B14,$Q$7:$Q$306,"*Fuel*")>0),"FUEL DOUBLE-COUNT",IF(AH14<>"Yes","VERIFY","OK")))))) | AN14: =IF(AND(AK14="Yes",OR(O14="Labour",O14="Plant")),Z14,0)
A15: =IF(B15="","",B15&"-"&TEXT(COUNTIF($B$7:B15,B15),"000")) | C15: =IFERROR(INDEX('QS Takeoff'!$A$3:$A$202,MATCH(B15,'QS Takeoff'!$B$3:$B$202,0)),"") | D15: =IFERROR(INDEX('QS Takeoff'!$C$3:$C$202,MATCH(B15,'QS Takeoff'!$B$3:$B$202,0)),"") | E15: =IFERROR(INDEX('QS Takeoff'!$E$3:$E$202,MATCH(B15,'QS Takeoff'!$B$3:$B$202,0)),"") | F15: =IFERROR(INDEX('QS Takeoff'!$D$3:$D$202,MATCH(B15,'QS Takeoff'!$B$3:$B$202,0)),"") | G15: =IFERROR(INDEX('QS Takeoff'!$J$3:$J$202,MATCH(B15,'QS Takeoff'!$B$3:$B$202,0)),"") | K15: =IF(OR(B15="",I15="",I15=0),"",E15/I15) | M15: =IF(L15>0,L15,K15) | Q15: =IFERROR(INDEX('Resource Rate Library'!$C$5:$C$200,MATCH(P15,'Resource Rate Library'!$A$5:$A$200,0)),"") | T15: =IFERROR(INDEX('Resource Rate Library'!$E$5:$E$200,MATCH(P15,'Resource Rate Library'!$A$5:$A$200,0)),"") | W15: =IFERROR(INDEX('Resource Rate Library'!$I$5:$I$200,MATCH(P15,'Resource Rate Library'!$A$5:$A$200,0)),0) | Y15: =IF(X15>0,X15,W15) | Z15: =IF(B15="","",IF(N15="Time x Count",M15*R15*IF(U15="",1,U15)*Y15,IF(N15="QS Qty x Factor",E15*R15*(1+IF(V15="",0,V15))*Y15,IF(N15="Direct Qty",S15*(1+IF(V15="",0,V15))*Y15,IF(N15="Lump Sum / Quote",S15*Y15,0))))) | AA15: =IFERROR(INDEX('Resource Rate Library'!$N$5:$N$200,MATCH(P15,'Resource Rate Library'!$A$5:$A$200,0)),"") | AD15: =IFERROR(INDEX('Resource Rate Library'!$G$5:$G$200,MATCH(P15,'Resource Rate Library'!$A$5:$A$200,0)),"") | AE15: =IFERROR(INDEX('Resource Rate Library'!$H$5:$H$200,MATCH(P15,'Resource Rate Library'!$A$5:$A$200,0)),"") | AI15: =IF(B15="","",IF(AND(P15="",N15<>"Lump Sum / Quote"),"RESOURCE CODE",IF(Y15=0,"RATE MISSING",IF(AND(O15="Plant",AD15="Yes",COUNTIFS($B$7:$B$306,B15,$O$7:$O$306,"Labour",$Q$7:$Q$306,"*Operator*")>0),"OPERATOR DOUBLE-COUNT",IF(AND(O15="Plant",AE15="Yes",COUNTIFS($B$7:$B$306,B15,$Q$7:$Q$306,"*Fuel*")>0),"FUEL DOUBLE-COUNT",IF(AH15<>"Yes","VERIFY","OK")))))) | AN15: =IF(AND(AK15="Yes",OR(O15="Labour",O15="Plant")),Z15,0)
A16: =IF(B16="","",B16&"-"&TEXT(COUNTIF($B$7:B16,B16),"000")) | C16: =IFERROR(INDEX('QS Takeoff'!$A$3:$A$202,MATCH(B16,'QS Takeoff'!$B$3:$B$202,0)),"") | D16: =IFERROR(INDEX('QS Takeoff'!$C$3:$C$202,MATCH(B16,'QS Takeoff'!$B$3:$B$202,0)),"") | E16: =IFERROR(INDEX('QS Takeoff'!$E$3:$E$202,MATCH(B16,'QS Takeoff'!$B$3:$B$202,0)),"") | F16: =IFERROR(INDEX('QS Takeoff'!$D$3:$D$202,MATCH(B16,'QS Takeoff'!$B$3:$B$202,0)),"") | G16: =IFERROR(INDEX('QS Takeoff'!$J$3:$J$202,MATCH(B16,'QS Takeoff'!$B$3:$B$202,0)),"") | K16: =IF(OR(B16="",I16="",I16=0),"",E16/I16) | M16: =IF(L16>0,L16,K16) | Q16: =IFERROR(INDEX('Resource Rate Library'!$C$5:$C$200,MATCH(P16,'Resource Rate Library'!$A$5:$A$200,0)),"") | T16: =IFERROR(INDEX('Resource Rate Library'!$E$5:$E$200,MATCH(P16,'Resource Rate Library'!$A$5:$A$200,0)),"") | W16: =IFERROR(INDEX('Resource Rate Library'!$I$5:$I$200,MATCH(P16,'Resource Rate Library'!$A$5:$A$200,0)),0) | Y16: =IF(X16>0,X16,W16) | Z16: =IF(B16="","",IF(N16="Time x Count",M16*R16*IF(U16="",1,U16)*Y16,IF(N16="QS Qty x Factor",E16*R16*(1+IF(V16="",0,V16))*Y16,IF(N16="Direct Qty",S16*(1+IF(V16="",0,V16))*Y16,IF(N16="Lump Sum / Quote",S16*Y16,0))))) | AA16: =IFERROR(INDEX('Resource Rate Library'!$N$5:$N$200,MATCH(P16,'Resource Rate Library'!$A$5:$A$200,0)),"") | AD16: =IFERROR(INDEX('Resource Rate Library'!$G$5:$G$200,MATCH(P16,'Resource Rate Library'!$A$5:$A$200,0)),"") | AE16: =IFERROR(INDEX('Resource Rate Library'!$H$5:$H$200,MATCH(P16,'Resource Rate Library'!$A$5:$A$200,0)),"") | AI16: =IF(B16="","",IF(AND(P16="",N16<>"Lump Sum / Quote"),"RESOURCE CODE",IF(Y16=0,"RATE MISSING",IF(AND(O16="Plant",AD16="Yes",COUNTIFS($B$7:$B$306,B16,$O$7:$O$306,"Labour",$Q$7:$Q$306,"*Operator*")>0),"OPERATOR DOUBLE-COUNT",IF(AND(O16="Plant",AE16="Yes",COUNTIFS($B$7:$B$306,B16,$Q$7:$Q$306,"*Fuel*")>0),"FUEL DOUBLE-COUNT",IF(AH16<>"Yes","VERIFY","OK")))))) | AN16: =IF(AND(AK16="Yes",OR(O16="Labour",O16="Plant")),Z16,0)
A17: =IF(B17="","",B17&"-"&TEXT(COUNTIF($B$7:B17,B17),"000")) | C17: =IFERROR(INDEX('QS Takeoff'!$A$3:$A$202,MATCH(B17,'QS Takeoff'!$B$3:$B$202,0)),"") | D17: =IFERROR(INDEX('QS Takeoff'!$C$3:$C$202,MATCH(B17,'QS Takeoff'!$B$3:$B$202,0)),"") | E17: =IFERROR(INDEX('QS Takeoff'!$E$3:$E$202,MATCH(B17,'QS Takeoff'!$B$3:$B$202,0)),"") | F17: =IFERROR(INDEX('QS Takeoff'!$D$3:$D$202,MATCH(B17,'QS Takeoff'!$B$3:$B$202,0)),"") | G17: =IFERROR(INDEX('QS Takeoff'!$J$3:$J$202,MATCH(B17,'QS Takeoff'!$B$3:$B$202,0)),"") | K17: =IF(OR(B17="",I17="",I17=0),"",E17/I17) | M17: =IF(L17>0,L17,K17) | Q17: =IFERROR(INDEX('Resource Rate Library'!$C$5:$C$200,MATCH(P17,'Resource Rate Library'!$A$5:$A$200,0)),"") | T17: =IFERROR(INDEX('Resource Rate Library'!$E$5:$E$200,MATCH(P17,'Resource Rate Library'!$A$5:$A$200,0)),"") | W17: =IFERROR(INDEX('Resource Rate Library'!$I$5:$I$200,MATCH(P17,'Resource Rate Library'!$A$5:$A$200,0)),0) | Y17: =IF(X17>0,X17,W17) | Z17: =IF(B17="","",IF(N17="Time x Count",M17*R17*IF(U17="",1,U17)*Y17,IF(N17="QS Qty x Factor",E17*R17*(1+IF(V17="",0,V17))*Y17,IF(N17="Direct Qty",S17*(1+IF(V17="",0,V17))*Y17,IF(N17="Lump Sum / Quote",S17*Y17,0))))) | AA17: =IFERROR(INDEX('Resource Rate Library'!$N$5:$N$200,MATCH(P17,'Resource Rate Library'!$A$5:$A$200,0)),"") | AD17: =IFERROR(INDEX('Resource Rate Library'!$G$5:$G$200,MATCH(P17,'Resource Rate Library'!$A$5:$A$200,0)),"") | AE17: =IFERROR(INDEX('Resource Rate Library'!$H$5:$H$200,MATCH(P17,'Resource Rate Library'!$A$5:$A$200,0)),"") | AI17: =IF(B17="","",IF(AND(P17="",N17<>"Lump Sum / Quote"),"RESOURCE CODE",IF(Y17=0,"RATE MISSING",IF(AND(O17="Plant",AD17="Yes",COUNTIFS($B$7:$B$306,B17,$O$7:$O$306,"Labour",$Q$7:$Q$306,"*Operator*")>0),"OPERATOR DOUBLE-COUNT",IF(AND(O17="Plant",AE17="Yes",COUNTIFS($B$7:$B$306,B17,$Q$7:$Q$306,"*Fuel*")>0),"FUEL DOUBLE-COUNT",IF(AH17<>"Yes","VERIFY","OK")))))) | AN17: =IF(AND(AK17="Yes",OR(O17="Labour",O17="Plant")),Z17,0)
A18: =IF(B18="","",B18&"-"&TEXT(COUNTIF($B$7:B18,B18),"000")) | C18: =IFERROR(INDEX('QS Takeoff'!$A$3:$A$202,MATCH(B18,'QS Takeoff'!$B$3:$B$202,0)),"") | D18: =IFERROR(INDEX('QS Takeoff'!$C$3:$C$202,MATCH(B18,'QS Takeoff'!$B$3:$B$202,0)),"") | E18: =IFERROR(INDEX('QS Takeoff'!$E$3:$E$202,MATCH(B18,'QS Takeoff'!$B$3:$B$202,0)),"") | F18: =IFERROR(INDEX('QS Takeoff'!$D$3:$D$202,MATCH(B18,'QS Takeoff'!$B$3:$B$202,0)),"") | G18: =IFERROR(INDEX('QS Takeoff'!$J$3:$J$202,MATCH(B18,'QS Takeoff'!$B$3:$B$202,0)),"") | K18: =IF(OR(B18="",I18="",I18=0),"",E18/I18) | M18: =IF(L18>0,L18,K18) | Q18: =IFERROR(INDEX('Resource Rate Library'!$C$5:$C$200,MATCH(P18,'Resource Rate Library'!$A$5:$A$200,0)),"") | T18: =IFERROR(INDEX('Resource Rate Library'!$E$5:$E$200,MATCH(P18,'Resource Rate Library'!$A$5:$A$200,0)),"") | W18: =IFERROR(INDEX('Resource Rate Library'!$I$5:$I$200,MATCH(P18,'Resource Rate Library'!$A$5:$A$200,0)),0) | Y18: =IF(X18>0,X18,W18) | Z18: =IF(B18="","",IF(N18="Time x Count",M18*R18*IF(U18="",1,U18)*Y18,IF(N18="QS Qty x Factor",E18*R18*(1+IF(V18="",0,V18))*Y18,IF(N18="Direct Qty",S18*(1+IF(V18="",0,V18))*Y18,IF(N18="Lump Sum / Quote",S18*Y18,0))))) | AA18: =IFERROR(INDEX('Resource Rate Library'!$N$5:$N$200,MATCH(P18,'Resource Rate Library'!$A$5:$A$200,0)),"") | AD18: =IFERROR(INDEX('Resource Rate Library'!$G$5:$G$200,MATCH(P18,'Resource Rate Library'!$A$5:$A$200,0)),"") | AE18: =IFERROR(INDEX('Resource Rate Library'!$H$5:$H$200,MATCH(P18,'Resource Rate Library'!$A$5:$A$200,0)),"") | AI18: =IF(B18="","",IF(AND(P18="",N18<>"Lump Sum / Quote"),"RESOURCE CODE",IF(Y18=0,"RATE MISSING",IF(AND(O18="Plant",AD18="Yes",COUNTIFS($B$7:$B$306,B18,$O$7:$O$306,"Labour",$Q$7:$Q$306,"*Operator*")>0),"OPERATOR DOUBLE-COUNT",IF(AND(O18="Plant",AE18="Yes",COUNTIFS($B$7:$B$306,B18,$Q$7:$Q$306,"*Fuel*")>0),"FUEL DOUBLE-COUNT",IF(AH18<>"Yes","VERIFY","OK")))))) | AN18: =IF(AND(AK18="Yes",OR(O18="Labour",O18="Plant")),Z18,0)
... A306: =IF(B306="","",B306&"-"&TEXT(COUNTIF($B$7:B306,B306),"000")) | C306: =IFERROR(INDEX('QS Takeoff'!$A$3:$A$202,MATCH(B306,'QS Takeoff'!$B$3:$B$202,0)),"") | D306: =IFERROR(INDEX('QS Takeoff'!$C$3:$C$202,MATCH(B306,'QS Takeoff'!$B$3:$B$202,0)),"") | E306: =IFERROR(INDEX('QS Takeoff'!$E$3:$E$202,MATCH(B306,'QS Takeoff'!$B$3:$B$202,0)),"") | F306: =IFERROR(INDEX('QS Takeoff'!$D$3:$D$202,MATCH(B306,'QS Takeoff'!$B$3:$B$202,0)),"") | G306: =IFERROR(INDEX('QS Takeoff'!$J$3:$J$202,MATCH(B306,'QS Takeoff'!$B$3:$B$202,0)),"") | K306: =IF(OR(B306="",I306="",I306=0),"",E306/I306) | M306: =IF(L306>0,L306,K306) | Q306: =IFERROR(INDEX('Resource Rate Library'!$C$5:$C$200,MATCH(P306,'Resource Rate Library'!$A$5:$A$200,0)),"") | T306: =IFERROR(INDEX('Resource Rate Library'!$E$5:$E$200,MATCH(P306,'Resource Rate Library'!$A$5:$A$200,0)),"") | W306: =IFERROR(INDEX('Resource Rate Library'!$I$5:$I$200,MATCH(P306,'Resource Rate Library'!$A$5:$A$200,0)),0) | Y306: =IF(X306>0,X306,W306) | Z306: =IF(B306="","",IF(N306="Time x Count",M306*R306*IF(U306="",1,U306)*Y306,IF(N306="QS Qty x Factor",E306*R306*(1+IF(V306="",0,V306))*Y306,IF(N306="Direct Qty",S306*(1+IF(V306="",0,V306))*Y306,IF(N306="Lump Sum / Quote",S306*Y306,0))))) | AA306: =IFERROR(INDEX('Resource Rate Library'!$N$5:$N$200,MATCH(P306,'Resource Rate Library'!$A$5:$A$200,0)),"") | AD306: =IFERROR(INDEX('Resource Rate Library'!$G$5:$G$200,MATCH(P306,'Resource Rate Library'!$A$5:$A$200,0)),"") | AE306: =IFERROR(INDEX('Resource Rate Library'!$H$5:$H$200,MATCH(P306,'Resource Rate Library'!$A$5:$A$200,0)),"") | AI306: =IF(B306="","",IF(AND(P306="",N306<>"Lump Sum / Quote"),"RESOURCE CODE",IF(Y306=0,"RATE MISSING",IF(AND(O306="Plant",AD306="Yes",COUNTIFS($B$7:$B$306,B306,$O$7:$O$306,"Labour",$Q$7:$Q$306,"*Operator*")>0),"OPERATOR DOUBLE-COUNT",IF(AND(O306="Plant",AE306="Yes",COUNTIFS($B$7:$B$306,B306,$Q$7:$Q$306,"*Fuel*")>0),"FUEL DOUBLE-COUNT",IF(AH306<>"Yes","VERIFY","OK")))))) | AN306: =IF(AND(AK306="Yes",OR(O306="Labour",O306="Plant")),Z306,0)

Sheet Resource Rate Library
A1: COMPANY RESOURCE RATE LIBRARY - MASTER ESTIMATE WORKBOOK
A2: Reusable company / benchmark resource library. Retain useful history; update verified rates with source, effective date, region, GST basis, inclusions/exclusions and supersession reason.
A3: Enter verified actual company/supplier rates with source, date, region, GST basis, inclusions and exclusions. Mark replaced rates superseded/inactive rather than deleting useful history.
A4: Resource Code | B4: Resource Category | C4: Resource Description | D4: Default Cost Type | E4: Unit | F4: Procurement Mode | G4: Operator Included? | H4: Fuel Included? | I4: Base Rate excl. GST | J4: Region / Market | K4: Effective Date | L4: Source Type | M4: Supplier / Source | N4: Source URL / Quote Ref | O4: Minimum / Mobilisation | P4: Rate Inclusions | Q4: Rate Exclusions | R4: Confidence | S4: Verification Status | T4: Notes
A5: LAB-FOREMAN | B5: Labour | C5: Civil foreman / working foreman | D5: Labour | E5: hr | F5: Internal / agency | G5: N/A | H5: N/A | I5: 64 | J5: Auckland / NZ | K5: 13-Aug-2026 | L5: Template market benchmark | M5: SEEK / statutory on-cost basis | N5: https://nz.seek.com/civil-drainage-jobs/in-All-Auckland | https://nz.seek.com/drainage-foreman-jobs/in-All-Auckland/full-time | P5: Direct employment allowance | Q5: Margin, vehicle, overtime | R5: Medium | S5: AMBER - market/on-cost benchmark; company payroll required | T5: Firm to company payroll before award
A6: LAB-SUPERVISOR | B6: Labour | C6: Site supervisor / project manager | D6: Labour | E6: hr | F6: Internal / agency | G6: N/A | H6: N/A | I6: 73 | J6: Auckland / NZ | K6: 13-Aug-2026 | L6: Template market benchmark | M6: SEEK / statutory on-cost basis | N6: https://nz.seek.com/civil-drainage-jobs/in-All-Auckland | https://nz.seek.com/drainage-foreman-jobs/in-All-Auckland/full-time | P6: Direct employment allowance | Q6: Margin, vehicle, overtime | R6: Medium | S6: AMBER - market/on-cost benchmark; company payroll required | T6: Firm to company payroll before award
A7: LAB-OPERATOR | B7: Labour | C7: Plant operator | D7: Labour | E7: hr | F7: Internal / agency | G7: N/A | H7: N/A | I7: 45 | J7: Auckland / NZ | K7: 13-Aug-2026 | L7: Template market benchmark | M7: Auckland civil market | N7: https://nz.seek.com/civil-drainage-jobs/in-All-Auckland | https://nz.seek.com/drainage-foreman-jobs/in-All-Auckland/full-time | P7: Direct employment allowance | Q7: Plant and overtime | R7: Medium | S7: AMBER - market/on-cost benchmark; company payroll required
A8: LAB-DRAINLAYER | B8: Labour | C8: Registered drainlayer / pipe layer | D8: Labour | E8: hr | F8: Internal / agency | G8: N/A | H8: N/A | I8: 51 | J8: Auckland / NZ | K8: 13-Aug-2026 | L8: Template market benchmark | M8: Auckland civil market | N8: https://nz.seek.com/civil-drainage-jobs/in-All-Auckland | https://nz.seek.com/drainage-foreman-jobs/in-All-Auckland/full-time | P8: Direct employment allowance | Q8: Vehicle and overtime | R8: Medium | S8: AMBER - market/on-cost benchmark; company payroll required
A9: LAB-LABOURER | B9: Labour | C9: Civil labourer | D9: Labour | E9: hr | F9: Internal / agency | G9: N/A | H9: N/A | I9: 38 | J9: Auckland / NZ | K9: 13-Aug-2026 | L9: Template market benchmark | M9: Auckland civil market | N9: https://nz.seek.com/civil-drainage-jobs/in-All-Auckland | https://nz.seek.com/drainage-foreman-jobs/in-All-Auckland/full-time | P9: Direct employment allowance | Q9: Overtime | R9: Medium | S9: AMBER - market/on-cost benchmark; company payroll required
A10: LAB-CONCRETE | B10: Labour | C10: Concrete placer / finisher | D10: Labour | E10: hr | F10: Internal / agency | G10: N/A | H10: N/A | I10: 44 | J10: Auckland / NZ | K10: 13-Aug-2026 | L10: Template market benchmark | M10: Auckland civil market | N10: https://nz.seek.com/civil-drainage-jobs/in-All-Auckland | https://nz.seek.com/drainage-foreman-jobs/in-All-Auckland/full-time | P10: Direct employment allowance | Q10: Specialist pump | R10: Medium | S10: AMBER - market/on-cost benchmark; company payroll required
A11: PL-EXC-1.7 | B11: Plant | C11: 1.7 t excavator wet hire | D11: Plant | E11: hr | F11: Wet hire | G11: Yes | H11: Yes | I11: 85 | J11: Auckland | K11: 13-Aug-2026 | L11: Published supplier wet-hire rate | M11: ASAP Machine Hire; NZ Machine Hire cross-check | N11: https://www.asapmachinehire.co.nz/price-list | https://www.nzmachinehire.co.nz/_files/ugd/d7f8c7_1379402df1a242f88fef70fc3ce1475c.pdf | O11: Delivery by quote | P11: Machine, operator, fuel and normal buckets | Q11: Delivery, overtime and specialist attachments | R11: High | S11: GREEN - 3-point checked | T11: Wet rate. Do not add a separate operator or fuel line.
A12: PL-EXC-5 | B12: Plant | C12: 5.5 t excavator wet hire | D12: Plant | E12: hr | F12: Wet hire | G12: Yes | H12: Yes | I12: 110 | J12: Auckland | K12: 13-Aug-2026 | L12: Published supplier wet-hire rate | M12: ASAP Machine Hire; NZ Machine Hire cross-check | N12: https://www.asapmachinehire.co.nz/price-list | https://www.nzmachinehire.co.nz/_files/ugd/d7f8c7_1379402df1a242f88fef70fc3ce1475c.pdf | O12: Delivery by quote | P12: Machine, operator, fuel and normal buckets | Q12: Delivery, overtime and specialist attachments | R12: High | S12: GREEN - 3-point checked | T12: Wet rate. Separate excavator-operator lines set to zero.
A13: PL-EXC-13 | B13: Plant | C13: 14 t excavator wet hire | D13: Plant | E13: hr | F13: Wet hire | G13: Yes | H13: Yes | I13: 150 | J13: Auckland | K13: 13-Aug-2026 | L13: Published supplier wet-hire rate | M13: ASAP Machine Hire; NZ Machine Hire cross-check | N13: https://www.asapmachinehire.co.nz/price-list | https://www.nzmachinehire.co.nz/_files/ugd/d7f8c7_1379402df1a242f88fef70fc3ce1475c.pdf | O13: Delivery by quote | P13: Machine, operator, fuel and normal buckets | Q13: Delivery, overtime and specialist attachments | R13: High | S13: GREEN - 3-point checked | T13: Published current wet rate. Separate excavator-operator lines set to zero.
A14: PL-ROLLER | B14: Plant | C14: 7-9 t roller wet-hire equivalent | D14: Plant | E14: hr | F14: Wet-hire equivalent | G14: Yes | H14: Yes | I14: 110 | J14: Auckland | K14: 13-Aug-2026 | L14: Two-supplier dry-rate build-up | M14: NZ Machine Hire; Hire Smart | N14: https://www.nzmachinehire.co.nz/all-rollers | https://www.hiresmart.co.nz/for-hire/rollers/ | O14: Transport by quote | P14: Dry hire, operator, normal fuel and insurance allowance | Q14: Transport, overtime and specialist attachments | R14: Medium | S14: AMBER - 3-point benchmark; quote required | T14: Built from two published dry rates plus operator/fuel allowance; obtain a project quote.
A15: PL-LOADER | B15: Plant | C15: Loader / skid-steer dry hire | D15: Plant | E15: hr | F15: Dry hire | G15: No | H15: No | I15: 120 | J15: Auckland | K15: 13-Aug-2026 | L15: Estimator benchmark | M15: Plant-hire market | N15: Allowance - obtain hire quote | P15: Machine only | Q15: Operator, fuel, mobilisation | R15: Medium | S15: AMBER - benchmark/allowance only
A16: MAT-IMPFILL | B16: Material | C16: AP65-equivalent approved engineered fill delivered | D16: Material | E16: m3 | F16: Merchant supply | G16: N/A | H16: N/A | I16: 65 | J16: Auckland | K16: 13-Aug-2026 | L16: Tender allowance | M16: Aggregate supplier | N16: https://www.urbanquarry.co.nz/pricelist-2-2 | https://www.aggregate2u.co.nz/aggregates-delivery-south-auckland | P16: Delivered clean approved fill | Q16: Testing and placement | R16: Low | S16: AMBER - two market checks; specification/delivery quote required | T16: Product specification and delivered rate still require supplier confirmation.
A17: MAT-AP65 | B17: Material | C17: AP65 subbase aggregate | D17: Material | E17: t | F17: Merchant supply | G17: N/A | H17: N/A | I17: 30.5 | J17: Auckland | K17: 13-Aug-2026 | L17: Template market benchmark | M17: Auckland quarry market | N17: https://www.urbanquarry.co.nz/pricelist-2-2 | https://www.aggregate2u.co.nz/aggregates-delivery-south-auckland | P17: Ex-quarry / base material allowance | Q17: Haul and placement | R17: High | S17: AMBER - two market checks; specification/delivery quote required | T17: Published GAP/AP benchmark; confirm specified grading and haul.
A18: MAT-AP40 | B18: Material | C18: AP40 / GAP40 basecourse aggregate | D18: Material | E18: t | F18: Merchant supply | G18: N/A | H18: N/A | I18: 31 | J18: Auckland | K18: 13-Aug-2026 | L18: Template market benchmark | M18: Auckland quarry market | N18: https://www.urbanquarry.co.nz/pricelist-2-2 | https://www.aggregate2u.co.nz/aggregates-delivery-south-auckland | P18: Ex-quarry / base material allowance | Q18: Haul and placement | R18: High | S18: AMBER - two market checks; specification/delivery quote required | T18: Published GAP/AP benchmark; confirm specified grading and haul.
A19: MAT-DRAINAGG | B19: Material | C19: Drainage aggregate | D19: Material | E19: t | F19: Merchant supply | G19: N/A | H19: N/A | I19: 48.5 | J19: Auckland | K19: 13-Aug-2026 | L19: Template market benchmark | M19: Auckland quarry market | N19: https://www.aggregate2u.co.nz/aggregates-delivery-south-auckland | https://www.urbanquarry.co.nz/pricelist-2-2 | P19: Aggregate | Q19: Haul and placement | R19: High | S19: AMBER - two market checks; specification/delivery quote required | T19: Drainage aggregate benchmark; confirm delivered project quote.
A20: MAT-GEOTEXTILE | B20: Material | C20: Bidim A19 or approved geotextile | D20: Material | E20: m2 | F20: Merchant supply | G20: N/A | H20: N/A | I20: 3.25 | J20: Auckland | K20: 13-Aug-2026 | L20: Template market benchmark | M20: Civil merchant | N20: Template baseline dated 13-Aug-2026 | P20: Material only | Q20: Installation | R20: Medium | S20: AMBER - benchmark/allowance only
A21: MAT-CONC25 | B21: Material | C21: 25 MPa ready-mix concrete | D21: Material | E21: m3 | F21: Delivered supply | G21: N/A | H21: N/A | I21: 325 | J21: Auckland | K21: 13-Aug-2026 | L21: Template market benchmark | M21: Ready-mix market | N21: Template baseline dated 13-Aug-2026 | P21: Delivered concrete allowance | Q21: Pump, testing, placing | R21: Medium | S21: AMBER - benchmark/allowance only
A22: MAT-MESH | B22: Material | C22: SE62 / 662 mesh allowance | D22: Material | E22: m2 | F22: Merchant supply | G22: N/A | H22: N/A | I22: 20 | J22: Auckland | K22: 13-Aug-2026 | L22: Template market benchmark | M22: Steel merchant | N22: Template baseline dated 13-Aug-2026 | P22: Mesh material | Q22: Chairs, laps above waste factor | R22: Medium | S22: AMBER - benchmark/allowance only | T22: Confirm project-specific mesh grade and specification before order.
A23: MAT-PIPE150 | B23: Material | C23: 150 mm uPVC RRJ drainage pipe | D23: Material | E23: lm | F23: Merchant supply | G23: N/A | H23: N/A | I23: 45 | J23: Auckland | K23: 13-Aug-2026 | L23: Tender allowance | M23: Civil merchant | N23: Quote required | P23: Pipe and standard joints | Q23: Fittings, bedding, install | R23: Low | S23: AMBER - benchmark/allowance only
A24: MAT-PIPE225 | B24: Material | C24: 225 mm uPVC RRJ stormwater pipe | D24: Material | E24: lm | F24: Merchant supply | G24: N/A | H24: N/A | I24: 95 | J24: Auckland | K24: 13-Aug-2026 | L24: Tender allowance | M24: Civil merchant | N24: Quote required | P24: Pipe and standard joints | Q24: Fittings, bedding, install | R24: Low | S24: AMBER - benchmark/allowance only
A25: MAT-SUB110 | B25: Material | C25: 110 mm perforated subsoil pipe with sock | D25: Material | E25: lm | F25: Merchant supply | G25: N/A | H25: N/A | I25: 20 | J25: Auckland | K25: 13-Aug-2026 | L25: Tender allowance | M25: Civil merchant | N25: Quote required | P25: Pipe and sock | Q25: Aggregate and install | R25: Low | S25: AMBER - benchmark/allowance only
A26: MAT-WATER50 | B26: Material | C26: 50 mm PE watermain and fittings allowance | D26: Material | E26: lm | F26: Merchant supply | G26: N/A | H26: N/A | I26: 22 | J26: Auckland | K26: 13-Aug-2026 | L26: Tender allowance | M26: Civil merchant | N26: Quote required | P26: PE pipe and normal fittings | Q26: Connection, meter, testing | R26: Low | S26: AMBER - benchmark/allowance only
A27: MAT-SWMH | B27: Material | C27: Precast stormwater manhole set | D27: Material | E27: ea | F27: Precast supplier | G27: N/A | H27: N/A | I27: 5500 | J27: Auckland | K27: 13-Aug-2026 | L27: Tender allowance | M27: Precast supplier | N27: Quote required | P27: Chamber/riser/lid allowance | Q27: Excavation, concrete, install | R27: Low | S27: AMBER - benchmark/allowance only
A28: MAT-SSMH | B28: Material | C28: Precast sewer manhole set | D28: Material | E28: ea | F28: Precast supplier | G28: N/A | H28: N/A | I28: 7000 | J28: Auckland | K28: 13-Aug-2026 | L28: Tender allowance | M28: Precast supplier | N28: Quote required | P28: Chamber/riser/lid allowance | Q28: Excavation, testing, install | R28: Low | S28: AMBER - benchmark/allowance only
A29: MAT-IC600 | B29: Material | C29: 600 mm inspection chamber set | D29: Material | E29: ea | F29: Merchant supply | G29: N/A | H29: N/A | I29: 1800 | J29: Auckland | K29: 13-Aug-2026 | L29: Tender allowance | M29: Civil merchant | N29: Quote required | P29: Chamber and lid | Q29: Excavation and install | R29: Low | S29: AMBER - benchmark/allowance only
A30: MAT-CP | B30: Material | C30: Standard catchpit set | D30: Material | E30: ea | F30: Precast supplier | G30: N/A | H30: N/A | I30: 1800 | J30: Auckland | K30: 13-Aug-2026 | L30: Tender allowance | M30: Precast supplier | N30: Quote required | P30: Chamber, lid and grate | Q30: Excavation and install | R30: Low | S30: AMBER - benchmark/allowance only
A31: MAT-DCP | B31: Material | C31: Double side-entry cesspit set | D31: Material | E31: ea | F31: Precast supplier | G31: N/A | H31: N/A | I31: 4500 | J31: Auckland | K31: 13-Aug-2026 | L31: Tender allowance | M31: Precast supplier | N31: Quote required | P31: Chamber, lid and grates | Q31: Excavation and install | R31: Low | S31: AMBER - benchmark/allowance only
A32: SUB-ASPHALT30 | B32: Subcontract | C32: 30 mm asphalt surfacing incl prime/seal | D32: Subcontract | E32: m2 | F32: Specialist subcontract | G32: Yes | H32: Yes | I32: 55 | J32: Auckland | K32: 13-Aug-2026 | L32: Budget allowance | M32: Asphalt subcontractor | N32: Quote required | P32: 30 mm asphalt surfacing allowance | Q32: Basecourse and testing | R32: Low | S32: RED - quote or job-specific evidence required
A33: SUB-KERB-T3 | B33: Subcontract | C33: Type 3 kerb and channel installed | D33: Subcontract | E33: lm | F33: Specialist subcontract | G33: Yes | H33: Yes | I33: 145 | J33: Auckland | K33: 13-Aug-2026 | L33: Budget allowance | M33: Kerb contractor | N33: Quote required | P33: Form/place/finish concrete kerb/channel | Q33: Excavation and major base repair | R33: Low | S33: RED - quote or job-specific evidence required
A34: SUB-KERB-T7 | B34: Subcontract | C34: Type 7 kerb installed | D34: Subcontract | E34: lm | F34: Specialist subcontract | G34: Yes | H34: Yes | I34: 115 | J34: Auckland | K34: 13-Aug-2026 | L34: Budget allowance | M34: Kerb contractor | N34: Quote required | P34: Form/place/finish kerb | Q34: Excavation and major base repair | R34: Low | S34: RED - quote or job-specific evidence required
A35: SUB-ACO-K100 | B35: Subcontract | C35: ACO K100S channel drain installed | D35: Subcontract | E35: lm | F35: Specialist subcontract | G35: Yes | H35: Yes | I35: 275 | J35: Auckland | K35: 13-Aug-2026 | L35: Budget allowance | M35: ACO / drainage installer | N35: Quote required | P35: Channel, grates and concrete surround allowance | Q35: Outlet structures and design changes | R35: Low | S35: RED - quote or job-specific evidence required
A36: SUB-SPECIALIST | B36: Subcontract | C36: Project-specific specialist package | D36: Subcontract | E36: LS | F36: Specialist subcontract | G36: N/A | H36: N/A | I36: 1 | J36: Project-specific | K36: 13-Aug-2026 | L36: Job override required | M36: Relevant specialist | N36: Quote / PC allowance shown in Resource Build-Up | P36: Only scope stated on build-up row | Q36: Unstated scope | R36: Low | S36: RED - quote or job-specific evidence required | T36: Base $1 forces explicit job-rate override
A37: OTH-GENERAL | B37: Other | C37: Project-specific transparent allowance | D37: Other | E37: LS | F37: Job-specific | G37: N/A | H37: N/A | I37: 1 | J37: Project-specific | K37: 13-Aug-2026 | L37: Job override required | M37: Estimator allowance | N37: Basis shown in Resource Build-Up | P37: Only scope stated on build-up row | Q37: Unstated scope | R37: Medium | S37: RED - quote or job-specific evidence required | T37: Base $1 forces explicit job-rate override
A38: OTH-DISPOSAL | B38: Other | C38: Clean spoil disposal / tipping fee | D38: Other | E38: t | F38: Commercial tip | G38: N/A | H38: N/A | I38: 22 | J38: Auckland | K38: 13-Aug-2026 | L38: Template market benchmark | M38: Auckland disposal market | N38: Template baseline dated 13-Aug-2026 | P38: Clean spoil tipping | Q38: Haul and contaminated material | R38: High | S38: AMBER - benchmark/allowance only
A39: LAB-RIGGER | B39: Labour | C39: Certified crane rigger / dogman / lifting crew | D39: Labour | E39: hr | F39: Specialist labour / subcontract | G39: N/A | H39: N/A | I39: 1 | J39: NZ / AU project-specific | K39: 15-Aug-2026 | L39: Job override required | M39: Crane / rigging subcontractor | N39: Quote required | O39: Minimum call-out by quote | P39: Certified rigger/dogman labour to stated lift methodology | Q39: Crane, rigging gear, travel and overtime unless specifically included | R39: Low | S39: RED - quote or job-specific evidence required | T39: Base $1 forces explicit job-rate override; verify competency and crew composition.
A40: PL-CRANE-70AT | B40: Plant | C40: 70 t all-terrain mobile crane wet hire | D40: Plant | E40: hr | F40: Specialist crane hire | G40: Yes | H40: Yes | I40: 1 | J40: NZ / AU project-specific | K40: 15-Aug-2026 | L40: Job override required | M40: Mobile crane supplier | N40: Quote required | O40: Minimum hire + mobilisation by quote | P40: Crane, operator and normal fuel subject to supplier quote | Q40: Mobilisation, ballast transport, rigging, dogman, mats, travel/overtime unless included | R40: Low | S40: RED - quote or job-specific evidence required | T40: Capacity class only. Verify certified load chart, lift radius, ballast, outrigger reactions, access and minimum hire.
A41: PL-CRANE-90AT | B41: Plant | C41: 90 t all-terrain mobile crane wet hire | D41: Plant | E41: hr | F41: Specialist crane hire | G41: Yes | H41: Yes | I41: 1 | J41: NZ / AU project-specific | K41: 15-Aug-2026 | L41: Job override required | M41: Mobile crane supplier | N41: Quote required | O41: Minimum hire + mobilisation by quote | P41: Crane, operator and normal fuel subject to supplier quote | Q41: Mobilisation, ballast transport, rigging, dogman, mats, travel/overtime unless included | R41: Low | S41: RED - quote or job-specific evidence required | T41: Capacity class only. Verify certified load chart, lift radius, ballast, outrigger reactions, access and minimum hire.
A42: PL-CRANE-120AT | B42: Plant | C42: 120 t all-terrain mobile crane wet hire | D42: Plant | E42: hr | F42: Specialist crane hire | G42: Yes | H42: Yes | I42: 1 | J42: NZ / AU project-specific | K42: 15-Aug-2026 | L42: Job override required | M42: Mobile crane supplier | N42: Quote required | O42: Minimum hire + mobilisation by quote | P42: Crane, operator and normal fuel subject to supplier quote | Q42: Mobilisation, ballast transport, rigging, dogman, mats, travel/overtime unless included | R42: Low | S42: RED - quote or job-specific evidence required | T42: Capacity class only. Verify certified load chart, lift radius, ballast, outrigger reactions, access and minimum hire.
A43: PL-CRANE-MATS | B43: Plant | C43: Crane mats / outrigger spreader mats hire set | D43: Plant | E43: day | F43: Specialist hire | G43: N/A | H43: N/A | I43: 1 | J43: NZ / AU project-specific | K43: 15-Aug-2026 | L43: Job override required | M43: Crane / temporary works supplier | N43: Quote required | O43: Minimum hire / transport by quote | P43: Mats/spreader set to supplier/temp-works requirement | Q43: Transport, placement, design/certification and abnormal ground treatment unless included | R43: Low | S43: RED - quote or job-specific evidence required | T43: Base $1 forces explicit job override. Check whether crane supplier already includes mats to avoid duplication.
A44: PL-RIGGING-SET | B44: Plant | C44: Certified crane rigging / lifting gear set | D44: Plant | E44: day | F44: Specialist hire | G44: N/A | H44: N/A | I44: 1 | J44: NZ / AU project-specific | K44: 15-Aug-2026 | L44: Job override required | M44: Crane / rigging supplier | N44: Quote required | O44: Minimum hire / mobilisation by quote | P44: Certified slings, shackles and stated lifting gear set | Q44: Project-specific lifting beam, proprietary clutches, engineered lifting frame and rigger labour unless included | R44: Low | S44: RED - quote or job-specific evidence required | T44: Base $1 forces explicit job override; reconcile with crane quote and precaster lifting requirements.
A45: PL-TRUCK-6W | B45: Plant | C45: 6-wheel tip truck wet hire | D45: Plant | E45: hr | F45: Wet hire / cartage | G45: Yes | H45: Yes | I45: 1 | J45: NZ / AU project-specific | K45: 15-Aug-2026 | L45: Job override required | M45: Civil cartage supplier | N45: Quote required | O45: Minimum hours / travel by quote | P45: Truck, driver and normal fuel subject to quote | Q45: Tipping fees, material supply, permits and abnormal waiting unless included | R45: Low | S45: RED - quote or job-specific evidence required | T45: Use for internal/site cartage where hourly wet hire is the truthful basis; do not duplicate supplier-delivery charges.
A46: PL-TRANSPORT-HEAVY | B46: Plant | C46: Heavy / oversize transporter or precast internal haul | D46: Plant | E46: trip | F46: Specialist transport | G46: Yes | H46: Yes | I46: 1 | J46: NZ / AU project-specific | K46: 15-Aug-2026 | L46: Job override required | M46: Heavy transport / precast carrier | N46: Quote required | O46: Mobilisation, permits and escort by quote | P46: Transport vehicle and driver to stated route/load | Q46: Craneage, loading/unloading, permits/escorts and route strengthening unless included | R46: Low | S46: RED - quote or job-specific evidence required | T46: Use only where contractor transport scope is confirmed. Verify route, axle/load limits, turning and delivery responsibility.
A47: OTH-CARTAGE-LOAD | B47: Other | C47: Supplier delivery / cartage charge per load | D47: Other | E47: load | F47: Job-specific supplier delivery | G47: N/A | H47: N/A | I47: 1 | J47: Project-specific | K47: 15-Aug-2026 | L47: Job override required | M47: Material supplier / carrier | N47: Quote required | O47: Load size / zone / minimum by quote | P47: Delivery/cartage charge only to stated site and load size | Q47: Material supply, waiting time, tipping, permits and rehandling unless included | R47: Low | S47: RED - quote or job-specific evidence required | T47: Reusable cost code only; project location, load size and delivered rate must be overridden from current evidence.
A48: SUB-PROOFROLL | B48: Subcontract | C48: Proof-roll / working-platform verification / field testing attendance | D48: Subcontract | E48: LS | F48: Specialist subcontract | G48: N/A | H48: N/A | I48: 1 | J48: NZ / AU project-specific | K48: 15-Aug-2026 | L48: Job override required | M48: Geotech / testing provider | N48: Quote required | O48: Attendance / testing scope by quote | P48: Proof-roll or stated field-verification/testing attendance | Q48: Temporary works design, geotech design certification, remediation and repeat visits unless included | R48: Low | S48: RED - quote or job-specific evidence required | T48: Keep testing/verification separate from temporary-works design and from physical platform construction.
A49: MAT-GEOGRID | B49: Material | C49: Geogrid / ground-stabilisation reinforcement - project specified | D49: Material | E49: m2 | F49: Merchant supply | G49: N/A | H49: N/A | I49: 1 | J49: NZ / AU project-specific | K49: 15-Aug-2026 | L49: Job override required | M49: Civil merchant / geosynthetics supplier | N49: Quote required | O49: Product/specification by quote | P49: Specified geogrid material only | Q49: Design, geotextile, aggregate, installation and laps/waste unless included | R49: Low | S49: RED - quote or job-specific evidence required | T49: No generic rate. Select product from temporary works/geotech design and obtain project-specific quote.
A50: HIST-LAB-FOREMAN-01 | B50: Labour | C50: Civil foreman / working foreman - historical contractor benchmark | D50: Labour | E50: hr | F50: Internal / agency | G50: N/A | H50: N/A | I50: 65 | J50: Auckland / NZ | K50: 17-Aug-2026 | L50: Historical contractor benchmark (AMBER) | M50: Internal historical contractor benchmark | N50: HBR-001; comparison baseline LAB-FOREMAN = $64.00/hr | P50: Direct employment allowance | Q50: Margin, vehicle, overtime | R50: Medium | S50: AMBER - historical benchmark only | T50: Verify against current project/company/supplier evidence before use.
A51: HIST-LAB-SUPERVISOR-01 | B51: Labour | C51: Site supervisor / project manager - historical contractor benchmark | D51: Labour | E51: hr | F51: Internal / agency | G51: N/A | H51: N/A | I51: 70 | J51: Auckland / NZ | K51: 17-Aug-2026 | L51: Historical contractor benchmark (AMBER) | M51: Internal historical contractor benchmark | N51: HBR-002; comparison baseline LAB-SUPERVISOR = $73.00/hr | P51: Direct employment allowance | Q51: Margin, vehicle, overtime | R51: Medium | S51: AMBER - historical benchmark only | T51: Verify against current project/company/supplier evidence before use.
A52: HIST-LAB-DRAINLAYER-01 | B52: Labour | C52: Registered drainlayer / pipe layer - historical contractor benchmark | D52: Labour | E52: hr | F52: Internal / agency | G52: N/A | H52: N/A | I52: 45 | J52: Auckland / NZ | K52: 17-Aug-2026 | L52: Historical contractor benchmark (AMBER) | M52: Internal historical contractor benchmark | N52: HBR-003; comparison baseline LAB-DRAINLAYER = $51.00/hr | P52: Direct employment allowance | Q52: Vehicle and overtime | R52: Medium | S52: AMBER - historical benchmark only | T52: Verify against current project/company/supplier evidence before use.
A53: HIST-PL-EXC-1.7-01 | B53: Plant | C53: 1.7 t excavator wet hire - historical contractor benchmark | D53: Plant | E53: hr | F53: Wet hire | G53: Yes | H53: Yes | I53: 75 | J53: Auckland | K53: 17-Aug-2026 | L53: Historical contractor benchmark (AMBER) | M53: Internal historical contractor benchmark | N53: HBR-004; comparison baseline PL-EXC-1.7 = $85.00/hr | O53: Delivery by quote | P53: Machine, operator, fuel and normal buckets | Q53: Delivery, overtime and specialist attachments | R53: Medium | S53: AMBER - historical benchmark only | T53: Verify against current project/company/supplier evidence before use.
A54: HIST-MAT-AP65-01 | B54: Material | C54: AP65 subbase aggregate - historical contractor benchmark | D54: Material | E54: t | F54: Merchant supply | G54: N/A | H54: N/A | I54: 29 | J54: Auckland | K54: 17-Aug-2026 | L54: Historical supplier benchmark (AMBER) | M54: Auckland quarry historical contractor basis | N54: HBR-005; comparison baseline MAT-AP65 = $30.50/t | P54: Ex-quarry / base material allowance | Q54: Haul and placement; confirm whether historical contractor $/t basis includes T&T direct delivery | R54: Medium | S54: AMBER - historical benchmark only | T54: Verify against current project/company/supplier evidence before use.
A55: HIST-MAT-AP40-01 | B55: Material | C55: AP40 / GAP40 basecourse aggregate - historical contractor benchmark | D55: Material | E55: t | F55: Merchant supply | G55: N/A | H55: N/A | I55: 29 | J55: Auckland | K55: 17-Aug-2026 | L55: Historical supplier benchmark (AMBER) | M55: Auckland quarry historical contractor basis | N55: HBR-006; comparison baseline MAT-AP40 = $31.00/t | P55: Ex-quarry / base material allowance | Q55: Haul and placement; confirm whether historical contractor $/t basis includes T&T direct delivery | R55: Medium | S55: AMBER - historical benchmark only | T55: Verify against current project/company/supplier evidence before use.
A56: HIST-MAT-DRAINAGG-01 | B56: Material | C56: Drainage aggregate - historical contractor benchmark | D56: Material | E56: t | F56: Merchant supply | G56: N/A | H56: N/A | I56: 36 | J56: Auckland | K56: 17-Aug-2026 | L56: Historical supplier benchmark (AMBER) | M56: Auckland quarry historical contractor basis | N56: HBR-007; comparison baseline MAT-DRAINAGG = $48.50/t | P56: Aggregate | Q56: Haul and placement; confirm whether historical contractor $/t basis includes T&T direct delivery | R56: Medium | S56: AMBER - historical benchmark only | T56: Verify against current project/company/supplier evidence before use.
A57: HIST-MAT-SWMH-01 | B57: Material | C57: Precast stormwater manhole set - historical contractor benchmark | D57: Material | E57: ea | F57: Precast supplier | G57: N/A | H57: N/A | I57: 7000 | J57: Auckland | K57: 17-Aug-2026 | L57: Historical contractor benchmark (AMBER) | M57: Internal historical contractor benchmark / authority requirement | N57: HBR-008; comparison baseline MAT-SWMH = $5,500/ea | P57: Chamber, riser, lid and safety grate allowance | Q57: Excavation, concrete and installation | R57: Medium | S57: AMBER - historical benchmark only | T57: Verify against current project/company/supplier evidence before use.
A58: HIST-OTH-FACILITIES-01 | B58: Other | C58: Temporary facilities, utilities and welfare weekly allowance - historical benchmark | D58: Other | E58: week | F58: Job-specific / hire allowance | G58: N/A | H58: N/A | I58: 410 | J58: Auckland | K58: 17-Aug-2026 | L58: Historical contractor benchmark (AMBER) | M58: Internal historical contractor benchmark | N58: HBR-009; 20-week historical control = $8,200 | O58: Confirm hire minimums and mobilisation | P58: Weekly facilities, toilet, temporary power/water and consumables allowance | Q58: Mobilisation, site-specific setup and abnormal servicing unless confirmed | R58: Medium | S58: AMBER - historical benchmark only | T58: Verify against current project/company/supplier evidence before use.
A59: HIST-SUB-SURVEY-SET-01 | B59: Subcontract | C59: Drainage construction setout package - historical benchmark | D59: Subcontract | E59: LS | F59: Specialist subcontract | G59: N/A | H59: N/A | I59: 1500 | J59: Auckland | K59: 17-Aug-2026 | L59: Historical supplier benchmark (AMBER) | M59: Historical survey supplier - identity withheld in client issue | N59: HBR-010; historical rate recorded excl. GST | O59: One drainage setout package | P59: Drainage construction setout | Q59: Other survey, rework, as-builts and additional visits | R59: Medium | S59: AMBER - historical benchmark only | T59: Verify against current project/company/supplier evidence before use.
A60: HIST-SUB-SURVEY-ASB-01 | B60: Subcontract | C60: Drainage as-built survey package - historical benchmark | D60: Subcontract | E60: LS | F60: Specialist subcontract | G60: N/A | H60: N/A | I60: 2500 | J60: Auckland | K60: 17-Aug-2026 | L60: Historical supplier benchmark (AMBER) | M60: Historical survey supplier - identity withheld in client issue | N60: HBR-011; historical rate recorded excl. GST | O60: One drainage as-built package | P60: Drainage as-built survey | Q60: Setout, other survey, rework and additional visits | R60: Medium | S60: AMBER - historical benchmark only | T60: Verify against current project/company/supplier evidence before use.
A61: HIST-SUB-GPR-VISIT-01 | B61: Subcontract | C61: GPR utility-locating visit - historical benchmark | D61: Subcontract | E61: visit | F61: Specialist subcontract | G61: N/A | H61: N/A | I61: 250 | J61: Auckland | K61: 17-Aug-2026 | L61: Historical supplier benchmark (AMBER) | M61: Historical utility-locating supplier - identity withheld in client issue | N61: HBR-012; historical commercial basis requires verification | O61: Per visit; minimums and mobilisation to confirm | P61: GPR utility-locating visit | Q61: Potholing, traffic management, additional visits and formal report unless confirmed | R61: Medium | S61: AMBER - historical benchmark only | T61: Verify against current project/company/supplier evidence before use.
A62: HIST-SUB-TMP-DAY-01 | B62: Subcontract | C62: Traffic management delivery day - historical benchmark | D62: Subcontract | E62: day | F62: Specialist subcontract | G62: Yes | H62: Yes | I62: 1600 | J62: Auckland | K62: 17-Aug-2026 | L62: Historical supplier benchmark (AMBER) | M62: Historical traffic-management supplier - identity withheld in client issue | N62: HBR-013; TMP plan/design additional | O62: Daily minimum; confirm working hours | P62: On-site traffic management delivery day | Q62: TMP plan/design, approvals, after-hours, fees and extensions | R62: Medium | S62: AMBER - historical benchmark only | T62: Verify against current project/company/supplier evidence before use.
A63: HIST-SUB-LINEMARK-01 | B63: Subcontract | C63: Standard line marking - historical benchmark | D63: Subcontract | E63: lm | F63: Specialist subcontract | G63: Yes | H63: Yes | I63: 22 | J63: Auckland | K63: 17-Aug-2026 | L63: Historical supplier benchmark (AMBER) | M63: Historical line-marking supplier - identity withheld in client issue | N63: HBR-014; historical line-marking benchmark | O63: Minimum job charge to confirm | P63: Standard line marking per lineal metre | Q63: Arrows, symbols, accessible markings, signs, preparation and traffic management unless quoted | R63: Medium | S63: AMBER - historical benchmark only | T63: Verify against current project/company/supplier evidence before use.
A64: MAT-AP20 | B64: Material | C64: AP20 / GAP20 basecourse aggregate | D64: Material | E64: t | F64: Merchant supply | G64: N/A | H64: N/A | I64: 39.5 | J64: Auckland | K64: 11-May-2026 | L64: Published supplier price | M64: The Urban Quarry - Onehunga | N64: https://www.urbanquarry.co.nz/pricelist-2-2 | P64: Ex-gate aggregate supply | Q64: GST, delivery/haul and placement | R64: High | S64: AMBER - current published price; delivered project quote required | T64: Valid from 11-May-2026 until further notice; current web check 06-Sep-2026.
A65: MAT-MESH665 | B65: Material | C65: 665 reinforcing mesh 4.51m x 1.96m | D65: Material | E65: sheet | F65: Merchant supply | G65: N/A | H65: N/A | I65: 62.5 | J65: Auckland | K65: 06-Sep-2026 | L65: Current published supplier price | M65: Quality Steel Supplies Auckland | N65: https://qualitysteelsupplies.co.nz/shop/ | P65: 665 mesh sheet supply | Q65: Delivery, laps/waste, chairs and installation | R65: High | S65: AMBER - current supplier price; project order/delivery quote required | T65: Current published price excl. GST. Effective cover/waste to be calculated in job build-up.
A66: MAT-KEYSTONE-COMPAC | B66: Material | C66: Firth Keystone Compac III straight-face block | D66: Material | E66: ea | F66: Merchant / manufacturer supply | G66: N/A | H66: N/A | I66: 19.35 | J66: Auckland / NZ | K66: 06-Sep-2026 | L66: Current published market benchmark | M66: Mighty Outdoor; Firth technical cross-check | N66: https://www.mightyoutdoor.co.nz/retaining-wall-selection/firth-retaining-blocks/keycomiii.html | https://www.firth.co.nz/paving-and-retaining/retaining-and-fences/compac-iii | P66: Straight-face Compac III block supply | Q66: Freight, pins, caps, corners, no-fines concrete and installation | R66: Medium | S66: AMBER - published market benchmark; project supplier quote required | T66: $22.25 incl. GST converted to $19.35 excl. GST; Bunnings current independent price is higher.
A67: MAT-KEYSTONE-CAP | B67: Material | C67: Firth Keystone Compac III capping unit | D67: Material | E67: ea | F67: Merchant / manufacturer supply | G67: N/A | H67: N/A | I67: 12.57 | J67: Auckland / NZ | K67: 06-Sep-2026 | L67: Current published market benchmark | M67: Bunnings NZ; Firth technical cross-check | N67: https://www.bunnings.co.nz/firth-100-x-457-x-270mm-compac-iii-rockface-keystone-retaining-cap_p0271202 | https://www.firth.co.nz/paving-and-retaining/retaining-and-fences/compac-iii | P67: Compac III cap supply | Q67: Freight, adhesive, blocks, corners and installation | R67: Medium | S67: AMBER - published market benchmark; project supplier quote required | T67: $14.45 incl. GST converted to $12.57 excl. GST. Confirm actual trade/supplier rate and colour.
A68: PL-EXC-3-INHOUSE | B68: Plant | C68: 3.0 t excavator in-house historical project rate - operator included | D68: Plant | E68: hr | F68: In-house / historical company-project control | G68: Yes | H68: Unclear - historical rate treated all-in; no separate fuel added | I68: 97.5 | J68: Auckland | K68: 19-Mar-2026 | L68: Historical project estimate / company control | M68: 48 Eastglen Road - Blackline estimate cost tracker | N68: Blackline_Estimate_Cost_Tracker_48_Eastglen.xlsx / 48 Eastglen project | P68: 3.0t excavator historical direct project rate incl. operator | Q68: Specialist auger attachment, mobilisation, overtime; fuel basis not separately evidenced | R68: Medium | S68: AMBER - company comparable; current-project productivity/plant availability to verify | T68: Use only as an in-house self-perform control. Independent reasonableness check: current 5.5t wet hire = $110/hr; do not add a separate operator.
A69: PL-AUGER-3T-INHOUSE | B69: Plant | C69: 3 t excavator auger / drill attachment in-house historical project rate | D69: Plant | E69: hr | F69: In-house / historical company-project control | G69: N/A | H69: N/A | I69: 22.5 | J69: Auckland | K69: 19-Mar-2026 | L69: Historical project estimate / company control | M69: 48 Eastglen Road - Blackline estimate cost tracker | N69: Blackline_Estimate_Cost_Tracker_48_Eastglen.xlsx / 48 Eastglen project | P69: Auger / drill attachment historical project rate | Q69: Excavator, operator, mobilisation, extraordinary wear, specialist casing/formtube | R69: Medium | S69: AMBER - company comparable; confirm 450/500mm tooling and condition | T69: Eastglen comparable used 3t drill gear as a separate plant resource. Pair with PL-EXC-3-INHOUSE; do not duplicate machine/operator.
A70: OTH-PORTABLE-TOILET | B70: Other | C70: Portable toilet hire and servicing - tender benchmark | D70: Other | E70: week | F70: Hire allowance | G70: N/A | H70: N/A | I70: 120 | J70: Auckland / NZ | K70: 08-Sep-2026 | L70: Reviewed comparable estimate allowance | M70: 3Bears / Orion Point Stage 5 | N70: Orion_Point_Stage5_Client_Estimate_Report_Draft.pdf | O70: Confirm delivery/pickup/servicing | P70: Portable toilet weekly hire/service allowance | Q70: Abnormal servicing, damage, relocation and project-specific supplier minimums | R70: Medium | S70: AMBER - comparable estimate benchmark | T70: Use as tender benchmark only; replace with Siteworks/supplier actual if provided.
A71: OTH-SITE-LOCKUP | B71: Other | C71: 20ft lockable container / site lockup - tender benchmark | D71: Other | E71: week | F71: Hire allowance | G71: N/A | H71: N/A | I71: 175 | J71: Auckland / NZ | K71: 08-Sep-2026 | L71: Reviewed comparable estimate allowance | M71: 3Bears / Orion Point Stage 5 | N71: Orion_Point_Stage5_Client_Estimate_Report_Draft.pdf | O71: Confirm delivery/pickup/minimum hire | P71: 20ft lockable container / site lockup weekly allowance | Q71: Separate office cabin, abnormal delivery/craneage, power and security | R71: Medium | S71: AMBER - comparable estimate benchmark | T71: Use as tender benchmark only; replace with Siteworks/supplier actual if provided.
A72: OTH-PLANT-TRANSPORT-PROXY | B72: Other | C72: Plant mobilisation / transporter wet-hire proxy | D72: Other | E72: hr | F72: Transport allowance | G72: Yes | H72: Yes | I72: 175 | J72: Auckland / NZ | K72: 08-Sep-2026 | L72: Current published supplier benchmark | M72: ASAP Machine Hire & Earthworks | N72: https://www.asapmachinehire.co.nz/price-list | O72: Actual 5.5t+ transporter rates by quote | P72: Truck/trailer, driver and normal fuel benchmark | Q72: Heavy transporter premium, permits, escorts, waiting and abnormal access | R72: Medium | S72: AMBER - transport proxy / heavy transporter rate to verify | T72: Published truck-and-trailer wet-hire benchmark only. ASAP states 5.5t+ transporter rates are by quote.
A73: MAT-SILTFENCE-50 | B73: Material | C73: Cirtex premium silt fence 1.0 x 50m, code 76027 | D73: Material | E73: roll | F73: Merchant supply | G73: N/A | H73: N/A | I73: 87.07 | J73: Auckland / NZ | K73: 08-Sep-2026 | L73: Current account pricebook | M73: CARTERS / Cirtex 76027 | N73: CARTERS Standard Price Book export 08-Sep-2026 | O73: 50m roll | P73: Fabric supply only | Q73: Posts, wire, clips/pins, caps, delivery and installation | R73: High | S73: GREEN - current account rate + independent current retail + quantity check | T73: CARTERS $87.07/roll excl GST. Independent Mitre10 $72.98. https://www.mitre10.co.nz/shop/strol-cirtex-silt-fence-woven-silt-sediment-control-fabric-1m-x-50m-black/p/228126
A74: MAT-YPOST-180 | B74: Material | C74: Fencing standard Y post 1.80m | D74: Material | E74: ea | F74: Merchant supply | G74: N/A | H74: N/A | I74: 12.8 | J74: Auckland / NZ | K74: 08-Sep-2026 | L74: Current account pricebook | M74: CARTERS | N74: CARTERS Standard Price Book export 08-Sep-2026 | O74: Each | P74: 1.8m Y post supply | Q74: Safety cap, delivery and installation | R74: High | S74: GREEN - current account rate + independent retail + spacing check | T74: CARTERS $12.80/ea excl GST. Bunnings current $11.93. https://www.bunnings.co.nz/summit-steel-wire-1-8m-black-y-post_p0814015
A75: MAT-YPOST-CAP | B75: Material | C75: Safety cap for starter / Y post | D75: Material | E75: ea | F75: Merchant supply | G75: N/A | H75: N/A | I75: 0.98 | J75: Auckland / NZ | K75: 08-Sep-2026 | L75: Current account pricebook | M75: CARTERS | N75: CARTERS Standard Price Book export 08-Sep-2026 | O75: Each | P75: Safety cap supply | Q75: Post and installation | R75: Medium | S75: AMBER - current primary price / independent direct price incomplete | T75: One cap per Y post.
A76: MAT-WIRE-HT650 | B76: Material | C76: Premium fencing wire 2.5mm HT, 25kg / 650m coil | D76: Material | E76: coil | F76: Merchant supply | G76: N/A | H76: N/A | I76: 114.91 | J76: Auckland / NZ | K76: 08-Sep-2026 | L76: Current account pricebook | M76: CARTERS | N76: CARTERS Standard Price Book export 08-Sep-2026 | O76: 650m coil | P76: High-tensile support wire | Q76: Fixings and installation | R76: Medium | S76: AMBER - current primary price | T76: One coil exceeds current working fence length and leaves repair reserve.
A77: MAT-SILTFENCE-PINS100 | B77: Material | C77: Cirtex 75mm SiltFence pins - 100 pack | D77: Material | E77: bag | F77: Retail / merchant | G77: N/A | H77: N/A | I77: 27 | J77: NZ / Auckland | K77: 09-Sep-2026 | L77: Current published retail | M77: Bunnings NZ / Cirtex 76062 | N77: https://www.bunnings.co.nz/search/products?q=siltfence+pack | O77: 100 pins/bag | P77: Pins for fixing fence fabric to support wire | Q77: Delivery and installation | R77: Medium | S77: AMBER - current retail / project merchant quote not held | T77: Cirtex guidance permits pins/clips; high-tensile wire basis uses up to 500mm fixing spacing.
A78: MAT-WIRE-STRAINER | B78: Material | C78: Wire strainer clip-lock type | D78: Material | E78: ea | F78: Merchant supply | G78: N/A | H78: N/A | I78: 4.88 | J78: Auckland / NZ | K78: 08-Sep-2026 | L78: Current account pricebook | M78: CARTERS / Strainrite | N78: CARTERS Standard Price Book export 08-Sep-2026 | O78: Each | P78: Wire strainer supply | Q78: Installation | R78: Medium | S78: AMBER - current primary / functional equivalent | T78: Cirtex calculator calls for one wire strainer per 25m; exact proprietary strainer not project-specified.
A79: MAT-GEOTEX-AS280ROLL | B79: Material | C79: Duraforce AS280 geotextile 1.9 x 50m roll, code 76021 | D79: Material | E79: roll | F79: Merchant supply | G79: N/A | H79: N/A | I79: 176.64 | J79: Auckland / NZ | K79: 08-Sep-2026 | L79: Current account pricebook | M79: CARTERS / Cirtex | N79: CARTERS Standard Price Book export 08-Sep-2026 | O79: 95m2 roll | P79: Geotextile material | Q79: Delivery and placement | R79: Medium | S79: AMBER - current primary / final approved geotextile grade to confirm | T79: One roll covers 49m2 entrance including overlaps/cuts.
A80: MAT-ESC-AGG15050 | B80: Material | C80: SGC 150/50 aggregate - stabilised entrance size control | D80: Material | E80: t | F80: Quarry supply | G80: N/A | H80: N/A | I80: 42 | J80: Auckland / NZ | K80: 09-Sep-2026 | L80: Current published quarry price | M80: The Landing Quarry - Mangere | N80: https://www.thelandingquarry.co.nz/products | O80: Ex-gate; published density 1.05t/m3 | P80: 150/50 aggregate supply | Q80: Delivery, placement; washed status/project acceptance not explicitly confirmed | R80: Medium | S80: AMBER - exact size current / washed status and delivery to confirm | T80: DWG241 requires 50-150mm washed aggregate. Published SGC150/50 matches size; source warns engineering gradings require project testing/confirmation.

Sheet Rate Verification
A1: RATE & ALLOWANCE VERIFICATION - MASTER ESTIMATE WORKBOOK
A2: GREEN requires: (1) current primary evidence, (2) an independent market check, and (3) a first-principles quantity/scope/arithmetic check. Anything less is AMBER; missing or conflicting is RED.
A3: Status | B3: Active rows | C3: Cost exposure excl. GST | E3: Status | F3: Active rows | G3: Cost exposure excl. GST
A4: GREEN | B4: =COUNTIF($T$8:$T$307,"GREEN - 3-point checked")+COUNTIF($T$8:$T$307,"GREEN - duplicate prevented") | C4: =SUMIF($T$8:$T$307,"GREEN - 3-point checked",$J$8:$J$307)+SUMIF($T$8:$T$307,"GREEN - duplicate prevented",$J$8:$J$307) | E4: RED | F4: =COUNTIF($T$8:$T$307,"RED - live quote/design evidence required")+COUNTIF($T$8:$T$307,"RED - allowance basis/quote required") | G4: =SUMIF($T$8:$T$307,"RED - live quote/design evidence required",$J$8:$J$307)+SUMIF($T$8:$T$307,"RED - allowance basis/quote required",$J$8:$J$307)
A5: AMBER | B5: =COUNTIF($T$8:$T$307,"AMBER - company cost rate required")+COUNTIF($T$8:$T$307,"AMBER - explicit allowance; second evidence required")+COUNTIF($T$8:$T$307,"AMBER - benchmark only")+COUNTIF($T$8:$T$307,"AMBER - 3-point benchmark; quote required")+COUNTIF($T$8:$T$307,"AMBER - specification/delivery quote required")+COUNTIF($T$8:$T$307,"AMBER - benchmarked PC; NZ supplier quote required")+COUNTIF($T$8:$T$307,"AMBER - PC SUM / QUOTE REQUIRED")+COUNTIF($T$8:$T$307,"AMBER - PC sum / part quote requested")+COUNTIF($T$8:$T$307,"AMBER - PC SUM / RFI HOLD")+COUNTIF($T$8:$T$307,"AMBER - PC SUM / DUPLICATION CHECK")+COUNTIF($T$8:$T$307,"AMBER - QUOTE REQUEST SENT")+COUNTIF($T$8:$T$307,"AMBER - PC SUM / DESIGN HOLD")+COUNTIF($T$8:$T$307,"AMBER - QUOTE REQUEST SENT / SCOPE CONFIRM") | C5: =SUMIF($T$8:$T$307,"AMBER - company cost rate required",$J$8:$J$307)+SUMIF($T$8:$T$307,"AMBER - explicit allowance; second evidence required",$J$8:$J$307)+SUMIF($T$8:$T$307,"AMBER - benchmark only",$J$8:$J$307)+SUMIF($T$8:$T$307,"AMBER - 3-point benchmark; quote required",$J$8:$J$307)+SUMIF($T$8:$T$307,"AMBER - specification/delivery quote required",$J$8:$J$307)+SUMIF($T$8:$T$307,"AMBER - benchmarked PC; NZ supplier quote required",$J$8:$J$307)+SUMIF($T$8:$T$307,"AMBER - PC SUM / QUOTE REQUIRED",$J$8:$J$307)+SUMIF($T$8:$T$307,"AMBER - PC sum / part quote requested",$J$8:$J$307)+SUMIF($T$8:$T$307,"AMBER - PC SUM / RFI HOLD",$J$8:$J$307)+SUMIF($T$8:$T$307,"AMBER - PC SUM / DUPLICATION CHECK",$J$8:$J$307)+SUMIF($T$8:$T$307,"AMBER - QUOTE REQUEST SENT",$J$8:$J$307)+SUMIF($T$8:$T$307,"AMBER - PC SUM / DESIGN HOLD",$J$8:$J$307)+SUMIF($T$8:$T$307,"AMBER - QUOTE REQUEST SENT / SCOPE CONFIRM",$J$8:$J$307) | E5: Release gate | F5: Tender issue only | G5: RED items must be disclosed and replaced before award
A7: Audit ID | B7: Build-Up Row | C7: QS Code | D7: WBS / Section | E7: Task / Method | F7: Resource Code | G7: Resource | H7: Unit | I7: Applied Rate | J7: Extended Cost | K7: Evidence 1 - primary/current | L7: Result 1 | M7: Evidence 2 - independent check | N7: Result 2 | O7: Evidence 3 - build-up/scope | P7: Result 3 | Q7: Score | R7: Source Date | S7: Confidence | T7: Release Status | U7: Required Action | V7: Scope / Assumption
A8: RV-001 | B8: ='Resource Build-Up'!A7 | C8: ='Resource Build-Up'!B7 | D8: ='Resource Build-Up'!C7 | E8: ='Resource Build-Up'!H7 | F8: ='Resource Build-Up'!P7 | G8: ='Resource Build-Up'!Q7 | H8: ='Resource Build-Up'!T7 | I8: ='Resource Build-Up'!Y7 | J8: ='Resource Build-Up'!Z7 | Q8: =COUNTIF(L8,"PASS")+COUNTIF(N8,"PASS")+COUNTIF(P8,"PASS") | R8: ='Resource Build-Up'!AC7 | S8: ='Resource Build-Up'!AF7 | V8: ='Resource Build-Up'!AG7
A9: RV-002 | B9: ='Resource Build-Up'!A8 | C9: ='Resource Build-Up'!B8 | D9: ='Resource Build-Up'!C8 | E9: ='Resource Build-Up'!H8 | F9: ='Resource Build-Up'!P8 | G9: ='Resource Build-Up'!Q8 | H9: ='Resource Build-Up'!T8 | I9: ='Resource Build-Up'!Y8 | J9: ='Resource Build-Up'!Z8 | Q9: =COUNTIF(L9,"PASS")+COUNTIF(N9,"PASS")+COUNTIF(P9,"PASS") | R9: ='Resource Build-Up'!AC8 | S9: ='Resource Build-Up'!AF8 | V9: ='Resource Build-Up'!AG8
A10: RV-003 | B10: ='Resource Build-Up'!A9 | C10: ='Resource Build-Up'!B9 | D10: ='Resource Build-Up'!C9 | E10: ='Resource Build-Up'!H9 | F10: ='Resource Build-Up'!P9 | G10: ='Resource Build-Up'!Q9 | H10: ='Resource Build-Up'!T9 | I10: ='Resource Build-Up'!Y9 | J10: ='Resource Build-Up'!Z9 | Q10: =COUNTIF(L10,"PASS")+COUNTIF(N10,"PASS")+COUNTIF(P10,"PASS") | R10: ='Resource Build-Up'!AC9 | S10: ='Resource Build-Up'!AF9 | V10: ='Resource Build-Up'!AG9
A11: RV-004 | B11: ='Resource Build-Up'!A10 | C11: ='Resource Build-Up'!B10 | D11: ='Resource Build-Up'!C10 | E11: ='Resource Build-Up'!H10 | F11: ='Resource Build-Up'!P10 | G11: ='Resource Build-Up'!Q10 | H11: ='Resource Build-Up'!T10 | I11: ='Resource Build-Up'!Y10 | J11: ='Resource Build-Up'!Z10 | Q11: =COUNTIF(L11,"PASS")+COUNTIF(N11,"PASS")+COUNTIF(P11,"PASS") | R11: ='Resource Build-Up'!AC10 | S11: ='Resource Build-Up'!AF10 | V11: ='Resource Build-Up'!AG10
A12: RV-005 | B12: ='Resource Build-Up'!A11 | C12: ='Resource Build-Up'!B11 | D12: ='Resource Build-Up'!C11 | E12: ='Resource Build-Up'!H11 | F12: ='Resource Build-Up'!P11 | G12: ='Resource Build-Up'!Q11 | H12: ='Resource Build-Up'!T11 | I12: ='Resource Build-Up'!Y11 | J12: ='Resource Build-Up'!Z11 | Q12: =COUNTIF(L12,"PASS")+COUNTIF(N12,"PASS")+COUNTIF(P12,"PASS") | R12: ='Resource Build-Up'!AC11 | S12: ='Resource Build-Up'!AF11 | V12: ='Resource Build-Up'!AG11
A13: RV-006 | B13: ='Resource Build-Up'!A12 | C13: ='Resource Build-Up'!B12 | D13: ='Resource Build-Up'!C12 | E13: ='Resource Build-Up'!H12 | F13: ='Resource Build-Up'!P12 | G13: ='Resource Build-Up'!Q12 | H13: ='Resource Build-Up'!T12 | I13: ='Resource Build-Up'!Y12 | J13: ='Resource Build-Up'!Z12 | Q13: =COUNTIF(L13,"PASS")+COUNTIF(N13,"PASS")+COUNTIF(P13,"PASS") | R13: ='Resource Build-Up'!AC12 | S13: ='Resource Build-Up'!AF12 | V13: ='Resource Build-Up'!AG12
A14: RV-007 | B14: ='Resource Build-Up'!A13 | C14: ='Resource Build-Up'!B13 | D14: ='Resource Build-Up'!C13 | E14: ='Resource Build-Up'!H13 | F14: ='Resource Build-Up'!P13 | G14: ='Resource Build-Up'!Q13 | H14: ='Resource Build-Up'!T13 | I14: ='Resource Build-Up'!Y13 | J14: ='Resource Build-Up'!Z13 | Q14: =COUNTIF(L14,"PASS")+COUNTIF(N14,"PASS")+COUNTIF(P14,"PASS") | R14: ='Resource Build-Up'!AC13 | S14: ='Resource Build-Up'!AF13 | V14: ='Resource Build-Up'!AG13
A15: RV-008 | B15: ='Resource Build-Up'!A14 | C15: ='Resource Build-Up'!B14 | D15: ='Resource Build-Up'!C14 | E15: ='Resource Build-Up'!H14 | F15: ='Resource Build-Up'!P14 | G15: ='Resource Build-Up'!Q14 | H15: ='Resource Build-Up'!T14 | I15: ='Resource Build-Up'!Y14 | J15: ='Resource Build-Up'!Z14 | Q15: =COUNTIF(L15,"PASS")+COUNTIF(N15,"PASS")+COUNTIF(P15,"PASS") | R15: ='Resource Build-Up'!AC14 | S15: ='Resource Build-Up'!AF14 | V15: ='Resource Build-Up'!AG14
A16: RV-009 | B16: ='Resource Build-Up'!A15 | C16: ='Resource Build-Up'!B15 | D16: ='Resource Build-Up'!C15 | E16: ='Resource Build-Up'!H15 | F16: ='Resource Build-Up'!P15 | G16: ='Resource Build-Up'!Q15 | H16: ='Resource Build-Up'!T15 | I16: ='Resource Build-Up'!Y15 | J16: ='Resource Build-Up'!Z15 | Q16: =COUNTIF(L16,"PASS")+COUNTIF(N16,"PASS")+COUNTIF(P16,"PASS") | R16: ='Resource Build-Up'!AC15 | S16: ='Resource Build-Up'!AF15 | V16: ='Resource Build-Up'!AG15
A17: RV-010 | B17: ='Resource Build-Up'!A16 | C17: ='Resource Build-Up'!B16 | D17: ='Resource Build-Up'!C16 | E17: ='Resource Build-Up'!H16 | F17: ='Resource Build-Up'!P16 | G17: ='Resource Build-Up'!Q16 | H17: ='Resource Build-Up'!T16 | I17: ='Resource Build-Up'!Y16 | J17: ='Resource Build-Up'!Z16 | Q17: =COUNTIF(L17,"PASS")+COUNTIF(N17,"PASS")+COUNTIF(P17,"PASS") | R17: ='Resource Build-Up'!AC16 | S17: ='Resource Build-Up'!AF16 | V17: ='Resource Build-Up'!AG16
A18: RV-011 | B18: ='Resource Build-Up'!A17 | C18: ='Resource Build-Up'!B17 | D18: ='Resource Build-Up'!C17 | E18: ='Resource Build-Up'!H17 | F18: ='Resource Build-Up'!P17 | G18: ='Resource Build-Up'!Q17 | H18: ='Resource Build-Up'!T17 | I18: ='Resource Build-Up'!Y17 | J18: ='Resource Build-Up'!Z17 | Q18: =COUNTIF(L18,"PASS")+COUNTIF(N18,"PASS")+COUNTIF(P18,"PASS") | R18: ='Resource Build-Up'!AC17 | S18: ='Resource Build-Up'!AF17 | V18: ='Resource Build-Up'!AG17
A19: RV-012 | B19: ='Resource Build-Up'!A18 | C19: ='Resource Build-Up'!B18 | D19: ='Resource Build-Up'!C18 | E19: ='Resource Build-Up'!H18 | F19: ='Resource Build-Up'!P18 | G19: ='Resource Build-Up'!Q18 | H19: ='Resource Build-Up'!T18 | I19: ='Resource Build-Up'!Y18 | J19: ='Resource Build-Up'!Z18 | Q19: =COUNTIF(L19,"PASS")+COUNTIF(N19,"PASS")+COUNTIF(P19,"PASS") | R19: ='Resource Build-Up'!AC18 | S19: ='Resource Build-Up'!AF18 | V19: ='Resource Build-Up'!AG18
... A307: RV-300 | B307: ='Resource Build-Up'!A306 | C307: ='Resource Build-Up'!B306 | D307: ='Resource Build-Up'!C306 | E307: ='Resource Build-Up'!H306 | F307: ='Resource Build-Up'!P306 | G307: ='Resource Build-Up'!Q306 | H307: ='Resource Build-Up'!T306 | I307: ='Resource Build-Up'!Y306 | J307: ='Resource Build-Up'!Z306 | Q307: =COUNTIF(L307,"PASS")+COUNTIF(N307,"PASS")+COUNTIF(P307,"PASS") | R307: ='Resource Build-Up'!AC306 | S307: ='Resource Build-Up'!AF306 | V307: ='Resource Build-Up'!AG306

Sheet Programme Export
A1: PROGRAMME BUILD-UP & MICROSOFT PROJECT EXPORT - MASTER ESTIMATE WORKBOOK
A2: Programme durations derive from Resource Build-Up quantity/productivity unless an explicit programme override is entered. Set the current project calendar, start date, holidays, shutdowns and work fronts before issue.
A3: MS Project: import Tasks and map Name, Duration, Predecessors, Fixed Cost, Text fields, Notes, Task Mode and Fixed Cost Accrual. Do not also import the same resource costs when Fixed Cost is used, or costs will double.
A4: Microsoft import guidance: https://support.microsoft.com/en-us/project/export-or-import-data-to-another-file-format
A5: PROGRAMME RECONCILIATION: J takes the largest linked Resource Build-Up applied duration for each QS code; K converts hours to working days; M uses the override in L when one is entered. Rows 7-206 follow QS Takeoff rows 3-202. Control tasks that are not QS items (cure, inspection holds, proof rolls) go in rows 207-226: type the code in D, the name in E, the days in L and predecessor codes in P.
A6: Import ID | B6: QS Row | C6: WBS / Section | D6: QS Code | E6: Task Name | F6: Quantity | G6: Unit | H6: QS Fixed Cost | I6: Resource Cost Check | J6: Max Resource Duration hrs | K6: Derived Duration days | L6: Programme Override days | M6: Export Duration days | N6: Duration | O6: Duration Basis | P6: Predecessor QS Codes | Q6: Predecessors | R6: Resource Summary | S6: Rate QA Status | T6: QS / Resource Difference | U6: Cost Check | V6: Task Mode | W6: Cost Accrual | X6: Notes | Y6: Task sequence (helper)
A7: 1 | B7: 3 | C7: =IF('QS Takeoff'!$B3="","",'QS Takeoff'!A3) | D7: =IF('QS Takeoff'!$B3="","",'QS Takeoff'!B3) | E7: =IF('QS Takeoff'!$B3="","",'QS Takeoff'!C3) | F7: =IF('QS Takeoff'!$B3="","",'QS Takeoff'!E3) | G7: =IF('QS Takeoff'!$B3="","",'QS Takeoff'!D3) | H7: =IF('QS Takeoff'!$B3="","",'QS Takeoff'!G3) | I7: =SUMIF('Resource Build-Up'!$B$7:$B$306,D7,'Resource Build-Up'!$Z$7:$Z$306) | J7: =IFERROR(_xlfn.MAXIFS('Resource Build-Up'!$M$7:$M$306,'Resource Build-Up'!$B$7:$B$306,D7),0) | K7: =IF(J7=0,"",ROUNDUP(J7/8,0)) | M7: =IF(L7<>"",L7,K7) | N7: =IF(M7="","",TEXT(M7,"0")&" days") | T7: =IF($D7="","",I7-N(H7)) | U7: =IF($D7="","",IF(ABS(T7)<0.01,"OK","CHECK")) | V7: Auto Scheduled | W7: Prorated | Y7: =IF($D7="","",COUNTIF($D$7:$D7,"?*"))
A8: 2 | B8: 4 | C8: =IF('QS Takeoff'!$B4="","",'QS Takeoff'!A4) | D8: =IF('QS Takeoff'!$B4="","",'QS Takeoff'!B4) | E8: =IF('QS Takeoff'!$B4="","",'QS Takeoff'!C4) | F8: =IF('QS Takeoff'!$B4="","",'QS Takeoff'!E4) | G8: =IF('QS Takeoff'!$B4="","",'QS Takeoff'!D4) | H8: =IF('QS Takeoff'!$B4="","",'QS Takeoff'!G4) | I8: =SUMIF('Resource Build-Up'!$B$7:$B$306,D8,'Resource Build-Up'!$Z$7:$Z$306) | J8: =IFERROR(_xlfn.MAXIFS('Resource Build-Up'!$M$7:$M$306,'Resource Build-Up'!$B$7:$B$306,D8),0) | K8: =IF(J8=0,"",ROUNDUP(J8/8,0)) | M8: =IF(L8<>"",L8,K8) | N8: =IF(M8="","",TEXT(M8,"0")&" days") | T8: =IF($D8="","",I8-N(H8)) | U8: =IF($D8="","",IF(ABS(T8)<0.01,"OK","CHECK")) | V8: Auto Scheduled | W8: Prorated | Y8: =IF($D8="","",COUNTIF($D$7:$D8,"?*"))
A9: 3 | B9: 5 | C9: =IF('QS Takeoff'!$B5="","",'QS Takeoff'!A5) | D9: =IF('QS Takeoff'!$B5="","",'QS Takeoff'!B5) | E9: =IF('QS Takeoff'!$B5="","",'QS Takeoff'!C5) | F9: =IF('QS Takeoff'!$B5="","",'QS Takeoff'!E5) | G9: =IF('QS Takeoff'!$B5="","",'QS Takeoff'!D5) | H9: =IF('QS Takeoff'!$B5="","",'QS Takeoff'!G5) | I9: =SUMIF('Resource Build-Up'!$B$7:$B$306,D9,'Resource Build-Up'!$Z$7:$Z$306) | J9: =IFERROR(_xlfn.MAXIFS('Resource Build-Up'!$M$7:$M$306,'Resource Build-Up'!$B$7:$B$306,D9),0) | K9: =IF(J9=0,"",ROUNDUP(J9/8,0)) | M9: =IF(L9<>"",L9,K9) | N9: =IF(M9="","",TEXT(M9,"0")&" days") | T9: =IF($D9="","",I9-N(H9)) | U9: =IF($D9="","",IF(ABS(T9)<0.01,"OK","CHECK")) | V9: Auto Scheduled | W9: Prorated | Y9: =IF($D9="","",COUNTIF($D$7:$D9,"?*"))
A10: 4 | B10: 6 | C10: =IF('QS Takeoff'!$B6="","",'QS Takeoff'!A6) | D10: =IF('QS Takeoff'!$B6="","",'QS Takeoff'!B6) | E10: =IF('QS Takeoff'!$B6="","",'QS Takeoff'!C6) | F10: =IF('QS Takeoff'!$B6="","",'QS Takeoff'!E6) | G10: =IF('QS Takeoff'!$B6="","",'QS Takeoff'!D6) | H10: =IF('QS Takeoff'!$B6="","",'QS Takeoff'!G6) | I10: =SUMIF('Resource Build-Up'!$B$7:$B$306,D10,'Resource Build-Up'!$Z$7:$Z$306) | J10: =IFERROR(_xlfn.MAXIFS('Resource Build-Up'!$M$7:$M$306,'Resource Build-Up'!$B$7:$B$306,D10),0) | K10: =IF(J10=0,"",ROUNDUP(J10/8,0)) | M10: =IF(L10<>"",L10,K10) | N10: =IF(M10="","",TEXT(M10,"0")&" days") | T10: =IF($D10="","",I10-N(H10)) | U10: =IF($D10="","",IF(ABS(T10)<0.01,"OK","CHECK")) | V10: Auto Scheduled | W10: Prorated | Y10: =IF($D10="","",COUNTIF($D$7:$D10,"?*"))
A11: 5 | B11: 7 | C11: =IF('QS Takeoff'!$B7="","",'QS Takeoff'!A7) | D11: =IF('QS Takeoff'!$B7="","",'QS Takeoff'!B7) | E11: =IF('QS Takeoff'!$B7="","",'QS Takeoff'!C7) | F11: =IF('QS Takeoff'!$B7="","",'QS Takeoff'!E7) | G11: =IF('QS Takeoff'!$B7="","",'QS Takeoff'!D7) | H11: =IF('QS Takeoff'!$B7="","",'QS Takeoff'!G7) | I11: =SUMIF('Resource Build-Up'!$B$7:$B$306,D11,'Resource Build-Up'!$Z$7:$Z$306) | J11: =IFERROR(_xlfn.MAXIFS('Resource Build-Up'!$M$7:$M$306,'Resource Build-Up'!$B$7:$B$306,D11),0) | K11: =IF(J11=0,"",ROUNDUP(J11/8,0)) | M11: =IF(L11<>"",L11,K11) | N11: =IF(M11="","",TEXT(M11,"0")&" days") | T11: =IF($D11="","",I11-N(H11)) | U11: =IF($D11="","",IF(ABS(T11)<0.01,"OK","CHECK")) | V11: Auto Scheduled | W11: Prorated | Y11: =IF($D11="","",COUNTIF($D$7:$D11,"?*"))
A12: 6 | B12: 8 | C12: =IF('QS Takeoff'!$B8="","",'QS Takeoff'!A8) | D12: =IF('QS Takeoff'!$B8="","",'QS Takeoff'!B8) | E12: =IF('QS Takeoff'!$B8="","",'QS Takeoff'!C8) | F12: =IF('QS Takeoff'!$B8="","",'QS Takeoff'!E8) | G12: =IF('QS Takeoff'!$B8="","",'QS Takeoff'!D8) | H12: =IF('QS Takeoff'!$B8="","",'QS Takeoff'!G8) | I12: =SUMIF('Resource Build-Up'!$B$7:$B$306,D12,'Resource Build-Up'!$Z$7:$Z$306) | J12: =IFERROR(_xlfn.MAXIFS('Resource Build-Up'!$M$7:$M$306,'Resource Build-Up'!$B$7:$B$306,D12),0) | K12: =IF(J12=0,"",ROUNDUP(J12/8,0)) | M12: =IF(L12<>"",L12,K12) | N12: =IF(M12="","",TEXT(M12,"0")&" days") | T12: =IF($D12="","",I12-N(H12)) | U12: =IF($D12="","",IF(ABS(T12)<0.01,"OK","CHECK")) | V12: Auto Scheduled | W12: Prorated | Y12: =IF($D12="","",COUNTIF($D$7:$D12,"?*"))
A13: 7 | B13: 9 | C13: =IF('QS Takeoff'!$B9="","",'QS Takeoff'!A9) | D13: =IF('QS Takeoff'!$B9="","",'QS Takeoff'!B9) | E13: =IF('QS Takeoff'!$B9="","",'QS Takeoff'!C9) | F13: =IF('QS Takeoff'!$B9="","",'QS Takeoff'!E9) | G13: =IF('QS Takeoff'!$B9="","",'QS Takeoff'!D9) | H13: =IF('QS Takeoff'!$B9="","",'QS Takeoff'!G9) | I13: =SUMIF('Resource Build-Up'!$B$7:$B$306,D13,'Resource Build-Up'!$Z$7:$Z$306) | J13: =IFERROR(_xlfn.MAXIFS('Resource Build-Up'!$M$7:$M$306,'Resource Build-Up'!$B$7:$B$306,D13),0) | K13: =IF(J13=0,"",ROUNDUP(J13/8,0)) | M13: =IF(L13<>"",L13,K13) | N13: =IF(M13="","",TEXT(M13,"0")&" days") | T13: =IF($D13="","",I13-N(H13)) | U13: =IF($D13="","",IF(ABS(T13)<0.01,"OK","CHECK")) | V13: Auto Scheduled | W13: Prorated | Y13: =IF($D13="","",COUNTIF($D$7:$D13,"?*"))
A14: 8 | B14: 10 | C14: =IF('QS Takeoff'!$B10="","",'QS Takeoff'!A10) | D14: =IF('QS Takeoff'!$B10="","",'QS Takeoff'!B10) | E14: =IF('QS Takeoff'!$B10="","",'QS Takeoff'!C10) | F14: =IF('QS Takeoff'!$B10="","",'QS Takeoff'!E10) | G14: =IF('QS Takeoff'!$B10="","",'QS Takeoff'!D10) | H14: =IF('QS Takeoff'!$B10="","",'QS Takeoff'!G10) | I14: =SUMIF('Resource Build-Up'!$B$7:$B$306,D14,'Resource Build-Up'!$Z$7:$Z$306) | J14: =IFERROR(_xlfn.MAXIFS('Resource Build-Up'!$M$7:$M$306,'Resource Build-Up'!$B$7:$B$306,D14),0) | K14: =IF(J14=0,"",ROUNDUP(J14/8,0)) | M14: =IF(L14<>"",L14,K14) | N14: =IF(M14="","",TEXT(M14,"0")&" days") | T14: =IF($D14="","",I14-N(H14)) | U14: =IF($D14="","",IF(ABS(T14)<0.01,"OK","CHECK")) | V14: Auto Scheduled | W14: Prorated | Y14: =IF($D14="","",COUNTIF($D$7:$D14,"?*"))
A15: 9 | B15: 11 | C15: =IF('QS Takeoff'!$B11="","",'QS Takeoff'!A11) | D15: =IF('QS Takeoff'!$B11="","",'QS Takeoff'!B11) | E15: =IF('QS Takeoff'!$B11="","",'QS Takeoff'!C11) | F15: =IF('QS Takeoff'!$B11="","",'QS Takeoff'!E11) | G15: =IF('QS Takeoff'!$B11="","",'QS Takeoff'!D11) | H15: =IF('QS Takeoff'!$B11="","",'QS Takeoff'!G11) | I15: =SUMIF('Resource Build-Up'!$B$7:$B$306,D15,'Resource Build-Up'!$Z$7:$Z$306) | J15: =IFERROR(_xlfn.MAXIFS('Resource Build-Up'!$M$7:$M$306,'Resource Build-Up'!$B$7:$B$306,D15),0) | K15: =IF(J15=0,"",ROUNDUP(J15/8,0)) | M15: =IF(L15<>"",L15,K15) | N15: =IF(M15="","",TEXT(M15,"0")&" days") | T15: =IF($D15="","",I15-N(H15)) | U15: =IF($D15="","",IF(ABS(T15)<0.01,"OK","CHECK")) | V15: Auto Scheduled | W15: Prorated | Y15: =IF($D15="","",COUNTIF($D$7:$D15,"?*"))
A16: 10 | B16: 12 | C16: =IF('QS Takeoff'!$B12="","",'QS Takeoff'!A12) | D16: =IF('QS Takeoff'!$B12="","",'QS Takeoff'!B12) | E16: =IF('QS Takeoff'!$B12="","",'QS Takeoff'!C12) | F16: =IF('QS Takeoff'!$B12="","",'QS Takeoff'!E12) | G16: =IF('QS Takeoff'!$B12="","",'QS Takeoff'!D12) | H16: =IF('QS Takeoff'!$B12="","",'QS Takeoff'!G12) | I16: =SUMIF('Resource Build-Up'!$B$7:$B$306,D16,'Resource Build-Up'!$Z$7:$Z$306) | J16: =IFERROR(_xlfn.MAXIFS('Resource Build-Up'!$M$7:$M$306,'Resource Build-Up'!$B$7:$B$306,D16),0) | K16: =IF(J16=0,"",ROUNDUP(J16/8,0)) | M16: =IF(L16<>"",L16,K16) | N16: =IF(M16="","",TEXT(M16,"0")&" days") | T16: =IF($D16="","",I16-N(H16)) | U16: =IF($D16="","",IF(ABS(T16)<0.01,"OK","CHECK")) | V16: Auto Scheduled | W16: Prorated | Y16: =IF($D16="","",COUNTIF($D$7:$D16,"?*"))
A17: 11 | B17: 13 | C17: =IF('QS Takeoff'!$B13="","",'QS Takeoff'!A13) | D17: =IF('QS Takeoff'!$B13="","",'QS Takeoff'!B13) | E17: =IF('QS Takeoff'!$B13="","",'QS Takeoff'!C13) | F17: =IF('QS Takeoff'!$B13="","",'QS Takeoff'!E13) | G17: =IF('QS Takeoff'!$B13="","",'QS Takeoff'!D13) | H17: =IF('QS Takeoff'!$B13="","",'QS Takeoff'!G13) | I17: =SUMIF('Resource Build-Up'!$B$7:$B$306,D17,'Resource Build-Up'!$Z$7:$Z$306) | J17: =IFERROR(_xlfn.MAXIFS('Resource Build-Up'!$M$7:$M$306,'Resource Build-Up'!$B$7:$B$306,D17),0) | K17: =IF(J17=0,"",ROUNDUP(J17/8,0)) | M17: =IF(L17<>"",L17,K17) | N17: =IF(M17="","",TEXT(M17,"0")&" days") | T17: =IF($D17="","",I17-N(H17)) | U17: =IF($D17="","",IF(ABS(T17)<0.01,"OK","CHECK")) | V17: Auto Scheduled | W17: Prorated | Y17: =IF($D17="","",COUNTIF($D$7:$D17,"?*"))
A18: 12 | B18: 14 | C18: =IF('QS Takeoff'!$B14="","",'QS Takeoff'!A14) | D18: =IF('QS Takeoff'!$B14="","",'QS Takeoff'!B14) | E18: =IF('QS Takeoff'!$B14="","",'QS Takeoff'!C14) | F18: =IF('QS Takeoff'!$B14="","",'QS Takeoff'!E14) | G18: =IF('QS Takeoff'!$B14="","",'QS Takeoff'!D14) | H18: =IF('QS Takeoff'!$B14="","",'QS Takeoff'!G14) | I18: =SUMIF('Resource Build-Up'!$B$7:$B$306,D18,'Resource Build-Up'!$Z$7:$Z$306) | J18: =IFERROR(_xlfn.MAXIFS('Resource Build-Up'!$M$7:$M$306,'Resource Build-Up'!$B$7:$B$306,D18),0) | K18: =IF(J18=0,"",ROUNDUP(J18/8,0)) | M18: =IF(L18<>"",L18,K18) | N18: =IF(M18="","",TEXT(M18,"0")&" days") | T18: =IF($D18="","",I18-N(H18)) | U18: =IF($D18="","",IF(ABS(T18)<0.01,"OK","CHECK")) | V18: Auto Scheduled | W18: Prorated | Y18: =IF($D18="","",COUNTIF($D$7:$D18,"?*"))
... A206: 200 | B206: 202 | C206: =IF('QS Takeoff'!$B202="","",'QS Takeoff'!A202) | D206: =IF('QS Takeoff'!$B202="","",'QS Takeoff'!B202) | E206: =IF('QS Takeoff'!$B202="","",'QS Takeoff'!C202) | F206: =IF('QS Takeoff'!$B202="","",'QS Takeoff'!E202) | G206: =IF('QS Takeoff'!$B202="","",'QS Takeoff'!D202) | H206: =IF('QS Takeoff'!$B202="","",'QS Takeoff'!G202) | I206: =SUMIF('Resource Build-Up'!$B$7:$B$306,D206,'Resource Build-Up'!$Z$7:$Z$306) | J206: =IFERROR(_xlfn.MAXIFS('Resource Build-Up'!$M$7:$M$306,'Resource Build-Up'!$B$7:$B$306,D206),0) | K206: =IF(J206=0,"",ROUNDUP(J206/8,0)) | M206: =IF(L206<>"",L206,K206) | N206: =IF(M206="","",TEXT(M206,"0")&" days") | T206: =IF($D206="","",I206-N(H206)) | U206: =IF($D206="","",IF(ABS(T206)<0.01,"OK","CHECK")) | V206: Auto Scheduled | W206: Prorated | Y206: =IF($D206="","",COUNTIF($D$7:$D206,"?*"))
A207: 201 | I207: =SUMIF('Resource Build-Up'!$B$7:$B$306,D207,'Resource Build-Up'!$Z$7:$Z$306) | J207: =IFERROR(_xlfn.MAXIFS('Resource Build-Up'!$M$7:$M$306,'Resource Build-Up'!$B$7:$B$306,D207),0) | K207: =IF(J207=0,"",ROUNDUP(J207/8,0)) | M207: =IF(L207<>"",L207,K207) | N207: =IF(M207="","",TEXT(M207,"0")&" days") | T207: =IF($D207="","",I207-N(H207)) | U207: =IF($D207="","",IF(ABS(T207)<0.01,"OK","CHECK")) | V207: Auto Scheduled | W207: Prorated | Y207: =IF($D207="","",COUNTIF($D$7:$D207,"?*"))
A208: 202 | I208: =SUMIF('Resource Build-Up'!$B$7:$B$306,D208,'Resource Build-Up'!$Z$7:$Z$306) | J208: =IFERROR(_xlfn.MAXIFS('Resource Build-Up'!$M$7:$M$306,'Resource Build-Up'!$B$7:$B$306,D208),0) | K208: =IF(J208=0,"",ROUNDUP(J208/8,0)) | M208: =IF(L208<>"",L208,K208) | N208: =IF(M208="","",TEXT(M208,"0")&" days") | T208: =IF($D208="","",I208-N(H208)) | U208: =IF($D208="","",IF(ABS(T208)<0.01,"OK","CHECK")) | V208: Auto Scheduled | W208: Prorated | Y208: =IF($D208="","",COUNTIF($D$7:$D208,"?*"))
A209: 203 | I209: =SUMIF('Resource Build-Up'!$B$7:$B$306,D209,'Resource Build-Up'!$Z$7:$Z$306) | J209: =IFERROR(_xlfn.MAXIFS('Resource Build-Up'!$M$7:$M$306,'Resource Build-Up'!$B$7:$B$306,D209),0) | K209: =IF(J209=0,"",ROUNDUP(J209/8,0)) | M209: =IF(L209<>"",L209,K209) | N209: =IF(M209="","",TEXT(M209,"0")&" days") | T209: =IF($D209="","",I209-N(H209)) | U209: =IF($D209="","",IF(ABS(T209)<0.01,"OK","CHECK")) | V209: Auto Scheduled | W209: Prorated | Y209: =IF($D209="","",COUNTIF($D$7:$D209,"?*"))
A210: 204 | I210: =SUMIF('Resource Build-Up'!$B$7:$B$306,D210,'Resource Build-Up'!$Z$7:$Z$306) | J210: =IFERROR(_xlfn.MAXIFS('Resource Build-Up'!$M$7:$M$306,'Resource Build-Up'!$B$7:$B$306,D210),0) | K210: =IF(J210=0,"",ROUNDUP(J210/8,0)) | M210: =IF(L210<>"",L210,K210) | N210: =IF(M210="","",TEXT(M210,"0")&" days") | T210: =IF($D210="","",I210-N(H210)) | U210: =IF($D210="","",IF(ABS(T210)<0.01,"OK","CHECK")) | V210: Auto Scheduled | W210: Prorated | Y210: =IF($D210="","",COUNTIF($D$7:$D210,"?*"))
A211: 205 | I211: =SUMIF('Resource Build-Up'!$B$7:$B$306,D211,'Resource Build-Up'!$Z$7:$Z$306) | J211: =IFERROR(_xlfn.MAXIFS('Resource Build-Up'!$M$7:$M$306,'Resource Build-Up'!$B$7:$B$306,D211),0) | K211: =IF(J211=0,"",ROUNDUP(J211/8,0)) | M211: =IF(L211<>"",L211,K211) | N211: =IF(M211="","",TEXT(M211,"0")&" days") | T211: =IF($D211="","",I211-N(H211)) | U211: =IF($D211="","",IF(ABS(T211)<0.01,"OK","CHECK")) | V211: Auto Scheduled | W211: Prorated | Y211: =IF($D211="","",COUNTIF($D$7:$D211,"?*"))
A212: 206 | I212: =SUMIF('Resource Build-Up'!$B$7:$B$306,D212,'Resource Build-Up'!$Z$7:$Z$306) | J212: =IFERROR(_xlfn.MAXIFS('Resource Build-Up'!$M$7:$M$306,'Resource Build-Up'!$B$7:$B$306,D212),0) | K212: =IF(J212=0,"",ROUNDUP(J212/8,0)) | M212: =IF(L212<>"",L212,K212) | N212: =IF(M212="","",TEXT(M212,"0")&" days") | T212: =IF($D212="","",I212-N(H212)) | U212: =IF($D212="","",IF(ABS(T212)<0.01,"OK","CHECK")) | V212: Auto Scheduled | W212: Prorated | Y212: =IF($D212="","",COUNTIF($D$7:$D212,"?*"))
A213: 207 | I213: =SUMIF('Resource Build-Up'!$B$7:$B$306,D213,'Resource Build-Up'!$Z$7:$Z$306) | J213: =IFERROR(_xlfn.MAXIFS('Resource Build-Up'!$M$7:$M$306,'Resource Build-Up'!$B$7:$B$306,D213),0) | K213: =IF(J213=0,"",ROUNDUP(J213/8,0)) | M213: =IF(L213<>"",L213,K213) | N213: =IF(M213="","",TEXT(M213,"0")&" days") | T213: =IF($D213="","",I213-N(H213)) | U213: =IF($D213="","",IF(ABS(T213)<0.01,"OK","CHECK")) | V213: Auto Scheduled | W213: Prorated | Y213: =IF($D213="","",COUNTIF($D$7:$D213,"?*"))
A214: 208 | I214: =SUMIF('Resource Build-Up'!$B$7:$B$306,D214,'Resource Build-Up'!$Z$7:$Z$306) | J214: =IFERROR(_xlfn.MAXIFS('Resource Build-Up'!$M$7:$M$306,'Resource Build-Up'!$B$7:$B$306,D214),0) | K214: =IF(J214=0,"",ROUNDUP(J214/8,0)) | M214: =IF(L214<>"",L214,K214) | N214: =IF(M214="","",TEXT(M214,"0")&" days") | T214: =IF($D214="","",I214-N(H214)) | U214: =IF($D214="","",IF(ABS(T214)<0.01,"OK","CHECK")) | V214: Auto Scheduled | W214: Prorated | Y214: =IF($D214="","",COUNTIF($D$7:$D214,"?*"))
A215: 209 | I215: =SUMIF('Resource Build-Up'!$B$7:$B$306,D215,'Resource Build-Up'!$Z$7:$Z$306) | J215: =IFERROR(_xlfn.MAXIFS('Resource Build-Up'!$M$7:$M$306,'Resource Build-Up'!$B$7:$B$306,D215),0) | K215: =IF(J215=0,"",ROUNDUP(J215/8,0)) | M215: =IF(L215<>"",L215,K215) | N215: =IF(M215="","",TEXT(M215,"0")&" days") | T215: =IF($D215="","",I215-N(H215)) | U215: =IF($D215="","",IF(ABS(T215)<0.01,"OK","CHECK")) | V215: Auto Scheduled | W215: Prorated | Y215: =IF($D215="","",COUNTIF($D$7:$D215,"?*"))
A216: 210 | I216: =SUMIF('Resource Build-Up'!$B$7:$B$306,D216,'Resource Build-Up'!$Z$7:$Z$306) | J216: =IFERROR(_xlfn.MAXIFS('Resource Build-Up'!$M$7:$M$306,'Resource Build-Up'!$B$7:$B$306,D216),0) | K216: =IF(J216=0,"",ROUNDUP(J216/8,0)) | M216: =IF(L216<>"",L216,K216) | N216: =IF(M216="","",TEXT(M216,"0")&" days") | T216: =IF($D216="","",I216-N(H216)) | U216: =IF($D216="","",IF(ABS(T216)<0.01,"OK","CHECK")) | V216: Auto Scheduled | W216: Prorated | Y216: =IF($D216="","",COUNTIF($D$7:$D216,"?*"))
A217: 211 | I217: =SUMIF('Resource Build-Up'!$B$7:$B$306,D217,'Resource Build-Up'!$Z$7:$Z$306) | J217: =IFERROR(_xlfn.MAXIFS('Resource Build-Up'!$M$7:$M$306,'Resource Build-Up'!$B$7:$B$306,D217),0) | K217: =IF(J217=0,"",ROUNDUP(J217/8,0)) | M217: =IF(L217<>"",L217,K217) | N217: =IF(M217="","",TEXT(M217,"0")&" days") | T217: =IF($D217="","",I217-N(H217)) | U217: =IF($D217="","",IF(ABS(T217)<0.01,"OK","CHECK")) | V217: Auto Scheduled | W217: Prorated | Y217: =IF($D217="","",COUNTIF($D$7:$D217,"?*"))
A218: 212 | I218: =SUMIF('Resource Build-Up'!$B$7:$B$306,D218,'Resource Build-Up'!$Z$7:$Z$306) | J218: =IFERROR(_xlfn.MAXIFS('Resource Build-Up'!$M$7:$M$306,'Resource Build-Up'!$B$7:$B$306,D218),0) | K218: =IF(J218=0,"",ROUNDUP(J218/8,0)) | M218: =IF(L218<>"",L218,K218) | N218: =IF(M218="","",TEXT(M218,"0")&" days") | T218: =IF($D218="","",I218-N(H218)) | U218: =IF($D218="","",IF(ABS(T218)<0.01,"OK","CHECK")) | V218: Auto Scheduled | W218: Prorated | Y218: =IF($D218="","",COUNTIF($D$7:$D218,"?*"))
... A226: 220 | I226: =SUMIF('Resource Build-Up'!$B$7:$B$306,D226,'Resource Build-Up'!$Z$7:$Z$306) | J226: =IFERROR(_xlfn.MAXIFS('Resource Build-Up'!$M$7:$M$306,'Resource Build-Up'!$B$7:$B$306,D226),0) | K226: =IF(J226=0,"",ROUNDUP(J226/8,0)) | M226: =IF(L226<>"",L226,K226) | N226: =IF(M226="","",TEXT(M226,"0")&" days") | T226: =IF($D226="","",I226-N(H226)) | U226: =IF($D226="","",IF(ABS(T226)<0.01,"OK","CHECK")) | V226: Auto Scheduled | W226: Prorated | Y226: =IF($D226="","",COUNTIF($D$7:$D226,"?*"))

Sheet MS Project Import
A1: ID | B1: Outline Level | C1: WBS | D1: Task Name | E1: Duration | F1: Predecessors | G1: Fixed Cost | H1: Start | I1: Finish | J1: Resource Names | K1: Category | L1: Source Estimate | M1: Quantity | N1: Unit | O1: Rate | P1: Amount Excl GST | Q1: Notes | R1: Predecessor codes | S1: Source row (helper)
A2: =IF($S2="","",1) | B2: =IF($S2="","",1) | C2: =IF($S2="","",INDEX('Programme Export'!$D$7:$D$226,$S2)&"") | D2: =IF($S2="","",INDEX('Programme Export'!$E$7:$E$226,$S2)&"") | E2: =IF($S2="","",INDEX('Programme Export'!$N$7:$N$226,$S2)&"") | F2: {=IF(R2="","",_xlfn.TEXTJOIN(";",TRUE,IFERROR(IF(TRIM(MID(SUBSTITUTE(SUBSTITUTE(SUBSTITUTE(R2,",",";")," ",";"),";",REPT(" ",60)),(ROW($1:$10)-1)*60+1,60))="","",MATCH(TRIM(MID(SUBSTITUTE(SUBSTITUTE(SUBSTITUTE(R2,",",";")," ",";"),";",REPT(" ",60)),(ROW($1:$10)-1)*60+1,60)),$C$2:$C$201,0)),"")))} | G2: =IF($S2="","",INDEX('Programme Export'!$H$7:$H$226,$S2)) | J2: =IF($S2="","",INDEX('Programme Export'!$R$7:$R$226,$S2)&"") | K2: =IF($S2="","",INDEX('Programme Export'!$C$7:$C$226,$S2)&"") | L2: =IF($S2="","",'Cover & Instructions'!$B$38) | M2: =IF($S2="","",INDEX('Programme Export'!$F$7:$F$226,$S2)) | N2: =IF($S2="","",INDEX('Programme Export'!$G$7:$G$226,$S2)&"") | O2: =IF($S2="","",IFERROR(P2/M2,0)) | P2: =IF($S2="","",INDEX('Programme Export'!$H$7:$H$226,$S2)) | Q2: =IF($S2="","",INDEX('Programme Export'!$X$7:$X$226,$S2)&"") | R2: =IF($S2="","",INDEX('Programme Export'!$P$7:$P$226,$S2)&"") | S2: =IFERROR(MATCH(1,'Programme Export'!$Y$7:$Y$226,0),"")
A3: =IF($S3="","",2) | B3: =IF($S3="","",1) | C3: =IF($S3="","",INDEX('Programme Export'!$D$7:$D$226,$S3)&"") | D3: =IF($S3="","",INDEX('Programme Export'!$E$7:$E$226,$S3)&"") | E3: =IF($S3="","",INDEX('Programme Export'!$N$7:$N$226,$S3)&"") | F3: {=IF(R3="","",_xlfn.TEXTJOIN(";",TRUE,IFERROR(IF(TRIM(MID(SUBSTITUTE(SUBSTITUTE(SUBSTITUTE(R3,",",";")," ",";"),";",REPT(" ",60)),(ROW($1:$10)-1)*60+1,60))="","",MATCH(TRIM(MID(SUBSTITUTE(SUBSTITUTE(SUBSTITUTE(R3,",",";")," ",";"),";",REPT(" ",60)),(ROW($1:$10)-1)*60+1,60)),$C$2:$C$201,0)),"")))} | G3: =IF($S3="","",INDEX('Programme Export'!$H$7:$H$226,$S3)) | J3: =IF($S3="","",INDEX('Programme Export'!$R$7:$R$226,$S3)&"") | K3: =IF($S3="","",INDEX('Programme Export'!$C$7:$C$226,$S3)&"") | L3: =IF($S3="","",'Cover & Instructions'!$B$38) | M3: =IF($S3="","",INDEX('Programme Export'!$F$7:$F$226,$S3)) | N3: =IF($S3="","",INDEX('Programme Export'!$G$7:$G$226,$S3)&"") | O3: =IF($S3="","",IFERROR(P3/M3,0)) | P3: =IF($S3="","",INDEX('Programme Export'!$H$7:$H$226,$S3)) | Q3: =IF($S3="","",INDEX('Programme Export'!$X$7:$X$226,$S3)&"") | R3: =IF($S3="","",INDEX('Programme Export'!$P$7:$P$226,$S3)&"") | S3: =IFERROR(MATCH(2,'Programme Export'!$Y$7:$Y$226,0),"")
A4: =IF($S4="","",3) | B4: =IF($S4="","",1) | C4: =IF($S4="","",INDEX('Programme Export'!$D$7:$D$226,$S4)&"") | D4: =IF($S4="","",INDEX('Programme Export'!$E$7:$E$226,$S4)&"") | E4: =IF($S4="","",INDEX('Programme Export'!$N$7:$N$226,$S4)&"") | F4: {=IF(R4="","",_xlfn.TEXTJOIN(";",TRUE,IFERROR(IF(TRIM(MID(SUBSTITUTE(SUBSTITUTE(SUBSTITUTE(R4,",",";")," ",";"),";",REPT(" ",60)),(ROW($1:$10)-1)*60+1,60))="","",MATCH(TRIM(MID(SUBSTITUTE(SUBSTITUTE(SUBSTITUTE(R4,",",";")," ",";"),";",REPT(" ",60)),(ROW($1:$10)-1)*60+1,60)),$C$2:$C$201,0)),"")))} | G4: =IF($S4="","",INDEX('Programme Export'!$H$7:$H$226,$S4)) | J4: =IF($S4="","",INDEX('Programme Export'!$R$7:$R$226,$S4)&"") | K4: =IF($S4="","",INDEX('Programme Export'!$C$7:$C$226,$S4)&"") | L4: =IF($S4="","",'Cover & Instructions'!$B$38) | M4: =IF($S4="","",INDEX('Programme Export'!$F$7:$F$226,$S4)) | N4: =IF($S4="","",INDEX('Programme Export'!$G$7:$G$226,$S4)&"") | O4: =IF($S4="","",IFERROR(P4/M4,0)) | P4: =IF($S4="","",INDEX('Programme Export'!$H$7:$H$226,$S4)) | Q4: =IF($S4="","",INDEX('Programme Export'!$X$7:$X$226,$S4)&"") | R4: =IF($S4="","",INDEX('Programme Export'!$P$7:$P$226,$S4)&"") | S4: =IFERROR(MATCH(3,'Programme Export'!$Y$7:$Y$226,0),"")
A5: =IF($S5="","",4) | B5: =IF($S5="","",1) | C5: =IF($S5="","",INDEX('Programme Export'!$D$7:$D$226,$S5)&"") | D5: =IF($S5="","",INDEX('Programme Export'!$E$7:$E$226,$S5)&"") | E5: =IF($S5="","",INDEX('Programme Export'!$N$7:$N$226,$S5)&"") | F5: {=IF(R5="","",_xlfn.TEXTJOIN(";",TRUE,IFERROR(IF(TRIM(MID(SUBSTITUTE(SUBSTITUTE(SUBSTITUTE(R5,",",";")," ",";"),";",REPT(" ",60)),(ROW($1:$10)-1)*60+1,60))="","",MATCH(TRIM(MID(SUBSTITUTE(SUBSTITUTE(SUBSTITUTE(R5,",",";")," ",";"),";",REPT(" ",60)),(ROW($1:$10)-1)*60+1,60)),$C$2:$C$201,0)),"")))} | G5: =IF($S5="","",INDEX('Programme Export'!$H$7:$H$226,$S5)) | J5: =IF($S5="","",INDEX('Programme Export'!$R$7:$R$226,$S5)&"") | K5: =IF($S5="","",INDEX('Programme Export'!$C$7:$C$226,$S5)&"") | L5: =IF($S5="","",'Cover & Instructions'!$B$38) | M5: =IF($S5="","",INDEX('Programme Export'!$F$7:$F$226,$S5)) | N5: =IF($S5="","",INDEX('Programme Export'!$G$7:$G$226,$S5)&"") | O5: =IF($S5="","",IFERROR(P5/M5,0)) | P5: =IF($S5="","",INDEX('Programme Export'!$H$7:$H$226,$S5)) | Q5: =IF($S5="","",INDEX('Programme Export'!$X$7:$X$226,$S5)&"") | R5: =IF($S5="","",INDEX('Programme Export'!$P$7:$P$226,$S5)&"") | S5: =IFERROR(MATCH(4,'Programme Export'!$Y$7:$Y$226,0),"")
A6: =IF($S6="","",5) | B6: =IF($S6="","",1) | C6: =IF($S6="","",INDEX('Programme Export'!$D$7:$D$226,$S6)&"") | D6: =IF($S6="","",INDEX('Programme Export'!$E$7:$E$226,$S6)&"") | E6: =IF($S6="","",INDEX('Programme Export'!$N$7:$N$226,$S6)&"") | F6: {=IF(R6="","",_xlfn.TEXTJOIN(";",TRUE,IFERROR(IF(TRIM(MID(SUBSTITUTE(SUBSTITUTE(SUBSTITUTE(R6,",",";")," ",";"),";",REPT(" ",60)),(ROW($1:$10)-1)*60+1,60))="","",MATCH(TRIM(MID(SUBSTITUTE(SUBSTITUTE(SUBSTITUTE(R6,",",";")," ",";"),";",REPT(" ",60)),(ROW($1:$10)-1)*60+1,60)),$C$2:$C$201,0)),"")))} | G6: =IF($S6="","",INDEX('Programme Export'!$H$7:$H$226,$S6)) | J6: =IF($S6="","",INDEX('Programme Export'!$R$7:$R$226,$S6)&"") | K6: =IF($S6="","",INDEX('Programme Export'!$C$7:$C$226,$S6)&"") | L6: =IF($S6="","",'Cover & Instructions'!$B$38) | M6: =IF($S6="","",INDEX('Programme Export'!$F$7:$F$226,$S6)) | N6: =IF($S6="","",INDEX('Programme Export'!$G$7:$G$226,$S6)&"") | O6: =IF($S6="","",IFERROR(P6/M6,0)) | P6: =IF($S6="","",INDEX('Programme Export'!$H$7:$H$226,$S6)) | Q6: =IF($S6="","",INDEX('Programme Export'!$X$7:$X$226,$S6)&"") | R6: =IF($S6="","",INDEX('Programme Export'!$P$7:$P$226,$S6)&"") | S6: =IFERROR(MATCH(5,'Programme Export'!$Y$7:$Y$226,0),"")
A7: =IF($S7="","",6) | B7: =IF($S7="","",1) | C7: =IF($S7="","",INDEX('Programme Export'!$D$7:$D$226,$S7)&"") | D7: =IF($S7="","",INDEX('Programme Export'!$E$7:$E$226,$S7)&"") | E7: =IF($S7="","",INDEX('Programme Export'!$N$7:$N$226,$S7)&"") | F7: {=IF(R7="","",_xlfn.TEXTJOIN(";",TRUE,IFERROR(IF(TRIM(MID(SUBSTITUTE(SUBSTITUTE(SUBSTITUTE(R7,",",";")," ",";"),";",REPT(" ",60)),(ROW($1:$10)-1)*60+1,60))="","",MATCH(TRIM(MID(SUBSTITUTE(SUBSTITUTE(SUBSTITUTE(R7,",",";")," ",";"),";",REPT(" ",60)),(ROW($1:$10)-1)*60+1,60)),$C$2:$C$201,0)),"")))} | G7: =IF($S7="","",INDEX('Programme Export'!$H$7:$H$226,$S7)) | J7: =IF($S7="","",INDEX('Programme Export'!$R$7:$R$226,$S7)&"") | K7: =IF($S7="","",INDEX('Programme Export'!$C$7:$C$226,$S7)&"") | L7: =IF($S7="","",'Cover & Instructions'!$B$38) | M7: =IF($S7="","",INDEX('Programme Export'!$F$7:$F$226,$S7)) | N7: =IF($S7="","",INDEX('Programme Export'!$G$7:$G$226,$S7)&"") | O7: =IF($S7="","",IFERROR(P7/M7,0)) | P7: =IF($S7="","",INDEX('Programme Export'!$H$7:$H$226,$S7)) | Q7: =IF($S7="","",INDEX('Programme Export'!$X$7:$X$226,$S7)&"") | R7: =IF($S7="","",INDEX('Programme Export'!$P$7:$P$226,$S7)&"") | S7: =IFERROR(MATCH(6,'Programme Export'!$Y$7:$Y$226,0),"")
A8: =IF($S8="","",7) | B8: =IF($S8="","",1) | C8: =IF($S8="","",INDEX('Programme Export'!$D$7:$D$226,$S8)&"") | D8: =IF($S8="","",INDEX('Programme Export'!$E$7:$E$226,$S8)&"") | E8: =IF($S8="","",INDEX('Programme Export'!$N$7:$N$226,$S8)&"") | F8: {=IF(R8="","",_xlfn.TEXTJOIN(";",TRUE,IFERROR(IF(TRIM(MID(SUBSTITUTE(SUBSTITUTE(SUBSTITUTE(R8,",",";")," ",";"),";",REPT(" ",60)),(ROW($1:$10)-1)*60+1,60))="","",MATCH(TRIM(MID(SUBSTITUTE(SUBSTITUTE(SUBSTITUTE(R8,",",";")," ",";"),";",REPT(" ",60)),(ROW($1:$10)-1)*60+1,60)),$C$2:$C$201,0)),"")))} | G8: =IF($S8="","",INDEX('Programme Export'!$H$7:$H$226,$S8)) | J8: =IF($S8="","",INDEX('Programme Export'!$R$7:$R$226,$S8)&"") | K8: =IF($S8="","",INDEX('Programme Export'!$C$7:$C$226,$S8)&"") | L8: =IF($S8="","",'Cover & Instructions'!$B$38) | M8: =IF($S8="","",INDEX('Programme Export'!$F$7:$F$226,$S8)) | N8: =IF($S8="","",INDEX('Programme Export'!$G$7:$G$226,$S8)&"") | O8: =IF($S8="","",IFERROR(P8/M8,0)) | P8: =IF($S8="","",INDEX('Programme Export'!$H$7:$H$226,$S8)) | Q8: =IF($S8="","",INDEX('Programme Export'!$X$7:$X$226,$S8)&"") | R8: =IF($S8="","",INDEX('Programme Export'!$P$7:$P$226,$S8)&"") | S8: =IFERROR(MATCH(7,'Programme Export'!$Y$7:$Y$226,0),"")
A9: =IF($S9="","",8) | B9: =IF($S9="","",1) | C9: =IF($S9="","",INDEX('Programme Export'!$D$7:$D$226,$S9)&"") | D9: =IF($S9="","",INDEX('Programme Export'!$E$7:$E$226,$S9)&"") | E9: =IF($S9="","",INDEX('Programme Export'!$N$7:$N$226,$S9)&"") | F9: {=IF(R9="","",_xlfn.TEXTJOIN(";",TRUE,IFERROR(IF(TRIM(MID(SUBSTITUTE(SUBSTITUTE(SUBSTITUTE(R9,",",";")," ",";"),";",REPT(" ",60)),(ROW($1:$10)-1)*60+1,60))="","",MATCH(TRIM(MID(SUBSTITUTE(SUBSTITUTE(SUBSTITUTE(R9,",",";")," ",";"),";",REPT(" ",60)),(ROW($1:$10)-1)*60+1,60)),$C$2:$C$201,0)),"")))} | G9: =IF($S9="","",INDEX('Programme Export'!$H$7:$H$226,$S9)) | J9: =IF($S9="","",INDEX('Programme Export'!$R$7:$R$226,$S9)&"") | K9: =IF($S9="","",INDEX('Programme Export'!$C$7:$C$226,$S9)&"") | L9: =IF($S9="","",'Cover & Instructions'!$B$38) | M9: =IF($S9="","",INDEX('Programme Export'!$F$7:$F$226,$S9)) | N9: =IF($S9="","",INDEX('Programme Export'!$G$7:$G$226,$S9)&"") | O9: =IF($S9="","",IFERROR(P9/M9,0)) | P9: =IF($S9="","",INDEX('Programme Export'!$H$7:$H$226,$S9)) | Q9: =IF($S9="","",INDEX('Programme Export'!$X$7:$X$226,$S9)&"") | R9: =IF($S9="","",INDEX('Programme Export'!$P$7:$P$226,$S9)&"") | S9: =IFERROR(MATCH(8,'Programme Export'!$Y$7:$Y$226,0),"")
A10: =IF($S10="","",9) | B10: =IF($S10="","",1) | C10: =IF($S10="","",INDEX('Programme Export'!$D$7:$D$226,$S10)&"") | D10: =IF($S10="","",INDEX('Programme Export'!$E$7:$E$226,$S10)&"") | E10: =IF($S10="","",INDEX('Programme Export'!$N$7:$N$226,$S10)&"") | F10: {=IF(R10="","",_xlfn.TEXTJOIN(";",TRUE,IFERROR(IF(TRIM(MID(SUBSTITUTE(SUBSTITUTE(SUBSTITUTE(R10,",",";")," ",";"),";",REPT(" ",60)),(ROW($1:$10)-1)*60+1,60))="","",MATCH(TRIM(MID(SUBSTITUTE(SUBSTITUTE(SUBSTITUTE(R10,",",";")," ",";"),";",REPT(" ",60)),(ROW($1:$10)-1)*60+1,60)),$C$2:$C$201,0)),"")))} | G10: =IF($S10="","",INDEX('Programme Export'!$H$7:$H$226,$S10)) | J10: =IF($S10="","",INDEX('Programme Export'!$R$7:$R$226,$S10)&"") | K10: =IF($S10="","",INDEX('Programme Export'!$C$7:$C$226,$S10)&"") | L10: =IF($S10="","",'Cover & Instructions'!$B$38) | M10: =IF($S10="","",INDEX('Programme Export'!$F$7:$F$226,$S10)) | N10: =IF($S10="","",INDEX('Programme Export'!$G$7:$G$226,$S10)&"") | O10: =IF($S10="","",IFERROR(P10/M10,0)) | P10: =IF($S10="","",INDEX('Programme Export'!$H$7:$H$226,$S10)) | Q10: =IF($S10="","",INDEX('Programme Export'!$X$7:$X$226,$S10)&"") | R10: =IF($S10="","",INDEX('Programme Export'!$P$7:$P$226,$S10)&"") | S10: =IFERROR(MATCH(9,'Programme Export'!$Y$7:$Y$226,0),"")
A11: =IF($S11="","",10) | B11: =IF($S11="","",1) | C11: =IF($S11="","",INDEX('Programme Export'!$D$7:$D$226,$S11)&"") | D11: =IF($S11="","",INDEX('Programme Export'!$E$7:$E$226,$S11)&"") | E11: =IF($S11="","",INDEX('Programme Export'!$N$7:$N$226,$S11)&"") | F11: {=IF(R11="","",_xlfn.TEXTJOIN(";",TRUE,IFERROR(IF(TRIM(MID(SUBSTITUTE(SUBSTITUTE(SUBSTITUTE(R11,",",";")," ",";"),";",REPT(" ",60)),(ROW($1:$10)-1)*60+1,60))="","",MATCH(TRIM(MID(SUBSTITUTE(SUBSTITUTE(SUBSTITUTE(R11,",",";")," ",";"),";",REPT(" ",60)),(ROW($1:$10)-1)*60+1,60)),$C$2:$C$201,0)),"")))} | G11: =IF($S11="","",INDEX('Programme Export'!$H$7:$H$226,$S11)) | J11: =IF($S11="","",INDEX('Programme Export'!$R$7:$R$226,$S11)&"") | K11: =IF($S11="","",INDEX('Programme Export'!$C$7:$C$226,$S11)&"") | L11: =IF($S11="","",'Cover & Instructions'!$B$38) | M11: =IF($S11="","",INDEX('Programme Export'!$F$7:$F$226,$S11)) | N11: =IF($S11="","",INDEX('Programme Export'!$G$7:$G$226,$S11)&"") | O11: =IF($S11="","",IFERROR(P11/M11,0)) | P11: =IF($S11="","",INDEX('Programme Export'!$H$7:$H$226,$S11)) | Q11: =IF($S11="","",INDEX('Programme Export'!$X$7:$X$226,$S11)&"") | R11: =IF($S11="","",INDEX('Programme Export'!$P$7:$P$226,$S11)&"") | S11: =IFERROR(MATCH(10,'Programme Export'!$Y$7:$Y$226,0),"")
A12: =IF($S12="","",11) | B12: =IF($S12="","",1) | C12: =IF($S12="","",INDEX('Programme Export'!$D$7:$D$226,$S12)&"") | D12: =IF($S12="","",INDEX('Programme Export'!$E$7:$E$226,$S12)&"") | E12: =IF($S12="","",INDEX('Programme Export'!$N$7:$N$226,$S12)&"") | F12: {=IF(R12="","",_xlfn.TEXTJOIN(";",TRUE,IFERROR(IF(TRIM(MID(SUBSTITUTE(SUBSTITUTE(SUBSTITUTE(R12,",",";")," ",";"),";",REPT(" ",60)),(ROW($1:$10)-1)*60+1,60))="","",MATCH(TRIM(MID(SUBSTITUTE(SUBSTITUTE(SUBSTITUTE(R12,",",";")," ",";"),";",REPT(" ",60)),(ROW($1:$10)-1)*60+1,60)),$C$2:$C$201,0)),"")))} | G12: =IF($S12="","",INDEX('Programme Export'!$H$7:$H$226,$S12)) | J12: =IF($S12="","",INDEX('Programme Export'!$R$7:$R$226,$S12)&"") | K12: =IF($S12="","",INDEX('Programme Export'!$C$7:$C$226,$S12)&"") | L12: =IF($S12="","",'Cover & Instructions'!$B$38) | M12: =IF($S12="","",INDEX('Programme Export'!$F$7:$F$226,$S12)) | N12: =IF($S12="","",INDEX('Programme Export'!$G$7:$G$226,$S12)&"") | O12: =IF($S12="","",IFERROR(P12/M12,0)) | P12: =IF($S12="","",INDEX('Programme Export'!$H$7:$H$226,$S12)) | Q12: =IF($S12="","",INDEX('Programme Export'!$X$7:$X$226,$S12)&"") | R12: =IF($S12="","",INDEX('Programme Export'!$P$7:$P$226,$S12)&"") | S12: =IFERROR(MATCH(11,'Programme Export'!$Y$7:$Y$226,0),"")
A13: =IF($S13="","",12) | B13: =IF($S13="","",1) | C13: =IF($S13="","",INDEX('Programme Export'!$D$7:$D$226,$S13)&"") | D13: =IF($S13="","",INDEX('Programme Export'!$E$7:$E$226,$S13)&"") | E13: =IF($S13="","",INDEX('Programme Export'!$N$7:$N$226,$S13)&"") | F13: {=IF(R13="","",_xlfn.TEXTJOIN(";",TRUE,IFERROR(IF(TRIM(MID(SUBSTITUTE(SUBSTITUTE(SUBSTITUTE(R13,",",";")," ",";"),";",REPT(" ",60)),(ROW($1:$10)-1)*60+1,60))="","",MATCH(TRIM(MID(SUBSTITUTE(SUBSTITUTE(SUBSTITUTE(R13,",",";")," ",";"),";",REPT(" ",60)),(ROW($1:$10)-1)*60+1,60)),$C$2:$C$201,0)),"")))} | G13: =IF($S13="","",INDEX('Programme Export'!$H$7:$H$226,$S13)) | J13: =IF($S13="","",INDEX('Programme Export'!$R$7:$R$226,$S13)&"") | K13: =IF($S13="","",INDEX('Programme Export'!$C$7:$C$226,$S13)&"") | L13: =IF($S13="","",'Cover & Instructions'!$B$38) | M13: =IF($S13="","",INDEX('Programme Export'!$F$7:$F$226,$S13)) | N13: =IF($S13="","",INDEX('Programme Export'!$G$7:$G$226,$S13)&"") | O13: =IF($S13="","",IFERROR(P13/M13,0)) | P13: =IF($S13="","",INDEX('Programme Export'!$H$7:$H$226,$S13)) | Q13: =IF($S13="","",INDEX('Programme Export'!$X$7:$X$226,$S13)&"") | R13: =IF($S13="","",INDEX('Programme Export'!$P$7:$P$226,$S13)&"") | S13: =IFERROR(MATCH(12,'Programme Export'!$Y$7:$Y$226,0),"")
A14: =IF($S14="","",13) | B14: =IF($S14="","",1) | C14: =IF($S14="","",INDEX('Programme Export'!$D$7:$D$226,$S14)&"") | D14: =IF($S14="","",INDEX('Programme Export'!$E$7:$E$226,$S14)&"") | E14: =IF($S14="","",INDEX('Programme Export'!$N$7:$N$226,$S14)&"") | F14: {=IF(R14="","",_xlfn.TEXTJOIN(";",TRUE,IFERROR(IF(TRIM(MID(SUBSTITUTE(SUBSTITUTE(SUBSTITUTE(R14,",",";")," ",";"),";",REPT(" ",60)),(ROW($1:$10)-1)*60+1,60))="","",MATCH(TRIM(MID(SUBSTITUTE(SUBSTITUTE(SUBSTITUTE(R14,",",";")," ",";"),";",REPT(" ",60)),(ROW($1:$10)-1)*60+1,60)),$C$2:$C$201,0)),"")))} | G14: =IF($S14="","",INDEX('Programme Export'!$H$7:$H$226,$S14)) | J14: =IF($S14="","",INDEX('Programme Export'!$R$7:$R$226,$S14)&"") | K14: =IF($S14="","",INDEX('Programme Export'!$C$7:$C$226,$S14)&"") | L14: =IF($S14="","",'Cover & Instructions'!$B$38) | M14: =IF($S14="","",INDEX('Programme Export'!$F$7:$F$226,$S14)) | N14: =IF($S14="","",INDEX('Programme Export'!$G$7:$G$226,$S14)&"") | O14: =IF($S14="","",IFERROR(P14/M14,0)) | P14: =IF($S14="","",INDEX('Programme Export'!$H$7:$H$226,$S14)) | Q14: =IF($S14="","",INDEX('Programme Export'!$X$7:$X$226,$S14)&"") | R14: =IF($S14="","",INDEX('Programme Export'!$P$7:$P$226,$S14)&"") | S14: =IFERROR(MATCH(13,'Programme Export'!$Y$7:$Y$226,0),"")
A15: =IF($S15="","",14) | B15: =IF($S15="","",1) | C15: =IF($S15="","",INDEX('Programme Export'!$D$7:$D$226,$S15)&"") | D15: =IF($S15="","",INDEX('Programme Export'!$E$7:$E$226,$S15)&"") | E15: =IF($S15="","",INDEX('Programme Export'!$N$7:$N$226,$S15)&"") | F15: {=IF(R15="","",_xlfn.TEXTJOIN(";",TRUE,IFERROR(IF(TRIM(MID(SUBSTITUTE(SUBSTITUTE(SUBSTITUTE(R15,",",";")," ",";"),";",REPT(" ",60)),(ROW($1:$10)-1)*60+1,60))="","",MATCH(TRIM(MID(SUBSTITUTE(SUBSTITUTE(SUBSTITUTE(R15,",",";")," ",";"),";",REPT(" ",60)),(ROW($1:$10)-1)*60+1,60)),$C$2:$C$201,0)),"")))} | G15: =IF($S15="","",INDEX('Programme Export'!$H$7:$H$226,$S15)) | J15: =IF($S15="","",INDEX('Programme Export'!$R$7:$R$226,$S15)&"") | K15: =IF($S15="","",INDEX('Programme Export'!$C$7:$C$226,$S15)&"") | L15: =IF($S15="","",'Cover & Instructions'!$B$38) | M15: =IF($S15="","",INDEX('Programme Export'!$F$7:$F$226,$S15)) | N15: =IF($S15="","",INDEX('Programme Export'!$G$7:$G$226,$S15)&"") | O15: =IF($S15="","",IFERROR(P15/M15,0)) | P15: =IF($S15="","",INDEX('Programme Export'!$H$7:$H$226,$S15)) | Q15: =IF($S15="","",INDEX('Programme Export'!$X$7:$X$226,$S15)&"") | R15: =IF($S15="","",INDEX('Programme Export'!$P$7:$P$226,$S15)&"") | S15: =IFERROR(MATCH(14,'Programme Export'!$Y$7:$Y$226,0),"")
A16: =IF($S16="","",15) | B16: =IF($S16="","",1) | C16: =IF($S16="","",INDEX('Programme Export'!$D$7:$D$226,$S16)&"") | D16: =IF($S16="","",INDEX('Programme Export'!$E$7:$E$226,$S16)&"") | E16: =IF($S16="","",INDEX('Programme Export'!$N$7:$N$226,$S16)&"") | F16: {=IF(R16="","",_xlfn.TEXTJOIN(";",TRUE,IFERROR(IF(TRIM(MID(SUBSTITUTE(SUBSTITUTE(SUBSTITUTE(R16,",",";")," ",";"),";",REPT(" ",60)),(ROW($1:$10)-1)*60+1,60))="","",MATCH(TRIM(MID(SUBSTITUTE(SUBSTITUTE(SUBSTITUTE(R16,",",";")," ",";"),";",REPT(" ",60)),(ROW($1:$10)-1)*60+1,60)),$C$2:$C$201,0)),"")))} | G16: =IF($S16="","",INDEX('Programme Export'!$H$7:$H$226,$S16)) | J16: =IF($S16="","",INDEX('Programme Export'!$R$7:$R$226,$S16)&"") | K16: =IF($S16="","",INDEX('Programme Export'!$C$7:$C$226,$S16)&"") | L16: =IF($S16="","",'Cover & Instructions'!$B$38) | M16: =IF($S16="","",INDEX('Programme Export'!$F$7:$F$226,$S16)) | N16: =IF($S16="","",INDEX('Programme Export'!$G$7:$G$226,$S16)&"") | O16: =IF($S16="","",IFERROR(P16/M16,0)) | P16: =IF($S16="","",INDEX('Programme Export'!$H$7:$H$226,$S16)) | Q16: =IF($S16="","",INDEX('Programme Export'!$X$7:$X$226,$S16)&"") | R16: =IF($S16="","",INDEX('Programme Export'!$P$7:$P$226,$S16)&"") | S16: =IFERROR(MATCH(15,'Programme Export'!$Y$7:$Y$226,0),"")
A17: =IF($S17="","",16) | B17: =IF($S17="","",1) | C17: =IF($S17="","",INDEX('Programme Export'!$D$7:$D$226,$S17)&"") | D17: =IF($S17="","",INDEX('Programme Export'!$E$7:$E$226,$S17)&"") | E17: =IF($S17="","",INDEX('Programme Export'!$N$7:$N$226,$S17)&"") | F17: {=IF(R17="","",_xlfn.TEXTJOIN(";",TRUE,IFERROR(IF(TRIM(MID(SUBSTITUTE(SUBSTITUTE(SUBSTITUTE(R17,",",";")," ",";"),";",REPT(" ",60)),(ROW($1:$10)-1)*60+1,60))="","",MATCH(TRIM(MID(SUBSTITUTE(SUBSTITUTE(SUBSTITUTE(R17,",",";")," ",";"),";",REPT(" ",60)),(ROW($1:$10)-1)*60+1,60)),$C$2:$C$201,0)),"")))} | G17: =IF($S17="","",INDEX('Programme Export'!$H$7:$H$226,$S17)) | J17: =IF($S17="","",INDEX('Programme Export'!$R$7:$R$226,$S17)&"") | K17: =IF($S17="","",INDEX('Programme Export'!$C$7:$C$226,$S17)&"") | L17: =IF($S17="","",'Cover & Instructions'!$B$38) | M17: =IF($S17="","",INDEX('Programme Export'!$F$7:$F$226,$S17)) | N17: =IF($S17="","",INDEX('Programme Export'!$G$7:$G$226,$S17)&"") | O17: =IF($S17="","",IFERROR(P17/M17,0)) | P17: =IF($S17="","",INDEX('Programme Export'!$H$7:$H$226,$S17)) | Q17: =IF($S17="","",INDEX('Programme Export'!$X$7:$X$226,$S17)&"") | R17: =IF($S17="","",INDEX('Programme Export'!$P$7:$P$226,$S17)&"") | S17: =IFERROR(MATCH(16,'Programme Export'!$Y$7:$Y$226,0),"")
A18: =IF($S18="","",17) | B18: =IF($S18="","",1) | C18: =IF($S18="","",INDEX('Programme Export'!$D$7:$D$226,$S18)&"") | D18: =IF($S18="","",INDEX('Programme Export'!$E$7:$E$226,$S18)&"") | E18: =IF($S18="","",INDEX('Programme Export'!$N$7:$N$226,$S18)&"") | F18: {=IF(R18="","",_xlfn.TEXTJOIN(";",TRUE,IFERROR(IF(TRIM(MID(SUBSTITUTE(SUBSTITUTE(SUBSTITUTE(R18,",",";")," ",";"),";",REPT(" ",60)),(ROW($1:$10)-1)*60+1,60))="","",MATCH(TRIM(MID(SUBSTITUTE(SUBSTITUTE(SUBSTITUTE(R18,",",";")," ",";"),";",REPT(" ",60)),(ROW($1:$10)-1)*60+1,60)),$C$2:$C$201,0)),"")))} | G18: =IF($S18="","",INDEX('Programme Export'!$H$7:$H$226,$S18)) | J18: =IF($S18="","",INDEX('Programme Export'!$R$7:$R$226,$S18)&"") | K18: =IF($S18="","",INDEX('Programme Export'!$C$7:$C$226,$S18)&"") | L18: =IF($S18="","",'Cover & Instructions'!$B$38) | M18: =IF($S18="","",INDEX('Programme Export'!$F$7:$F$226,$S18)) | N18: =IF($S18="","",INDEX('Programme Export'!$G$7:$G$226,$S18)&"") | O18: =IF($S18="","",IFERROR(P18/M18,0)) | P18: =IF($S18="","",INDEX('Programme Export'!$H$7:$H$226,$S18)) | Q18: =IF($S18="","",INDEX('Programme Export'!$X$7:$X$226,$S18)&"") | R18: =IF($S18="","",INDEX('Programme Export'!$P$7:$P$226,$S18)&"") | S18: =IFERROR(MATCH(17,'Programme Export'!$Y$7:$Y$226,0),"")
A19: =IF($S19="","",18) | B19: =IF($S19="","",1) | C19: =IF($S19="","",INDEX('Programme Export'!$D$7:$D$226,$S19)&"") | D19: =IF($S19="","",INDEX('Programme Export'!$E$7:$E$226,$S19)&"") | E19: =IF($S19="","",INDEX('Programme Export'!$N$7:$N$226,$S19)&"") | F19: {=IF(R19="","",_xlfn.TEXTJOIN(";",TRUE,IFERROR(IF(TRIM(MID(SUBSTITUTE(SUBSTITUTE(SUBSTITUTE(R19,",",";")," ",";"),";",REPT(" ",60)),(ROW($1:$10)-1)*60+1,60))="","",MATCH(TRIM(MID(SUBSTITUTE(SUBSTITUTE(SUBSTITUTE(R19,",",";")," ",";"),";",REPT(" ",60)),(ROW($1:$10)-1)*60+1,60)),$C$2:$C$201,0)),"")))} | G19: =IF($S19="","",INDEX('Programme Export'!$H$7:$H$226,$S19)) | J19: =IF($S19="","",INDEX('Programme Export'!$R$7:$R$226,$S19)&"") | K19: =IF($S19="","",INDEX('Programme Export'!$C$7:$C$226,$S19)&"") | L19: =IF($S19="","",'Cover & Instructions'!$B$38) | M19: =IF($S19="","",INDEX('Programme Export'!$F$7:$F$226,$S19)) | N19: =IF($S19="","",INDEX('Programme Export'!$G$7:$G$226,$S19)&"") | O19: =IF($S19="","",IFERROR(P19/M19,0)) | P19: =IF($S19="","",INDEX('Programme Export'!$H$7:$H$226,$S19)) | Q19: =IF($S19="","",INDEX('Programme Export'!$X$7:$X$226,$S19)&"") | R19: =IF($S19="","",INDEX('Programme Export'!$P$7:$P$226,$S19)&"") | S19: =IFERROR(MATCH(18,'Programme Export'!$Y$7:$Y$226,0),"")
A20: =IF($S20="","",19) | B20: =IF($S20="","",1) | C20: =IF($S20="","",INDEX('Programme Export'!$D$7:$D$226,$S20)&"") | D20: =IF($S20="","",INDEX('Programme Export'!$E$7:$E$226,$S20)&"") | E20: =IF($S20="","",INDEX('Programme Export'!$N$7:$N$226,$S20)&"") | F20: {=IF(R20="","",_xlfn.TEXTJOIN(";",TRUE,IFERROR(IF(TRIM(MID(SUBSTITUTE(SUBSTITUTE(SUBSTITUTE(R20,",",";")," ",";"),";",REPT(" ",60)),(ROW($1:$10)-1)*60+1,60))="","",MATCH(TRIM(MID(SUBSTITUTE(SUBSTITUTE(SUBSTITUTE(R20,",",";")," ",";"),";",REPT(" ",60)),(ROW($1:$10)-1)*60+1,60)),$C$2:$C$201,0)),"")))} | G20: =IF($S20="","",INDEX('Programme Export'!$H$7:$H$226,$S20)) | J20: =IF($S20="","",INDEX('Programme Export'!$R$7:$R$226,$S20)&"") | K20: =IF($S20="","",INDEX('Programme Export'!$C$7:$C$226,$S20)&"") | L20: =IF($S20="","",'Cover & Instructions'!$B$38) | M20: =IF($S20="","",INDEX('Programme Export'!$F$7:$F$226,$S20)) | N20: =IF($S20="","",INDEX('Programme Export'!$G$7:$G$226,$S20)&"") | O20: =IF($S20="","",IFERROR(P20/M20,0)) | P20: =IF($S20="","",INDEX('Programme Export'!$H$7:$H$226,$S20)) | Q20: =IF($S20="","",INDEX('Programme Export'!$X$7:$X$226,$S20)&"") | R20: =IF($S20="","",INDEX('Programme Export'!$P$7:$P$226,$S20)&"") | S20: =IFERROR(MATCH(19,'Programme Export'!$Y$7:$Y$226,0),"")
A21: =IF($S21="","",20) | B21: =IF($S21="","",1) | C21: =IF($S21="","",INDEX('Programme Export'!$D$7:$D$226,$S21)&"") | D21: =IF($S21="","",INDEX('Programme Export'!$E$7:$E$226,$S21)&"") | E21: =IF($S21="","",INDEX('Programme Export'!$N$7:$N$226,$S21)&"") | F21: {=IF(R21="","",_xlfn.TEXTJOIN(";",TRUE,IFERROR(IF(TRIM(MID(SUBSTITUTE(SUBSTITUTE(SUBSTITUTE(R21,",",";")," ",";"),";",REPT(" ",60)),(ROW($1:$10)-1)*60+1,60))="","",MATCH(TRIM(MID(SUBSTITUTE(SUBSTITUTE(SUBSTITUTE(R21,",",";")," ",";"),";",REPT(" ",60)),(ROW($1:$10)-1)*60+1,60)),$C$2:$C$201,0)),"")))} | G21: =IF($S21="","",INDEX('Programme Export'!$H$7:$H$226,$S21)) | J21: =IF($S21="","",INDEX('Programme Export'!$R$7:$R$226,$S21)&"") | K21: =IF($S21="","",INDEX('Programme Export'!$C$7:$C$226,$S21)&"") | L21: =IF($S21="","",'Cover & Instructions'!$B$38) | M21: =IF($S21="","",INDEX('Programme Export'!$F$7:$F$226,$S21)) | N21: =IF($S21="","",INDEX('Programme Export'!$G$7:$G$226,$S21)&"") | O21: =IF($S21="","",IFERROR(P21/M21,0)) | P21: =IF($S21="","",INDEX('Programme Export'!$H$7:$H$226,$S21)) | Q21: =IF($S21="","",INDEX('Programme Export'!$X$7:$X$226,$S21)&"") | R21: =IF($S21="","",INDEX('Programme Export'!$P$7:$P$226,$S21)&"") | S21: =IFERROR(MATCH(20,'Programme Export'!$Y$7:$Y$226,0),"")
A22: =IF($S22="","",21) | B22: =IF($S22="","",1) | C22: =IF($S22="","",INDEX('Programme Export'!$D$7:$D$226,$S22)&"") | D22: =IF($S22="","",INDEX('Programme Export'!$E$7:$E$226,$S22)&"") | E22: =IF($S22="","",INDEX('Programme Export'!$N$7:$N$226,$S22)&"") | F22: {=IF(R22="","",_xlfn.TEXTJOIN(";",TRUE,IFERROR(IF(TRIM(MID(SUBSTITUTE(SUBSTITUTE(SUBSTITUTE(R22,",",";")," ",";"),";",REPT(" ",60)),(ROW($1:$10)-1)*60+1,60))="","",MATCH(TRIM(MID(SUBSTITUTE(SUBSTITUTE(SUBSTITUTE(R22,",",";")," ",";"),";",REPT(" ",60)),(ROW($1:$10)-1)*60+1,60)),$C$2:$C$201,0)),"")))} | G22: =IF($S22="","",INDEX('Programme Export'!$H$7:$H$226,$S22)) | J22: =IF($S22="","",INDEX('Programme Export'!$R$7:$R$226,$S22)&"") | K22: =IF($S22="","",INDEX('Programme Export'!$C$7:$C$226,$S22)&"") | L22: =IF($S22="","",'Cover & Instructions'!$B$38) | M22: =IF($S22="","",INDEX('Programme Export'!$F$7:$F$226,$S22)) | N22: =IF($S22="","",INDEX('Programme Export'!$G$7:$G$226,$S22)&"") | O22: =IF($S22="","",IFERROR(P22/M22,0)) | P22: =IF($S22="","",INDEX('Programme Export'!$H$7:$H$226,$S22)) | Q22: =IF($S22="","",INDEX('Programme Export'!$X$7:$X$226,$S22)&"") | R22: =IF($S22="","",INDEX('Programme Export'!$P$7:$P$226,$S22)&"") | S22: =IFERROR(MATCH(21,'Programme Export'!$Y$7:$Y$226,0),"")
A23: =IF($S23="","",22) | B23: =IF($S23="","",1) | C23: =IF($S23="","",INDEX('Programme Export'!$D$7:$D$226,$S23)&"") | D23: =IF($S23="","",INDEX('Programme Export'!$E$7:$E$226,$S23)&"") | E23: =IF($S23="","",INDEX('Programme Export'!$N$7:$N$226,$S23)&"") | F23: {=IF(R23="","",_xlfn.TEXTJOIN(";",TRUE,IFERROR(IF(TRIM(MID(SUBSTITUTE(SUBSTITUTE(SUBSTITUTE(R23,",",";")," ",";"),";",REPT(" ",60)),(ROW($1:$10)-1)*60+1,60))="","",MATCH(TRIM(MID(SUBSTITUTE(SUBSTITUTE(SUBSTITUTE(R23,",",";")," ",";"),";",REPT(" ",60)),(ROW($1:$10)-1)*60+1,60)),$C$2:$C$201,0)),"")))} | G23: =IF($S23="","",INDEX('Programme Export'!$H$7:$H$226,$S23)) | J23: =IF($S23="","",INDEX('Programme Export'!$R$7:$R$226,$S23)&"") | K23: =IF($S23="","",INDEX('Programme Export'!$C$7:$C$226,$S23)&"") | L23: =IF($S23="","",'Cover & Instructions'!$B$38) | M23: =IF($S23="","",INDEX('Programme Export'!$F$7:$F$226,$S23)) | N23: =IF($S23="","",INDEX('Programme Export'!$G$7:$G$226,$S23)&"") | O23: =IF($S23="","",IFERROR(P23/M23,0)) | P23: =IF($S23="","",INDEX('Programme Export'!$H$7:$H$226,$S23)) | Q23: =IF($S23="","",INDEX('Programme Export'!$X$7:$X$226,$S23)&"") | R23: =IF($S23="","",INDEX('Programme Export'!$P$7:$P$226,$S23)&"") | S23: =IFERROR(MATCH(22,'Programme Export'!$Y$7:$Y$226,0),"")
A24: =IF($S24="","",23) | B24: =IF($S24="","",1) | C24: =IF($S24="","",INDEX('Programme Export'!$D$7:$D$226,$S24)&"") | D24: =IF($S24="","",INDEX('Programme Export'!$E$7:$E$226,$S24)&"") | E24: =IF($S24="","",INDEX('Programme Export'!$N$7:$N$226,$S24)&"") | F24: {=IF(R24="","",_xlfn.TEXTJOIN(";",TRUE,IFERROR(IF(TRIM(MID(SUBSTITUTE(SUBSTITUTE(SUBSTITUTE(R24,",",";")," ",";"),";",REPT(" ",60)),(ROW($1:$10)-1)*60+1,60))="","",MATCH(TRIM(MID(SUBSTITUTE(SUBSTITUTE(SUBSTITUTE(R24,",",";")," ",";"),";",REPT(" ",60)),(ROW($1:$10)-1)*60+1,60)),$C$2:$C$201,0)),"")))} | G24: =IF($S24="","",INDEX('Programme Export'!$H$7:$H$226,$S24)) | J24: =IF($S24="","",INDEX('Programme Export'!$R$7:$R$226,$S24)&"") | K24: =IF($S24="","",INDEX('Programme Export'!$C$7:$C$226,$S24)&"") | L24: =IF($S24="","",'Cover & Instructions'!$B$38) | M24: =IF($S24="","",INDEX('Programme Export'!$F$7:$F$226,$S24)) | N24: =IF($S24="","",INDEX('Programme Export'!$G$7:$G$226,$S24)&"") | O24: =IF($S24="","",IFERROR(P24/M24,0)) | P24: =IF($S24="","",INDEX('Programme Export'!$H$7:$H$226,$S24)) | Q24: =IF($S24="","",INDEX('Programme Export'!$X$7:$X$226,$S24)&"") | R24: =IF($S24="","",INDEX('Programme Export'!$P$7:$P$226,$S24)&"") | S24: =IFERROR(MATCH(23,'Programme Export'!$Y$7:$Y$226,0),"")
A25: =IF($S25="","",24) | B25: =IF($S25="","",1) | C25: =IF($S25="","",INDEX('Programme Export'!$D$7:$D$226,$S25)&"") | D25: =IF($S25="","",INDEX('Programme Export'!$E$7:$E$226,$S25)&"") | E25: =IF($S25="","",INDEX('Programme Export'!$N$7:$N$226,$S25)&"") | F25: {=IF(R25="","",_xlfn.TEXTJOIN(";",TRUE,IFERROR(IF(TRIM(MID(SUBSTITUTE(SUBSTITUTE(SUBSTITUTE(R25,",",";")," ",";"),";",REPT(" ",60)),(ROW($1:$10)-1)*60+1,60))="","",MATCH(TRIM(MID(SUBSTITUTE(SUBSTITUTE(SUBSTITUTE(R25,",",";")," ",";"),";",REPT(" ",60)),(ROW($1:$10)-1)*60+1,60)),$C$2:$C$201,0)),"")))} | G25: =IF($S25="","",INDEX('Programme Export'!$H$7:$H$226,$S25)) | J25: =IF($S25="","",INDEX('Programme Export'!$R$7:$R$226,$S25)&"") | K25: =IF($S25="","",INDEX('Programme Export'!$C$7:$C$226,$S25)&"") | L25: =IF($S25="","",'Cover & Instructions'!$B$38) | M25: =IF($S25="","",INDEX('Programme Export'!$F$7:$F$226,$S25)) | N25: =IF($S25="","",INDEX('Programme Export'!$G$7:$G$226,$S25)&"") | O25: =IF($S25="","",IFERROR(P25/M25,0)) | P25: =IF($S25="","",INDEX('Programme Export'!$H$7:$H$226,$S25)) | Q25: =IF($S25="","",INDEX('Programme Export'!$X$7:$X$226,$S25)&"") | R25: =IF($S25="","",INDEX('Programme Export'!$P$7:$P$226,$S25)&"") | S25: =IFERROR(MATCH(24,'Programme Export'!$Y$7:$Y$226,0),"")
A26: =IF($S26="","",25) | B26: =IF($S26="","",1) | C26: =IF($S26="","",INDEX('Programme Export'!$D$7:$D$226,$S26)&"") | D26: =IF($S26="","",INDEX('Programme Export'!$E$7:$E$226,$S26)&"") | E26: =IF($S26="","",INDEX('Programme Export'!$N$7:$N$226,$S26)&"") | F26: {=IF(R26="","",_xlfn.TEXTJOIN(";",TRUE,IFERROR(IF(TRIM(MID(SUBSTITUTE(SUBSTITUTE(SUBSTITUTE(R26,",",";")," ",";"),";",REPT(" ",60)),(ROW($1:$10)-1)*60+1,60))="","",MATCH(TRIM(MID(SUBSTITUTE(SUBSTITUTE(SUBSTITUTE(R26,",",";")," ",";"),";",REPT(" ",60)),(ROW($1:$10)-1)*60+1,60)),$C$2:$C$201,0)),"")))} | G26: =IF($S26="","",INDEX('Programme Export'!$H$7:$H$226,$S26)) | J26: =IF($S26="","",INDEX('Programme Export'!$R$7:$R$226,$S26)&"") | K26: =IF($S26="","",INDEX('Programme Export'!$C$7:$C$226,$S26)&"") | L26: =IF($S26="","",'Cover & Instructions'!$B$38) | M26: =IF($S26="","",INDEX('Programme Export'!$F$7:$F$226,$S26)) | N26: =IF($S26="","",INDEX('Programme Export'!$G$7:$G$226,$S26)&"") | O26: =IF($S26="","",IFERROR(P26/M26,0)) | P26: =IF($S26="","",INDEX('Programme Export'!$H$7:$H$226,$S26)) | Q26: =IF($S26="","",INDEX('Programme Export'!$X$7:$X$226,$S26)&"") | R26: =IF($S26="","",INDEX('Programme Export'!$P$7:$P$226,$S26)&"") | S26: =IFERROR(MATCH(25,'Programme Export'!$Y$7:$Y$226,0),"")
A27: =IF($S27="","",26) | B27: =IF($S27="","",1) | C27: =IF($S27="","",INDEX('Programme Export'!$D$7:$D$226,$S27)&"") | D27: =IF($S27="","",INDEX('Programme Export'!$E$7:$E$226,$S27)&"") | E27: =IF($S27="","",INDEX('Programme Export'!$N$7:$N$226,$S27)&"") | F27: {=IF(R27="","",_xlfn.TEXTJOIN(";",TRUE,IFERROR(IF(TRIM(MID(SUBSTITUTE(SUBSTITUTE(SUBSTITUTE(R27,",",";")," ",";"),";",REPT(" ",60)),(ROW($1:$10)-1)*60+1,60))="","",MATCH(TRIM(MID(SUBSTITUTE(SUBSTITUTE(SUBSTITUTE(R27,",",";")," ",";"),";",REPT(" ",60)),(ROW($1:$10)-1)*60+1,60)),$C$2:$C$201,0)),"")))} | G27: =IF($S27="","",INDEX('Programme Export'!$H$7:$H$226,$S27)) | J27: =IF($S27="","",INDEX('Programme Export'!$R$7:$R$226,$S27)&"") | K27: =IF($S27="","",INDEX('Programme Export'!$C$7:$C$226,$S27)&"") | L27: =IF($S27="","",'Cover & Instructions'!$B$38) | M27: =IF($S27="","",INDEX('Programme Export'!$F$7:$F$226,$S27)) | N27: =IF($S27="","",INDEX('Programme Export'!$G$7:$G$226,$S27)&"") | O27: =IF($S27="","",IFERROR(P27/M27,0)) | P27: =IF($S27="","",INDEX('Programme Export'!$H$7:$H$226,$S27)) | Q27: =IF($S27="","",INDEX('Programme Export'!$X$7:$X$226,$S27)&"") | R27: =IF($S27="","",INDEX('Programme Export'!$P$7:$P$226,$S27)&"") | S27: =IFERROR(MATCH(26,'Programme Export'!$Y$7:$Y$226,0),"")
A28: =IF($S28="","",27) | B28: =IF($S28="","",1) | C28: =IF($S28="","",INDEX('Programme Export'!$D$7:$D$226,$S28)&"") | D28: =IF($S28="","",INDEX('Programme Export'!$E$7:$E$226,$S28)&"") | E28: =IF($S28="","",INDEX('Programme Export'!$N$7:$N$226,$S28)&"") | F28: {=IF(R28="","",_xlfn.TEXTJOIN(";",TRUE,IFERROR(IF(TRIM(MID(SUBSTITUTE(SUBSTITUTE(SUBSTITUTE(R28,",",";")," ",";"),";",REPT(" ",60)),(ROW($1:$10)-1)*60+1,60))="","",MATCH(TRIM(MID(SUBSTITUTE(SUBSTITUTE(SUBSTITUTE(R28,",",";")," ",";"),";",REPT(" ",60)),(ROW($1:$10)-1)*60+1,60)),$C$2:$C$201,0)),"")))} | G28: =IF($S28="","",INDEX('Programme Export'!$H$7:$H$226,$S28)) | J28: =IF($S28="","",INDEX('Programme Export'!$R$7:$R$226,$S28)&"") | K28: =IF($S28="","",INDEX('Programme Export'!$C$7:$C$226,$S28)&"") | L28: =IF($S28="","",'Cover & Instructions'!$B$38) | M28: =IF($S28="","",INDEX('Programme Export'!$F$7:$F$226,$S28)) | N28: =IF($S28="","",INDEX('Programme Export'!$G$7:$G$226,$S28)&"") | O28: =IF($S28="","",IFERROR(P28/M28,0)) | P28: =IF($S28="","",INDEX('Programme Export'!$H$7:$H$226,$S28)) | Q28: =IF($S28="","",INDEX('Programme Export'!$X$7:$X$226,$S28)&"") | R28: =IF($S28="","",INDEX('Programme Export'!$P$7:$P$226,$S28)&"") | S28: =IFERROR(MATCH(27,'Programme Export'!$Y$7:$Y$226,0),"")
A29: =IF($S29="","",28) | B29: =IF($S29="","",1) | C29: =IF($S29="","",INDEX('Programme Export'!$D$7:$D$226,$S29)&"") | D29: =IF($S29="","",INDEX('Programme Export'!$E$7:$E$226,$S29)&"") | E29: =IF($S29="","",INDEX('Programme Export'!$N$7:$N$226,$S29)&"") | F29: {=IF(R29="","",_xlfn.TEXTJOIN(";",TRUE,IFERROR(IF(TRIM(MID(SUBSTITUTE(SUBSTITUTE(SUBSTITUTE(R29,",",";")," ",";"),";",REPT(" ",60)),(ROW($1:$10)-1)*60+1,60))="","",MATCH(TRIM(MID(SUBSTITUTE(SUBSTITUTE(SUBSTITUTE(R29,",",";")," ",";"),";",REPT(" ",60)),(ROW($1:$10)-1)*60+1,60)),$C$2:$C$201,0)),"")))} | G29: =IF($S29="","",INDEX('Programme Export'!$H$7:$H$226,$S29)) | J29: =IF($S29="","",INDEX('Programme Export'!$R$7:$R$226,$S29)&"") | K29: =IF($S29="","",INDEX('Programme Export'!$C$7:$C$226,$S29)&"") | L29: =IF($S29="","",'Cover & Instructions'!$B$38) | M29: =IF($S29="","",INDEX('Programme Export'!$F$7:$F$226,$S29)) | N29: =IF($S29="","",INDEX('Programme Export'!$G$7:$G$226,$S29)&"") | O29: =IF($S29="","",IFERROR(P29/M29,0)) | P29: =IF($S29="","",INDEX('Programme Export'!$H$7:$H$226,$S29)) | Q29: =IF($S29="","",INDEX('Programme Export'!$X$7:$X$226,$S29)&"") | R29: =IF($S29="","",INDEX('Programme Export'!$P$7:$P$226,$S29)&"") | S29: =IFERROR(MATCH(28,'Programme Export'!$Y$7:$Y$226,0),"")
A30: =IF($S30="","",29) | B30: =IF($S30="","",1) | C30: =IF($S30="","",INDEX('Programme Export'!$D$7:$D$226,$S30)&"") | D30: =IF($S30="","",INDEX('Programme Export'!$E$7:$E$226,$S30)&"") | E30: =IF($S30="","",INDEX('Programme Export'!$N$7:$N$226,$S30)&"") | F30: {=IF(R30="","",_xlfn.TEXTJOIN(";",TRUE,IFERROR(IF(TRIM(MID(SUBSTITUTE(SUBSTITUTE(SUBSTITUTE(R30,",",";")," ",";"),";",REPT(" ",60)),(ROW($1:$10)-1)*60+1,60))="","",MATCH(TRIM(MID(SUBSTITUTE(SUBSTITUTE(SUBSTITUTE(R30,",",";")," ",";"),";",REPT(" ",60)),(ROW($1:$10)-1)*60+1,60)),$C$2:$C$201,0)),"")))} | G30: =IF($S30="","",INDEX('Programme Export'!$H$7:$H$226,$S30)) | J30: =IF($S30="","",INDEX('Programme Export'!$R$7:$R$226,$S30)&"") | K30: =IF($S30="","",INDEX('Programme Export'!$C$7:$C$226,$S30)&"") | L30: =IF($S30="","",'Cover & Instructions'!$B$38) | M30: =IF($S30="","",INDEX('Programme Export'!$F$7:$F$226,$S30)) | N30: =IF($S30="","",INDEX('Programme Export'!$G$7:$G$226,$S30)&"") | O30: =IF($S30="","",IFERROR(P30/M30,0)) | P30: =IF($S30="","",INDEX('Programme Export'!$H$7:$H$226,$S30)) | Q30: =IF($S30="","",INDEX('Programme Export'!$X$7:$X$226,$S30)&"") | R30: =IF($S30="","",INDEX('Programme Export'!$P$7:$P$226,$S30)&"") | S30: =IFERROR(MATCH(29,'Programme Export'!$Y$7:$Y$226,0),"")
A31: =IF($S31="","",30) | B31: =IF($S31="","",1) | C31: =IF($S31="","",INDEX('Programme Export'!$D$7:$D$226,$S31)&"") | D31: =IF($S31="","",INDEX('Programme Export'!$E$7:$E$226,$S31)&"") | E31: =IF($S31="","",INDEX('Programme Export'!$N$7:$N$226,$S31)&"") | F31: {=IF(R31="","",_xlfn.TEXTJOIN(";",TRUE,IFERROR(IF(TRIM(MID(SUBSTITUTE(SUBSTITUTE(SUBSTITUTE(R31,",",";")," ",";"),";",REPT(" ",60)),(ROW($1:$10)-1)*60+1,60))="","",MATCH(TRIM(MID(SUBSTITUTE(SUBSTITUTE(SUBSTITUTE(R31,",",";")," ",";"),";",REPT(" ",60)),(ROW($1:$10)-1)*60+1,60)),$C$2:$C$201,0)),"")))} | G31: =IF($S31="","",INDEX('Programme Export'!$H$7:$H$226,$S31)) | J31: =IF($S31="","",INDEX('Programme Export'!$R$7:$R$226,$S31)&"") | K31: =IF($S31="","",INDEX('Programme Export'!$C$7:$C$226,$S31)&"") | L31: =IF($S31="","",'Cover & Instructions'!$B$38) | M31: =IF($S31="","",INDEX('Programme Export'!$F$7:$F$226,$S31)) | N31: =IF($S31="","",INDEX('Programme Export'!$G$7:$G$226,$S31)&"") | O31: =IF($S31="","",IFERROR(P31/M31,0)) | P31: =IF($S31="","",INDEX('Programme Export'!$H$7:$H$226,$S31)) | Q31: =IF($S31="","",INDEX('Programme Export'!$X$7:$X$226,$S31)&"") | R31: =IF($S31="","",INDEX('Programme Export'!$P$7:$P$226,$S31)&"") | S31: =IFERROR(MATCH(30,'Programme Export'!$Y$7:$Y$226,0),"")
A32: =IF($S32="","",31) | B32: =IF($S32="","",1) | C32: =IF($S32="","",INDEX('Programme Export'!$D$7:$D$226,$S32)&"") | D32: =IF($S32="","",INDEX('Programme Export'!$E$7:$E$226,$S32)&"") | E32: =IF($S32="","",INDEX('Programme Export'!$N$7:$N$226,$S32)&"") | F32: {=IF(R32="","",_xlfn.TEXTJOIN(";",TRUE,IFERROR(IF(TRIM(MID(SUBSTITUTE(SUBSTITUTE(SUBSTITUTE(R32,",",";")," ",";"),";",REPT(" ",60)),(ROW($1:$10)-1)*60+1,60))="","",MATCH(TRIM(MID(SUBSTITUTE(SUBSTITUTE(SUBSTITUTE(R32,",",";")," ",";"),";",REPT(" ",60)),(ROW($1:$10)-1)*60+1,60)),$C$2:$C$201,0)),"")))} | G32: =IF($S32="","",INDEX('Programme Export'!$H$7:$H$226,$S32)) | J32: =IF($S32="","",INDEX('Programme Export'!$R$7:$R$226,$S32)&"") | K32: =IF($S32="","",INDEX('Programme Export'!$C$7:$C$226,$S32)&"") | L32: =IF($S32="","",'Cover & Instructions'!$B$38) | M32: =IF($S32="","",INDEX('Programme Export'!$F$7:$F$226,$S32)) | N32: =IF($S32="","",INDEX('Programme Export'!$G$7:$G$226,$S32)&"") | O32: =IF($S32="","",IFERROR(P32/M32,0)) | P32: =IF($S32="","",INDEX('Programme Export'!$H$7:$H$226,$S32)) | Q32: =IF($S32="","",INDEX('Programme Export'!$X$7:$X$226,$S32)&"") | R32: =IF($S32="","",INDEX('Programme Export'!$P$7:$P$226,$S32)&"") | S32: =IFERROR(MATCH(31,'Programme Export'!$Y$7:$Y$226,0),"")
A33: =IF($S33="","",32) | B33: =IF($S33="","",1) | C33: =IF($S33="","",INDEX('Programme Export'!$D$7:$D$226,$S33)&"") | D33: =IF($S33="","",INDEX('Programme Export'!$E$7:$E$226,$S33)&"") | E33: =IF($S33="","",INDEX('Programme Export'!$N$7:$N$226,$S33)&"") | F33: {=IF(R33="","",_xlfn.TEXTJOIN(";",TRUE,IFERROR(IF(TRIM(MID(SUBSTITUTE(SUBSTITUTE(SUBSTITUTE(R33,",",";")," ",";"),";",REPT(" ",60)),(ROW($1:$10)-1)*60+1,60))="","",MATCH(TRIM(MID(SUBSTITUTE(SUBSTITUTE(SUBSTITUTE(R33,",",";")," ",";"),";",REPT(" ",60)),(ROW($1:$10)-1)*60+1,60)),$C$2:$C$201,0)),"")))} | G33: =IF($S33="","",INDEX('Programme Export'!$H$7:$H$226,$S33)) | J33: =IF($S33="","",INDEX('Programme Export'!$R$7:$R$226,$S33)&"") | K33: =IF($S33="","",INDEX('Programme Export'!$C$7:$C$226,$S33)&"") | L33: =IF($S33="","",'Cover & Instructions'!$B$38) | M33: =IF($S33="","",INDEX('Programme Export'!$F$7:$F$226,$S33)) | N33: =IF($S33="","",INDEX('Programme Export'!$G$7:$G$226,$S33)&"") | O33: =IF($S33="","",IFERROR(P33/M33,0)) | P33: =IF($S33="","",INDEX('Programme Export'!$H$7:$H$226,$S33)) | Q33: =IF($S33="","",INDEX('Programme Export'!$X$7:$X$226,$S33)&"") | R33: =IF($S33="","",INDEX('Programme Export'!$P$7:$P$226,$S33)&"") | S33: =IFERROR(MATCH(32,'Programme Export'!$Y$7:$Y$226,0),"")
A34: =IF($S34="","",33) | B34: =IF($S34="","",1) | C34: =IF($S34="","",INDEX('Programme Export'!$D$7:$D$226,$S34)&"") | D34: =IF($S34="","",INDEX('Programme Export'!$E$7:$E$226,$S34)&"") | E34: =IF($S34="","",INDEX('Programme Export'!$N$7:$N$226,$S34)&"") | F34: {=IF(R34="","",_xlfn.TEXTJOIN(";",TRUE,IFERROR(IF(TRIM(MID(SUBSTITUTE(SUBSTITUTE(SUBSTITUTE(R34,",",";")," ",";"),";",REPT(" ",60)),(ROW($1:$10)-1)*60+1,60))="","",MATCH(TRIM(MID(SUBSTITUTE(SUBSTITUTE(SUBSTITUTE(R34,",",";")," ",";"),";",REPT(" ",60)),(ROW($1:$10)-1)*60+1,60)),$C$2:$C$201,0)),"")))} | G34: =IF($S34="","",INDEX('Programme Export'!$H$7:$H$226,$S34)) | J34: =IF($S34="","",INDEX('Programme Export'!$R$7:$R$226,$S34)&"") | K34: =IF($S34="","",INDEX('Programme Export'!$C$7:$C$226,$S34)&"") | L34: =IF($S34="","",'Cover & Instructions'!$B$38) | M34: =IF($S34="","",INDEX('Programme Export'!$F$7:$F$226,$S34)) | N34: =IF($S34="","",INDEX('Programme Export'!$G$7:$G$226,$S34)&"") | O34: =IF($S34="","",IFERROR(P34/M34,0)) | P34: =IF($S34="","",INDEX('Programme Export'!$H$7:$H$226,$S34)) | Q34: =IF($S34="","",INDEX('Programme Export'!$X$7:$X$226,$S34)&"") | R34: =IF($S34="","",INDEX('Programme Export'!$P$7:$P$226,$S34)&"") | S34: =IFERROR(MATCH(33,'Programme Export'!$Y$7:$Y$226,0),"")
